Workbook

Sheet Summary
A1: Client Test Cases — Lending and Depository Management
A2: Detailed functional test cases with explicit preconditions, data, steps, and expected results. Statuses are reset for client execution.
A4: Module | B4: Area | C4: Test Cases | D4: Automated | E4: Passed | F4: Failed | G4: Not Executed | H4: Blocked
A5: Loan Account | B5: Lending Management | C5: =COUNTA('LME Loan Account'!$A$7:$A$143)-4 | D5: =COUNTIF('LME Loan Account'!$H$7:$H$143,"Yes") | E5: =COUNTIF('LME Loan Account'!$I$7:$I$143,"Passed") | F5: =COUNTIF('LME Loan Account'!$I$7:$I$143,"Failed") | G5: =COUNTIF('LME Loan Account'!$I$7:$I$143,"Not Executed") | H5: =COUNTIF('LME Loan Account'!$I$7:$I$143,"Blocked")
A6: Loan Type | B6: Lending Management | C6: =COUNTA('LME Loan Type'!$A$7:$A$77)-4 | D6: =COUNTIF('LME Loan Type'!$H$7:$H$77,"Yes") | E6: =COUNTIF('LME Loan Type'!$I$7:$I$77,"Passed") | F6: =COUNTIF('LME Loan Type'!$I$7:$I$77,"Failed") | G6: =COUNTIF('LME Loan Type'!$I$7:$I$77,"Not Executed") | H6: =COUNTIF('LME Loan Type'!$I$7:$I$77,"Blocked")
A7: Loan Type Automation Method | B7: Lending Management | C7: =COUNTA('LME Automation Method'!$A$7:$A$17)-4 | D7: =COUNTIF('LME Automation Method'!$H$7:$H$17,"Yes") | E7: =COUNTIF('LME Automation Method'!$I$7:$I$17,"Passed") | F7: =COUNTIF('LME Automation Method'!$I$7:$I$17,"Failed") | G7: =COUNTIF('LME Automation Method'!$I$7:$I$17,"Not Executed") | H7: =COUNTIF('LME Automation Method'!$I$7:$I$17,"Blocked")
A8: Loan Type Standard Automation | B8: Lending Management | C8: =COUNTA('LME Loan Type - Standard'!$A$7:$A$45)-4 | D8: =COUNTIF('LME Loan Type - Standard'!$H$7:$H$45,"Yes") | E8: =COUNTIF('LME Loan Type - Standard'!$I$7:$I$45,"Passed") | F8: =COUNTIF('LME Loan Type - Standard'!$I$7:$I$45,"Failed") | G8: =COUNTIF('LME Loan Type - Standard'!$I$7:$I$45,"Not Executed") | H8: =COUNTIF('LME Loan Type - Standard'!$I$7:$I$45,"Blocked")
A9: Loan Interest Rate | B9: Lending Management | C9: =COUNTA('LME Interest Rate'!$A$7:$A$53)-4 | D9: =COUNTIF('LME Interest Rate'!$H$7:$H$53,"Yes") | E9: =COUNTIF('LME Interest Rate'!$I$7:$I$53,"Passed") | F9: =COUNTIF('LME Interest Rate'!$I$7:$I$53,"Failed") | G9: =COUNTIF('LME Interest Rate'!$I$7:$I$53,"Not Executed") | H9: =COUNTIF('LME Interest Rate'!$I$7:$I$53,"Blocked")
A10: Loan Category | B10: Lending Management | C10: =COUNTA('LME Loan Category'!$A$7:$A$78)-4 | D10: =COUNTIF('LME Loan Category'!$H$7:$H$78,"Yes") | E10: =COUNTIF('LME Loan Category'!$I$7:$I$78,"Passed") | F10: =COUNTIF('LME Loan Category'!$I$7:$I$78,"Failed") | G10: =COUNTIF('LME Loan Category'!$I$7:$I$78,"Not Executed") | H10: =COUNTIF('LME Loan Category'!$I$7:$I$78,"Blocked")
A11: Loan Fee Type | B11: Lending Management | C11: =COUNTA('LME Loan Fee Type'!$A$7:$A$60)-4 | D11: =COUNTIF('LME Loan Fee Type'!$H$7:$H$60,"Yes") | E11: =COUNTIF('LME Loan Fee Type'!$I$7:$I$60,"Passed") | F11: =COUNTIF('LME Loan Fee Type'!$I$7:$I$60,"Failed") | G11: =COUNTIF('LME Loan Fee Type'!$I$7:$I$60,"Not Executed") | H11: =COUNTIF('LME Loan Fee Type'!$I$7:$I$60,"Blocked")
A12: Fee Capitalization | B12: Lending Management | C12: =COUNTA('LME Fee Capitalization'!$A$7:$A$96)-4 | D12: =COUNTIF('LME Fee Capitalization'!$H$7:$H$96,"Yes") | E12: =COUNTIF('LME Fee Capitalization'!$I$7:$I$96,"Passed") | F12: =COUNTIF('LME Fee Capitalization'!$I$7:$I$96,"Failed") | G12: =COUNTIF('LME Fee Capitalization'!$I$7:$I$96,"Not Executed") | H12: =COUNTIF('LME Fee Capitalization'!$I$7:$I$96,"Blocked")
A13: Loan Adjustment | B13: Lending Management | C13: =COUNTA('LME Loan Adjustment'!$A$7:$A$167)-4 | D13: =COUNTIF('LME Loan Adjustment'!$H$7:$H$167,"Yes") | E13: =COUNTIF('LME Loan Adjustment'!$I$7:$I$167,"Passed") | F13: =COUNTIF('LME Loan Adjustment'!$I$7:$I$167,"Failed") | G13: =COUNTIF('LME Loan Adjustment'!$I$7:$I$167,"Not Executed") | H13: =COUNTIF('LME Loan Adjustment'!$I$7:$I$167,"Blocked")
A14: Loan Write-Off | B14: Lending Management | C14: =COUNTA('LME Loan Write-Off'!$A$7:$A$85)-4 | D14: =COUNTIF('LME Loan Write-Off'!$H$7:$H$85,"Yes") | E14: =COUNTIF('LME Loan Write-Off'!$I$7:$I$85,"Passed") | F14: =COUNTIF('LME Loan Write-Off'!$I$7:$I$85,"Failed") | G14: =COUNTIF('LME Loan Write-Off'!$I$7:$I$85,"Not Executed") | H14: =COUNTIF('LME Loan Write-Off'!$I$7:$I$85,"Blocked")
A15: Loan Statements | B15: Lending Management | C15: =COUNTA('LME Statements'!$A$7:$A$52)-4 | D15: =COUNTIF('LME Statements'!$H$7:$H$52,"Yes") | E15: =COUNTIF('LME Statements'!$I$7:$I$52,"Passed") | F15: =COUNTIF('LME Statements'!$I$7:$I$52,"Failed") | G15: =COUNTIF('LME Statements'!$I$7:$I$52,"Not Executed") | H15: =COUNTIF('LME Statements'!$I$7:$I$52,"Blocked")
A16: Lending Workbench | B16: Lending Management | C16: =COUNTA('LME Workbench'!$A$7:$A$44) | D16: =COUNTIF('LME Workbench'!$H$7:$H$44,"Yes") | E16: =COUNTIF('LME Workbench'!$I$7:$I$44,"Passed") | F16: =COUNTIF('LME Workbench'!$I$7:$I$44,"Failed") | G16: =COUNTIF('LME Workbench'!$I$7:$I$44,"Not Executed") | H16: =COUNTIF('LME Workbench'!$I$7:$I$44,"Blocked")
A17: Loan Ledger Report | B17: Lending Management | C17: =COUNTA('LME Ledger Report'!$A$7:$A$92) | D17: =COUNTIF('LME Ledger Report'!$H$7:$H$92,"Yes") | E17: =COUNTIF('LME Ledger Report'!$I$7:$I$92,"Passed") | F17: =COUNTIF('LME Ledger Report'!$I$7:$I$92,"Failed") | G17: =COUNTIF('LME Ledger Report'!$I$7:$I$92,"Not Executed") | H17: =COUNTIF('LME Ledger Report'!$I$7:$I$92,"Blocked")
A18: Roll Forward Report | B18: Lending Management | C18: =COUNTA('LME Roll Forward'!$A$7:$A$57) | D18: =COUNTIF('LME Roll Forward'!$H$7:$H$57,"Yes") | E18: =COUNTIF('LME Roll Forward'!$I$7:$I$57,"Passed") | F18: =COUNTIF('LME Roll Forward'!$I$7:$I$57,"Failed") | G18: =COUNTIF('LME Roll Forward'!$I$7:$I$57,"Not Executed") | H18: =COUNTIF('LME Roll Forward'!$I$7:$I$57,"Blocked")
A19: Loan Payment | B19: Lending Management | C19: =COUNTA('LME Loan Payment from depositor'!$A$7:$A$99)-4 | D19: =COUNTIF('LME Loan Payment from depositor'!$H$7:$H$99,"Yes") | E19: =COUNTIF('LME Loan Payment from depositor'!$I$7:$I$99,"Passed") | F19: =COUNTIF('LME Loan Payment from depositor'!$I$7:$I$99,"Failed") | G19: =COUNTIF('LME Loan Payment from depositor'!$I$7:$I$99,"Not Executed") | H19: =COUNTIF('LME Loan Payment from depositor'!$I$7:$I$99,"Blocked")
A20: Overpayment | B20: Lending Management | C20: =COUNTA('LME Overpayment'!$A$7:$A$88)-4 | D20: =COUNTIF('LME Overpayment'!$H$7:$H$88,"Yes") | E20: =COUNTIF('LME Overpayment'!$I$7:$I$88,"Passed") | F20: =COUNTIF('LME Overpayment'!$I$7:$I$88,"Failed") | G20: =COUNTIF('LME Overpayment'!$I$7:$I$88,"Not Executed") | H20: =COUNTIF('LME Overpayment'!$I$7:$I$88,"Blocked")
A21: AR Payment | B21: Lending Management | C21: =COUNTA('LME AR Payment'!$A$7:$A$14) | D21: =COUNTIF('LME AR Payment'!$H$7:$H$14,"Yes") | E21: =COUNTIF('LME AR Payment'!$I$7:$I$14,"Passed") | F21: =COUNTIF('LME AR Payment'!$I$7:$I$14,"Failed") | G21: =COUNTIF('LME AR Payment'!$I$7:$I$14,"Not Executed") | H21: =COUNTIF('LME AR Payment'!$I$7:$I$14,"Blocked")
A22: Account | B22: Depository Management | C22: =COUNTA('DMS Account'!$A$7:$A$150)-4 | D22: =COUNTIF('DMS Account'!$H$7:$H$150,"Yes") | E22: =COUNTIF('DMS Account'!$I$7:$I$150,"Passed") | F22: =COUNTIF('DMS Account'!$I$7:$I$150,"Failed") | G22: =COUNTIF('DMS Account'!$I$7:$I$150,"Not Executed") | H22: =COUNTIF('DMS Account'!$I$7:$I$150,"Blocked")
A23: Account Category | B23: Depository Management | C23: =COUNTA('DMS Account Category'!$A$7:$A$55)-4 | D23: =COUNTIF('DMS Account Category'!$H$7:$H$55,"Yes") | E23: =COUNTIF('DMS Account Category'!$I$7:$I$55,"Passed") | F23: =COUNTIF('DMS Account Category'!$I$7:$I$55,"Failed") | G23: =COUNTIF('DMS Account Category'!$I$7:$I$55,"Not Executed") | H23: =COUNTIF('DMS Account Category'!$I$7:$I$55,"Blocked")
A24: Interest Rate | B24: Depository Management | C24: =COUNTA('DMS Interest Rate'!$A$7:$A$41)-4 | D24: =COUNTIF('DMS Interest Rate'!$H$7:$H$41,"Yes") | E24: =COUNTIF('DMS Interest Rate'!$I$7:$I$41,"Passed") | F24: =COUNTIF('DMS Interest Rate'!$I$7:$I$41,"Failed") | G24: =COUNTIF('DMS Interest Rate'!$I$7:$I$41,"Not Executed") | H24: =COUNTIF('DMS Interest Rate'!$I$7:$I$41,"Blocked")
A25: Fee Type | B25: Depository Management | C25: =COUNTA('DMS Fee Type'!$A$7:$A$35)-4 | D25: =COUNTIF('DMS Fee Type'!$H$7:$H$35,"Yes") | E25: =COUNTIF('DMS Fee Type'!$I$7:$I$35,"Passed") | F25: =COUNTIF('DMS Fee Type'!$I$7:$I$35,"Failed") | G25: =COUNTIF('DMS Fee Type'!$I$7:$I$35,"Not Executed") | H25: =COUNTIF('DMS Fee Type'!$I$7:$I$35,"Blocked")
A26: Other Adjustment | B26: Depository Management | C26: =COUNTA('DMS Other Adj Type'!$A$7:$A$37)-4 | D26: =COUNTIF('DMS Other Adj Type'!$H$7:$H$37,"Yes") | E26: =COUNTIF('DMS Other Adj Type'!$I$7:$I$37,"Passed") | F26: =COUNTIF('DMS Other Adj Type'!$I$7:$I$37,"Failed") | G26: =COUNTIF('DMS Other Adj Type'!$I$7:$I$37,"Not Executed") | H26: =COUNTIF('DMS Other Adj Type'!$I$7:$I$37,"Blocked")
A27: Adjustment | B27: Depository Management | C27: =COUNTA('DMS Adjustment'!$A$7:$A$229)-4 | D27: =COUNTIF('DMS Adjustment'!$H$7:$H$229,"Yes") | E27: =COUNTIF('DMS Adjustment'!$I$7:$I$229,"Passed") | F27: =COUNTIF('DMS Adjustment'!$I$7:$I$229,"Failed") | G27: =COUNTIF('DMS Adjustment'!$I$7:$I$229,"Not Executed") | H27: =COUNTIF('DMS Adjustment'!$I$7:$I$229,"Blocked")
A28: Deposits | B28: Depository Management | C28: =COUNTA('DMS Deposits'!$A$7:$A$183)-4 | D28: =COUNTIF('DMS Deposits'!$H$7:$H$183,"Yes") | E28: =COUNTIF('DMS Deposits'!$I$7:$I$183,"Passed") | F28: =COUNTIF('DMS Deposits'!$I$7:$I$183,"Failed") | G28: =COUNTIF('DMS Deposits'!$I$7:$I$183,"Not Executed") | H28: =COUNTIF('DMS Deposits'!$I$7:$I$183,"Blocked")
A29: Withdrawal | B29: Depository Management | C29: =COUNTA('DMS Withdrawal'!$A$7:$A$203)-4 | D29: =COUNTIF('DMS Withdrawal'!$H$7:$H$203,"Yes") | E29: =COUNTIF('DMS Withdrawal'!$I$7:$I$203,"Passed") | F29: =COUNTIF('DMS Withdrawal'!$I$7:$I$203,"Failed") | G29: =COUNTIF('DMS Withdrawal'!$I$7:$I$203,"Not Executed") | H29: =COUNTIF('DMS Withdrawal'!$I$7:$I$203,"Blocked")
A30: Transfer | B30: Depository Management | C30: =COUNTA('DMS Transfer'!$A$7:$A$297)-4 | D30: =COUNTIF('DMS Transfer'!$H$7:$H$297,"Yes") | E30: =COUNTIF('DMS Transfer'!$I$7:$I$297,"Passed") | F30: =COUNTIF('DMS Transfer'!$I$7:$I$297,"Failed") | G30: =COUNTIF('DMS Transfer'!$I$7:$I$297,"Not Executed") | H30: =COUNTIF('DMS Transfer'!$I$7:$I$297,"Blocked")
A31: Close Account | B31: Depository Management | C31: =COUNTA('DMS Close Account'!$A$7:$A$93)-4 | D31: =COUNTIF('DMS Close Account'!$H$7:$H$93,"Yes") | E31: =COUNTIF('DMS Close Account'!$I$7:$I$93,"Passed") | F31: =COUNTIF('DMS Close Account'!$I$7:$I$93,"Failed") | G31: =COUNTIF('DMS Close Account'!$I$7:$I$93,"Not Executed") | H31: =COUNTIF('DMS Close Account'!$I$7:$I$93,"Blocked")
A32: Statements | B32: Depository Management
A33: TOTAL | C33: =SUM(C5:C32) | D33: =SUM(D5:D32) | E33: =SUM(E5:E32) | F33: =SUM(F5:F32) | G33: =SUM(G5:G32) | H33: =SUM(H5:H32)
A35: Scope and usage notes
A36: 1. All test-case sheets use the exact 10 requested columns.
A37: 2. Status defaults to Not Executed; IS Automated defaults to TBD until the automation inventory is approved.
A38: 3. Existing scenarios were normalized from the supplied regression/test-case workbooks; prior execution results and defect commentary were intentionally not carried into the client baseline.
A39: 4. New Deposits, Withdrawal, Transfer, Close Depository Account, Statements, and Lending Overpayment cases are requirement-based design coverage. Jira references are marked TBD until approved requirement keys are supplied.
A40: 5. Items whose behavior depends on product policy (for example cross-currency transfers, account reopening, and overpayment disposition/allocation) are flagged in Comments for client confirmation.

Sheet LME Loan Account
A1: Lending - Loan Account
A2: Common Preconditions | C2: 1. User is signed in to Sage Intacct. 2. The correct Lending Management or Depository Management entity is selected. 3. The module is enabled for the company. 4. The user has the permission required for the scenario. 5. Required master/configuration records are active and available.
A4: Navigation: Applications > Lending Management > Loan account | Client baseline | 133 test cases | Updated 2026-08-27
A6: Test Case ID | B6: Test Scenario | C6: Preconditions | D6: Test Data | E6: Test Steps | F6: Expected Result | G6: Requirement/Jira Reference | H6: IS Automated | I6: Status | J6: Comments
A7: CREATE (54 test cases)
A8: LME-LA-001 | B8: Loan information section present | C8: Refer to Common Preconditions above. | D8: Account category: QA Loan Category Account number: LA-QA-001 User role: Full Access | E8: 1. Sign in to Sage Intacct with the test user. 2. Navigate to Applications > Lending Management > Loan account. 3. Open the page or record relevant to the scenario. 4. Perform the scenario action: Loan information section present. 5. Apply or complete the action where applicable. 6. Observe the page, messages, saved data, balances, and related records as applicable. | F8: Section heading visible | G8: TEST_CASES_Loan_Account.xlsx / TC-LA-002 | H8: TBD | I8: Not Executed | J8: Source section: B. Create page (IDs: TC-LA-001–058)
A9: LME-LA-002 | B9: Loan information fields present | C9: Refer to Common Preconditions above. | D9: Account category: QA Loan Category Account number: LA-QA-001 Account name: Client QA Loan 001 Customer: 1--Power Aerospace Materials Loan type: QA Non-Revolving Interest rate: 5.0000% Origination amount: 10000.00 Origination date: 2026-08-01 | E9: 1. Sign in to Sage Intacct with the test user. 2. Navigate to Applications > Lending Management > Loan account. 3. Open the page or record relevant to the scenario. 4. Perform the scenario action: Loan information fields present. 5. Apply or complete the action where applicable. 6. Observe the page, messages, saved data, balances, and related records as applicable. | F9: Account category/number/name, Customer, Vendor, Attachment, Description, Email statements, Amount all present | G9: TEST_CASES_Loan_Account.xlsx / TC-LA-003 | H9: TBD | I9: Not Executed | J9: Source section: B. Create page (IDs: TC-LA-001–058)
A10: LME-LA-003 | B10: Account category mandatory | C10: Refer to Common Preconditions above. | D10: Other required fields: Use the valid values listed below Target field: Blank Account category: QA Loan Category Account number: LA-QA-001 Account name: Client QA Loan 001 Customer: 1--Power Aerospace Materials | E10: 1. Sign in to Sage Intacct with the test user. 2. Navigate to Applications > Lending Management > Loan account. 3. Open the page or record relevant to the scenario. 4. Perform the scenario action: Account category mandatory. 5. Apply or complete the action where applicable. 6. Observe the page, messages, saved data, balances, and related records as applicable. | F10: Red asterisk shown | G10: TEST_CASES_Loan_Account.xlsx / TC-LA-004 | H10: TBD | I10: Not Executed | J10: Source section: B. Create page (IDs: TC-LA-001–058)
A11: LME-LA-004 | B11: Empty Account category error | C11: Refer to Common Preconditions above. | D11: Other required fields: Use the valid values listed below Target field: Blank Account category: QA Loan Category Account number: LA-QA-001 Account name: Client QA Loan 001 Customer: 1--Power Aerospace Materials | E11: 1. Sign in to Sage Intacct with the test user. 2. Navigate to Applications > Lending Management > Loan account. 3. Open the page or record relevant to the scenario. 4. Perform the scenario action: Empty Account category error. 5. Apply or complete the action where applicable. 6. Observe the page, messages, saved data, balances, and related records as applicable. | F11: "Account category is required for loan account." | G11: TEST_CASES_Loan_Account.xlsx / TC-LA-005 | H11: TBD | I11: Not Executed | J11: Source section: B. Create page (IDs: TC-LA-001–058)
A12: LME-LA-005 | B12: Account number mandatory | C12: Refer to Common Preconditions above. | D12: Other required fields: Use the valid values listed below Target field: Blank Account category: QA Loan Category Account number: LA-QA-001 Account name: Client QA Loan 001 Customer: 1--Power Aerospace Materials | E12: 1. Sign in to Sage Intacct with the test user. 2. Navigate to Applications > Lending Management > Loan account. 3. Open the page or record relevant to the scenario. 4. Perform the scenario action: Account number mandatory. 5. Apply or complete the action where applicable. 6. Observe the page, messages, saved data, balances, and related records as applicable. | F12: Red asterisk shown | G12: TEST_CASES_Loan_Account.xlsx / TC-LA-006 | H12: TBD | I12: Not Executed | J12: Source section: B. Create page (IDs: TC-LA-001–058)
A13: LME-LA-006 | B13: Empty Account number (no-sequence category) | C13: Refer to Common Preconditions above. | D13: Other required fields: Use the valid values listed below Target field: Blank Account category: QA Loan Category Account number: LA-QA-001 Account name: Client QA Loan 001 Customer: 1--Power Aerospace Materials | E13: 1. Sign in to Sage Intacct with the test user. 2. Navigate to Applications > Lending Management > Loan account. 3. Open the page or record relevant to the scenario. 4. Perform the scenario action: Empty Account number (no-sequence category). 5. Apply or complete the action where applicable. 6. Observe the page, messages, saved data, balances, and related records as applicable. | F13: Friendly error, no object-path leak (fixed) | G13: TEST_CASES_Loan_Account.xlsx / TC-LA-008 | H13: TBD | I13: Not Executed | J13: Source section: B. Create page (IDs: TC-LA-001–058)
A14: LME-LA-007 | B14: Account name mandatory | C14: Refer to Common Preconditions above. | D14: Other required fields: Use the valid values listed below Target field: Blank Account category: QA Loan Category Account number: LA-QA-001 Account name: Client QA Loan 001 Customer: 1--Power Aerospace Materials | E14: 1. Sign in to Sage Intacct with the test user. 2. Navigate to Applications > Lending Management > Loan account. 3. Open the page or record relevant to the scenario. 4. Perform the scenario action: Account name mandatory. 5. Apply or complete the action where applicable. 6. Observe the page, messages, saved data, balances, and related records as applicable. | F14: Red asterisk shown | G14: TEST_CASES_Loan_Account.xlsx / TC-LA-009 | H14: TBD | I14: Not Executed | J14: Source section: B. Create page (IDs: TC-LA-001–058)
A15: LME-LA-008 | B15: Empty Account name error | C15: Refer to Common Preconditions above. | D15: Other required fields: Use the valid values listed below Target field: Blank Account category: QA Loan Category Account number: LA-QA-001 Account name: Client QA Loan 001 Customer: 1--Power Aerospace Materials | E15: 1. Sign in to Sage Intacct with the test user. 2. Navigate to Applications > Lending Management > Loan account. 3. Open the page or record relevant to the scenario. 4. Perform the scenario action: Empty Account name error. 5. Apply or complete the action where applicable. 6. Observe the page, messages, saved data, balances, and related records as applicable. | F15: "Account name is required for loan account." | G15: TEST_CASES_Loan_Account.xlsx / TC-LA-010 | H15: TBD | I15: Not Executed | J15: Source section: B. Create page (IDs: TC-LA-001–058)
A16: LME-LA-009 | B16: Account name >200 chars rejected | C16: Refer to Common Preconditions above. | D16: Account category: QA Loan Category Account number: LA-QA-001 Account name: Client QA Loan 001 Customer: 1--Power Aerospace Materials Loan type: QA Non-Revolving Interest rate: 5.0000% Origination amount: 10000.00 Origination date: 2026-08-01 | E16: 1. Sign in to Sage Intacct with the test user. 2. Navigate to Applications > Lending Management > Loan account. 3. Open the page or record relevant to the scenario. 4. Perform the scenario action: Account name >200 chars rejected. 5. Apply or complete the action where applicable. 6. Observe the page, messages, saved data, balances, and related records as applicable. | F16: Friendly message, no raw i18n key (fixed) | G16: TEST_CASES_Loan_Account.xlsx / TC-LA-011 | H16: TBD | I16: Not Executed | J16: Source section: B. Create page (IDs: TC-LA-001–058)
A17: LME-LA-010 | B17: Customer mandatory | C17: Refer to Common Preconditions above. | D17: Other required fields: Use the valid values listed below Target field: Blank Account category: QA Loan Category Account number: LA-QA-001 Account name: Client QA Loan 001 Customer: 1--Power Aerospace Materials | E17: 1. Sign in to Sage Intacct with the test user. 2. Navigate to Applications > Lending Management > Loan account. 3. Open the page or record relevant to the scenario. 4. Perform the scenario action: Customer mandatory. 5. Apply or complete the action where applicable. 6. Observe the page, messages, saved data, balances, and related records as applicable. | F17: Red asterisk shown | G17: TEST_CASES_Loan_Account.xlsx / TC-LA-012 | H17: TBD | I17: Not Executed | J17: Source section: B. Create page (IDs: TC-LA-001–058)
A18: LME-LA-011 | B18: Empty Customer error | C18: Refer to Common Preconditions above. | D18: Other required fields: Use the valid values listed below Target field: Blank Account category: QA Loan Category Account number: LA-QA-001 Account name: Client QA Loan 001 Customer: 1--Power Aerospace Materials | E18: 1. Sign in to Sage Intacct with the test user. 2. Navigate to Applications > Lending Management > Loan account. 3. Open the page or record relevant to the scenario. 4. Perform the scenario action: Empty Customer error. 5. Apply or complete the action where applicable. 6. Observe the page, messages, saved data, balances, and related records as applicable. | F18: "Customer is required for loan account." | G18: TEST_CASES_Loan_Account.xlsx / TC-LA-013 | H18: TBD | I18: Not Executed | J18: Source section: B. Create page (IDs: TC-LA-001–058)
A19: LME-LA-012 | B19: Vendor mandatory | C19: Refer to Common Preconditions above. | D19: Other required fields: Use the valid values listed below Target field: Blank Account category: QA Loan Category Account number: LA-QA-001 Account name: Client QA Loan 001 Customer: 1--Power Aerospace Materials | E19: 1. Sign in to Sage Intacct with the test user. 2. Navigate to Applications > Lending Management > Loan account. 3. Open the page or record relevant to the scenario. 4. Perform the scenario action: Vendor mandatory. 5. Apply or complete the action where applicable. 6. Observe the page, messages, saved data, balances, and related records as applicable. | F19: Red asterisk shown | G19: TEST_CASES_Loan_Account.xlsx / TC-LA-014 | H19: TBD | I19: Not Executed | J19: Source section: B. Create page (IDs: TC-LA-001–058)
... A29: LME-LA-022 | B29: Empty Interest rate error | C29: Refer to Common Preconditions above. | D29: Other required fields: Use the valid values listed below Target field: Blank Account category: QA Loan Category Account number: LA-QA-001 Account name: Client QA Loan 001 Customer: 1--Power Aerospace Materials | E29: 1. Sign in to Sage Intacct with the test user. 2. Navigate to Applications > Lending Management > Loan account. 3. Open the page or record relevant to the scenario. 4. Perform the scenario action: Empty Interest rate error. 5. Apply or complete the action where applicable. 6. Observe the page, messages, saved data, balances, and related records as applicable. | F29: Friendly "Interest rate is required..." (fixed, was NPE) | G29: TEST_CASES_Loan_Account.xlsx / TC-LA-024 | H29: TBD | I29: Not Executed | J29: Source section: B. Create page (IDs: TC-LA-001–058)
A30: LME-LA-023 | B30: Non-revolving reveals Term/First payment fields | C30: Refer to Common Preconditions above. | E30: 1. Sign in to Sage Intacct with the test user. 2. Navigate to Applications > Lending Management > Loan account. 3. Open the page or record relevant to the scenario. 4. Perform the scenario action: Non-revolving reveals Term/First payment fields. 5. Apply or complete the action where applicable. 6. Observe the page, messages, saved data, balances, and related records as applicable. | F30: Fields + Preview link visible | G30: TEST_CASES_Loan_Account.xlsx / TC-LA-025 | H30: TBD | I30: Not Executed | J30: Source section: B. Create page (IDs: TC-LA-001–058)
A31: LME-LA-024 | B31: Revolving reveals amortization checkbox | C31: Refer to Common Preconditions above. | D31: Account category: QA Loan Category Account number: LA-QA-001 Account name: Client QA Loan 001 Customer: 1--Power Aerospace Materials Loan type: QA Non-Revolving Interest rate: 5.0000% Origination amount: 10000.00 Origination date: 2026-08-01 | E31: 1. Sign in to Sage Intacct with the test user. 2. Navigate to Applications > Lending Management > Loan account. 3. Open the page or record relevant to the scenario. 4. Perform the scenario action: Revolving reveals amortization checkbox. 5. Apply or complete the action where applicable. 6. Observe the page, messages, saved data, balances, and related records as applicable. | F31: Checkbox + Renewal date visible | G31: TEST_CASES_Loan_Account.xlsx / TC-LA-026 | H31: TBD | I31: Not Executed | J31: Source section: B. Create page (IDs: TC-LA-001–058)
A32: LME-LA-025 | B32: Valid Non-revolving save succeeds | C32: Refer to Common Preconditions above. | D32: Account category: QA Loan Category Account number: LA-QA-001 Account name: Client QA Loan 001 Customer: 1--Power Aerospace Materials Loan type: QA Non-Revolving Interest rate: 5.0000% Origination amount: 10000.00 Origination date: 2026-08-01 | E32: 1. Sign in to Sage Intacct with the test user. 2. Navigate to Applications > Lending Management > Loan account. 3. Open the page or record relevant to the scenario. 4. Perform the scenario action: Valid Non-revolving save succeeds. 5. Click Save or the applicable submit action. 6. Observe the page, messages, saved data, balances, and related records as applicable. | F32: Redirects to View page | G32: TEST_CASES_Loan_Account.xlsx / TC-LA-027 | H32: TBD | I32: Not Executed | J32: Source section: B. Create page (IDs: TC-LA-001–058)
A33: LME-LA-026 | B33: [KNOWN DEFECT] Revolving+amortization save crashes | C33: Refer to Common Preconditions above. | D33: Account category: QA Loan Category Account number: LA-QA-001 Account name: Client QA Loan 001 Customer: 1--Power Aerospace Materials Loan type: QA Non-Revolving Interest rate: 5.0000% Origination amount: 10000.00 Origination date: 2026-08-01 | E33: 1. Sign in to Sage Intacct with the test user. 2. Navigate to Applications > Lending Management > Loan account. 3. Open the page or record relevant to the scenario. 4. Perform the scenario action: [KNOWN DEFECT] Revolving+amortization save crashes. 5. Click Save or the applicable submit action. 6. Observe the page, messages, saved data, balances, and related records as applicable. | F33: Raw exception toasts, stays on Create | G33: TEST_CASES_Loan_Account.xlsx / TC-LA-028 | H33: TBD | I33: Not Executed | J33: Source section: B. Create page (IDs: TC-LA-001–058)
A34: LME-LA-027 | B34: Preview amortization schedule modal | C34: Refer to Common Preconditions above. | D34: Account category: QA Loan Category Account number: LA-QA-001 Account name: Client QA Loan 001 Customer: 1--Power Aerospace Materials Loan type: QA Non-Revolving Interest rate: 5.0000% Origination amount: 10000.00 Origination date: 2026-08-01 | E34: 1. Sign in to Sage Intacct with the test user. 2. Navigate to Applications > Lending Management > Loan account. 3. Open the page or record relevant to the scenario. 4. Perform the scenario action: Preview amortization schedule modal. 5. Apply or complete the action where applicable. 6. Observe the page, messages, saved data, balances, and related records as applicable. | F34: Populated table with expected columns | G34: TEST_CASES_Loan_Account.xlsx / TC-LA-029 | H34: TBD | I34: Not Executed | J34: Source section: B. Create page (IDs: TC-LA-001–058)
A35: LME-LA-028 | B35: Amount mandatory numeric | C35: Refer to Common Preconditions above. | D35: Other required fields: Use the valid values listed below Target field: Blank | E35: 1. Sign in to Sage Intacct with the test user. 2. Navigate to Applications > Lending Management > Loan account. 3. Open the page or record relevant to the scenario. 4. Perform the scenario action: Amount mandatory numeric. 5. Apply or complete the action where applicable. 6. Observe the page, messages, saved data, balances, and related records as applicable. | F35: Red asterisk shown | G35: TEST_CASES_Loan_Account.xlsx / TC-LA-030 | H35: TBD | I35: Not Executed | J35: Source section: B. Create page (IDs: TC-LA-001–058)
A36: LME-LA-029 | B36: Empty Amount error | C36: Refer to Common Preconditions above. | D36: Other required fields: Use the valid values listed below Target field: Blank | E36: 1. Sign in to Sage Intacct with the test user. 2. Navigate to Applications > Lending Management > Loan account. 3. Open the page or record relevant to the scenario. 4. Perform the scenario action: Empty Amount error. 5. Apply or complete the action where applicable. 6. Observe the page, messages, saved data, balances, and related records as applicable. | F36: "Amount is required for loan account." | G36: TEST_CASES_Loan_Account.xlsx / TC-LA-031 | H36: TBD | I36: Not Executed | J36: Source section: B. Create page (IDs: TC-LA-001–058)
A37: LME-LA-030 | B37: Negative Amount rejected | C37: Refer to Common Preconditions above. | D37: Amount: -1.00 | E37: 1. Sign in to Sage Intacct with the test user. 2. Navigate to Applications > Lending Management > Loan account. 3. Open the page or record relevant to the scenario. 4. Perform the scenario action: Negative Amount rejected. 5. Apply or complete the action where applicable. 6. Observe the page, messages, saved data, balances, and related records as applicable. | F37: Friendly message, no /originationAmount leak (fixed) | G37: TEST_CASES_Loan_Account.xlsx / TC-LA-032 | H37: TBD | I37: Not Executed | J37: Source section: B. Create page (IDs: TC-LA-001–058)
A38: LME-LA-031 | B38: Amount = 0 accepted | C38: Refer to Common Preconditions above. | E38: 1. Sign in to Sage Intacct with the test user. 2. Navigate to Applications > Lending Management > Loan account. 3. Open the page or record relevant to the scenario. 4. Perform the scenario action: Amount = 0 accepted. 5. Apply or complete the action where applicable. 6. Observe the page, messages, saved data, balances, and related records as applicable. | F38: Record created | G38: TEST_CASES_Loan_Account.xlsx / TC-LA-033 | H38: TBD | I38: Not Executed | J38: Source section: B. Create page (IDs: TC-LA-001–058)
A39: LME-LA-032 | B39: Dimensions section fields present | C39: Refer to Common Preconditions above. | D39: Account category: QA Loan Category Account number: LA-QA-001 User role: Full Access | E39: 1. Sign in to Sage Intacct with the test user. 2. Navigate to Applications > Lending Management > Loan account. 3. Open the page or record relevant to the scenario. 4. Perform the scenario action: Dimensions section fields present. 5. Apply or complete the action where applicable. 6. Observe the page, messages, saved data, balances, and related records as applicable. | F39: Department, Location, Project, Employee, Item, Class, Contract | G39: TEST_CASES_Loan_Account.xlsx / TC-LA-034 | H39: TBD | I39: Not Executed | J39: Source section: B. Create page (IDs: TC-LA-001–058)
A40: LME-LA-033 | B40: Non-Location dimensions not mandatory | C40: Refer to Common Preconditions above. | D40: Other required fields: Use the valid values listed below Target field: Blank Account category: QA Loan Category Account number: LA-QA-001 Account name: Client QA Loan 001 Customer: 1--Power Aerospace Materials | E40: 1. Sign in to Sage Intacct with the test user. 2. Navigate to Applications > Lending Management > Loan account. 3. Open the page or record relevant to the scenario. 4. Perform the scenario action: Non-Location dimensions not mandatory. 5. Apply or complete the action where applicable. 6. Observe the page, messages, saved data, balances, and related records as applicable. | F40: No asterisk on Department/Project/Class/Item | G40: TEST_CASES_Loan_Account.xlsx / TC-LA-035 | H40: TBD | I40: Not Executed | J40: Source section: B. Create page (IDs: TC-LA-001–058)
A41: LME-LA-034 | B41: [KNOWN DEFECT] Location has no asterisk | C41: Refer to Common Preconditions above. | D41: Account category: QA Loan Category Account number: LA-QA-001 Account name: Client QA Loan 001 Customer: 1--Power Aerospace Materials Loan type: QA Non-Revolving Interest rate: 5.0000% Origination amount: 10000.00 Origination date: 2026-08-01 | E41: 1. Sign in to Sage Intacct with the test user. 2. Navigate to Applications > Lending Management > Loan account. 3. Open the page or record relevant to the scenario. 4. Perform the scenario action: [KNOWN DEFECT] Location has no asterisk. 5. Apply or complete the action where applicable. 6. Observe the page, messages, saved data, balances, and related records as applicable. | F41: Missing despite being enforced | G41: TEST_CASES_Loan_Account.xlsx / TC-LA-036 | H41: TBD | I41: Not Executed | J41: Source section: B. Create page (IDs: TC-LA-001–058)
A42: LME-LA-035 | B42: Empty Location error | C42: Refer to Common Preconditions above. | D42: Other required fields: Use the valid values listed below Target field: Blank Account category: QA Loan Category Account number: LA-QA-001 Account name: Client QA Loan 001 Customer: 1--Power Aerospace Materials | E42: 1. Sign in to Sage Intacct with the test user. 2. Navigate to Applications > Lending Management > Loan account. 3. Open the page or record relevant to the scenario. 4. Perform the scenario action: Empty Location error. 5. Apply or complete the action where applicable. 6. Observe the page, messages, saved data, balances, and related records as applicable. | F42: "Location is required for loan account." | G42: TEST_CASES_Loan_Account.xlsx / TC-LA-037 | H42: TBD | I42: Not Executed | J42: Source section: B. Create page (IDs: TC-LA-001–058)
A43: LME-LA-036 | B43: Valid Location succeeds | C43: Refer to Common Preconditions above. | D43: Account category: QA Loan Category Account number: LA-QA-001 Account name: Client QA Loan 001 Customer: 1--Power Aerospace Materials Loan type: QA Non-Revolving Interest rate: 5.0000% Origination amount: 10000.00 Origination date: 2026-08-01 | E43: 1. Sign in to Sage Intacct with the test user. 2. Navigate to Applications > Lending Management > Loan account. 3. Open the page or record relevant to the scenario. 4. Perform the scenario action: Valid Location succeeds. 5. Apply or complete the action where applicable. 6. Observe the page, messages, saved data, balances, and related records as applicable. | F43: Record created | G43: TEST_CASES_Loan_Account.xlsx / TC-LA-038 | H43: TBD | I43: Not Executed | J43: Source section: B. Create page (IDs: TC-LA-001–058)
A44: LME-LA-037 | B44: Save split-button options | C44: Refer to Common Preconditions above. | D44: Account category: QA Loan Category Account number: LA-QA-001 Account name: Client QA Loan 001 Customer: 1--Power Aerospace Materials Loan type: QA Non-Revolving Interest rate: 5.0000% Origination amount: 10000.00 Origination date: 2026-08-01 | E44: 1. Sign in to Sage Intacct with the test user. 2. Navigate to Applications > Lending Management > Loan account. 3. Open the page or record relevant to the scenario. 4. Perform the scenario action: Save split-button options. 5. Click Save or the applicable submit action. 6. Observe the page, messages, saved data, balances, and related records as applicable. | F44: Save, Save and close, Save and new | G44: TEST_CASES_Loan_Account.xlsx / TC-LA-039 | H44: TBD | I44: Not Executed | J44: Source section: B. Create page (IDs: TC-LA-001–058)
A45: LME-LA-038 | B45: Success message on valid save | C45: Refer to Common Preconditions above. | D45: Account category: QA Loan Category Account number: LA-QA-001 Account name: Client QA Loan 001 Customer: 1--Power Aerospace Materials Loan type: QA Non-Revolving Interest rate: 5.0000% Origination amount: 10000.00 Origination date: 2026-08-01 | E45: 1. Sign in to Sage Intacct with the test user. 2. Navigate to Applications > Lending Management > Loan account. 3. Open the page or record relevant to the scenario. 4. Perform the scenario action: Success message on valid save. 5. Click Save or the applicable submit action. 6. Observe the page, messages, saved data, balances, and related records as applicable. | F45: Toast/redirect confirms | G45: TEST_CASES_Loan_Account.xlsx / TC-LA-041 | H45: TBD | I45: Not Executed | J45: Source section: B. Create page (IDs: TC-LA-001–058)
A46: LME-LA-039 | B46: Validation errors show banner + inline | C46: Refer to Common Preconditions above. | D46: Account category: QA Loan Category Account number: LA-QA-001 Account name: Client QA Loan 001 Customer: 1--Power Aerospace Materials Loan type: QA Non-Revolving Interest rate: 5.0000% Origination amount: 10000.00 Origination date: 2026-08-01 | E46: 1. Sign in to Sage Intacct with the test user. 2. Navigate to Applications > Lending Management > Loan account. 3. Open the page or record relevant to the scenario. 4. Perform the scenario action: Validation errors show banner + inline. 5. Apply or complete the action where applicable. 6. Observe the page, messages, saved data, balances, and related records as applicable. | F46: Both present | G46: TEST_CASES_Loan_Account.xlsx / TC-LA-042 | H46: TBD | I46: Not Executed | J46: Source section: B. Create page (IDs: TC-LA-001–058)
A47: LME-LA-040 | B47: Account category dropdown active-only | C47: Refer to Common Preconditions above. | D47: Account category: QA Loan Category Account number: LA-QA-001 Account name: Client QA Loan 001 Customer: 1--Power Aerospace Materials Loan type: QA Non-Revolving Interest rate: 5.0000% Origination amount: 10000.00 Origination date: 2026-08-01 | E47: 1. Sign in to Sage Intacct with the test user. 2. Navigate to Applications > Lending Management > Loan account. 3. Open the page or record relevant to the scenario. 4. Perform the scenario action: Account category dropdown active-only. 5. Apply or complete the action where applicable. 6. Observe the page, messages, saved data, balances, and related records as applicable. | F47: Active category found | G47: TEST_CASES_Loan_Account.xlsx / TC-LA-043 | H47: TBD | I47: Not Executed | J47: Source section: B. Create page (IDs: TC-LA-001–058)
A48: LME-LA-041 | B48: Customer dropdown active-only | C48: Refer to Common Preconditions above. | D48: Account category: QA Loan Category Account number: LA-QA-001 Account name: Client QA Loan 001 Customer: 1--Power Aerospace Materials Loan type: QA Non-Revolving Interest rate: 5.0000% Origination amount: 10000.00 Origination date: 2026-08-01 | E48: 1. Sign in to Sage Intacct with the test user. 2. Navigate to Applications > Lending Management > Loan account. 3. Open the page or record relevant to the scenario. 4. Perform the scenario action: Customer dropdown active-only. 5. Apply or complete the action where applicable. 6. Observe the page, messages, saved data, balances, and related records as applicable. | F48: Active customer found | G48: TEST_CASES_Loan_Account.xlsx / TC-LA-044 | H48: TBD | I48: Not Executed | J48: Source section: B. Create page (IDs: TC-LA-001–058)
A49: LME-LA-042 | B49: Vendor dropdown active-only | C49: Refer to Common Preconditions above. | D49: Account category: QA Loan Category Account number: LA-QA-001 Account name: Client QA Loan 001 Customer: 1--Power Aerospace Materials Loan type: QA Non-Revolving Interest rate: 5.0000% Origination amount: 10000.00 Origination date: 2026-08-01 | E49: 1. Sign in to Sage Intacct with the test user. 2. Navigate to Applications > Lending Management > Loan account. 3. Open the page or record relevant to the scenario. 4. Perform the scenario action: Vendor dropdown active-only. 5. Apply or complete the action where applicable. 6. Observe the page, messages, saved data, balances, and related records as applicable. | F49: Active vendor found | G49: TEST_CASES_Loan_Account.xlsx / TC-LA-045 | H49: TBD | I49: Not Executed | J49: Source section: B. Create page (IDs: TC-LA-001–058)
A50: LME-LA-043 | B50: Empty Description accepted | C50: Refer to Common Preconditions above. | D50: Description: Client QA test text Other required fields: Use the valid values listed below Target field: Blank Account category: QA Loan Category Account number: LA-QA-001 Account name: Client QA Loan 001 Customer: 1--Power Aerospace Materials | E50: 1. Sign in to Sage Intacct with the test user. 2. Navigate to Applications > Lending Management > Loan account. 3. Open the page or record relevant to the scenario. 4. Perform the scenario action: Empty Description accepted. 5. Apply or complete the action where applicable. 6. Observe the page, messages, saved data, balances, and related records as applicable. | F50: View shows "--" | G50: TEST_CASES_Loan_Account.xlsx / TC-LA-047 | H50: TBD | I50: Not Executed | J50: Source section: B. Create page (IDs: TC-LA-001–058)
... A61: LME-LA-054 | B61: Whitespace Account name rejected | C61: Refer to Common Preconditions above. | D61: Account category: QA Loan Category Account number: LA-QA-001 Account name: Client QA Loan 001 Customer: 1--Power Aerospace Materials Loan type: QA Non-Revolving Interest rate: 5.0000% Origination amount: 10000.00 Origination date: 2026-08-01 | E61: 1. Sign in to Sage Intacct with the test user. 2. Navigate to Applications > Lending Management > Loan account. 3. Open the page or record relevant to the scenario. 4. Perform the scenario action: Whitespace Account name rejected. 5. Apply or complete the action where applicable. 6. Observe the page, messages, saved data, balances, and related records as applicable. | F61: Friendly message (fixed) | G61: TEST_CASES_Loan_Account.xlsx / TC-LA-058 | H61: TBD | I61: Not Executed | J61: Source section: B. Create page (IDs: TC-LA-001–058)
A62: EDIT (35 test cases)
A63: LME-LA-055 | B63: Edit button present | C63: Refer to Common Preconditions above. | D63: Account category: QA Loan Category Account number: LA-QA-001 Account name: Client QA Loan 001 Customer: 1--Power Aerospace Materials Loan type: QA Non-Revolving Interest rate: 5.0000% Origination amount: 10000.00 Origination date: 2026-08-01 | E63: 1. Sign in to Sage Intacct with the test user. 2. Navigate to Applications > Lending Management > Loan account. 3. Open an existing record, click Edit, and change the field(s) relevant to the scenario. 4. Perform the scenario action: Edit button present. 5. Click Save or the applicable submit action. 6. Observe the page, messages, saved data, balances, and related records as applicable. | F63: Visible | G63: TEST_CASES_Loan_Account.xlsx / TC-LA-084 | H63: TBD | I63: Not Executed | J63: Source section: C. View page (IDs: TC-LA-071–088)
A64: LME-LA-056 | B64: Edit navigates to Edit page | C64: Refer to Common Preconditions above. | D64: Account category: QA Loan Category Account number: LA-QA-001 Account name: Client QA Loan 001 Customer: 1--Power Aerospace Materials Loan type: QA Non-Revolving Interest rate: 5.0000% Origination amount: 10000.00 Origination date: 2026-08-01 | E64: 1. Sign in to Sage Intacct with the test user. 2. Navigate to Applications > Lending Management > Loan account. 3. Open an existing record, click Edit, and change the field(s) relevant to the scenario. 4. Perform the scenario action: Edit navigates to Edit page. 5. Click Save or the applicable submit action. 6. Observe the page, messages, saved data, balances, and related records as applicable. | F64: Edit heading visible | G64: TEST_CASES_Loan_Account.xlsx / TC-LA-085 | H64: TBD | I64: Not Executed | J64: Source section: C. View page (IDs: TC-LA-071–088)
A65: LME-LA-057 | B65: [KNOWN DEFECT] Edit heading exposes object path | C65: Refer to Common Preconditions above. | D65: Account category: QA Loan Category Account number: LA-QA-001 Account name: Client QA Loan 001 Customer: 1--Power Aerospace Materials Loan type: QA Non-Revolving Interest rate: 5.0000% Origination amount: 10000.00 Origination date: 2026-08-01 | E65: 1. Sign in to Sage Intacct with the test user. 2. Navigate to Applications > Lending Management > Loan account. 3. Open an existing record, click Edit, and change the field(s) relevant to the scenario. 4. Perform the scenario action: [KNOWN DEFECT] Edit heading exposes object path. 5. Click Save or the applicable submit action. 6. Observe the page, messages, saved data, balances, and related records as applicable. | F65: loan-management/loan-account" in H1 | G65: TEST_CASES_Loan_Account.xlsx / TC-LA-098 | H65: TBD | I65: Not Executed | J65: Source section: E. Edit page (IDs: TC-LA-098–130)
A66: LME-LA-058 | B66: Loan information section present on Edit | C66: Refer to Common Preconditions above. | D66: Account category: QA Loan Category Account number: LA-QA-001 Account name: Client QA Loan 001 Customer: 1--Power Aerospace Materials Loan type: QA Non-Revolving Interest rate: 5.0000% Origination amount: 10000.00 Origination date: 2026-08-01 | E66: 1. Sign in to Sage Intacct with the test user. 2. Navigate to Applications > Lending Management > Loan account. 3. Open an existing record, click Edit, and change the field(s) relevant to the scenario. 4. Perform the scenario action: Loan information section present on Edit. 5. Click Save or the applicable submit action. 6. Observe the page, messages, saved data, balances, and related records as applicable. | F66: Visible | G66: TEST_CASES_Loan_Account.xlsx / TC-LA-099 | H66: TBD | I66: Not Executed | J66: Source section: E. Edit page (IDs: TC-LA-098–130)
A67: LME-LA-059 | B67: Account category read-only, drillable | C67: Refer to Common Preconditions above. | D67: Account category: QA Loan Category Account number: LA-QA-001 Account name: Client QA Loan 001 Customer: 1--Power Aerospace Materials Loan type: QA Non-Revolving Interest rate: 5.0000% Origination amount: 10000.00 Origination date: 2026-08-01 | E67: 1. Sign in to Sage Intacct with the test user. 2. Navigate to Applications > Lending Management > Loan account. 3. Open the page or record relevant to the scenario. 4. Perform the scenario action: Account category read-only, drillable. 5. Apply or complete the action where applicable. 6. Observe the page, messages, saved data, balances, and related records as applicable. | F67: Link, no combobox | G67: TEST_CASES_Loan_Account.xlsx / TC-LA-100 | H67: TBD | I67: Not Executed | J67: Source section: E. Edit page (IDs: TC-LA-098–130)
A68: LME-LA-060 | B68: Account number read-only | C68: Refer to Common Preconditions above. | D68: Account category: QA Loan Category Account number: LA-QA-001 Account name: Client QA Loan 001 Customer: 1--Power Aerospace Materials Loan type: QA Non-Revolving Interest rate: 5.0000% Origination amount: 10000.00 Origination date: 2026-08-01 | E68: 1. Sign in to Sage Intacct with the test user. 2. Navigate to Applications > Lending Management > Loan account. 3. Open the page or record relevant to the scenario. 4. Perform the scenario action: Account number read-only. 5. Apply or complete the action where applicable. 6. Observe the page, messages, saved data, balances, and related records as applicable. | F68: Not editable (no <input> at all) | G68: TEST_CASES_Loan_Account.xlsx / TC-LA-101 | H68: TBD | I68: Not Executed | J68: Source section: E. Edit page (IDs: TC-LA-098–130)
A69: LME-LA-061 | B69: Account name mandatory, editable | C69: Refer to Common Preconditions above. | D69: Other required fields: Use the valid values listed below Target field: Blank Account category: QA Loan Category Account number: LA-QA-001 Account name: Client QA Loan 001 Customer: 1--Power Aerospace Materials | E69: 1. Sign in to Sage Intacct with the test user. 2. Navigate to Applications > Lending Management > Loan account. 3. Open an existing record, click Edit, and change the field(s) relevant to the scenario. 4. Perform the scenario action: Account name mandatory, editable. 5. Click Save or the applicable submit action. 6. Observe the page, messages, saved data, balances, and related records as applicable. | F69: Asterisk + editable | G69: TEST_CASES_Loan_Account.xlsx / TC-LA-102 | H69: TBD | I69: Not Executed | J69: Source section: E. Edit page (IDs: TC-LA-098–130)
A70: LME-LA-062 | B70: Valid Account name change saves | C70: Refer to Common Preconditions above. | D70: Account category: QA Loan Category Account number: LA-QA-001 Account name: Client QA Loan 001 Customer: 1--Power Aerospace Materials Loan type: QA Non-Revolving Interest rate: 5.0000% Origination amount: 10000.00 Origination date: 2026-08-01 | E70: 1. Sign in to Sage Intacct with the test user. 2. Navigate to Applications > Lending Management > Loan account. 3. Open the page or record relevant to the scenario. 4. Perform the scenario action: Valid Account name change saves. 5. Click Save or the applicable submit action. 6. Observe the page, messages, saved data, balances, and related records as applicable. | F70: Change reflected | G70: TEST_CASES_Loan_Account.xlsx / TC-LA-103 | H70: TBD | I70: Not Executed | J70: Source section: E. Edit page (IDs: TC-LA-098–130)
A71: LME-LA-063 | B71: Account name >200 chars rejected on Edit | C71: Refer to Common Preconditions above. | D71: Account category: QA Loan Category Account number: LA-QA-001 Account name: Client QA Loan 001 Customer: 1--Power Aerospace Materials Loan type: QA Non-Revolving Interest rate: 5.0000% Origination amount: 10000.00 Origination date: 2026-08-01 | E71: 1. Sign in to Sage Intacct with the test user. 2. Navigate to Applications > Lending Management > Loan account. 3. Open an existing record, click Edit, and change the field(s) relevant to the scenario. 4. Perform the scenario action: Account name >200 chars rejected on Edit. 5. Click Save or the applicable submit action. 6. Observe the page, messages, saved data, balances, and related records as applicable. | F71: Friendly message (fixed) | G71: TEST_CASES_Loan_Account.xlsx / TC-LA-104 | H71: TBD | I71: Not Executed | J71: Source section: E. Edit page (IDs: TC-LA-098–130)
A72: LME-LA-064 | B72: Empty Account name error on Edit | C72: Refer to Common Preconditions above. | D72: Other required fields: Use the valid values listed below Target field: Blank Account category: QA Loan Category Account number: LA-QA-001 Account name: Client QA Loan 001 Customer: 1--Power Aerospace Materials | E72: 1. Sign in to Sage Intacct with the test user. 2. Navigate to Applications > Lending Management > Loan account. 3. Open an existing record, click Edit, and change the field(s) relevant to the scenario. 4. Perform the scenario action: Empty Account name error on Edit. 5. Click Save or the applicable submit action. 6. Observe the page, messages, saved data, balances, and related records as applicable. | F72: Proper message | G72: TEST_CASES_Loan_Account.xlsx / TC-LA-105 | H72: TBD | I72: Not Executed | J72: Source section: E. Edit page (IDs: TC-LA-098–130)
A73: LME-LA-065 | B73: Customer read-only, drillable | C73: Refer to Common Preconditions above. | D73: Account category: QA Loan Category Account number: LA-QA-001 Account name: Client QA Loan 001 Customer: 1--Power Aerospace Materials Loan type: QA Non-Revolving Interest rate: 5.0000% Origination amount: 10000.00 Origination date: 2026-08-01 | E73: 1. Sign in to Sage Intacct with the test user. 2. Navigate to Applications > Lending Management > Loan account. 3. Open the page or record relevant to the scenario. 4. Perform the scenario action: Customer read-only, drillable. 5. Apply or complete the action where applicable. 6. Observe the page, messages, saved data, balances, and related records as applicable. | F73: Link, no combobox | G73: TEST_CASES_Loan_Account.xlsx / TC-LA-106 | H73: TBD | I73: Not Executed | J73: Source section: E. Edit page (IDs: TC-LA-098–130)
A74: LME-LA-066 | B74: [KNOWN DEFECT] Vendor read-only even unassigned | C74: Refer to Common Preconditions above. | D74: Account category: QA Loan Category Account number: LA-QA-001 Account name: Client QA Loan 001 Customer: 1--Power Aerospace Materials Loan type: QA Non-Revolving Interest rate: 5.0000% Origination amount: 10000.00 Origination date: 2026-08-01 | E74: 1. Sign in to Sage Intacct with the test user. 2. Navigate to Applications > Lending Management > Loan account. 3. Open the page or record relevant to the scenario. 4. Perform the scenario action: [KNOWN DEFECT] Vendor read-only even unassigned. 5. Apply or complete the action where applicable. 6. Observe the page, messages, saved data, balances, and related records as applicable. | F74: Link, no combobox | G74: TEST_CASES_Loan_Account.xlsx / TC-LA-107 | H74: TBD | I74: Not Executed | J74: Source section: E. Edit page (IDs: TC-LA-098–130)
... A81: LME-LA-073 | B81: [KNOWN DEFECT] Term in months absent on Edit | C81: Refer to Common Preconditions above. | D81: Account category: QA Loan Category Account number: LA-QA-001 Account name: Client QA Loan 001 Customer: 1--Power Aerospace Materials Loan type: QA Non-Revolving Interest rate: 5.0000% Origination amount: 10000.00 Origination date: 2026-08-01 | E81: 1. Sign in to Sage Intacct with the test user. 2. Navigate to Applications > Lending Management > Loan account. 3. Open an existing record, click Edit, and change the field(s) relevant to the scenario. 4. Perform the scenario action: [KNOWN DEFECT] Term in months absent on Edit. 5. Click Save or the applicable submit action. 6. Observe the page, messages, saved data, balances, and related records as applicable. | F81: Field missing | G81: TEST_CASES_Loan_Account.xlsx / TC-LA-114 | H81: TBD | I81: Not Executed | J81: Source section: E. Edit page (IDs: TC-LA-098–130)
A82: LME-LA-074 | B82: [KNOWN DEFECT] First payment date absent on Edit | C82: Refer to Common Preconditions above. | E82: 1. Sign in to Sage Intacct with the test user. 2. Navigate to Applications > Lending Management > Loan account. 3. Open an existing record, click Edit, and change the field(s) relevant to the scenario. 4. Perform the scenario action: [KNOWN DEFECT] First payment date absent on Edit. 5. Click Save or the applicable submit action. 6. Observe the page, messages, saved data, balances, and related records as applicable. | F82: Field missing | G82: TEST_CASES_Loan_Account.xlsx / TC-LA-115 | H82: TBD | I82: Not Executed | J82: Source section: E. Edit page (IDs: TC-LA-098–130)
A83: LME-LA-075 | B83: Interest rate mandatory on Edit | C83: Refer to Common Preconditions above. | D83: Other required fields: Use the valid values listed below Target field: Blank Account category: QA Loan Category Account number: LA-QA-001 Account name: Client QA Loan 001 Customer: 1--Power Aerospace Materials | E83: 1. Sign in to Sage Intacct with the test user. 2. Navigate to Applications > Lending Management > Loan account. 3. Open an existing record, click Edit, and change the field(s) relevant to the scenario. 4. Perform the scenario action: Interest rate mandatory on Edit. 5. Click Save or the applicable submit action. 6. Observe the page, messages, saved data, balances, and related records as applicable. | F83: Red asterisk | G83: TEST_CASES_Loan_Account.xlsx / TC-LA-116 | H83: TBD | I83: Not Executed | J83: Source section: E. Edit page (IDs: TC-LA-098–130)
A84: LME-LA-076 | B84: Valid Interest rate update succeeds | C84: Refer to Common Preconditions above. | D84: Account category: QA Loan Category Account number: LA-QA-001 Account name: Client QA Loan 001 Customer: 1--Power Aerospace Materials Loan type: QA Non-Revolving Interest rate: 5.0000% Origination amount: 10000.00 Origination date: 2026-08-01 | E84: 1. Sign in to Sage Intacct with the test user. 2. Navigate to Applications > Lending Management > Loan account. 3. Open an existing record, click Edit, and change the field(s) relevant to the scenario. 4. Perform the scenario action: Valid Interest rate update succeeds. 5. Click Save or the applicable submit action. 6. Observe the page, messages, saved data, balances, and related records as applicable. | F84: Record saved | G84: TEST_CASES_Loan_Account.xlsx / TC-LA-117 | H84: TBD | I84: Not Executed | J84: Source section: E. Edit page (IDs: TC-LA-098–130)
A85: LME-LA-077 | B85: Origination date mandatory on Edit | C85: Refer to Common Preconditions above. | D85: Other required fields: Use the valid values listed below Target field: Blank Account category: QA Loan Category Account number: LA-QA-001 Account name: Client QA Loan 001 Customer: 1--Power Aerospace Materials | E85: 1. Sign in to Sage Intacct with the test user. 2. Navigate to Applications > Lending Management > Loan account. 3. Open an existing record, click Edit, and change the field(s) relevant to the scenario. 4. Perform the scenario action: Origination date mandatory on Edit. 5. Click Save or the applicable submit action. 6. Observe the page, messages, saved data, balances, and related records as applicable. | F85: Red asterisk | G85: TEST_CASES_Loan_Account.xlsx / TC-LA-118 | H85: TBD | I85: Not Executed | J85: Source section: E. Edit page (IDs: TC-LA-098–130)
A86: LME-LA-078 | B86: Origination date can be backdated | C86: Refer to Common Preconditions above. | D86: Account category: QA Loan Category Account number: LA-QA-001 Account name: Client QA Loan 001 Customer: 1--Power Aerospace Materials Loan type: QA Non-Revolving Interest rate: 5.0000% Origination amount: 10000.00 Origination date: 2026-08-01 | E86: 1. Sign in to Sage Intacct with the test user. 2. Navigate to Applications > Lending Management > Loan account. 3. Open the page or record relevant to the scenario. 4. Perform the scenario action: Origination date can be backdated. 5. Apply or complete the action where applicable. 6. Observe the page, messages, saved data, balances, and related records as applicable. | F86: Record saved | G86: TEST_CASES_Loan_Account.xlsx / TC-LA-119 | H86: TBD | I86: Not Executed | J86: Source section: E. Edit page (IDs: TC-LA-098–130)
A87: LME-LA-079 | B87: Amount mandatory numeric on Edit | C87: Refer to Common Preconditions above. | D87: Other required fields: Use the valid values listed below Target field: Blank | E87: 1. Sign in to Sage Intacct with the test user. 2. Navigate to Applications > Lending Management > Loan account. 3. Open an existing record, click Edit, and change the field(s) relevant to the scenario. 4. Perform the scenario action: Amount mandatory numeric on Edit. 5. Click Save or the applicable submit action. 6. Observe the page, messages, saved data, balances, and related records as applicable. | F87: Red asterisk | G87: TEST_CASES_Loan_Account.xlsx / TC-LA-120 | H87: TBD | I87: Not Executed | J87: Source section: E. Edit page (IDs: TC-LA-098–130)
A88: LME-LA-080 | B88: Negative Amount rejected on Edit | C88: Refer to Common Preconditions above. | D88: Amount: -1.00 | E88: 1. Sign in to Sage Intacct with the test user. 2. Navigate to Applications > Lending Management > Loan account. 3. Open an existing record, click Edit, and change the field(s) relevant to the scenario. 4. Perform the scenario action: Negative Amount rejected on Edit. 5. Click Save or the applicable submit action. 6. Observe the page, messages, saved data, balances, and related records as applicable. | F88: Friendly message (fixed) | G88: TEST_CASES_Loan_Account.xlsx / TC-LA-121 | H88: TBD | I88: Not Executed | J88: Source section: E. Edit page (IDs: TC-LA-098–130)
A89: LME-LA-081 | B89: Zero-amount account updatable | C89: Refer to Common Preconditions above. | D89: Amount: 0.00 | E89: 1. Sign in to Sage Intacct with the test user. 2. Navigate to Applications > Lending Management > Loan account. 3. Open the page or record relevant to the scenario. 4. Perform the scenario action: Zero-amount account updatable. 5. Apply or complete the action where applicable. 6. Observe the page, messages, saved data, balances, and related records as applicable. | F89: Amount changes | G89: TEST_CASES_Loan_Account.xlsx / TC-LA-122 | H89: TBD | I89: Not Executed | J89: Source section: E. Edit page (IDs: TC-LA-098–130)
A90: LME-LA-082 | B90: Empty Amount error on Edit | C90: Refer to Common Preconditions above. | D90: Other required fields: Use the valid values listed below Target field: Blank | E90: 1. Sign in to Sage Intacct with the test user. 2. Navigate to Applications > Lending Management > Loan account. 3. Open an existing record, click Edit, and change the field(s) relevant to the scenario. 4. Perform the scenario action: Empty Amount error on Edit. 5. Click Save or the applicable submit action. 6. Observe the page, messages, saved data, balances, and related records as applicable. | F90: Proper message | G90: TEST_CASES_Loan_Account.xlsx / TC-LA-123 | H90: TBD | I90: Not Executed | J90: Source section: E. Edit page (IDs: TC-LA-098–130)
A91: LME-LA-083 | B91: [KNOWN DEFECT] Location no asterisk on Edit | C91: Refer to Common Preconditions above. | D91: Account category: QA Loan Category Account number: LA-QA-001 Account name: Client QA Loan 001 Customer: 1--Power Aerospace Materials Loan type: QA Non-Revolving Interest rate: 5.0000% Origination amount: 10000.00 Origination date: 2026-08-01 | E91: 1. Sign in to Sage Intacct with the test user. 2. Navigate to Applications > Lending Management > Loan account. 3. Open an existing record, click Edit, and change the field(s) relevant to the scenario. 4. Perform the scenario action: [KNOWN DEFECT] Location no asterisk on Edit. 5. Click Save or the applicable submit action. 6. Observe the page, messages, saved data, balances, and related records as applicable. | F91: Missing despite enforcement | G91: TEST_CASES_Loan_Account.xlsx / TC-LA-124 | H91: TBD | I91: Not Executed | J91: Source section: E. Edit page (IDs: TC-LA-098–130)
A92: LME-LA-084 | B92: Valid Location update succeeds | C92: Refer to Common Preconditions above. | D92: Account category: QA Loan Category Account number: LA-QA-001 Account name: Client QA Loan 001 Customer: 1--Power Aerospace Materials Loan type: QA Non-Revolving Interest rate: 5.0000% Origination amount: 10000.00 Origination date: 2026-08-01 | E92: 1. Sign in to Sage Intacct with the test user. 2. Navigate to Applications > Lending Management > Loan account. 3. Open an existing record, click Edit, and change the field(s) relevant to the scenario. 4. Perform the scenario action: Valid Location update succeeds. 5. Click Save or the applicable submit action. 6. Observe the page, messages, saved data, balances, and related records as applicable. | F92: Record saved | G92: TEST_CASES_Loan_Account.xlsx / TC-LA-125 | H92: TBD | I92: Not Executed | J92: Source section: E. Edit page (IDs: TC-LA-098–130)
A93: LME-LA-085 | B93: Save split-button visible on Edit | C93: Refer to Common Preconditions above. | D93: Account category: QA Loan Category Account number: LA-QA-001 Account name: Client QA Loan 001 Customer: 1--Power Aerospace Materials Loan type: QA Non-Revolving Interest rate: 5.0000% Origination amount: 10000.00 Origination date: 2026-08-01 | E93: 1. Sign in to Sage Intacct with the test user. 2. Navigate to Applications > Lending Management > Loan account. 3. Open an existing record, click Edit, and change the field(s) relevant to the scenario. 4. Perform the scenario action: Save split-button visible on Edit. 5. Click Save or the applicable submit action. 6. Observe the page, messages, saved data, balances, and related records as applicable. | F93: Visible | G93: TEST_CASES_Loan_Account.xlsx / TC-LA-126 | H93: TBD | I93: Not Executed | J93: Source section: E. Edit page (IDs: TC-LA-098–130)
A94: LME-LA-086 | B94: Save and close navigates away from Edit | C94: Refer to Common Preconditions above. | D94: Account category: QA Loan Category Account number: LA-QA-001 Account name: Client QA Loan 001 Customer: 1--Power Aerospace Materials Loan type: QA Non-Revolving Interest rate: 5.0000% Origination amount: 10000.00 Origination date: 2026-08-01 | E94: 1. Sign in to Sage Intacct with the test user. 2. Navigate to Applications > Lending Management > Loan account. 3. Open an existing record, click Edit, and change the field(s) relevant to the scenario. 4. Perform the scenario action: Save and close navigates away from Edit. 5. Click Save or the applicable submit action. 6. Observe the page, messages, saved data, balances, and related records as applicable. | F94: Leaves Edit form | G94: TEST_CASES_Loan_Account.xlsx / TC-LA-127 | H94: TBD | I94: Not Executed | J94: Source section: E. Edit page (IDs: TC-LA-098–130)
... A97: LME-LA-089 | B97: Updated values reflect on View page | C97: Refer to Common Preconditions above. | D97: Account category: QA Loan Category Account number: LA-QA-001 Account name: Client QA Loan 001 Customer: 1--Power Aerospace Materials Loan type: QA Non-Revolving Interest rate: 5.0000% Origination amount: 10000.00 Origination date: 2026-08-01 | E97: 1. Sign in to Sage Intacct with the test user. 2. Navigate to Applications > Lending Management > Loan account. 3. Open an existing record, click Edit, and change the field(s) relevant to the scenario. 4. Perform the scenario action: Updated values reflect on View page. 5. Click Save or the applicable submit action. 6. Observe the page, messages, saved data, balances, and related records as applicable. | F97: New values visible | G97: TEST_CASES_Loan_Account.xlsx / TC-LA-130 | H97: TBD | I97: Not Executed | J97: Source section: E. Edit page (IDs: TC-LA-098–130)
A98: VIEW (31 test cases)
A99: LME-LA-090 | B99: Page title is 'Loans' | C99: Refer to Common Preconditions above. | D99: Account category: QA Loan Category Account number: LA-QA-001 User role: Full Access | E99: 1. Sign in to Sage Intacct with the test user. 2. Navigate to Applications > Lending Management > Loan account. 3. Open the page or record relevant to the scenario. 4. Perform the scenario action: Page title is 'Loans'. 5. Apply or complete the action where applicable. 6. Observe the page, messages, saved data, balances, and related records as applicable. | F99: H1 "Loans" visible | G99: TEST_CASES_Loan_Account.xlsx / TC-LA-131 | H99: TBD | I99: Not Executed | J99: Source section: A. List page (IDs: TC-LA-131–145)
A100: LME-LA-091 | B100: Create button visible | C100: Refer to Common Preconditions above. | D100: Account category: QA Loan Category Account number: LA-QA-001 User role: Full Access | E100: 1. Sign in to Sage Intacct with the test user. 2. Navigate to Applications > Lending Management > Loan account. 3. Click Create and populate the form using the stated test data. 4. Perform the scenario action: Create button visible. 5. Click Save or the applicable submit action. 6. Observe the page, messages, saved data, balances, and related records as applicable. | F100: Create action visible/enabled | G100: TEST_CASES_Loan_Account.xlsx / TC-LA-132 | H100: TBD | I100: Not Executed | J100: Source section: A. List page (IDs: TC-LA-131–145)
A101: LME-LA-092 | B101: Grid has required columns | C101: Refer to Common Preconditions above. | D101: Account category: QA Loan Category Account number: LA-QA-001 Account name: Client QA Loan 001 Customer: 1--Power Aerospace Materials Loan type: QA Non-Revolving Interest rate: 5.0000% Origination amount: 10000.00 Origination date: 2026-08-01 | E101: 1. Sign in to Sage Intacct with the test user. 2. Navigate to Applications > Lending Management > Loan account. 3. Open the page or record relevant to the scenario. 4. Perform the scenario action: Grid has required columns. 5. Apply or complete the action where applicable. 6. Observe the page, messages, saved data, balances, and related records as applicable. | F101: Account number, Account name, Account category, Loan type, Customer, Vendor, State, Status shown | G101: TEST_CASES_Loan_Account.xlsx / TC-LA-133 | H101: TBD | I101: Not Executed | J101: Source section: A. List page (IDs: TC-LA-131–145)
A102: LME-LA-093 | B102: Account number filter has Contains placeholder | C102: Refer to Common Preconditions above. | D102: Account category: QA Loan Category Account number: QA | E102: 1. Sign in to Sage Intacct with the test user. 2. Navigate to Applications > Lending Management > Loan account. 3. Enter the stated value in the relevant filter and apply it. 4. Perform the scenario action: Account number filter has Contains placeholder. 5. Apply or complete the action where applicable. 6. Observe the page, messages, saved data, balances, and related records as applicable. | F102: Text input placeholder="Contains" | G102: TEST_CASES_Loan_Account.xlsx / TC-LA-134 | H102: TBD | I102: Not Executed | J102: Source section: A. List page (IDs: TC-LA-131–145)
A103: LME-LA-094 | B103: Account name filter has Contains placeholder | C103: Refer to Common Preconditions above. | D103: Account name: QA Account category: QA Loan Category Account number: LA-QA-001 | E103: 1. Sign in to Sage Intacct with the test user. 2. Navigate to Applications > Lending Management > Loan account. 3. Enter the stated value in the relevant filter and apply it. 4. Perform the scenario action: Account name filter has Contains placeholder. 5. Apply or complete the action where applicable. 6. Observe the page, messages, saved data, balances, and related records as applicable. | F103: Text input placeholder="Contains" | G103: TEST_CASES_Loan_Account.xlsx / TC-LA-135 | H103: TBD | I103: Not Executed | J103: Source section: A. List page (IDs: TC-LA-131–145)
A104: LME-LA-095 | B104: Grid shows at least one record after creation | C104: Refer to Common Preconditions above. | D104: Account category: QA Loan Category Account number: LA-QA-001 Account name: Client QA Loan 001 Customer: 1--Power Aerospace Materials Loan type: QA Non-Revolving Interest rate: 5.0000% Origination amount: 10000.00 Origination date: 2026-08-01 | E104: 1. Sign in to Sage Intacct with the test user. 2. Navigate to Applications > Lending Management > Loan account. 3. Open the page or record relevant to the scenario. 4. Perform the scenario action: Grid shows at least one record after creation. 5. Apply or complete the action where applicable. 6. Observe the page, messages, saved data, balances, and related records as applicable. | F104: ≥1 row matching a freshly-created record | G104: TEST_CASES_Loan_Account.xlsx / TC-LA-136 | H104: TBD | I104: Not Executed | J104: Source section: A. List page (IDs: TC-LA-131–145)
A105: LME-LA-096 | B105: Filtering by an existing Account name shows that record | C105: Refer to Common Preconditions above. | D105: Account name: QA Account category: QA Loan Category Account number: LA-QA-001 | E105: 1. Sign in to Sage Intacct with the test user. 2. Navigate to Applications > Lending Management > Loan account. 3. Enter the stated value in the relevant filter and apply it. 4. Perform the scenario action: Filtering by an existing Account name shows that record. 5. Apply or complete the action where applicable. 6. Observe the page, messages, saved data, balances, and related records as applicable. | F105: Row visible after filter | G105: TEST_CASES_Loan_Account.xlsx / TC-LA-137 | H105: TBD | I105: Not Executed | J105: Source section: A. List page (IDs: TC-LA-131–145)
A106: LME-LA-097 | B106: Pagination shows item count | C106: Refer to Common Preconditions above. | D106: Account category: QA Loan Category Account number: LA-QA-001 Account name: Client QA Loan 001 Customer: 1--Power Aerospace Materials Loan type: QA Non-Revolving Interest rate: 5.0000% Origination amount: 10000.00 Origination date: 2026-08-01 | E106: 1. Sign in to Sage Intacct with the test user. 2. Navigate to Applications > Lending Management > Loan account. 3. Open the page or record relevant to the scenario. 4. Perform the scenario action: Pagination shows item count. 5. Apply or complete the action where applicable. 6. Observe the page, messages, saved data, balances, and related records as applicable. | F106: Footer shows "N items" | G106: TEST_CASES_Loan_Account.xlsx / TC-LA-141 | H106: TBD | I106: Not Executed | J106: Source section: A. List page (IDs: TC-LA-131–145)
A107: LME-LA-098 | B107: Manage view button visible | C107: Refer to Common Preconditions above. | D107: Account category: QA Loan Category Account number: LA-QA-001 User role: Full Access | E107: 1. Sign in to Sage Intacct with the test user. 2. Navigate to Applications > Lending Management > Loan account. 3. Open the page or record relevant to the scenario. 4. Perform the scenario action: Manage view button visible. 5. Apply or complete the action where applicable. 6. Observe the page, messages, saved data, balances, and related records as applicable. | F107: Visible | G107: TEST_CASES_Loan_Account.xlsx / TC-LA-142 | H107: TBD | I107: Not Executed | J107: Source section: A. List page (IDs: TC-LA-131–145)
A108: LME-LA-099 | B108: Filters button visible | C108: Refer to Common Preconditions above. | D108: Filter value: QA Account category: QA Loan Category Account number: LA-QA-001 | E108: 1. Sign in to Sage Intacct with the test user. 2. Navigate to Applications > Lending Management > Loan account. 3. Enter the stated value in the relevant filter and apply it. 4. Perform the scenario action: Filters button visible. 5. Apply or complete the action where applicable. 6. Observe the page, messages, saved data, balances, and related records as applicable. | F108: Visible | G108: TEST_CASES_Loan_Account.xlsx / TC-LA-143 | H108: TBD | I108: Not Executed | J108: Source section: A. List page (IDs: TC-LA-131–145)
A109: LME-LA-100 | B109: List view / Split view toggles present | C109: Refer to Common Preconditions above. | D109: Account category: QA Loan Category Account number: LA-QA-001 Account name: Client QA Loan 001 Customer: 1--Power Aerospace Materials Loan type: QA Non-Revolving Interest rate: 5.0000% Origination amount: 10000.00 Origination date: 2026-08-01 | E109: 1. Sign in to Sage Intacct with the test user. 2. Navigate to Applications > Lending Management > Loan account. 3. Open the page or record relevant to the scenario. 4. Perform the scenario action: List view / Split view toggles present. 5. Apply or complete the action where applicable. 6. Observe the page, messages, saved data, balances, and related records as applicable. | F109: Both visible | G109: TEST_CASES_Loan_Account.xlsx / TC-LA-144 | H109: TBD | I109: Not Executed | J109: Source section: A. List page (IDs: TC-LA-131–145)
A110: LME-LA-101 | B110: Opening a record navigates to its View page | C110: Refer to Common Preconditions above. | D110: Account category: QA Loan Category Account number: LA-QA-001 Account name: Client QA Loan 001 Customer: 1--Power Aerospace Materials Loan type: QA Non-Revolving Interest rate: 5.0000% Origination amount: 10000.00 Origination date: 2026-08-01 | E110: 1. Sign in to Sage Intacct with the test user. 2. Navigate to Applications > Lending Management > Loan account. 3. Open the page or record relevant to the scenario. 4. Perform the scenario action: Opening a record navigates to its View page. 5. Apply or complete the action where applicable. 6. Observe the page, messages, saved data, balances, and related records as applicable. | F110: H1 "Loan: <id>" visible | G110: TEST_CASES_Loan_Account.xlsx / TC-LA-145 | H110: TBD | I110: Not Executed | J110: Source section: A. List page (IDs: TC-LA-131–145)
... A129: LME-LA-120 | B129: View data matches created values | C129: Refer to Common Preconditions above. | D129: Account category: QA Loan Category Account number: LA-QA-001 Account name: Client QA Loan 001 Customer: 1--Power Aerospace Materials Loan type: QA Non-Revolving Interest rate: 5.0000% Origination amount: 10000.00 Origination date: 2026-08-01 | E129: 1. Sign in to Sage Intacct with the test user. 2. Navigate to Applications > Lending Management > Loan account. 3. Click Create and populate the form using the stated test data. 4. Perform the scenario action: View data matches created values. 5. Click Save or the applicable submit action. 6. Observe the page, messages, saved data, balances, and related records as applicable. | F129: Name/Amount/Customer/Vendor match | G129: TEST_CASES_Loan_Account.xlsx / TC-LA-088 | H129: TBD | I129: Not Executed | J129: Source section: C. View page (IDs: TC-LA-071–088)
A130: DELETE (13 test cases)
A131: LME-LA-121 | B131: Bulk Delete disabled by default | C131: Refer to Common Preconditions above. | D131: Account category: QA Loan Category Account number: LA-QA-001 Account name: Client QA Loan 001 Customer: 1--Power Aerospace Materials Loan type: QA Non-Revolving Interest rate: 5.0000% Origination amount: 10000.00 Origination date: 2026-08-01 | E131: 1. Sign in to Sage Intacct with the test user. 2. Navigate to Applications > Lending Management > Loan account. 3. Open or select the disposable record and initiate Delete. 4. Perform the scenario action: Bulk Delete disabled by default. 5. Confirm the action when prompted. 6. Observe the page, messages, saved data, balances, and related records as applicable. | F131: Toolbar Delete disabled | G131: TEST_CASES_Loan_Account.xlsx / TC-LA-138 | H131: TBD | I131: Not Executed | J131: Source section: A. List page (IDs: TC-LA-131–145)
A132: LME-LA-122 | B132: Bulk Delete enabled after selecting a row | C132: Refer to Common Preconditions above. | D132: Account category: QA Loan Category Account number: LA-QA-001 Account name: Client QA Loan 001 Customer: 1--Power Aerospace Materials Loan type: QA Non-Revolving Interest rate: 5.0000% Origination amount: 10000.00 Origination date: 2026-08-01 | E132: 1. Sign in to Sage Intacct with the test user. 2. Navigate to Applications > Lending Management > Loan account. 3. Open or select the disposable record and initiate Delete. 4. Perform the scenario action: Bulk Delete enabled after selecting a row. 5. Confirm the action when prompted. 6. Observe the page, messages, saved data, balances, and related records as applicable. | F132: Toolbar Delete becomes enabled | G132: TEST_CASES_Loan_Account.xlsx / TC-LA-139 | H132: TBD | I132: Not Executed | J132: Source section: A. List page (IDs: TC-LA-131–145)
A133: LME-LA-123 | B133: Select All enables Delete | C133: Refer to Common Preconditions above. | D133: Account category: QA Loan Category Account number: LA-QA-001 Account name: Client QA Loan 001 Customer: 1--Power Aerospace Materials Loan type: QA Non-Revolving Interest rate: 5.0000% Origination amount: 10000.00 Origination date: 2026-08-01 | E133: 1. Sign in to Sage Intacct with the test user. 2. Navigate to Applications > Lending Management > Loan account. 3. Open or select the disposable record and initiate Delete. 4. Perform the scenario action: Select All enables Delete. 5. Confirm the action when prompted. 6. Observe the page, messages, saved data, balances, and related records as applicable. | F133: All checkboxes checked, Delete enabled | G133: TEST_CASES_Loan_Account.xlsx / TC-LA-140 | H133: TBD | I133: Not Executed | J133: Source section: A. List page (IDs: TC-LA-131–145)
A134: LME-LA-124 | B134: Delete button present | C134: Refer to Common Preconditions above. | D134: Account category: QA Loan Category Account number: LA-QA-001 Account name: Client QA Loan 001 Customer: 1--Power Aerospace Materials Loan type: QA Non-Revolving Interest rate: 5.0000% Origination amount: 10000.00 Origination date: 2026-08-01 | E134: 1. Sign in to Sage Intacct with the test user. 2. Navigate to Applications > Lending Management > Loan account. 3. Open or select the disposable record and initiate Delete. 4. Perform the scenario action: Delete button present. 5. Confirm the action when prompted. 6. Observe the page, messages, saved data, balances, and related records as applicable. | F134: Visible | G134: TEST_CASES_Loan_Account.xlsx / TC-LA-086 | H134: TBD | I134: Not Executed | J134: Source section: C. View page (IDs: TC-LA-071–088)
A135: LME-LA-125 | B135: Delete opens confirmation modal | C135: Refer to Common Preconditions above. | D135: Account category: QA Loan Category Account number: LA-QA-001 Account name: Client QA Loan 001 Customer: 1--Power Aerospace Materials Loan type: QA Non-Revolving Interest rate: 5.0000% Origination amount: 10000.00 Origination date: 2026-08-01 | E135: 1. Sign in to Sage Intacct with the test user. 2. Navigate to Applications > Lending Management > Loan account. 3. Open or select the disposable record and initiate Delete. 4. Perform the scenario action: Delete opens confirmation modal. 5. Confirm the action when prompted. 6. Observe the page, messages, saved data, balances, and related records as applicable. | F135: Modal visible | G135: TEST_CASES_Loan_Account.xlsx / TC-LA-089 | H135: TBD | I135: Not Executed | J135: Source section: D. Delete (IDs: TC-LA-089–097)
A136: LME-LA-126 | B136: Modal title is 'Delete loan account' | C136: Refer to Common Preconditions above. | D136: Account category: QA Loan Category Account number: LA-QA-001 Account name: Client QA Loan 001 Customer: 1--Power Aerospace Materials Loan type: QA Non-Revolving Interest rate: 5.0000% Origination amount: 10000.00 Origination date: 2026-08-01 | E136: 1. Sign in to Sage Intacct with the test user. 2. Navigate to Applications > Lending Management > Loan account. 3. Open or select the disposable record and initiate Delete. 4. Perform the scenario action: Modal title is 'Delete loan account'. 5. Confirm the action when prompted. 6. Observe the page, messages, saved data, balances, and related records as applicable. | F136: Exact match | G136: TEST_CASES_Loan_Account.xlsx / TC-LA-090 | H136: TBD | I136: Not Executed | J136: Source section: D. Delete (IDs: TC-LA-089–097)
A137: LME-LA-127 | B137: Modal message properly localised | C137: Refer to Common Preconditions above. | D137: Account category: QA Loan Category Account number: LA-QA-001 Account name: Client QA Loan 001 Customer: 1--Power Aerospace Materials Loan type: QA Non-Revolving Interest rate: 5.0000% Origination amount: 10000.00 Origination date: 2026-08-01 | E137: 1. Sign in to Sage Intacct with the test user. 2. Navigate to Applications > Lending Management > Loan account. 3. Open the page or record relevant to the scenario. 4. Perform the scenario action: Modal message properly localised. 5. Apply or complete the action where applicable. 6. Observe the page, messages, saved data, balances, and related records as applicable. | F137: No raw i18n key, names the record | G137: TEST_CASES_Loan_Account.xlsx / TC-LA-091 | H137: TBD | I137: Not Executed | J137: Source section: D. Delete (IDs: TC-LA-089–097)
A138: LME-LA-128 | B138: Confirm delete removes from list | C138: Refer to Common Preconditions above. | D138: Account category: QA Loan Category Account number: LA-QA-001 Account name: Client QA Loan 001 Customer: 1--Power Aerospace Materials Loan type: QA Non-Revolving Interest rate: 5.0000% Origination amount: 10000.00 Origination date: 2026-08-01 | E138: 1. Sign in to Sage Intacct with the test user. 2. Navigate to Applications > Lending Management > Loan account. 3. Open or select the disposable record and initiate Delete. 4. Perform the scenario action: Confirm delete removes from list. 5. Confirm the action when prompted. 6. Observe the page, messages, saved data, balances, and related records as applicable. | F138: Record gone | G138: TEST_CASES_Loan_Account.xlsx / TC-LA-092 | H138: TBD | I138: Not Executed | J138: Source section: D. Delete (IDs: TC-LA-089–097)
A139: LME-LA-129 | B139: Cancel closes modal without deleting | C139: Refer to Common Preconditions above. | D139: Account category: QA Loan Category Account number: LA-QA-001 Account name: Client QA Loan 001 Customer: 1--Power Aerospace Materials Loan type: QA Non-Revolving Interest rate: 5.0000% Origination amount: 10000.00 Origination date: 2026-08-01 | E139: 1. Sign in to Sage Intacct with the test user. 2. Navigate to Applications > Lending Management > Loan account. 3. Open the page or record relevant to the scenario. 4. Perform the scenario action: Cancel closes modal without deleting. 5. Apply or complete the action where applicable. 6. Observe the page, messages, saved data, balances, and related records as applicable. | F139: Record still present | G139: TEST_CASES_Loan_Account.xlsx / TC-LA-093 | H139: TBD | I139: Not Executed | J139: Source section: D. Delete (IDs: TC-LA-089–097)
A140: LME-LA-130 | B140: Delete redirects to Loans list | C140: Refer to Common Preconditions above. | D140: Account category: QA Loan Category Account number: LA-QA-001 Account name: Client QA Loan 001 Customer: 1--Power Aerospace Materials Loan type: QA Non-Revolving Interest rate: 5.0000% Origination amount: 10000.00 Origination date: 2026-08-01 | E140: 1. Sign in to Sage Intacct with the test user. 2. Navigate to Applications > Lending Management > Loan account. 3. Open or select the disposable record and initiate Delete. 4. Perform the scenario action: Delete redirects to Loans list. 5. Confirm the action when prompted. 6. Observe the page, messages, saved data, balances, and related records as applicable. | F140: List heading visible | G140: TEST_CASES_Loan_Account.xlsx / TC-LA-094 | H140: TBD | I140: Not Executed | J140: Source section: D. Delete (IDs: TC-LA-089–097)
A141: LME-LA-131 | B141: Unassigned record deletes cleanly | C141: Refer to Common Preconditions above. | D141: Account category: QA Loan Category Account number: LA-QA-001 Account name: Client QA Loan 001 Customer: 1--Power Aerospace Materials Loan type: QA Non-Revolving Interest rate: 5.0000% Origination amount: 10000.00 Origination date: 2026-08-01 | E141: 1. Sign in to Sage Intacct with the test user. 2. Navigate to Applications > Lending Management > Loan account. 3. Open or select the disposable record and initiate Delete. 4. Perform the scenario action: Unassigned record deletes cleanly. 5. Confirm the action when prompted. 6. Observe the page, messages, saved data, balances, and related records as applicable. | F141: No conflict wording | G141: TEST_CASES_Loan_Account.xlsx / TC-LA-095 | H141: TBD | I141: Not Executed | J141: Source section: D. Delete (IDs: TC-LA-089–097)
A142: LME-LA-132 | B142: X icon closes modal without deleting | C142: Refer to Common Preconditions above. | D142: Account category: QA Loan Category Account number: LA-QA-001 Account name: Client QA Loan 001 Customer: 1--Power Aerospace Materials Loan type: QA Non-Revolving Interest rate: 5.0000% Origination amount: 10000.00 Origination date: 2026-08-01 | E142: 1. Sign in to Sage Intacct with the test user. 2. Navigate to Applications > Lending Management > Loan account. 3. Open the page or record relevant to the scenario. 4. Perform the scenario action: X icon closes modal without deleting. 5. Apply or complete the action where applicable. 6. Observe the page, messages, saved data, balances, and related records as applicable. | F142: Record still present | G142: TEST_CASES_Loan_Account.xlsx / TC-LA-096 | H142: TBD | I142: Not Executed | J142: Source section: D. Delete (IDs: TC-LA-089–097)
A143: LME-LA-133 | B143: Amortization schedule row count matches Term | C143: Refer to Common Preconditions above. | D143: Account category: QA Loan Category Account number: LA-QA-001 Account name: Client QA Loan 001 Customer: 1--Power Aerospace Materials Loan type: QA Non-Revolving Interest rate: 5.0000% Origination amount: 10000.00 Origination date: 2026-08-01 | E143: 1. Sign in to Sage Intacct with the test user. 2. Navigate to Applications > Lending Management > Loan account. 3. Open the page or record relevant to the scenario. 4. Perform the scenario action: Amortization schedule row count matches Term. 5. Apply or complete the action where applicable. 6. Observe the page, messages, saved data, balances, and related records as applicable. | F143: 12 rows for Term=12 (skips if the tab isn't present on this record) | G143: TEST_CASES_Loan_Account.xlsx / TC-LA-097 | H143: TBD | I143: Not Executed | J143: Source section: D. Delete (IDs: TC-LA-089–097)

Sheet LME Loan Type
A1: Lending - Loan Type
A2: Common Preconditions | C2: 1. User is signed in to Sage Intacct. 2. The correct Lending Management or Depository Management entity is selected. 3. The module is enabled for the company. 4. The user has the permission required for the scenario. 5. Required master/configuration records are active and available.
A4: Navigation: Applications > Lending Management > Loan type | Client baseline | 67 test cases | Updated 2026-08-27
A6: Test Case ID | B6: Test Scenario | C6: Preconditions | D6: Test Data | E6: Test Steps | F6: Expected Result | G6: Requirement/Jira Reference | H6: IS Automated | I6: Status | J6: Comments
A7: CREATE (21 test cases)
A8: LME-LT-001 | B8: Loan type name field present | C8: Refer to Common Preconditions above. | D8: Name: QA Non-Revolving Loan Type Type: Non-revolving Interest calculation method: Simple Description: Client QA loan type | E8: 1. Sign in to Sage Intacct with the test user. 2. Navigate to Applications > Lending Management > Loan type. 3. Open the page or record relevant to the scenario. 4. Perform the scenario action: Loan type name field present. 5. Apply or complete the action where applicable. 6. Observe the page, messages, saved data, balances, and related records as applicable. | F8: Text input visible | G8: TEST_CASES_Loan_Type.xlsx / TC-LT-028 | H8: TBD | I8: Not Executed | J8: Source section: B. Create (IDs: TC-LT-028–046, TC-LT-057–066 new)
A9: LME-LT-002 | B9: Empty name blocked | C9: Refer to Common Preconditions above. | D9: Other required fields: Use the valid values listed below Target field: Blank Name: QA Non-Revolving Loan Type Type: Non-revolving Interest calculation method: Simple Description: Client QA loan type | E9: 1. Sign in to Sage Intacct with the test user. 2. Navigate to Applications > Lending Management > Loan type. 3. Open the page or record relevant to the scenario. 4. Perform the scenario action: Empty name blocked. 5. Apply or complete the action where applicable. 6. Observe the page, messages, saved data, balances, and related records as applicable. | F9: Validation error / stays on Create | G9: TEST_CASES_Loan_Type.xlsx / TC-LT-029 | H9: TBD | I9: Not Executed | J9: Source section: B. Create (IDs: TC-LT-028–046, TC-LT-057–066 new)
A10: LME-LT-003 | B10: Description optional | C10: Refer to Common Preconditions above. | D10: Name: QA Non-Revolving Loan Type Type: Non-revolving Interest calculation method: Simple Description: Client QA test text | E10: 1. Sign in to Sage Intacct with the test user. 2. Navigate to Applications > Lending Management > Loan type. 3. Open the page or record relevant to the scenario. 4. Perform the scenario action: Description optional. 5. Apply or complete the action where applicable. 6. Observe the page, messages, saved data, balances, and related records as applicable. | F10: No asterisk on label | G10: TEST_CASES_Loan_Type.xlsx / TC-LT-030 | H10: TBD | I10: Not Executed | J10: Source section: B. Create (IDs: TC-LT-028–046, TC-LT-057–066 new)
A11: LME-LT-004 | B11: Type defaults visible | C11: Refer to Common Preconditions above. | D11: Name: QA Non-Revolving Loan Type Type: Non-revolving Interest calculation method: Simple Description: Client QA loan type | E11: 1. Sign in to Sage Intacct with the test user. 2. Navigate to Applications > Lending Management > Loan type. 3. Open the page or record relevant to the scenario. 4. Perform the scenario action: Type defaults visible. 5. Apply or complete the action where applicable. 6. Observe the page, messages, saved data, balances, and related records as applicable. | F11: Revolving/Non-revolving radios visible | G11: TEST_CASES_Loan_Type.xlsx / TC-LT-031 | H11: TBD | I11: Not Executed | J11: Source section: B. Create (IDs: TC-LT-028–046, TC-LT-057–066 new)
A12: LME-LT-005 | B12: Interest type options | C12: Refer to Common Preconditions above. | D12: Name: QA Non-Revolving Loan Type Type: Non-revolving Interest calculation method: Simple Description: Client QA loan type | E12: 1. Sign in to Sage Intacct with the test user. 2. Navigate to Applications > Lending Management > Loan type. 3. Open the page or record relevant to the scenario. 4. Perform the scenario action: Interest type options. 5. Apply or complete the action where applicable. 6. Observe the page, messages, saved data, balances, and related records as applicable. | F12: 'Simple' and 'Compound' both listed | G12: TEST_CASES_Loan_Type.xlsx / TC-LT-032 | H12: TBD | I12: Not Executed | J12: Source section: B. Create (IDs: TC-LT-028–046, TC-LT-057–066 new)
A13: LME-LT-006 | B13: Interest calculation method required | C13: Refer to Common Preconditions above. | D13: Other required fields: Use the valid values listed below Target field: Blank Name: QA Non-Revolving Loan Type Type: Non-revolving Interest calculation method: Simple Description: Client QA loan type | E13: 1. Sign in to Sage Intacct with the test user. 2. Navigate to Applications > Lending Management > Loan type. 3. Open the page or record relevant to the scenario. 4. Perform the scenario action: Interest calculation method required. 5. Apply or complete the action where applicable. 6. Observe the page, messages, saved data, balances, and related records as applicable. | F13: Appears (conditionally, after Type selected) with `*` | G13: TEST_CASES_Loan_Type.xlsx / TC-LT-033 | H13: TBD | I13: Not Executed | J13: Source section: B. Create (IDs: TC-LT-028–046, TC-LT-057–066 new)
A14: LME-LT-007 | B14: Interest calculation method options (Revolving) | C14: Refer to Common Preconditions above. | D14: Name: QA Non-Revolving Loan Type Type: Non-revolving Interest calculation method: Simple Description: Client QA loan type | E14: 1. Sign in to Sage Intacct with the test user. 2. Navigate to Applications > Lending Management > Loan type. 3. Open the page or record relevant to the scenario. 4. Perform the scenario action: Interest calculation method options (Revolving). 5. Apply or complete the action where applicable. 6. Observe the page, messages, saved data, balances, and related records as applicable. | F14: 'Actual/365' and 'Actual/360' listed | G14: TEST_CASES_Loan_Type.xlsx / TC-LT-034 | H14: TBD | I14: Not Executed | J14: Source section: B. Create (IDs: TC-LT-028–046, TC-LT-057–066 new)
A15: LME-LT-008 | B15: **[new]** Interest calculation method options (Non-revolving) | C15: Refer to Common Preconditions above. | D15: Name: QA Non-Revolving Loan Type Type: Non-revolving Interest calculation method: Simple Description: Client QA loan type | E15: 1. Sign in to Sage Intacct with the test user. 2. Navigate to Applications > Lending Management > Loan type. 3. Open the page or record relevant to the scenario. 4. Perform the scenario action: **[new]** Interest calculation method options (Non-revolving). 5. Apply or complete the action where applicable. 6. Observe the page, messages, saved data, balances, and related records as applicable. | F15: 'Actual/365', 'Actual/360', **and '30/360'** all listed (superset of Revolving's two) | G15: TEST_CASES_Loan_Type.xlsx / TC-LT-034b | H15: TBD | I15: Not Executed | J15: Source section: B. Create (IDs: TC-LT-028–046, TC-LT-057–066 new)
A16: LME-LT-009 | B16: Status defaults to Active | C16: Refer to Common Preconditions above. | D16: Name: QA Non-Revolving Loan Type Type: Non-revolving Interest calculation method: Simple Description: Client QA loan type | E16: 1. Sign in to Sage Intacct with the test user. 2. Navigate to Applications > Lending Management > Loan type. 3. Open the page or record relevant to the scenario. 4. Perform the scenario action: Status defaults to Active. 5. Apply or complete the action where applicable. 6. Observe the page, messages, saved data, balances, and related records as applicable. | F16: Confirmed on View after save (no Status field on Create itself) | G16: TEST_CASES_Loan_Type.xlsx / TC-LT-035 | H16: TBD | I16: Not Executed | J16: Source section: B. Create (IDs: TC-LT-028–046, TC-LT-057–066 new)
A17: LME-LT-010 | B17: Order Entry transaction definition required | C17: Refer to Common Preconditions above. | D17: Other required fields: Use the valid values listed below Target field: Blank Name: QA Non-Revolving Loan Type Type: Non-revolving Interest calculation method: Simple Description: Client QA loan type | E17: 1. Sign in to Sage Intacct with the test user. 2. Navigate to Applications > Lending Management > Loan type. 3. Open the page or record relevant to the scenario. 4. Perform the scenario action: Order Entry transaction definition required. 5. Apply or complete the action where applicable. 6. Observe the page, messages, saved data, balances, and related records as applicable. | F17: `*` next to label | G17: TEST_CASES_Loan_Type.xlsx / TC-LT-036 | H17: TBD | I17: Not Executed | J17: Source section: B. Create (IDs: TC-LT-028–046, TC-LT-057–066 new)
A18: LME-LT-011 | B18: Item for loan principal posting required | C18: Refer to Common Preconditions above. | D18: Other required fields: Use the valid values listed below Target field: Blank Name: QA Non-Revolving Loan Type Type: Non-revolving Interest calculation method: Simple Description: Client QA loan type | E18: 1. Sign in to Sage Intacct with the test user. 2. Navigate to Applications > Lending Management > Loan type. 3. Open the page or record relevant to the scenario. 4. Perform the scenario action: Item for loan principal posting required. 5. Apply or complete the action where applicable. 6. Observe the page, messages, saved data, balances, and related records as applicable. | F18: `*` next to label | G18: TEST_CASES_Loan_Type.xlsx / TC-LT-037 | H18: TBD | I18: Not Executed | J18: Source section: B. Create (IDs: TC-LT-028–046, TC-LT-057–066 new)
A19: LME-LT-012 | B19: Item for loan interest posting required | C19: Refer to Common Preconditions above. | D19: Other required fields: Use the valid values listed below Target field: Blank Name: QA Non-Revolving Loan Type Type: Non-revolving Interest calculation method: Simple Description: Client QA loan type | E19: 1. Sign in to Sage Intacct with the test user. 2. Navigate to Applications > Lending Management > Loan type. 3. Open the page or record relevant to the scenario. 4. Perform the scenario action: Item for loan interest posting required. 5. Apply or complete the action where applicable. 6. Observe the page, messages, saved data, balances, and related records as applicable. | F19: `*` next to label | G19: TEST_CASES_Loan_Type.xlsx / TC-LT-038 | H19: TBD | I19: Not Executed | J19: Source section: B. Create (IDs: TC-LT-028–046, TC-LT-057–066 new)
... A28: LME-LT-021 | B28: **[new]** Stale Fee type value blocks save after switching row Type away from Fee | C28: Refer to Common Preconditions above. | D28: Name: QA Non-Revolving Loan Type Type: Non-revolving Interest calculation method: Simple Description: Client QA loan type | E28: 1. Sign in to Sage Intacct with the test user. 2. Navigate to Applications > Lending Management > Loan type. 3. Open the page or record relevant to the scenario. 4. Perform the scenario action: **[new]** Stale Fee type value blocks save after switching row Type away from Fee. 5. Click Save or the applicable submit action. 6. Observe the page, messages, saved data, balances, and related records as applicable. | F28: Setting a row's Type to Fee + a Fee type value, then switching Type to Interest/Principal without clearing Fee type, and saving, shows: "PRINCIPAL_OR_INTEREST_SHOULD_NOT_HAVE_ANY_FEE_SELECTED" | G28: TEST_CASES_Loan_Type.xlsx / TC-LT-066 | H28: TBD | I28: Not Executed | J28: Source section: B. Create (IDs: TC-LT-028–046, TC-LT-057–066 new)
A29: EDIT (11 test cases)
A30: LME-LT-022 | B30: Edit button visible | C30: Refer to Common Preconditions above. | D30: Name: QA Non-Revolving Loan Type Type: Non-revolving Interest calculation method: Simple Description: Client QA loan type | E30: 1. Sign in to Sage Intacct with the test user. 2. Navigate to Applications > Lending Management > Loan type. 3. Open an existing record, click Edit, and change the field(s) relevant to the scenario. 4. Perform the scenario action: Edit button visible. 5. Click Save or the applicable submit action. 6. Observe the page, messages, saved data, balances, and related records as applicable. | F30: Visible (directly in header) | G30: TEST_CASES_Loan_Type.xlsx / TC-LT-023 | H30: TBD | I30: Not Executed | J30: Source section: C. View (IDs: TC-LT-015–027)
A31: LME-LT-023 | B31: Edit form pre-populates name | C31: Refer to Common Preconditions above. | D31: Name: QA Non-Revolving Loan Type Type: Non-revolving Interest calculation method: Simple Description: Client QA loan type | E31: 1. Sign in to Sage Intacct with the test user. 2. Navigate to Applications > Lending Management > Loan type. 3. Open an existing record, click Edit, and change the field(s) relevant to the scenario. 4. Perform the scenario action: Edit form pre-populates name. 5. Click Save or the applicable submit action. 6. Observe the page, messages, saved data, balances, and related records as applicable. | F31: Pre-filled | G31: TEST_CASES_Loan_Type.xlsx / TC-LT-047 | H31: TBD | I31: Not Executed | J31: Source section: D. Edit (IDs: TC-LT-047–056)
A32: LME-LT-024 | B32: Edit form pre-populates Description | C32: Refer to Common Preconditions above. | D32: Name: QA Non-Revolving Loan Type Type: Non-revolving Interest calculation method: Simple Description: Client QA test text | E32: 1. Sign in to Sage Intacct with the test user. 2. Navigate to Applications > Lending Management > Loan type. 3. Open an existing record, click Edit, and change the field(s) relevant to the scenario. 4. Perform the scenario action: Edit form pre-populates Description. 5. Click Save or the applicable submit action. 6. Observe the page, messages, saved data, balances, and related records as applicable. | F32: Pre-filled | G32: TEST_CASES_Loan_Type.xlsx / TC-LT-048 | H32: TBD | I32: Not Executed | J32: Source section: D. Edit (IDs: TC-LT-047–056)
A33: LME-LT-025 | B33: Type is read-only in Edit | C33: Refer to Common Preconditions above. | D33: Name: QA Non-Revolving Loan Type Type: Non-revolving Interest calculation method: Simple Description: Client QA loan type | E33: 1. Sign in to Sage Intacct with the test user. 2. Navigate to Applications > Lending Management > Loan type. 3. Open an existing record, click Edit, and change the field(s) relevant to the scenario. 4. Perform the scenario action: Type is read-only in Edit. 5. Click Save or the applicable submit action. 6. Observe the page, messages, saved data, balances, and related records as applicable. | F33: Plain text, not editable dropdown/radio | G33: TEST_CASES_Loan_Type.xlsx / TC-LT-049 | H33: TBD | I33: Not Executed | J33: Source section: D. Edit (IDs: TC-LT-047–056)
A34: LME-LT-026 | B34: Edit form pre-populates Interest type | C34: Refer to Common Preconditions above. | D34: Name: QA Non-Revolving Loan Type Type: Non-revolving Interest calculation method: Simple Description: Client QA loan type | E34: 1. Sign in to Sage Intacct with the test user. 2. Navigate to Applications > Lending Management > Loan type. 3. Open an existing record, click Edit, and change the field(s) relevant to the scenario. 4. Perform the scenario action: Edit form pre-populates Interest type. 5. Click Save or the applicable submit action. 6. Observe the page, messages, saved data, balances, and related records as applicable. | F34: Shown | G34: TEST_CASES_Loan_Type.xlsx / TC-LT-050 | H34: TBD | I34: Not Executed | J34: Source section: D. Edit (IDs: TC-LT-047–056)
A35: LME-LT-027 | B35: Edit form pre-populates Interest calculation method | C35: Refer to Common Preconditions above. | D35: Name: QA Non-Revolving Loan Type Type: Non-revolving Interest calculation method: Simple Description: Client QA loan type | E35: 1. Sign in to Sage Intacct with the test user. 2. Navigate to Applications > Lending Management > Loan type. 3. Open an existing record, click Edit, and change the field(s) relevant to the scenario. 4. Perform the scenario action: Edit form pre-populates Interest calculation method. 5. Click Save or the applicable submit action. 6. Observe the page, messages, saved data, balances, and related records as applicable. | F35: Shown | G35: TEST_CASES_Loan_Type.xlsx / TC-LT-051 | H35: TBD | I35: Not Executed | J35: Source section: D. Edit (IDs: TC-LT-047–056)
A36: LME-LT-028 | B36: Edit form pre-populates Status | C36: Refer to Common Preconditions above. | D36: Name: QA Non-Revolving Loan Type Type: Non-revolving Interest calculation method: Simple Description: Client QA loan type | E36: 1. Sign in to Sage Intacct with the test user. 2. Navigate to Applications > Lending Management > Loan type. 3. Open an existing record, click Edit, and change the field(s) relevant to the scenario. 4. Perform the scenario action: Edit form pre-populates Status. 5. Click Save or the applicable submit action. 6. Observe the page, messages, saved data, balances, and related records as applicable. | F36: Shown ('Active') | G36: TEST_CASES_Loan_Type.xlsx / TC-LT-052 | H36: TBD | I36: Not Executed | J36: Source section: D. Edit (IDs: TC-LT-047–056)
A37: LME-LT-029 | B37: Clearing name and saving shows validation error | C37: Refer to Common Preconditions above. | D37: Name: QA Non-Revolving Loan Type Type: Non-revolving Interest calculation method: Simple Description: Client QA loan type | E37: 1. Sign in to Sage Intacct with the test user. 2. Navigate to Applications > Lending Management > Loan type. 3. Open the page or record relevant to the scenario. 4. Perform the scenario action: Clearing name and saving shows validation error. 5. Apply or complete the action where applicable. 6. Observe the page, messages, saved data, balances, and related records as applicable. | F37: Stays on Edit | G37: TEST_CASES_Loan_Type.xlsx / TC-LT-053 | H37: TBD | I37: Not Executed | J37: Source section: D. Edit (IDs: TC-LT-047–056)
A38: LME-LT-030 | B38: Cancelling edit does not save changes | C38: Refer to Common Preconditions above. | D38: Name: QA Non-Revolving Loan Type Type: Non-revolving Interest calculation method: Simple Description: Client QA loan type | E38: 1. Sign in to Sage Intacct with the test user. 2. Navigate to Applications > Lending Management > Loan type. 3. Open an existing record, click Edit, and change the field(s) relevant to the scenario. 4. Perform the scenario action: Cancelling edit does not save changes. 5. Click Save or the applicable submit action. 6. Observe the page, messages, saved data, balances, and related records as applicable. | F38: Back on View, original name intact | G38: TEST_CASES_Loan_Type.xlsx / TC-LT-054 | H38: TBD | I38: Not Executed | J38: Source section: D. Edit (IDs: TC-LT-047–056)
A39: LME-LT-031 | B39: Payment priority rows pre-populated in Edit | C39: Refer to Common Preconditions above. | E39: 1. Sign in to Sage Intacct with the test user. 2. Navigate to Applications > Lending Management > Loan type. 3. Open an existing record, click Edit, and change the field(s) relevant to the scenario. 4. Perform the scenario action: Payment priority rows pre-populated in Edit. 5. Click Save or the applicable submit action. 6. Observe the page, messages, saved data, balances, and related records as applicable. | F39: Existing rows shown | G39: TEST_CASES_Loan_Type.xlsx / TC-LT-055 | H39: TBD | I39: Not Executed | J39: Source section: D. Edit (IDs: TC-LT-047–056)
A40: LME-LT-032 | B40: Save button (with dropdown) visible | C40: Refer to Common Preconditions above. | D40: Name: QA Non-Revolving Loan Type Type: Non-revolving Interest calculation method: Simple Description: Client QA loan type | E40: 1. Sign in to Sage Intacct with the test user. 2. Navigate to Applications > Lending Management > Loan type. 3. Open the page or record relevant to the scenario. 4. Perform the scenario action: Save button (with dropdown) visible. 5. Click Save or the applicable submit action. 6. Observe the page, messages, saved data, balances, and related records as applicable. | F40: Visible, nested under header More actions | G40: TEST_CASES_Loan_Type.xlsx / TC-LT-056 | H40: TBD | I40: Not Executed | J40: Source section: D. Edit (IDs: TC-LT-047–056)
A41: VIEW (25 test cases)
A42: LME-LT-033 | B42: Page title is 'Loan types' | C42: Refer to Common Preconditions above. | D42: Name: QA Non-Revolving Loan Type Type: Non-revolving User role: Full Access | E42: 1. Sign in to Sage Intacct with the test user. 2. Navigate to Applications > Lending Management > Loan type. 3. Open the page or record relevant to the scenario. 4. Perform the scenario action: Page title is 'Loan types'. 5. Apply or complete the action where applicable. 6. Observe the page, messages, saved data, balances, and related records as applicable. | F42: H1 "Loan types" visible | G42: TEST_CASES_Loan_Type.xlsx / TC-LT-001 | H42: TBD | I42: Not Executed | J42: Source section: A. List page (IDs: TC-LT-001–014)
A43: LME-LT-034 | B43: Create button visible | C43: Refer to Common Preconditions above. | D43: Name: QA Non-Revolving Loan Type Type: Non-revolving User role: Full Access | E43: 1. Sign in to Sage Intacct with the test user. 2. Navigate to Applications > Lending Management > Loan type. 3. Click Create and populate the form using the stated test data. 4. Perform the scenario action: Create button visible. 5. Click Save or the applicable submit action. 6. Observe the page, messages, saved data, balances, and related records as applicable. | F43: Create action visible/enabled | G43: TEST_CASES_Loan_Type.xlsx / TC-LT-002 | H43: TBD | I43: Not Executed | J43: Source section: A. List page (IDs: TC-LT-001–014)
A44: LME-LT-035 | B44: Grid has required columns | C44: Refer to Common Preconditions above. | D44: Name: QA Non-Revolving Loan Type Type: Non-revolving Interest calculation method: Simple Description: Client QA loan type | E44: 1. Sign in to Sage Intacct with the test user. 2. Navigate to Applications > Lending Management > Loan type. 3. Open the page or record relevant to the scenario. 4. Perform the scenario action: Grid has required columns. 5. Apply or complete the action where applicable. 6. Observe the page, messages, saved data, balances, and related records as applicable. | F44: Loan type, Interest calculation method, Description columns shown | G44: TEST_CASES_Loan_Type.xlsx / TC-LT-003 | H44: TBD | I44: Not Executed | J44: Source section: A. List page (IDs: TC-LT-001–014)
A45: LME-LT-036 | B45: Name filter has Contains placeholder | C45: Refer to Common Preconditions above. | D45: Filter value: QA Name: QA Non-Revolving Loan Type Type: Non-revolving | E45: 1. Sign in to Sage Intacct with the test user. 2. Navigate to Applications > Lending Management > Loan type. 3. Enter the stated value in the relevant filter and apply it. 4. Perform the scenario action: Name filter has Contains placeholder. 5. Apply or complete the action where applicable. 6. Observe the page, messages, saved data, balances, and related records as applicable. | F45: Text input `placeholder="Contains"` for Loan type column | G45: TEST_CASES_Loan_Type.xlsx / TC-LT-004 | H45: TBD | I45: Not Executed | J45: Source section: A. List page (IDs: TC-LT-001–014)
A46: LME-LT-037 | B46: Type filter is a dropdown | C46: Refer to Common Preconditions above. | D46: Filter value: QA Name: QA Non-Revolving Loan Type Type: Non-revolving | E46: 1. Sign in to Sage Intacct with the test user. 2. Navigate to Applications > Lending Management > Loan type. 3. Enter the stated value in the relevant filter and apply it. 4. Perform the scenario action: Type filter is a dropdown. 5. Apply or complete the action where applicable. 6. Observe the page, messages, saved data, balances, and related records as applicable. | F46: Combobox shown for the Revolving/Non-revolving filter column | G46: TEST_CASES_Loan_Type.xlsx / TC-LT-005 | H46: TBD | I46: Not Executed | J46: Source section: A. List page (IDs: TC-LT-001–014)
A47: LME-LT-038 | B47: Grid shows at least one record | C47: Refer to Common Preconditions above. | D47: Name: QA Non-Revolving Loan Type Type: Non-revolving Interest calculation method: Simple Description: Client QA loan type | E47: 1. Sign in to Sage Intacct with the test user. 2. Navigate to Applications > Lending Management > Loan type. 3. Open the page or record relevant to the scenario. 4. Perform the scenario action: Grid shows at least one record. 5. Apply or complete the action where applicable. 6. Observe the page, messages, saved data, balances, and related records as applicable. | F47: ≥1 row in the grid | G47: TEST_CASES_Loan_Type.xlsx / TC-LT-006 | H47: TBD | I47: Not Executed | J47: Source section: A. List page (IDs: TC-LT-001–014)
A48: LME-LT-039 | B48: Filtering by name returns matching records | C48: Refer to Common Preconditions above. | D48: Filter value: QA Name: QA Non-Revolving Loan Type Type: Non-revolving | E48: 1. Sign in to Sage Intacct with the test user. 2. Navigate to Applications > Lending Management > Loan type. 3. Enter the stated value in the relevant filter and apply it. 4. Perform the scenario action: Filtering by name returns matching records. 5. Apply or complete the action where applicable. 6. Observe the page, messages, saved data, balances, and related records as applicable. | F48: Only matching rows remain | G48: TEST_CASES_Loan_Type.xlsx / TC-LT-007 | H48: TBD | I48: Not Executed | J48: Source section: A. List page (IDs: TC-LT-001–014)
A49: LME-LT-040 | B49: Pagination shows item count | C49: Refer to Common Preconditions above. | D49: Name: QA Non-Revolving Loan Type Type: Non-revolving Interest calculation method: Simple Description: Client QA loan type | E49: 1. Sign in to Sage Intacct with the test user. 2. Navigate to Applications > Lending Management > Loan type. 3. Open the page or record relevant to the scenario. 4. Perform the scenario action: Pagination shows item count. 5. Apply or complete the action where applicable. 6. Observe the page, messages, saved data, balances, and related records as applicable. | F49: Footer shows "N items" | G49: TEST_CASES_Loan_Type.xlsx / TC-LT-011 | H49: TBD | I49: Not Executed | J49: Source section: A. List page (IDs: TC-LT-001–014)
A50: LME-LT-041 | B50: Manage view button visible | C50: Refer to Common Preconditions above. | D50: Name: QA Non-Revolving Loan Type Type: Non-revolving User role: Full Access | E50: 1. Sign in to Sage Intacct with the test user. 2. Navigate to Applications > Lending Management > Loan type. 3. Open the page or record relevant to the scenario. 4. Perform the scenario action: Manage view button visible. 5. Apply or complete the action where applicable. 6. Observe the page, messages, saved data, balances, and related records as applicable. | F50: Visible | G50: TEST_CASES_Loan_Type.xlsx / TC-LT-012 | H50: TBD | I50: Not Executed | J50: Source section: A. List page (IDs: TC-LT-001–014)
A51: LME-LT-042 | B51: Filters button visible | C51: Refer to Common Preconditions above. | D51: Filter value: QA Name: QA Non-Revolving Loan Type Type: Non-revolving | E51: 1. Sign in to Sage Intacct with the test user. 2. Navigate to Applications > Lending Management > Loan type. 3. Enter the stated value in the relevant filter and apply it. 4. Perform the scenario action: Filters button visible. 5. Apply or complete the action where applicable. 6. Observe the page, messages, saved data, balances, and related records as applicable. | F51: Visible | G51: TEST_CASES_Loan_Type.xlsx / TC-LT-013 | H51: TBD | I51: Not Executed | J51: Source section: A. List page (IDs: TC-LT-001–014)
A52: LME-LT-043 | B52: List view / Split view toggles present | C52: Refer to Common Preconditions above. | D52: Name: QA Non-Revolving Loan Type Type: Non-revolving Interest calculation method: Simple Description: Client QA loan type | E52: 1. Sign in to Sage Intacct with the test user. 2. Navigate to Applications > Lending Management > Loan type. 3. Open the page or record relevant to the scenario. 4. Perform the scenario action: List view / Split view toggles present. 5. Apply or complete the action where applicable. 6. Observe the page, messages, saved data, balances, and related records as applicable. | F52: Both visible | G52: TEST_CASES_Loan_Type.xlsx / TC-LT-014 | H52: TBD | I52: Not Executed | J52: Source section: A. List page (IDs: TC-LT-001–014)
A53: LME-LT-044 | B53: Payment priority grid columns | C53: Refer to Common Preconditions above. | D53: Name: QA Non-Revolving Loan Type Type: Non-revolving User role: Full Access | E53: 1. Sign in to Sage Intacct with the test user. 2. Navigate to Applications > Lending Management > Loan type. 3. Open the page or record relevant to the scenario. 4. Perform the scenario action: Payment priority grid columns. 5. Apply or complete the action where applicable. 6. Observe the page, messages, saved data, balances, and related records as applicable. | F53: Type, Fee type visible (+ Sort order) | G53: TEST_CASES_Loan_Type.xlsx / TC-LT-040 | H53: TBD | I53: Not Executed | J53: Source section: B. Create (IDs: TC-LT-028–046, TC-LT-057–066 new)
... A66: LME-LT-057 | B66: Back arrow navigates to list | C66: Refer to Common Preconditions above. | D66: Name: QA Non-Revolving Loan Type Type: Non-revolving Interest calculation method: Simple Description: Client QA loan type | E66: 1. Sign in to Sage Intacct with the test user. 2. Navigate to Applications > Lending Management > Loan type. 3. Open the page or record relevant to the scenario. 4. Perform the scenario action: Back arrow navigates to list. 5. Apply or complete the action where applicable. 6. Observe the page, messages, saved data, balances, and related records as applicable. | F66: Returns to list | G66: TEST_CASES_Loan_Type.xlsx / TC-LT-027 | H66: TBD | I66: Not Executed | J66: Source section: C. View (IDs: TC-LT-015–027)
A67: DELETE (10 test cases)
A68: LME-LT-058 | B68: Bulk Delete disabled by default | C68: Refer to Common Preconditions above. | D68: Name: QA Non-Revolving Loan Type Type: Non-revolving Interest calculation method: Simple Description: Client QA loan type | E68: 1. Sign in to Sage Intacct with the test user. 2. Navigate to Applications > Lending Management > Loan type. 3. Open or select the disposable record and initiate Delete. 4. Perform the scenario action: Bulk Delete disabled by default. 5. Confirm the action when prompted. 6. Observe the page, messages, saved data, balances, and related records as applicable. | F68: Toolbar Delete disabled | G68: TEST_CASES_Loan_Type.xlsx / TC-LT-008 | H68: TBD | I68: Not Executed | J68: Source section: A. List page (IDs: TC-LT-001–014)
A69: LME-LT-059 | B69: Bulk Delete enabled after selecting a row | C69: Refer to Common Preconditions above. | D69: Name: QA Non-Revolving Loan Type Type: Non-revolving Interest calculation method: Simple Description: Client QA loan type | E69: 1. Sign in to Sage Intacct with the test user. 2. Navigate to Applications > Lending Management > Loan type. 3. Open or select the disposable record and initiate Delete. 4. Perform the scenario action: Bulk Delete enabled after selecting a row. 5. Confirm the action when prompted. 6. Observe the page, messages, saved data, balances, and related records as applicable. | F69: Toolbar Delete becomes enabled | G69: TEST_CASES_Loan_Type.xlsx / TC-LT-009 | H69: TBD | I69: Not Executed | J69: Source section: A. List page (IDs: TC-LT-001–014)
A70: LME-LT-060 | B70: Select All enables Delete | C70: Refer to Common Preconditions above. | D70: Name: QA Non-Revolving Loan Type Type: Non-revolving Interest calculation method: Simple Description: Client QA loan type | E70: 1. Sign in to Sage Intacct with the test user. 2. Navigate to Applications > Lending Management > Loan type. 3. Open or select the disposable record and initiate Delete. 4. Perform the scenario action: Select All enables Delete. 5. Confirm the action when prompted. 6. Observe the page, messages, saved data, balances, and related records as applicable. | F70: All checkboxes checked, Delete enabled | G70: TEST_CASES_Loan_Type.xlsx / TC-LT-010 | H70: TBD | I70: Not Executed | J70: Source section: A. List page (IDs: TC-LT-001–014)
A71: LME-LT-061 | B71: Remove row decrements grid | C71: Refer to Common Preconditions above. | D71: Name: QA Non-Revolving Loan Type Type: Non-revolving Interest calculation method: Simple Description: Client QA loan type | E71: 1. Sign in to Sage Intacct with the test user. 2. Navigate to Applications > Lending Management > Loan type. 3. Open the page or record relevant to the scenario. 4. Perform the scenario action: Remove row decrements grid. 5. Apply or complete the action where applicable. 6. Observe the page, messages, saved data, balances, and related records as applicable. | F71: Row removed | G71: TEST_CASES_Loan_Type.xlsx / TC-LT-042 | H71: TBD | I71: Not Executed | J71: Source section: B. Create (IDs: TC-LT-028–046, TC-LT-057–066 new)
A72: LME-LT-062 | B72: Delete button visible | C72: Refer to Common Preconditions above. | D72: Name: QA Non-Revolving Loan Type Type: Non-revolving Interest calculation method: Simple Description: Client QA loan type | E72: 1. Sign in to Sage Intacct with the test user. 2. Navigate to Applications > Lending Management > Loan type. 3. Open or select the disposable record and initiate Delete. 4. Perform the scenario action: Delete button visible. 5. Confirm the action when prompted. 6. Observe the page, messages, saved data, balances, and related records as applicable. | F72: Visible (directly in header) | G72: TEST_CASES_Loan_Type.xlsx / TC-LT-024 | H72: TBD | I72: Not Executed | J72: Source section: C. View (IDs: TC-LT-015–027)
A73: LME-LT-063 | B73: Delete opens confirmation modal | C73: Refer to Common Preconditions above. | D73: Name: QA Non-Revolving Loan Type Type: Non-revolving Interest calculation method: Simple Description: Client QA loan type | E73: 1. Sign in to Sage Intacct with the test user. 2. Navigate to Applications > Lending Management > Loan type. 3. Open or select the disposable record and initiate Delete. 4. Perform the scenario action: Delete opens confirmation modal. 5. Confirm the action when prompted. 6. Observe the page, messages, saved data, balances, and related records as applicable. | F73: Dialog heading "Delete loan type" appears | G73: TEST_CASES_Loan_Type.xlsx / TC-LT-059 | H73: TBD | I73: Not Executed | J73: Source section: E. Delete (IDs: TC-LT-059–063, new — not present in the original spreadsheet)
A74: LME-LT-064 | B74: Modal message names the record | C74: Refer to Common Preconditions above. | D74: Name: QA Non-Revolving Loan Type Type: Non-revolving Interest calculation method: Simple Description: Client QA loan type | E74: 1. Sign in to Sage Intacct with the test user. 2. Navigate to Applications > Lending Management > Loan type. 3. Open the page or record relevant to the scenario. 4. Perform the scenario action: Modal message names the record. 5. Apply or complete the action where applicable. 6. Observe the page, messages, saved data, balances, and related records as applicable. | F74: Contains the loan type name + "will be permanently deleted" | G74: TEST_CASES_Loan_Type.xlsx / TC-LT-060 | H74: TBD | I74: Not Executed | J74: Source section: E. Delete (IDs: TC-LT-059–063, new — not present in the original spreadsheet)
A75: LME-LT-065 | B75: Confirm deletes | C75: Refer to Common Preconditions above. | D75: Name: QA Non-Revolving Loan Type Type: Non-revolving Interest calculation method: Simple Description: Client QA loan type | E75: 1. Sign in to Sage Intacct with the test user. 2. Navigate to Applications > Lending Management > Loan type. 3. Open or select the disposable record and initiate Delete. 4. Perform the scenario action: Confirm deletes. 5. Confirm the action when prompted. 6. Observe the page, messages, saved data, balances, and related records as applicable. | F75: Record removed from list | G75: TEST_CASES_Loan_Type.xlsx / TC-LT-061 | H75: TBD | I75: Not Executed | J75: Source section: E. Delete (IDs: TC-LT-059–063, new — not present in the original spreadsheet)
A76: LME-LT-066 | B76: Cancel in modal keeps record | C76: Refer to Common Preconditions above. | D76: Name: QA Non-Revolving Loan Type Type: Non-revolving Interest calculation method: Simple Description: Client QA loan type | E76: 1. Sign in to Sage Intacct with the test user. 2. Navigate to Applications > Lending Management > Loan type. 3. Open the page or record relevant to the scenario. 4. Perform the scenario action: Cancel in modal keeps record. 5. Apply or complete the action where applicable. 6. Observe the page, messages, saved data, balances, and related records as applicable. | F76: Modal closes; record still on View | G76: TEST_CASES_Loan_Type.xlsx / TC-LT-062 | H76: TBD | I76: Not Executed | J76: Source section: E. Delete (IDs: TC-LT-059–063, new — not present in the original spreadsheet)
A77: LME-LT-067 | B77: Deleting from View redirects to list | C77: Refer to Common Preconditions above. | D77: Name: QA Non-Revolving Loan Type Type: Non-revolving Interest calculation method: Simple Description: Client QA loan type | E77: 1. Sign in to Sage Intacct with the test user. 2. Navigate to Applications > Lending Management > Loan type. 3. Open the page or record relevant to the scenario. 4. Perform the scenario action: Deleting from View redirects to list. 5. Apply or complete the action where applicable. 6. Observe the page, messages, saved data, balances, and related records as applicable. | F77: Back on "Loan types" list after confirm | G77: TEST_CASES_Loan_Type.xlsx / TC-LT-063 | H77: TBD | I77: Not Executed | J77: Source section: E. Delete (IDs: TC-LT-059–063, new — not present in the original spreadsheet)

Sheet LME Automation Method
A1: Lending - Loan Type Automation Method
A2: Common Preconditions | C2: 1. User is signed in to Sage Intacct. 2. The correct Lending Management or Depository Management entity is selected. 3. The module is enabled for the company. 4. The user has the permission required for the scenario. 5. Required master/configuration records are active and available.
A4: Navigation: Applications > Lending Management > Loan type | Client baseline | 7 test cases | Updated 2026-08-27
A6: Test Case ID | B6: Test Scenario | C6: Preconditions | D6: Test Data | E6: Test Steps | F6: Expected Result | G6: Requirement/Jira Reference | H6: IS Automated | I6: Status | J6: Comments
A7: CREATE (6 test cases)
A8: LME-AM-001 | B8: Create a Loan Type with Standard automation | C8: Refer to Common Preconditions above. | D8: Name: QA Standard Automation Loan Type Automation method: Standard First statement date: N/A (not applicable to Standard) | E8: 1. Sign in to Sage Intacct with the test user. 2. Navigate to Applications > Lending Management > Loan type. 3. Prepare the test data: open Create Loan Type and select Automation method = Standard. 4. Complete the remaining required fields and save. 5. Submit, post, run, or confirm the action as applicable. 6. Review the confirmation, record, balances, accounting entries, and related history applicable to this scenario. | F8: The loan type is created successfully with the Automation method saved as Standard. | G8: Lending - Loan Type Automation Method client requirement; Jira reference TBD | H8: TBD | I8: Not Executed
A9: LME-AM-002 | B9: Create a Loan Type with Month end automation | C9: Refer to Common Preconditions above. | D9: Name: QA Month End Automation Loan Type Automation method: Month end First statement date: 2026-09-01 | E9: 1. Sign in to Sage Intacct with the test user. 2. Navigate to Applications > Lending Management > Loan type. 3. Prepare the test data: open Create Loan Type and select Automation method = Month end. 4. Enter a valid First statement date, complete the remaining required fields, and save. 5. Submit, post, run, or confirm the action as applicable. 6. Review the confirmation, record, balances, accounting entries, and related history applicable to this scenario. | F9: The loan type is created successfully with the Automation method saved as Month end and the First statement date saved as entered. | G9: Lending - Loan Type Automation Method client requirement; Jira reference TBD | H9: TBD | I9: Not Executed
A10: LME-AM-003 | B10: Hide First statement date when Standard automation is selected | C10: Refer to Common Preconditions above. | D10: Automation method: Standard | E10: 1. Sign in to Sage Intacct with the test user. 2. Navigate to Applications > Lending Management > Loan type. 3. Prepare the test data: select Automation method = Standard on the Create/Edit Loan Type form. 4. Inspect the form for the First statement date field. 5. Submit, post, run, or confirm the action as applicable. 6. Review the confirmation, record, balances, accounting entries, and related history applicable to this scenario. | F10: The First statement date field is not displayed on the form when Standard automation is selected. | G10: Lending - Loan Type Automation Method client requirement; Jira reference TBD | H10: TBD | I10: Not Executed
A11: LME-AM-004 | B11: Show First statement date when Month end automation is selected | C11: Refer to Common Preconditions above. | D11: Automation method: Month end | E11: 1. Sign in to Sage Intacct with the test user. 2. Navigate to Applications > Lending Management > Loan type. 3. Prepare the test data: select Automation method = Month end on the Create/Edit Loan Type form. 4. Inspect the form for the First statement date field. 5. Submit, post, run, or confirm the action as applicable. 6. Review the confirmation, record, balances, accounting entries, and related history applicable to this scenario. | F11: The First statement date field is displayed on the form when Month end automation is selected. | G11: Lending - Loan Type Automation Method client requirement; Jira reference TBD | H11: TBD | I11: Not Executed
A12: LME-AM-005 | B12: Require First statement date as mandatory when Month end automation is selected | C12: Refer to Common Preconditions above. | D12: Automation method: Month end First statement date: (field displayed, marked required) | E12: 1. Sign in to Sage Intacct with the test user. 2. Navigate to Applications > Lending Management > Loan type. 3. Prepare the test data: select Automation method = Month end on the Create Loan Type form. 4. Inspect the First statement date field for a mandatory-field indicator (e.g. red asterisk). 5. Submit, post, run, or confirm the action as applicable. 6. Review the confirmation, record, balances, accounting entries, and related history applicable to this scenario. | F12: The First statement date field is marked as mandatory when Month end automation is selected. | G12: Lending - Loan Type Automation Method client requirement; Jira reference TBD | H12: TBD | I12: Not Executed
A13: LME-AM-006 | B13: Block saving a Loan Type when Month end automation is selected and First statement date is not provided | C13: Refer to Common Preconditions above. | D13: Automation method: Month end First statement date: (left blank) | E13: 1. Sign in to Sage Intacct with the test user. 2. Navigate to Applications > Lending Management > Loan type. 3. Prepare the test data: select Automation method = Month end and leave the First statement date field blank. 4. Attempt to save the loan type. 5. Submit, post, run, or confirm the action as applicable. 6. Review the confirmation, record, balances, accounting entries, and related history applicable to this scenario. | F13: The save is blocked and a validation error is displayed indicating First statement date is required when Month end automation is selected. | G13: Lending - Loan Type Automation Method client requirement; Jira reference TBD | H13: TBD | I13: Not Executed
A14: EDIT (1 test case)
A15: LME-AM-007 | B15: Prevent updating the Automation method after the Loan Type has been saved | C15: Refer to Common Preconditions above. An existing Loan Type has already been saved with a chosen Automation method. | D15: Existing loan type: QA Month End Automation Loan Type Saved automation method: Month end | E15: 1. Sign in to Sage Intacct with the test user. 2. Navigate to Applications > Lending Management > Loan type. 3. Prepare the test data: open the existing loan type for edit and attempt to change the Automation method field. 4. Attempt to modify and save the Automation method value. 5. Submit, post, run, or confirm the action as applicable. 6. Review the confirmation, record, balances, accounting entries, and related history applicable to this scenario. | F15: The Automation method field is not editable (read-only or disabled) once the loan type has been saved; the value cannot be updated after initial creation. | G15: Lending - Loan Type Automation Method client requirement; Jira reference TBD | H15: TBD | I15: Not Executed
A16: VIEW (0 test cases)
A17: DELETE (0 test cases)

Sheet LME Loan Type - Standard
A1: Lending - Loan Type Standard Automation
A2: Common Preconditions | C2: 1. User is signed in to Sage Intacct. 2. The correct Lending Management or Depository Management entity is selected. 3. The module is enabled for the company. 4. The user has the permission required for the scenario. 5. Required master/configuration records are active and available.
A4: Navigation: Applications > Lending Management > Loan type | Client baseline | 35 test cases | Updated 2026-08-27
A6: Test Case ID | B6: Test Scenario | C6: Preconditions | D6: Test Data | E6: Test Steps | F6: Expected Result | G6: Requirement/Jira Reference | H6: IS Automated | I6: Status | J6: Comments
A7: CREATE (30 test cases)
A8: LME-LTS-001 | B8: Create a Loan Type with Standard automation | C8: Refer to Common Preconditions above. | D8: Name: QA Standard Automation Loan Type Automation method: Standard First statement date: N/A (not applicable to Standard) | E8: 1. Sign in to Sage Intacct with the test user. 2. Navigate to Applications > Lending Management > Loan type. 3. Prepare the test data: open Create Loan Type and select Automation method = Standard. 4. Complete the remaining required fields and save. 5. Submit, post, run, or confirm the action as applicable. 6. Review the confirmation, record, balances, accounting entries, and related history applicable to this scenario. | F8: The loan type is created successfully with the Automation method saved as Standard. | G8: Lending - Loan Type Standard Automation client requirement; Jira reference TBD | H8: TBD | I8: Not Executed
A9: LME-LTS-002 | B9: Create a Loan Type with Month end automation | C9: Refer to Common Preconditions above. | D9: Name: QA Month End Automation Loan Type Automation method: Month end First statement date: 2026-09-01 | E9: 1. Sign in to Sage Intacct with the test user. 2. Navigate to Applications > Lending Management > Loan type. 3. Prepare the test data: open Create Loan Type and select Automation method = Month end. 4. Enter a valid First statement date, complete the remaining required fields, and save. 5. Submit, post, run, or confirm the action as applicable. 6. Review the confirmation, record, balances, accounting entries, and related history applicable to this scenario. | F9: The loan type is created successfully with the Automation method saved as Month end and the First statement date saved as entered. | G9: Lending - Loan Type Standard Automation client requirement; Jira reference TBD | H9: TBD | I9: Not Executed
A10: LME-LTS-003 | B10: Hide First statement date when Standard automation is selected | C10: Refer to Common Preconditions above. | D10: Automation method: Standard | E10: 1. Sign in to Sage Intacct with the test user. 2. Navigate to Applications > Lending Management > Loan type. 3. Prepare the test data: select Automation method = Standard on the Create/Edit Loan Type form. 4. Inspect the form for the First statement date field. 5. Submit, post, run, or confirm the action as applicable. 6. Review the confirmation, record, balances, accounting entries, and related history applicable to this scenario. | F10: The First statement date field is not displayed on the form when Standard automation is selected. | G10: Lending - Loan Type Standard Automation client requirement; Jira reference TBD | H10: TBD | I10: Not Executed
A11: LME-LTS-004 | B11: Show First statement date when Month end automation is selected | C11: Refer to Common Preconditions above. | D11: Automation method: Month end | E11: 1. Sign in to Sage Intacct with the test user. 2. Navigate to Applications > Lending Management > Loan type. 3. Prepare the test data: select Automation method = Month end on the Create/Edit Loan Type form. 4. Inspect the form for the First statement date field. 5. Submit, post, run, or confirm the action as applicable. 6. Review the confirmation, record, balances, accounting entries, and related history applicable to this scenario. | F11: The First statement date field is displayed on the form when Month end automation is selected. | G11: Lending - Loan Type Standard Automation client requirement; Jira reference TBD | H11: TBD | I11: Not Executed
A12: LME-LTS-005 | B12: Require First statement date as mandatory when Month end automation is selected | C12: Refer to Common Preconditions above. | D12: Automation method: Month end First statement date: (field displayed, marked required) | E12: 1. Sign in to Sage Intacct with the test user. 2. Navigate to Applications > Lending Management > Loan type. 3. Prepare the test data: select Automation method = Month end on the Create Loan Type form. 4. Inspect the First statement date field for a mandatory-field indicator (e.g. red asterisk). 5. Submit, post, run, or confirm the action as applicable. 6. Review the confirmation, record, balances, accounting entries, and related history applicable to this scenario. | F12: The First statement date field is marked as mandatory when Month end automation is selected. | G12: Lending - Loan Type Standard Automation client requirement; Jira reference TBD | H12: TBD | I12: Not Executed
A13: LME-LTS-006 | B13: Block saving a Loan Type when Month end automation is selected and First statement date is not provided | C13: Refer to Common Preconditions above. | D13: Automation method: Month end First statement date: (left blank) | E13: 1. Sign in to Sage Intacct with the test user. 2. Navigate to Applications > Lending Management > Loan type. 3. Prepare the test data: select Automation method = Month end and leave the First statement date field blank. 4. Attempt to save the loan type. 5. Submit, post, run, or confirm the action as applicable. 6. Review the confirmation, record, balances, accounting entries, and related history applicable to this scenario. | F13: The save is blocked and a validation error is displayed indicating First statement date is required when Month end automation is selected. | G13: Lending - Loan Type Standard Automation client requirement; Jira reference TBD | H13: TBD | I13: Not Executed
A14: LME-LTS-007 | B14: Confirm Presentment method is available when Standard automation is enabled | C14: Refer to Common Preconditions above. | D14: Automation method: Standard | E14: 1. Sign in to Sage Intacct with the test user. 2. Navigate to Applications > Lending Management > Loan type. 3. Prepare the test data: select Automation method = Standard on the Create Loan Type form. 4. Inspect the form for the Presentment method field. 5. Submit, post, run, or confirm the action as applicable. 6. Review the confirmation, record, balances, accounting entries, and related history applicable to this scenario. | F14: The Presentment method field is present and available for selection when Standard automation is enabled, consistent with the Standard automation implementation. | G14: Lending - Loan Type Standard Automation client requirement; Jira reference TBD | H14: TBD | I14: Not Executed
A15: LME-LTS-008 | B15: Save a Loan Type with a valid Presentment method value | C15: Refer to Common Preconditions above. Automation method is set to Standard. | D15: Automation method: Standard Presentment method: Invoice | E15: 1. Sign in to Sage Intacct with the test user. 2. Navigate to Applications > Lending Management > Loan type. 3. Prepare the test data: select Automation method = Standard and choose a valid Presentment method value. 4. Complete the remaining required fields and save. 5. Submit, post, run, or confirm the action as applicable. 6. Review the confirmation, record, balances, accounting entries, and related history applicable to this scenario. | F15: The loan type is saved successfully with the selected Presentment method value persisted correctly. | G15: Lending - Loan Type Standard Automation client requirement; Jira reference TBD | H15: TBD | I15: Not Executed
A16: LME-LTS-009 | B16: Confirm Presentment method accepts Invoice, Statement, and Invoice & Statements options | C16: Refer to Common Preconditions above. Automation method is set to Standard. | D16: Automation method: Standard Presentment method candidates: Invoice, Statement, Invoice & Statements | E16: 1. Sign in to Sage Intacct with the test user. 2. Navigate to Applications > Lending Management > Loan type. 3. Prepare the test data: select Automation method = Standard and open the Presentment method dropdown. 4. Select each of Invoice, Statement, and Invoice & Statements in turn and save. 5. Submit, post, run, or confirm the action as applicable. 6. Review the confirmation, record, balances, accounting entries, and related history applicable to this scenario. | F16: All three options (Invoice, Statement, Invoice & Statements) are available in the Presentment method dropdown and each saves correctly when selected. | G16: Lending - Loan Type Standard Automation client requirement; Jira reference TBD | H16: TBD | I16: Not Executed
A17: LME-LTS-010 | B17: Confirm Presentment method is only accepted when Standard automation is enabled | C17: Refer to Common Preconditions above. | D17: Automation method: Standard Presentment method: Invoice | E17: 1. Sign in to Sage Intacct with the test user. 2. Navigate to Applications > Lending Management > Loan type. 3. Prepare the test data: select Automation method = Standard, set a Presentment method value, and save. 4. Confirm the value is accepted and saved. 5. Submit, post, run, or confirm the action as applicable. 6. Review the confirmation, record, balances, accounting entries, and related history applicable to this scenario. | F17: The Presentment method value is accepted and saved only while Automation method = Standard. | G17: Lending - Loan Type Standard Automation client requirement; Jira reference TBD | H17: TBD | I17: Not Executed
A18: LME-LTS-011 | B18: Reject Presentment method when Automation method is Month end | C18: Refer to Common Preconditions above. | D18: Automation method: Month end Presentment method: (attempted selection) | E18: 1. Sign in to Sage Intacct with the test user. 2. Navigate to Applications > Lending Management > Loan type. 3. Prepare the test data: select Automation method = Month end and attempt to set or submit a Presentment method value. 4. Attempt to save the loan type. 5. Submit, post, run, or confirm the action as applicable. 6. Review the confirmation, record, balances, accounting entries, and related history applicable to this scenario. | F18: Presentment method is not accepted for Month end automation; a validation error is displayed indicating Presentment method does not apply to Month end automation. | G18: Lending - Loan Type Standard Automation client requirement; Jira reference TBD | H18: TBD | I18: Not Executed
A19: LME-LTS-012 | B19: Confirm the Recurring schedules section is present on the Loan Type screen | C19: Refer to Common Preconditions above. | D19: N/A | E19: 1. Sign in to Sage Intacct with the test user. 2. Navigate to Applications > Lending Management > Loan type. 3. Prepare the test data: open the Create/Edit Loan Type form. 4. Expand the Recurring schedules section. 5. Submit, post, run, or confirm the action as applicable. 6. Review the confirmation, record, balances, accounting entries, and related history applicable to this scenario. | F19: The Recurring schedules section is displayed on the Loan Type screen and can be expanded/collapsed. | G19: Lending - Loan Type Standard Automation client requirement; Jira reference TBD | H19: TBD | I19: Not Executed
... A37: LME-LTS-030 | B37: Block creating a Loan Type without Recurrence schedule fields when Automation method is Standard | C37: Refer to Common Preconditions above. | D37: Automation method: Standard Loan invoice repeats: (left blank) Loan statement repeats: (left blank) | E37: 1. Sign in to Sage Intacct with the test user. 2. Navigate to Applications > Lending Management > Loan type. 3. Prepare the test data: select Automation method = Standard and leave Loan invoice repeats and Loan statement repeats unselected. 4. Attempt to save the loan type. 5. Submit, post, run, or confirm the action as applicable. 6. Review the confirmation, record, balances, accounting entries, and related history applicable to this scenario. | F37: The loan type cannot be created without Recurrence schedule field values when Automation method is Standard; submission is blocked with a validation error. | G37: Lending - Loan Type Standard Automation client requirement; Jira reference TBD | H37: TBD | I37: Not Executed
A38: EDIT (1 test case)
A39: LME-LTS-031 | B39: Prevent updating the Automation method after the Loan Type has been saved | C39: Refer to Common Preconditions above. An existing Loan Type has already been saved with a chosen Automation method. | D39: Existing loan type: QA Month End Automation Loan Type Saved automation method: Month end | E39: 1. Sign in to Sage Intacct with the test user. 2. Navigate to Applications > Lending Management > Loan type. 3. Prepare the test data: open the existing loan type for edit and attempt to change the Automation method field. 4. Attempt to modify and save the Automation method value. 5. Submit, post, run, or confirm the action as applicable. 6. Review the confirmation, record, balances, accounting entries, and related history applicable to this scenario. | F39: The Automation method field is not editable (read-only or disabled) once the loan type has been saved; the value cannot be updated after initial creation. | G39: Lending - Loan Type Standard Automation client requirement; Jira reference TBD | H39: TBD | I39: Not Executed
A40: VIEW (4 test cases)
A41: LME-LTS-032 | B41: Hide Presentment method on the View page when Automation method is Month end | C41: Refer to Common Preconditions above. An existing loan type saved with Automation method = Month end is available. | D41: Existing loan type: QA Month End Automation Loan Type Automation method: Month end | E41: 1. Sign in to Sage Intacct with the test user. 2. Navigate to Applications > Lending Management > Loan type. 3. Prepare the test data: open the existing Month end loan type in the View page. 4. Inspect the View page for the Presentment method field. 5. Submit, post, run, or confirm the action as applicable. 6. Review the confirmation, record, balances, accounting entries, and related history applicable to this scenario. | F41: The Presentment method field is not displayed on the View page when Automation method is Month end. | G41: Lending - Loan Type Standard Automation client requirement; Jira reference TBD | H41: TBD | I41: Not Executed
A42: LME-LTS-033 | B42: Show Presentment method on the View page when Automation method is Standard | C42: Refer to Common Preconditions above. An existing loan type saved with Automation method = Standard is available. | D42: Existing loan type: QA Standard Automation Loan Type Automation method: Standard | E42: 1. Sign in to Sage Intacct with the test user. 2. Navigate to Applications > Lending Management > Loan type. 3. Prepare the test data: open the existing Standard loan type in the View page. 4. Inspect the View page for the Presentment method field. 5. Submit, post, run, or confirm the action as applicable. 6. Review the confirmation, record, balances, accounting entries, and related history applicable to this scenario. | F42: The Presentment method field is displayed on the View page when Automation method is Standard. | G42: Lending - Loan Type Standard Automation client requirement; Jira reference TBD | H42: TBD | I42: Not Executed
A43: LME-LTS-034 | B43: Hide Recurrence schedule fields on the View page when Automation method is Month end | C43: Refer to Common Preconditions above. An existing loan type saved with Automation method = Month end is available. | D43: Existing loan type: QA Month End Automation Loan Type Automation method: Month end | E43: 1. Sign in to Sage Intacct with the test user. 2. Navigate to Applications > Lending Management > Loan type. 3. Prepare the test data: open the existing Month end loan type in the View page. 4. Inspect the View page for the Loan invoice repeats and Loan statement repeats fields. 5. Submit, post, run, or confirm the action as applicable. 6. Review the confirmation, record, balances, accounting entries, and related history applicable to this scenario. | F43: The Recurrence schedule fields are not displayed on the View page when Automation method is Month end. | G43: Lending - Loan Type Standard Automation client requirement; Jira reference TBD | H43: TBD | I43: Not Executed
A44: LME-LTS-035 | B44: Show Recurrence schedule fields on the View page when Automation method is Standard | C44: Refer to Common Preconditions above. An existing loan type saved with Automation method = Standard is available. | D44: Existing loan type: QA Standard Automation Loan Type Automation method: Standard | E44: 1. Sign in to Sage Intacct with the test user. 2. Navigate to Applications > Lending Management > Loan type. 3. Prepare the test data: open the existing Standard loan type in the View page. 4. Inspect the View page for the Loan invoice repeats and Loan statement repeats fields. 5. Submit, post, run, or confirm the action as applicable. 6. Review the confirmation, record, balances, accounting entries, and related history applicable to this scenario. | F44: The Recurrence schedule fields are displayed on the View page when Automation method is Standard. | G44: Lending - Loan Type Standard Automation client requirement; Jira reference TBD | H44: TBD | I44: Not Executed
A45: DELETE (0 test cases)

Sheet LME Interest Rate
A1: Lending - Loan Interest Rate
A2: Common Preconditions | C2: 1. User is signed in to Sage Intacct. 2. The correct Lending Management or Depository Management entity is selected. 3. The module is enabled for the company. 4. The user has the permission required for the scenario. 5. Required master/configuration records are active and available.
A4: Navigation: Applications > Lending Management > Loan interest rate | Client baseline | 43 test cases | Updated 2026-08-27
A6: Test Case ID | B6: Test Scenario | C6: Preconditions | D6: Test Data | E6: Test Steps | F6: Expected Result | G6: Requirement/Jira Reference | H6: IS Automated | I6: Status | J6: Comments
A7: CREATE (9 test cases)
A8: LME-LIR-001 | B8: Name field present, required | C8: Refer to Common Preconditions above. | D8: Other required fields: Use the valid values listed below Target field: Blank Name: QA Interest Rate 5 Percent Loan type: QA Non-Revolving Start date: 2026-08-01 Interest rate: 5.0000% | E8: 1. Sign in to Sage Intacct with the test user. 2. Navigate to Applications > Lending Management > Loan interest rate. 3. Open the page or record relevant to the scenario. 4. Perform the scenario action: Name field present, required. 5. Apply or complete the action where applicable. 6. Observe the page, messages, saved data, balances, and related records as applicable. | F8: Text input visible, `*` on label | G8: TEST_CASES_Loan_Interest_Rate.xlsx / TC-LIR-011 | H8: TBD | I8: Not Executed | J8: Source section: B. Create (IDs: TC-LIR-011–024)
A9: LME-LIR-002 | B9: Empty name blocked | C9: Refer to Common Preconditions above. | D9: Other required fields: Use the valid values listed below Target field: Blank Name: QA Interest Rate 5 Percent Loan type: QA Non-Revolving Start date: 2026-08-01 Interest rate: 5.0000% | E9: 1. Sign in to Sage Intacct with the test user. 2. Navigate to Applications > Lending Management > Loan interest rate. 3. Open the page or record relevant to the scenario. 4. Perform the scenario action: Empty name blocked. 5. Apply or complete the action where applicable. 6. Observe the page, messages, saved data, balances, and related records as applicable. | F9: Validation error / stays on Create | G9: TEST_CASES_Loan_Interest_Rate.xlsx / TC-LIR-012 | H9: TBD | I9: Not Executed | J9: Source section: B. Create (IDs: TC-LIR-011–024)
A10: LME-LIR-003 | B10: Type radios visible | C10: Refer to Common Preconditions above. | D10: Name: QA Interest Rate 5 Percent Loan type: QA Non-Revolving Start date: 2026-08-01 Interest rate: 5.0000% Notes: Client QA rate | E10: 1. Sign in to Sage Intacct with the test user. 2. Navigate to Applications > Lending Management > Loan interest rate. 3. Open the page or record relevant to the scenario. 4. Perform the scenario action: Type radios visible. 5. Apply or complete the action where applicable. 6. Observe the page, messages, saved data, balances, and related records as applicable. | F10: Revolving / Non-revolving both present | G10: TEST_CASES_Loan_Interest_Rate.xlsx / TC-LIR-013 | H10: TBD | I10: Not Executed | J10: Source section: B. Create (IDs: TC-LIR-011–024)
A11: LME-LIR-004 | B11: Add row button present | C11: Refer to Common Preconditions above. | D11: Name: QA Interest Rate 5 Percent Loan type: QA Non-Revolving User role: Full Access | E11: 1. Sign in to Sage Intacct with the test user. 2. Navigate to Applications > Lending Management > Loan interest rate. 3. Open the page or record relevant to the scenario. 4. Perform the scenario action: Add row button present. 5. Apply or complete the action where applicable. 6. Observe the page, messages, saved data, balances, and related records as applicable. | F11: Visible in Loan interest rate schedule section | G11: TEST_CASES_Loan_Interest_Rate.xlsx / TC-LIR-014 | H11: TBD | I11: Not Executed | J11: Source section: B. Create (IDs: TC-LIR-011–024)
A12: LME-LIR-005 | B12: At least one schedule row required | C12: Refer to Common Preconditions above. | D12: Other required fields: Use the valid values listed below Target field: Blank Name: QA Interest Rate 5 Percent Loan type: QA Non-Revolving Start date: 2026-08-01 Interest rate: 5.0000% | E12: 1. Sign in to Sage Intacct with the test user. 2. Navigate to Applications > Lending Management > Loan interest rate. 3. Open the page or record relevant to the scenario. 4. Perform the scenario action: At least one schedule row required. 5. Apply or complete the action where applicable. 6. Observe the page, messages, saved data, balances, and related records as applicable. | F12: Saving with 0 rows shows: "At-least one rate entry is required for a Loan Interest Rate" | G12: TEST_CASES_Loan_Interest_Rate.xlsx / TC-LIR-020 | H12: TBD | I12: Not Executed | J12: Source section: B. Create (IDs: TC-LIR-011–024)
A13: LME-LIR-006 | B13: Start date must be first of month | C13: Refer to Common Preconditions above. | D13: Name: QA Interest Rate 5 Percent Loan type: QA Non-Revolving Start date: 2026-08-01 Interest rate: 5.0000% Notes: Client QA rate | E13: 1. Sign in to Sage Intacct with the test user. 2. Navigate to Applications > Lending Management > Loan interest rate. 3. Open the page or record relevant to the scenario. 4. Perform the scenario action: Start date must be first of month. 5. Apply or complete the action where applicable. 6. Observe the page, messages, saved data, balances, and related records as applicable. | F13: Saving a row with a non-1st start date shows: "Interest rate entries can be only effective from the first date of the month" | G13: TEST_CASES_Loan_Interest_Rate.xlsx / TC-LIR-021 | H13: TBD | I13: Not Executed | J13: Source section: B. Create (IDs: TC-LIR-011–024)
A14: LME-LIR-007 | B14: Save button visible | C14: Refer to Common Preconditions above. | D14: Name: QA Interest Rate 5 Percent Loan type: QA Non-Revolving Start date: 2026-08-01 Interest rate: 5.0000% Notes: Client QA rate | E14: 1. Sign in to Sage Intacct with the test user. 2. Navigate to Applications > Lending Management > Loan interest rate. 3. Open the page or record relevant to the scenario. 4. Perform the scenario action: Save button visible. 5. Click Save or the applicable submit action. 6. Observe the page, messages, saved data, balances, and related records as applicable. | F14: Visible | G14: TEST_CASES_Loan_Interest_Rate.xlsx / TC-LIR-022 | H14: TBD | I14: Not Executed | J14: Source section: B. Create (IDs: TC-LIR-011–024)
A15: LME-LIR-008 | B15: Cancel returns to list without saving | C15: Refer to Common Preconditions above. | D15: Name: QA Interest Rate 5 Percent Loan type: QA Non-Revolving Start date: 2026-08-01 Interest rate: 5.0000% Notes: Client QA rate | E15: 1. Sign in to Sage Intacct with the test user. 2. Navigate to Applications > Lending Management > Loan interest rate. 3. Open the page or record relevant to the scenario. 4. Perform the scenario action: Cancel returns to list without saving. 5. Apply or complete the action where applicable. 6. Observe the page, messages, saved data, balances, and related records as applicable. | F15: Back on list, no new record | G15: TEST_CASES_Loan_Interest_Rate.xlsx / TC-LIR-023 | H15: TBD | I15: Not Executed | J15: Source section: B. Create (IDs: TC-LIR-011–024)
A16: LME-LIR-009 | B16: Valid record saves | C16: Refer to Common Preconditions above. | D16: Name: QA Interest Rate 5 Percent Loan type: QA Non-Revolving Start date: 2026-08-01 Interest rate: 5.0000% Notes: Client QA rate | E16: 1. Sign in to Sage Intacct with the test user. 2. Navigate to Applications > Lending Management > Loan interest rate. 3. Open the page or record relevant to the scenario. 4. Perform the scenario action: Valid record saves. 5. Click Save or the applicable submit action. 6. Observe the page, messages, saved data, balances, and related records as applicable. | F16: Full valid Name + Type + one schedule row (1st-of-month date) saves and lands on View | G16: TEST_CASES_Loan_Interest_Rate.xlsx / TC-LIR-024 | H16: TBD | I16: Not Executed | J16: Source section: B. Create (IDs: TC-LIR-011–024)
A17: EDIT (9 test cases)
A18: LME-LIR-010 | B18: Edit button visible | C18: Refer to Common Preconditions above. | D18: Name: QA Interest Rate 5 Percent Loan type: QA Non-Revolving Start date: 2026-08-01 Interest rate: 5.0000% Notes: Client QA rate | E18: 1. Sign in to Sage Intacct with the test user. 2. Navigate to Applications > Lending Management > Loan interest rate. 3. Open an existing record, click Edit, and change the field(s) relevant to the scenario. 4. Perform the scenario action: Edit button visible. 5. Click Save or the applicable submit action. 6. Observe the page, messages, saved data, balances, and related records as applicable. | F18: Visible directly in header | G18: TEST_CASES_Loan_Interest_Rate.xlsx / TC-LIR-029 | H18: TBD | I18: Not Executed | J18: Source section: C. View (IDs: TC-LIR-025–030)
A19: LME-LIR-011 | B19: Edit heading format | C19: Refer to Common Preconditions above. | D19: Name: QA Interest Rate 5 Percent Loan type: QA Non-Revolving Start date: 2026-08-01 Interest rate: 5.0000% Notes: Client QA rate | E19: 1. Sign in to Sage Intacct with the test user. 2. Navigate to Applications > Lending Management > Loan interest rate. 3. Open an existing record, click Edit, and change the field(s) relevant to the scenario. 4. Perform the scenario action: Edit heading format. 5. Click Save or the applicable submit action. 6. Observe the page, messages, saved data, balances, and related records as applicable. | F19: `Edit loan-management/loan-interest-rate: <ID>--<Name>` | G19: TEST_CASES_Loan_Interest_Rate.xlsx / TC-LIR-031 | H19: TBD | I19: Not Executed | J19: Source section: D. Edit (IDs: TC-LIR-031–038)
A20: LME-LIR-012 | B20: Edit form pre-populates Name | C20: Refer to Common Preconditions above. | D20: Name: QA Interest Rate 5 Percent Loan type: QA Non-Revolving Start date: 2026-08-01 Interest rate: 5.0000% Notes: Client QA rate | E20: 1. Sign in to Sage Intacct with the test user. 2. Navigate to Applications > Lending Management > Loan interest rate. 3. Open an existing record, click Edit, and change the field(s) relevant to the scenario. 4. Perform the scenario action: Edit form pre-populates Name. 5. Click Save or the applicable submit action. 6. Observe the page, messages, saved data, balances, and related records as applicable. | F20: Pre-filled | G20: TEST_CASES_Loan_Interest_Rate.xlsx / TC-LIR-032 | H20: TBD | I20: Not Executed | J20: Source section: D. Edit (IDs: TC-LIR-031–038)
A21: LME-LIR-013 | B21: Type is read-only in Edit | C21: Refer to Common Preconditions above. | D21: Name: QA Interest Rate 5 Percent Loan type: QA Non-Revolving Start date: 2026-08-01 Interest rate: 5.0000% Notes: Client QA rate | E21: 1. Sign in to Sage Intacct with the test user. 2. Navigate to Applications > Lending Management > Loan interest rate. 3. Open an existing record, click Edit, and change the field(s) relevant to the scenario. 4. Perform the scenario action: Type is read-only in Edit. 5. Click Save or the applicable submit action. 6. Observe the page, messages, saved data, balances, and related records as applicable. | F21: Plain text, no radio buttons | G21: TEST_CASES_Loan_Interest_Rate.xlsx / TC-LIR-033 | H21: TBD | I21: Not Executed | J21: Source section: D. Edit (IDs: TC-LIR-031–038)
A22: LME-LIR-014 | B22: Edit form pre-populates Status | C22: Refer to Common Preconditions above. | D22: Name: QA Interest Rate 5 Percent Loan type: QA Non-Revolving Start date: 2026-08-01 Interest rate: 5.0000% Notes: Client QA rate | E22: 1. Sign in to Sage Intacct with the test user. 2. Navigate to Applications > Lending Management > Loan interest rate. 3. Open an existing record, click Edit, and change the field(s) relevant to the scenario. 4. Perform the scenario action: Edit form pre-populates Status. 5. Click Save or the applicable submit action. 6. Observe the page, messages, saved data, balances, and related records as applicable. | F22: Shown ('Active') | G22: TEST_CASES_Loan_Interest_Rate.xlsx / TC-LIR-034 | H22: TBD | I22: Not Executed | J22: Source section: D. Edit (IDs: TC-LIR-031–038)
A23: LME-LIR-015 | B23: Schedule rows pre-populated in Edit | C23: Refer to Common Preconditions above. | D23: Name: QA Interest Rate 5 Percent Loan type: QA Non-Revolving Start date: 2026-08-01 Interest rate: 5.0000% Notes: Client QA rate | E23: 1. Sign in to Sage Intacct with the test user. 2. Navigate to Applications > Lending Management > Loan interest rate. 3. Open an existing record, click Edit, and change the field(s) relevant to the scenario. 4. Perform the scenario action: Schedule rows pre-populated in Edit. 5. Click Save or the applicable submit action. 6. Observe the page, messages, saved data, balances, and related records as applicable. | F23: Existing row(s) shown | G23: TEST_CASES_Loan_Interest_Rate.xlsx / TC-LIR-035 | H23: TBD | I23: Not Executed | J23: Source section: D. Edit (IDs: TC-LIR-031–038)
A24: LME-LIR-016 | B24: Clearing Name and saving shows validation error | C24: Refer to Common Preconditions above. | D24: Name: QA Interest Rate 5 Percent Loan type: QA Non-Revolving Start date: 2026-08-01 Interest rate: 5.0000% Notes: Client QA rate | E24: 1. Sign in to Sage Intacct with the test user. 2. Navigate to Applications > Lending Management > Loan interest rate. 3. Open the page or record relevant to the scenario. 4. Perform the scenario action: Clearing Name and saving shows validation error. 5. Apply or complete the action where applicable. 6. Observe the page, messages, saved data, balances, and related records as applicable. | F24: Stays on Edit | G24: TEST_CASES_Loan_Interest_Rate.xlsx / TC-LIR-036 | H24: TBD | I24: Not Executed | J24: Source section: D. Edit (IDs: TC-LIR-031–038)
A25: LME-LIR-017 | B25: Cancel discards changes | C25: Refer to Common Preconditions above. | D25: Name: QA Interest Rate 5 Percent Loan type: QA Non-Revolving Start date: 2026-08-01 Interest rate: 5.0000% Notes: Client QA rate | E25: 1. Sign in to Sage Intacct with the test user. 2. Navigate to Applications > Lending Management > Loan interest rate. 3. Open the page or record relevant to the scenario. 4. Perform the scenario action: Cancel discards changes. 5. Apply or complete the action where applicable. 6. Observe the page, messages, saved data, balances, and related records as applicable. | F25: Back on View, original name intact | G25: TEST_CASES_Loan_Interest_Rate.xlsx / TC-LIR-037 | H25: TBD | I25: Not Executed | J25: Source section: D. Edit (IDs: TC-LIR-031–038)
A26: LME-LIR-018 | B26: Save persists changes | C26: Refer to Common Preconditions above. | D26: Name: QA Interest Rate 5 Percent Loan type: QA Non-Revolving Start date: 2026-08-01 Interest rate: 5.0000% Notes: Client QA rate | E26: 1. Sign in to Sage Intacct with the test user. 2. Navigate to Applications > Lending Management > Loan interest rate. 3. Open the page or record relevant to the scenario. 4. Perform the scenario action: Save persists changes. 5. Click Save or the applicable submit action. 6. Observe the page, messages, saved data, balances, and related records as applicable. | F26: View reflects the updated name | G26: TEST_CASES_Loan_Interest_Rate.xlsx / TC-LIR-038 | H26: TBD | I26: Not Executed | J26: Source section: D. Edit (IDs: TC-LIR-031–038)
A27: VIEW (16 test cases)
A28: LME-LIR-019 | B28: List page loads | C28: Refer to Common Preconditions above. | D28: Name: QA Interest Rate 5 Percent Loan type: QA Non-Revolving User role: Full Access | E28: 1. Sign in to Sage Intacct with the test user. 2. Navigate to Applications > Lending Management > Loan interest rate. 3. Open the page or record relevant to the scenario. 4. Perform the scenario action: List page loads. 5. Apply or complete the action where applicable. 6. Observe the page, messages, saved data, balances, and related records as applicable. | F28: H1 "Loan interest rates" visible | G28: TEST_CASES_Loan_Interest_Rate.xlsx / TC-LIR-001 | H28: TBD | I28: Not Executed | J28: Source section: A. List page (IDs: TC-LIR-001–010)
A29: LME-LIR-020 | B29: Create button visible | C29: Refer to Common Preconditions above. | D29: Name: QA Interest Rate 5 Percent Loan type: QA Non-Revolving User role: Full Access | E29: 1. Sign in to Sage Intacct with the test user. 2. Navigate to Applications > Lending Management > Loan interest rate. 3. Click Create and populate the form using the stated test data. 4. Perform the scenario action: Create button visible. 5. Click Save or the applicable submit action. 6. Observe the page, messages, saved data, balances, and related records as applicable. | F29: Visible/enabled | G29: TEST_CASES_Loan_Interest_Rate.xlsx / TC-LIR-002 | H29: TBD | I29: Not Executed | J29: Source section: A. List page (IDs: TC-LIR-001–010)
A30: LME-LIR-021 | B30: Grid columns present | C30: Refer to Common Preconditions above. | D30: Name: QA Interest Rate 5 Percent Loan type: QA Non-Revolving User role: Full Access | E30: 1. Sign in to Sage Intacct with the test user. 2. Navigate to Applications > Lending Management > Loan interest rate. 3. Open the page or record relevant to the scenario. 4. Perform the scenario action: Grid columns present. 5. Apply or complete the action where applicable. 6. Observe the page, messages, saved data, balances, and related records as applicable. | F30: Name, Loan type, Status columns shown | G30: TEST_CASES_Loan_Interest_Rate.xlsx / TC-LIR-003 | H30: TBD | I30: Not Executed | J30: Source section: A. List page (IDs: TC-LIR-001–010)
A31: LME-LIR-022 | B31: Name filter has Contains placeholder | C31: Refer to Common Preconditions above. | D31: Filter value: QA Name: QA Interest Rate 5 Percent Loan type: QA Non-Revolving | E31: 1. Sign in to Sage Intacct with the test user. 2. Navigate to Applications > Lending Management > Loan interest rate. 3. Enter the stated value in the relevant filter and apply it. 4. Perform the scenario action: Name filter has Contains placeholder. 5. Apply or complete the action where applicable. 6. Observe the page, messages, saved data, balances, and related records as applicable. | F31: `placeholder="Contains"` textbox for Name column | G31: TEST_CASES_Loan_Interest_Rate.xlsx / TC-LIR-004 | H31: TBD | I31: Not Executed | J31: Source section: A. List page (IDs: TC-LIR-001–010)
A32: LME-LIR-023 | B32: Loan type filter is a dropdown | C32: Refer to Common Preconditions above. | D32: Name: QA Interest Rate 5 Percent Loan type: QA | E32: 1. Sign in to Sage Intacct with the test user. 2. Navigate to Applications > Lending Management > Loan interest rate. 3. Enter the stated value in the relevant filter and apply it. 4. Perform the scenario action: Loan type filter is a dropdown. 5. Apply or complete the action where applicable. 6. Observe the page, messages, saved data, balances, and related records as applicable. | F32: Combobox shown for the Loan type filter column | G32: TEST_CASES_Loan_Interest_Rate.xlsx / TC-LIR-005 | H32: TBD | I32: Not Executed | J32: Source section: A. List page (IDs: TC-LIR-001–010)
A33: LME-LIR-024 | B33: Status filter defaults to Active | C33: Refer to Common Preconditions above. | D33: Status: Active Name: QA Interest Rate 5 Percent Loan type: QA Non-Revolving | E33: 1. Sign in to Sage Intacct with the test user. 2. Navigate to Applications > Lending Management > Loan interest rate. 3. Enter the stated value in the relevant filter and apply it. 4. Perform the scenario action: Status filter defaults to Active. 5. Apply or complete the action where applicable. 6. Observe the page, messages, saved data, balances, and related records as applicable. | F33: Status column filter combobox shows "Active" | G33: TEST_CASES_Loan_Interest_Rate.xlsx / TC-LIR-006 | H33: TBD | I33: Not Executed | J33: Source section: A. List page (IDs: TC-LIR-001–010)
A34: LME-LIR-025 | B34: Grid shows at least one record | C34: Refer to Common Preconditions above. | D34: Name: QA Interest Rate 5 Percent Loan type: QA Non-Revolving Start date: 2026-08-01 Interest rate: 5.0000% Notes: Client QA rate | E34: 1. Sign in to Sage Intacct with the test user. 2. Navigate to Applications > Lending Management > Loan interest rate. 3. Open the page or record relevant to the scenario. 4. Perform the scenario action: Grid shows at least one record. 5. Apply or complete the action where applicable. 6. Observe the page, messages, saved data, balances, and related records as applicable. | F34: ≥1 row | G34: TEST_CASES_Loan_Interest_Rate.xlsx / TC-LIR-007 | H34: TBD | I34: Not Executed | J34: Source section: A. List page (IDs: TC-LIR-001–010)
A35: LME-LIR-026 | B35: Name filter returns matching record | C35: Refer to Common Preconditions above. | D35: Filter value: QA Name: QA Interest Rate 5 Percent Loan type: QA Non-Revolving | E35: 1. Sign in to Sage Intacct with the test user. 2. Navigate to Applications > Lending Management > Loan interest rate. 3. Enter the stated value in the relevant filter and apply it. 4. Perform the scenario action: Name filter returns matching record. 5. Apply or complete the action where applicable. 6. Observe the page, messages, saved data, balances, and related records as applicable. | F35: Filtering by an existing name shows that record | G35: TEST_CASES_Loan_Interest_Rate.xlsx / TC-LIR-008 | H35: TBD | I35: Not Executed | J35: Source section: A. List page (IDs: TC-LIR-001–010)
A36: LME-LIR-027 | B36: Schedule grid columns | C36: Refer to Common Preconditions above. | D36: Name: QA Interest Rate 5 Percent Loan type: QA Non-Revolving User role: Full Access | E36: 1. Sign in to Sage Intacct with the test user. 2. Navigate to Applications > Lending Management > Loan interest rate. 3. Open the page or record relevant to the scenario. 4. Perform the scenario action: Schedule grid columns. 5. Apply or complete the action where applicable. 6. Observe the page, messages, saved data, balances, and related records as applicable. | F36: Start date, Interest rate (%), Notes, Attachment all visible | G36: TEST_CASES_Loan_Interest_Rate.xlsx / TC-LIR-015 | H36: TBD | I36: Not Executed | J36: Source section: B. Create (IDs: TC-LIR-011–024)
A37: LME-LIR-028 | B37: Start date column marked required | C37: Refer to Common Preconditions above. | D37: Name: QA Interest Rate 5 Percent Loan type: QA Non-Revolving Start date: 2026-08-01 Interest rate: 5.0000% Notes: Client QA rate | E37: 1. Sign in to Sage Intacct with the test user. 2. Navigate to Applications > Lending Management > Loan interest rate. 3. Open the page or record relevant to the scenario. 4. Perform the scenario action: Start date column marked required. 5. Apply or complete the action where applicable. 6. Observe the page, messages, saved data, balances, and related records as applicable. | F37: `*` on Start date header | G37: TEST_CASES_Loan_Interest_Rate.xlsx / TC-LIR-016 | H37: TBD | I37: Not Executed | J37: Source section: B. Create (IDs: TC-LIR-011–024)
A38: LME-LIR-029 | B38: Interest rate column marked required | C38: Refer to Common Preconditions above. | D38: Name: QA Interest Rate 5 Percent Loan type: QA Non-Revolving Start date: 2026-08-01 Interest rate: 5.0000% Notes: Client QA rate | E38: 1. Sign in to Sage Intacct with the test user. 2. Navigate to Applications > Lending Management > Loan interest rate. 3. Open the page or record relevant to the scenario. 4. Perform the scenario action: Interest rate column marked required. 5. Apply or complete the action where applicable. 6. Observe the page, messages, saved data, balances, and related records as applicable. | F38: `*` on Interest rate (%) header | G38: TEST_CASES_Loan_Interest_Rate.xlsx / TC-LIR-017 | H38: TBD | I38: Not Executed | J38: Source section: B. Create (IDs: TC-LIR-011–024)
A39: LME-LIR-030 | B39: Add row increments grid | C39: Refer to Common Preconditions above. | D39: Name: QA Interest Rate 5 Percent Loan type: QA Non-Revolving Start date: 2026-08-01 Interest rate: 5.0000% Notes: Client QA rate | E39: 1. Sign in to Sage Intacct with the test user. 2. Navigate to Applications > Lending Management > Loan interest rate. 3. Open the page or record relevant to the scenario. 4. Perform the scenario action: Add row increments grid. 5. Apply or complete the action where applicable. 6. Observe the page, messages, saved data, balances, and related records as applicable. | F39: One new row added | G39: TEST_CASES_Loan_Interest_Rate.xlsx / TC-LIR-018 | H39: TBD | I39: Not Executed | J39: Source section: B. Create (IDs: TC-LIR-011–024)
... A43: LME-LIR-034 | B43: View displays Status = Active | C43: Refer to Common Preconditions above. | D43: Name: QA Interest Rate 5 Percent Loan type: QA Non-Revolving Start date: 2026-08-01 Interest rate: 5.0000% Notes: Client QA rate | E43: 1. Sign in to Sage Intacct with the test user. 2. Navigate to Applications > Lending Management > Loan interest rate. 3. Open the page or record relevant to the scenario. 4. Perform the scenario action: View displays Status = Active. 5. Apply or complete the action where applicable. 6. Observe the page, messages, saved data, balances, and related records as applicable. | F43: 'Active' shown (absent from Create, present here) | G43: TEST_CASES_Loan_Interest_Rate.xlsx / TC-LIR-028 | H43: TBD | I43: Not Executed | J43: Source section: C. View (IDs: TC-LIR-025–030)
A44: DELETE (9 test cases)
A45: LME-LIR-035 | B45: Bulk Delete disabled by default | C45: Refer to Common Preconditions above. | D45: Name: QA Interest Rate 5 Percent Loan type: QA Non-Revolving Start date: 2026-08-01 Interest rate: 5.0000% Notes: Client QA rate | E45: 1. Sign in to Sage Intacct with the test user. 2. Navigate to Applications > Lending Management > Loan interest rate. 3. Open or select the disposable record and initiate Delete. 4. Perform the scenario action: Bulk Delete disabled by default. 5. Confirm the action when prompted. 6. Observe the page, messages, saved data, balances, and related records as applicable. | F45: Toolbar Delete disabled with no row selected | G45: TEST_CASES_Loan_Interest_Rate.xlsx / TC-LIR-009 | H45: TBD | I45: Not Executed | J45: Source section: A. List page (IDs: TC-LIR-001–010)
A46: LME-LIR-036 | B46: Bulk Delete enabled after selecting a row | C46: Refer to Common Preconditions above. | D46: Name: QA Interest Rate 5 Percent Loan type: QA Non-Revolving Start date: 2026-08-01 Interest rate: 5.0000% Notes: Client QA rate | E46: 1. Sign in to Sage Intacct with the test user. 2. Navigate to Applications > Lending Management > Loan interest rate. 3. Open or select the disposable record and initiate Delete. 4. Perform the scenario action: Bulk Delete enabled after selecting a row. 5. Confirm the action when prompted. 6. Observe the page, messages, saved data, balances, and related records as applicable. | F46: Toolbar Delete becomes enabled | G46: TEST_CASES_Loan_Interest_Rate.xlsx / TC-LIR-010 | H46: TBD | I46: Not Executed | J46: Source section: A. List page (IDs: TC-LIR-001–010)
A47: LME-LIR-037 | B47: Remove row decrements grid | C47: Refer to Common Preconditions above. | D47: Name: QA Interest Rate 5 Percent Loan type: QA Non-Revolving Start date: 2026-08-01 Interest rate: 5.0000% Notes: Client QA rate | E47: 1. Sign in to Sage Intacct with the test user. 2. Navigate to Applications > Lending Management > Loan interest rate. 3. Open the page or record relevant to the scenario. 4. Perform the scenario action: Remove row decrements grid. 5. Apply or complete the action where applicable. 6. Observe the page, messages, saved data, balances, and related records as applicable. | F47: Row removed | G47: TEST_CASES_Loan_Interest_Rate.xlsx / TC-LIR-019 | H47: TBD | I47: Not Executed | J47: Source section: B. Create (IDs: TC-LIR-011–024)
A48: LME-LIR-038 | B48: Delete button visible | C48: Refer to Common Preconditions above. | D48: Name: QA Interest Rate 5 Percent Loan type: QA Non-Revolving Start date: 2026-08-01 Interest rate: 5.0000% Notes: Client QA rate | E48: 1. Sign in to Sage Intacct with the test user. 2. Navigate to Applications > Lending Management > Loan interest rate. 3. Open or select the disposable record and initiate Delete. 4. Perform the scenario action: Delete button visible. 5. Confirm the action when prompted. 6. Observe the page, messages, saved data, balances, and related records as applicable. | F48: Visible directly in header | G48: TEST_CASES_Loan_Interest_Rate.xlsx / TC-LIR-030 | H48: TBD | I48: Not Executed | J48: Source section: C. View (IDs: TC-LIR-025–030)
A49: LME-LIR-039 | B49: Delete opens confirmation modal | C49: Refer to Common Preconditions above. | D49: Name: QA Interest Rate 5 Percent Loan type: QA Non-Revolving Start date: 2026-08-01 Interest rate: 5.0000% Notes: Client QA rate | E49: 1. Sign in to Sage Intacct with the test user. 2. Navigate to Applications > Lending Management > Loan interest rate. 3. Open or select the disposable record and initiate Delete. 4. Perform the scenario action: Delete opens confirmation modal. 5. Confirm the action when prompted. 6. Observe the page, messages, saved data, balances, and related records as applicable. | F49: Dialog heading "Delete loan interest rate" appears | G49: TEST_CASES_Loan_Interest_Rate.xlsx / TC-LIR-039 | H49: TBD | I49: Not Executed | J49: Source section: E. Delete (IDs: TC-LIR-039–043)
A50: LME-LIR-040 | B50: Modal message names the record | C50: Refer to Common Preconditions above. | D50: Name: QA Interest Rate 5 Percent Loan type: QA Non-Revolving Start date: 2026-08-01 Interest rate: 5.0000% Notes: Client QA rate | E50: 1. Sign in to Sage Intacct with the test user. 2. Navigate to Applications > Lending Management > Loan interest rate. 3. Open the page or record relevant to the scenario. 4. Perform the scenario action: Modal message names the record. 5. Apply or complete the action where applicable. 6. Observe the page, messages, saved data, balances, and related records as applicable. | F50: Contains the record name + "will be permanently deleted" | G50: TEST_CASES_Loan_Interest_Rate.xlsx / TC-LIR-040 | H50: TBD | I50: Not Executed | J50: Source section: E. Delete (IDs: TC-LIR-039–043)
A51: LME-LIR-041 | B51: Confirm deletes | C51: Refer to Common Preconditions above. | D51: Name: QA Interest Rate 5 Percent Loan type: QA Non-Revolving Start date: 2026-08-01 Interest rate: 5.0000% Notes: Client QA rate | E51: 1. Sign in to Sage Intacct with the test user. 2. Navigate to Applications > Lending Management > Loan interest rate. 3. Open or select the disposable record and initiate Delete. 4. Perform the scenario action: Confirm deletes. 5. Confirm the action when prompted. 6. Observe the page, messages, saved data, balances, and related records as applicable. | F51: Record removed from list | G51: TEST_CASES_Loan_Interest_Rate.xlsx / TC-LIR-041 | H51: TBD | I51: Not Executed | J51: Source section: E. Delete (IDs: TC-LIR-039–043)
A52: LME-LIR-042 | B52: Cancel in modal keeps record | C52: Refer to Common Preconditions above. | D52: Name: QA Interest Rate 5 Percent Loan type: QA Non-Revolving Start date: 2026-08-01 Interest rate: 5.0000% Notes: Client QA rate | E52: 1. Sign in to Sage Intacct with the test user. 2. Navigate to Applications > Lending Management > Loan interest rate. 3. Open the page or record relevant to the scenario. 4. Perform the scenario action: Cancel in modal keeps record. 5. Apply or complete the action where applicable. 6. Observe the page, messages, saved data, balances, and related records as applicable. | F52: Modal closes; record still on View | G52: TEST_CASES_Loan_Interest_Rate.xlsx / TC-LIR-042 | H52: TBD | I52: Not Executed | J52: Source section: E. Delete (IDs: TC-LIR-039–043)
A53: LME-LIR-043 | B53: Delete redirects to list | C53: Refer to Common Preconditions above. | D53: Name: QA Interest Rate 5 Percent Loan type: QA Non-Revolving Start date: 2026-08-01 Interest rate: 5.0000% Notes: Client QA rate | E53: 1. Sign in to Sage Intacct with the test user. 2. Navigate to Applications > Lending Management > Loan interest rate. 3. Open or select the disposable record and initiate Delete. 4. Perform the scenario action: Delete redirects to list. 5. Confirm the action when prompted. 6. Observe the page, messages, saved data, balances, and related records as applicable. | F53: Back on "Loan interest rates" list after confirm | G53: TEST_CASES_Loan_Interest_Rate.xlsx / TC-LIR-043 | H53: TBD | I53: Not Executed | J53: Source section: E. Delete (IDs: TC-LIR-039–043)

Sheet LME Loan Category
A1: Lending - Loan Category
A2: Common Preconditions | C2: 1. User is signed in to Sage Intacct. 2. The correct Lending Management or Depository Management entity is selected. 3. The module is enabled for the company. 4. The user has the permission required for the scenario. 5. Required master/configuration records are active and available.
A4: Navigation: Applications > Lending Management > Loan account category | Client baseline | 68 test cases | Updated 2026-08-27
A6: Test Case ID | B6: Test Scenario | C6: Preconditions | D6: Test Data | E6: Test Steps | F6: Expected Result | G6: Requirement/Jira Reference | H6: IS Automated | I6: Status | J6: Comments
A7: CREATE (46 test cases)
A8: LME-LC-001 | B8: verify that create page contains following sections Loan category information | C8: Refer to Common Preconditions above. | D8: Name: QA Loan Category Description: Client QA loan category User role: Full Access | E8: 1. Sign in to Sage Intacct with the test user. 2. Navigate to Applications > Lending Management > Loan account category. 3. Click Create and populate the form using the stated test data. 4. Perform the scenario action: verify that create page contains following sections Loan category information. 5. Click Save or the applicable submit action. 6. Observe the page, messages, saved data, balances, and related records as applicable. | F8: Create page contains following sections Loan category information. | G8: SNL final test cases.xlsx / Loan Category - CRUD / row 9 | H8: TBD | I8: Not Executed
A9: LME-LC-002 | B9: Verify that Name is a mandatory field with red * mark | C9: Refer to Common Preconditions above. | D9: Other required fields: Use the valid values listed below Target field: Blank Name: QA Loan Category Description: Client QA loan category Status: Active | E9: 1. Sign in to Sage Intacct with the test user. 2. Navigate to Applications > Lending Management > Loan account category. 3. Open the page or record relevant to the scenario. 4. Perform the scenario action: Verify that Name is a mandatory field with red * mark. 5. Apply or complete the action where applicable. 6. Observe the page, messages, saved data, balances, and related records as applicable. | F9: Name is a mandatory field with red * mark. | G9: SNL final test cases.xlsx / Loan Category - CRUD / row 10 | H9: TBD | I9: Not Executed
A10: LME-LC-003 | B10: Verify record can be created successfully with a valid name | C10: Refer to Common Preconditions above. | D10: Name: QA Loan Category Description: Client QA loan category Status: Active | E10: 1. Sign in to Sage Intacct with the test user. 2. Navigate to Applications > Lending Management > Loan account category. 3. Click Create and populate the form using the stated test data. 4. Perform the scenario action: Verify record can be created successfully with a valid name. 5. Click Save or the applicable submit action. 6. Observe the page, messages, saved data, balances, and related records as applicable. | F10: Record can be created successfully with a valid name. | G10: SNL final test cases.xlsx / Loan Category - CRUD / row 11 | H10: TBD | I10: Not Executed
A11: LME-LC-004 | B11: Verify max length of name is 200 characters | C11: Refer to Common Preconditions above. | D11: Boundary value 3: Configured limit + 1 characters Boundary value 2: Configured limit characters Boundary value 1: Configured limit - 1 characters Name: QA Loan Category Description: Client QA loan category Status: Active | E11: 1. Sign in to Sage Intacct with the test user. 2. Navigate to Applications > Lending Management > Loan account category. 3. Open the page or record relevant to the scenario. 4. Perform the scenario action: Verify max length of name is 200 characters. 5. Apply or complete the action where applicable. 6. Observe the page, messages, saved data, balances, and related records as applicable. | F11: Max length of name is 200 characters. | G11: SNL final test cases.xlsx / Loan Category - CRUD / row 12 | H11: TBD | I11: Not Executed
A12: LME-LC-005 | B12: Verify that an error is returned when the name field value is more than 200 character | C12: Refer to Common Preconditions above. | D12: Boundary value 3: Configured limit + 1 characters Boundary value 2: Configured limit characters Boundary value 1: Configured limit - 1 characters Name: QA Loan Category Description: Client QA loan category Status: Active | E12: 1. Sign in to Sage Intacct with the test user. 2. Navigate to Applications > Lending Management > Loan account category. 3. Open the page or record relevant to the scenario. 4. Perform the scenario action: Verify that an error is returned when the name field value is more than 200 character. 5. Apply or complete the action where applicable. 6. Observe the page, messages, saved data, balances, and related records as applicable. | F12: An error is returned when the name field value is more than 200 character. | G12: SNL final test cases.xlsx / Loan Category - CRUD / row 13 | H12: TBD | I12: Not Executed
A13: LME-LC-006 | B13: Verify that proper error is returned when the name field value is null/empty string | C13: Refer to Common Preconditions above. | D13: Other required fields: Use the valid values listed below Target field: Blank Name: QA Loan Category Description: Client QA loan category Status: Active | E13: 1. Sign in to Sage Intacct with the test user. 2. Navigate to Applications > Lending Management > Loan account category. 3. Open the page or record relevant to the scenario. 4. Perform the scenario action: Verify that proper error is returned when the name field value is null/empty string. 5. Apply or complete the action where applicable. 6. Observe the page, messages, saved data, balances, and related records as applicable. | F13: Proper error is returned when the name field value is null/empty string. | G13: SNL final test cases.xlsx / Loan Category - CRUD / row 14 | H13: TBD | I13: Not Executed
A14: LME-LC-007 | B14: Verify that an error is returned when the name field value is white space only | C14: Refer to Common Preconditions above. | D14: Name: QA Loan Category Description: Client QA loan category Status: Active | E14: 1. Sign in to Sage Intacct with the test user. 2. Navigate to Applications > Lending Management > Loan account category. 3. Open the page or record relevant to the scenario. 4. Perform the scenario action: Verify that an error is returned when the name field value is white space only. 5. Apply or complete the action where applicable. 6. Observe the page, messages, saved data, balances, and related records as applicable. | F14: An error is returned when the name field value is white space only. | G14: SNL final test cases.xlsx / Loan Category - CRUD / row 15 | H14: TBD | I14: Not Executed
A15: LME-LC-008 | B15: Verify that an error is returned when the name field value is in invalid format | C15: Refer to Common Preconditions above. | D15: Name: QA Loan Category Description: Client QA loan category Status: Active | E15: 1. Sign in to Sage Intacct with the test user. 2. Navigate to Applications > Lending Management > Loan account category. 3. Open the page or record relevant to the scenario. 4. Perform the scenario action: Verify that an error is returned when the name field value is in invalid format. 5. Apply or complete the action where applicable. 6. Observe the page, messages, saved data, balances, and related records as applicable. | F15: An error is returned when the name field value is in invalid format. | G15: SNL final test cases.xlsx / Loan Category - CRUD / row 16 | H15: TBD | I15: Not Executed
A16: LME-LC-009 | B16: Verify Description is not a mandatory field | C16: Refer to Common Preconditions above. | D16: Other required fields: Use the valid values listed below Target field: Blank Name: QA Loan Category Description: Client QA test text Status: Active | E16: 1. Sign in to Sage Intacct with the test user. 2. Navigate to Applications > Lending Management > Loan account category. 3. Open the page or record relevant to the scenario. 4. Perform the scenario action: Verify Description is not a mandatory field. 5. Apply or complete the action where applicable. 6. Observe the page, messages, saved data, balances, and related records as applicable. | F16: Description is not a mandatory field. | G16: SNL final test cases.xlsx / Loan Category - CRUD / row 17 | H16: TBD | I16: Not Executed
A17: LME-LC-010 | B17: Verify that a valid description within 500 characters is accepted | C17: Refer to Common Preconditions above. | D17: Boundary value 3: Configured limit + 1 characters Boundary value 2: Configured limit characters Boundary value 1: Configured limit - 1 characters Name: QA Loan Category Description: Client QA test text Status: Active | E17: 1. Sign in to Sage Intacct with the test user. 2. Navigate to Applications > Lending Management > Loan account category. 3. Open the page or record relevant to the scenario. 4. Perform the scenario action: Verify that a valid description within 500 characters is accepted. 5. Apply or complete the action where applicable. 6. Observe the page, messages, saved data, balances, and related records as applicable. | F17: A valid description within 500 characters is accepted. | G17: SNL final test cases.xlsx / Loan Category - CRUD / row 18 | H17: TBD | I17: Not Executed
A18: LME-LC-011 | B18: Verify that an empty description is accepted | C18: Refer to Common Preconditions above. | D18: Other required fields: Use the valid values listed below Target field: Blank Name: QA Loan Category Description: Client QA test text Status: Active | E18: 1. Sign in to Sage Intacct with the test user. 2. Navigate to Applications > Lending Management > Loan account category. 3. Open the page or record relevant to the scenario. 4. Perform the scenario action: Verify that an empty description is accepted. 5. Apply or complete the action where applicable. 6. Observe the page, messages, saved data, balances, and related records as applicable. | F18: An empty description is accepted. | G18: SNL final test cases.xlsx / Loan Category - CRUD / row 19 | H18: TBD | I18: Not Executed
A19: LME-LC-012 | B19: Verify that a description exceeding 1000 characters is not allowed | C19: Refer to Common Preconditions above. | D19: Boundary value 3: Configured limit + 1 characters Boundary value 2: Configured limit characters Boundary value 1: Configured limit - 1 characters Amount: 1200.00 Available balance: 1000.00 Name: QA Loan Category Description: Client QA test text Status: Active | E19: 1. Sign in to Sage Intacct with the test user. 2. Navigate to Applications > Lending Management > Loan account category. 3. Open the page or record relevant to the scenario. 4. Perform the scenario action: Verify that a description exceeding 1000 characters is not allowed. 5. Apply or complete the action where applicable. 6. Observe the page, messages, saved data, balances, and related records as applicable. | F19: A description exceeding 1000 characters is not allowed. | G19: SNL final test cases.xlsx / Loan Category - CRUD / row 20 | H19: TBD | I19: Not Executed
... A53: LME-LC-046 | B53: Verify that an invalid request format for document sequence key returns proper error | C53: Refer to Common Preconditions above. | D53: Name: QA Loan Category Description: Client QA loan category Status: Active | E53: 1. Sign in to Sage Intacct with the test user. 2. Navigate to Applications > Lending Management > Loan account category. 3. Open the page or record relevant to the scenario. 4. Perform the scenario action: Verify that an invalid request format for document sequence key returns proper error. 5. Apply or complete the action where applicable. 6. Observe the page, messages, saved data, balances, and related records as applicable. | F53: An invalid request format for document sequence key returns proper error. | G53: SNL final test cases.xlsx / Loan Category - CRUD / row 75 | H53: TBD | I53: Not Executed
A54: EDIT (6 test cases)
A55: LME-LC-047 | B55: Verify 'Edit' button is visible and functional in view page | C55: Refer to Common Preconditions above. | D55: Name: QA Loan Category Description: Client QA loan category Status: Active | E55: 1. Sign in to Sage Intacct with the test user. 2. Navigate to Applications > Lending Management > Loan account category. 3. Open an existing record, click Edit, and change the field(s) relevant to the scenario. 4. Perform the scenario action: Verify 'Edit' button is visible and functional in view page. 5. Click Save or the applicable submit action. 6. Observe the page, messages, saved data, balances, and related records as applicable. | F55: 'Edit' button is visible and functional in view page. | G55: SNL final test cases.xlsx / Loan Category - CRUD / row 43 | H55: TBD | I55: Not Executed
A56: LME-LC-048 | B56: Verify page title is 'Edit loan account category: Name' | C56: Refer to Common Preconditions above. | D56: Name: QA Loan Category Description: Client QA loan category Status: Active | E56: 1. Sign in to Sage Intacct with the test user. 2. Navigate to Applications > Lending Management > Loan account category. 3. Open an existing record, click Edit, and change the field(s) relevant to the scenario. 4. Perform the scenario action: Verify page title is 'Edit loan account category: Name'. 5. Click Save or the applicable submit action. 6. Observe the page, messages, saved data, balances, and related records as applicable. | F56: Page title is 'Edit loan account category: Name'. | G56: SNL final test cases.xlsx / Loan Category - CRUD / row 53 | H56: TBD | I56: Not Executed
A57: LME-LC-049 | B57: Verify record can be edited successfully with a valid name | C57: Refer to Common Preconditions above. | D57: Name: QA Loan Category Description: Client QA loan category Status: Active | E57: 1. Sign in to Sage Intacct with the test user. 2. Navigate to Applications > Lending Management > Loan account category. 3. Open an existing record, click Edit, and change the field(s) relevant to the scenario. 4. Perform the scenario action: Verify record can be edited successfully with a valid name. 5. Click Save or the applicable submit action. 6. Observe the page, messages, saved data, balances, and related records as applicable. | F57: Record can be edited successfully with a valid name. | G57: SNL final test cases.xlsx / Loan Category - CRUD / row 55 | H57: TBD | I57: Not Executed
A58: LME-LC-050 | B58: Verify 'Save' button is visible in edit page | C58: Refer to Common Preconditions above. | D58: Name: QA Loan Category Description: Client QA loan category Status: Active | E58: 1. Sign in to Sage Intacct with the test user. 2. Navigate to Applications > Lending Management > Loan account category. 3. Open an existing record, click Edit, and change the field(s) relevant to the scenario. 4. Perform the scenario action: Verify 'Save' button is visible in edit page. 5. Click Save or the applicable submit action. 6. Observe the page, messages, saved data, balances, and related records as applicable. | F58: 'Save' button is visible in edit page. | G58: SNL final test cases.xlsx / Loan Category - CRUD / row 61 | H58: TBD | I58: Not Executed
A59: LME-LC-051 | B59: Verify category can be edited from any location | C59: Refer to Common Preconditions above. | D59: Name: QA Loan Category Description: Client QA loan category Status: Active | E59: 1. Sign in to Sage Intacct with the test user. 2. Navigate to Applications > Lending Management > Loan account category. 3. Open an existing record, click Edit, and change the field(s) relevant to the scenario. 4. Perform the scenario action: Verify category can be edited from any location. 5. Click Save or the applicable submit action. 6. Observe the page, messages, saved data, balances, and related records as applicable. | F59: Category can be edited from any location. | G59: SNL final test cases.xlsx / Loan Category - CRUD / row 76 | H59: TBD | I59: Not Executed
