Workbook

Sheet Summary
A1: Client Test Cases — Lending and Depository Management
A2: Detailed functional test cases with explicit preconditions, data, steps, and expected results. Statuses are reset for client execution.
A3: OVERNIGHT AUDIT SUMMARY (2026-08-30 18:09:23): 4177 test cases reviewed across 43 sheets | 1 updated | 68 added | 81 scenarios flagged as unverifiable (see 'SCENARIOS NOT VERIFIABLE' sheet).
A5: Module | B5: Area | C5: Test Cases | D5: Automated | E5: Passed | F5: Failed | G5: Not Executed | H5: Blocked
A6: Loan Account | B6: Lending Management | C6: =COUNTA('LME Loan Account'!$B$14:$B$2000) | D6: =COUNTIF('LME Loan Account'!$H$14:$H$2000,"Yes") | E6: =COUNTIF('LME Loan Account'!$I$14:$I$2000,"Passed") | F6: =COUNTIF('LME Loan Account'!$I$14:$I$2000,"Failed") | G6: =COUNTIF('LME Loan Account'!$I$14:$I$2000,"Not Executed") | H6: =COUNTIF('LME Loan Account'!$I$14:$I$2000,"Blocked")
A7: Configuration | B7: Lending Management | C7: =COUNTA('LME Configuration'!$B$14:$B$2000) | D7: =COUNTIF('LME Configuration'!$H$14:$H$2000,"Yes") | E7: =COUNTIF('LME Configuration'!$I$14:$I$2000,"Passed") | F7: =COUNTIF('LME Configuration'!$I$14:$I$2000,"Failed") | G7: =COUNTIF('LME Configuration'!$I$14:$I$2000,"Not Executed") | H7: =COUNTIF('LME Configuration'!$I$14:$I$2000,"Blocked")
A8: Loan Type | B8: Lending Management | C8: =COUNTA('LME Loan Type'!$B$14:$B$2000) | D8: =COUNTIF('LME Loan Type'!$H$14:$H$2000,"Yes") | E8: =COUNTIF('LME Loan Type'!$I$14:$I$2000,"Passed") | F8: =COUNTIF('LME Loan Type'!$I$14:$I$2000,"Failed") | G8: =COUNTIF('LME Loan Type'!$I$14:$I$2000,"Not Executed") | H8: =COUNTIF('LME Loan Type'!$I$14:$I$2000,"Blocked")
A9: Loan Type Standard Automation | B9: Lending Management | C9: =COUNTA('LME Loan Type - Standard'!$B$14:$B$2000) | D9: =COUNTIF('LME Loan Type - Standard'!$H$14:$H$2000,"Yes") | E9: =COUNTIF('LME Loan Type - Standard'!$I$14:$I$2000,"Passed") | F9: =COUNTIF('LME Loan Type - Standard'!$I$14:$I$2000,"Failed") | G9: =COUNTIF('LME Loan Type - Standard'!$I$14:$I$2000,"Not Executed") | H9: =COUNTIF('LME Loan Type - Standard'!$I$14:$I$2000,"Blocked")
A10: Standard Automation Scenarios | B10: Lending Management | C10: =COUNTA('Standard automation scenarios'!$B$14:$B$2000) | D10: =COUNTIF('Standard automation scenarios'!$H$14:$H$2000,"Yes") | E10: =COUNTIF('Standard automation scenarios'!$I$14:$I$2000,"Passed") | F10: =COUNTIF('Standard automation scenarios'!$I$14:$I$2000,"Failed") | G10: =COUNTIF('Standard automation scenarios'!$I$14:$I$2000,"Not Executed") | H10: =COUNTIF('Standard automation scenarios'!$I$14:$I$2000,"Blocked")
A11: Standard Statement Generation and Reversal | B11: Lending Management | C11: =COUNTA('LME Standard Statements'!$B$14:$B$2000) | D11: =COUNTIF('LME Standard Statements'!$H$14:$H$2000,"Yes") | E11: =COUNTIF('LME Standard Statements'!$I$14:$I$2000,"Passed") | F11: =COUNTIF('LME Standard Statements'!$I$14:$I$2000,"Failed") | G11: =COUNTIF('LME Standard Statements'!$I$14:$I$2000,"Not Executed") | H11: =COUNTIF('LME Standard Statements'!$I$14:$I$2000,"Blocked")
A12: Standard Statement Generation & Reversal - Detailed | B12: Lending Management | C12: =COUNTA('LME Std Stmt Gen Rev'!$B$14:$B$2000) | D12: =COUNTIF('LME Std Stmt Gen Rev'!$H$14:$H$2000,"Yes") | E12: =COUNTIF('LME Std Stmt Gen Rev'!$I$14:$I$2000,"Passed") | F12: =COUNTIF('LME Std Stmt Gen Rev'!$I$14:$I$2000,"Failed") | G12: =COUNTIF('LME Std Stmt Gen Rev'!$I$14:$I$2000,"Not Executed") | H12: =COUNTIF('LME Std Stmt Gen Rev'!$I$14:$I$2000,"Blocked")
A13: Loan Interest Rate | B13: Lending Management | C13: =COUNTA('LME Interest Rate'!$B$14:$B$2000) | D13: =COUNTIF('LME Interest Rate'!$H$14:$H$2000,"Yes") | E13: =COUNTIF('LME Interest Rate'!$I$14:$I$2000,"Passed") | F13: =COUNTIF('LME Interest Rate'!$I$14:$I$2000,"Failed") | G13: =COUNTIF('LME Interest Rate'!$I$14:$I$2000,"Not Executed") | H13: =COUNTIF('LME Interest Rate'!$I$14:$I$2000,"Blocked")
A14: Interest Calculation (Monthly) | B14: Lending Management | C14: =COUNTA('LME Interest Calc - Monthly'!$B$14:$B$2000) | D14: =COUNTIF('LME Interest Calc - Monthly'!$H$14:$H$2000,"Yes") | E14: =COUNTIF('LME Interest Calc - Monthly'!$I$14:$I$2000,"Passed") | F14: =COUNTIF('LME Interest Calc - Monthly'!$I$14:$I$2000,"Failed") | G14: =COUNTIF('LME Interest Calc - Monthly'!$I$14:$I$2000,"Not Executed") | H14: =COUNTIF('LME Interest Calc - Monthly'!$I$14:$I$2000,"Blocked")
A15: Interest Calculation (Standard) | B15: Lending Management | C15: =COUNTA('LME Interest Calc - Standard'!$B$14:$B$2000) | D15: =COUNTIF('LME Interest Calc - Standard'!$H$14:$H$2000,"Yes") | E15: =COUNTIF('LME Interest Calc - Standard'!$I$14:$I$2000,"Passed") | F15: =COUNTIF('LME Interest Calc - Standard'!$I$14:$I$2000,"Failed") | G15: =COUNTIF('LME Interest Calc - Standard'!$I$14:$I$2000,"Not Executed") | H15: =COUNTIF('LME Interest Calc - Standard'!$I$14:$I$2000,"Blocked")
A16: Loan Category | B16: Lending Management | C16: =COUNTA('LME Loan Category'!$B$14:$B$1995) | D16: =COUNTIF('LME Loan Category'!$H$14:$H$1995,"Yes") | E16: =COUNTIF('LME Loan Category'!$I$14:$I$1995,"Passed") | F16: =COUNTIF('LME Loan Category'!$I$14:$I$1995,"Failed") | G16: =COUNTIF('LME Loan Category'!$I$14:$I$1995,"Not Executed") | H16: =COUNTIF('LME Loan Category'!$I$14:$I$1995,"Blocked")
A17: Loan Fee Type | B17: Lending Management | C17: =COUNTA('LME Loan Fee Type'!$B$14:$B$2000) | D17: =COUNTIF('LME Loan Fee Type'!$H$14:$H$2000,"Yes") | E17: =COUNTIF('LME Loan Fee Type'!$I$14:$I$2000,"Passed") | F17: =COUNTIF('LME Loan Fee Type'!$I$14:$I$2000,"Failed") | G17: =COUNTIF('LME Loan Fee Type'!$I$14:$I$2000,"Not Executed") | H17: =COUNTIF('LME Loan Fee Type'!$I$14:$I$2000,"Blocked")
A18: Fee Capitalization | B18: Lending Management | C18: =COUNTA('LME Fee Capitalization'!$B$14:$B$2000) | D18: =COUNTIF('LME Fee Capitalization'!$H$14:$H$2000,"Yes") | E18: =COUNTIF('LME Fee Capitalization'!$I$14:$I$2000,"Passed") | F18: =COUNTIF('LME Fee Capitalization'!$I$14:$I$2000,"Failed") | G18: =COUNTIF('LME Fee Capitalization'!$I$14:$I$2000,"Not Executed") | H18: =COUNTIF('LME Fee Capitalization'!$I$14:$I$2000,"Blocked")
A19: Loan Adjustment | B19: Lending Management | C19: =COUNTA('LME Loan Adjustment'!$B$14:$B$2000) | D19: =COUNTIF('LME Loan Adjustment'!$H$14:$H$2000,"Yes") | E19: =COUNTIF('LME Loan Adjustment'!$I$14:$I$2000,"Passed") | F19: =COUNTIF('LME Loan Adjustment'!$I$14:$I$2000,"Failed") | G19: =COUNTIF('LME Loan Adjustment'!$I$14:$I$2000,"Not Executed") | H19: =COUNTIF('LME Loan Adjustment'!$I$14:$I$2000,"Blocked")
A20: Loan Write-Off | B20: Lending Management | C20: =COUNTA('LME Loan Write-Off'!$B$14:$B$2000) | D20: =COUNTIF('LME Loan Write-Off'!$H$14:$H$2000,"Yes") | E20: =COUNTIF('LME Loan Write-Off'!$I$14:$I$2000,"Passed") | F20: =COUNTIF('LME Loan Write-Off'!$I$14:$I$2000,"Failed") | G20: =COUNTIF('LME Loan Write-Off'!$I$14:$I$2000,"Not Executed") | H20: =COUNTIF('LME Loan Write-Off'!$I$14:$I$2000,"Blocked")
A21: Loan Statements | B21: Lending Management | C21: =COUNTA('LME Statements'!$B$14:$B$2000) | D21: =COUNTIF('LME Statements'!$H$14:$H$2000,"Yes") | E21: =COUNTIF('LME Statements'!$I$14:$I$2000,"Passed") | F21: =COUNTIF('LME Statements'!$I$14:$I$2000,"Failed") | G21: =COUNTIF('LME Statements'!$I$14:$I$2000,"Not Executed") | H21: =COUNTIF('LME Statements'!$I$14:$I$2000,"Blocked")
A22: Interest and Statement Periods Workflow | B22: Lending Management | C22: =COUNTA('LME Interest and Stmt Runs'!$B$14:$B$2000) | D22: =COUNTIF('LME Interest and Stmt Runs'!$H$14:$H$2000,"Yes") | E22: =COUNTIF('LME Interest and Stmt Runs'!$I$14:$I$2000,"Passed") | F22: =COUNTIF('LME Interest and Stmt Runs'!$I$14:$I$2000,"Failed") | G22: =COUNTIF('LME Interest and Stmt Runs'!$I$14:$I$2000,"Not Executed") | H22: =COUNTIF('LME Interest and Stmt Runs'!$I$14:$I$2000,"Blocked")
A23: Loan Ledger Report | B23: Lending Management | C23: =COUNTA('LME Ledger Report'!$B$14:$B$2000) | D23: =COUNTIF('LME Ledger Report'!$H$14:$H$2000,"Yes") | E23: =COUNTIF('LME Ledger Report'!$I$14:$I$2000,"Passed") | F23: =COUNTIF('LME Ledger Report'!$I$14:$I$2000,"Failed") | G23: =COUNTIF('LME Ledger Report'!$I$14:$I$2000,"Not Executed") | H23: =COUNTIF('LME Ledger Report'!$I$14:$I$2000,"Blocked")
A24: Roll Forward Report | B24: Lending Management | C24: =COUNTA('LME Roll Forward'!$B$14:$B$2000) | D24: =COUNTIF('LME Roll Forward'!$H$14:$H$2000,"Yes") | E24: =COUNTIF('LME Roll Forward'!$I$14:$I$2000,"Passed") | F24: =COUNTIF('LME Roll Forward'!$I$14:$I$2000,"Failed") | G24: =COUNTIF('LME Roll Forward'!$I$14:$I$2000,"Not Executed") | H24: =COUNTIF('LME Roll Forward'!$I$14:$I$2000,"Blocked")
A25: Loan Payment | B25: Lending Management | C25: =COUNTA('LME Loan Payment from depositor'!$B$14:$B$2000) | D25: =COUNTIF('LME Loan Payment from depositor'!$H$14:$H$2000,"Yes") | E25: =COUNTIF('LME Loan Payment from depositor'!$I$14:$I$2000,"Passed") | F25: =COUNTIF('LME Loan Payment from depositor'!$I$14:$I$2000,"Failed") | G25: =COUNTIF('LME Loan Payment from depositor'!$I$14:$I$2000,"Not Executed") | H25: =COUNTIF('LME Loan Payment from depositor'!$I$14:$I$2000,"Blocked")
A26: Overpayment | B26: Lending Management | C26: =COUNTA('LME Overpayment'!$B$14:$B$2000) | D26: =COUNTIF('LME Overpayment'!$H$14:$H$2000,"Yes") | E26: =COUNTIF('LME Overpayment'!$I$14:$I$2000,"Passed") | F26: =COUNTIF('LME Overpayment'!$I$14:$I$2000,"Failed") | G26: =COUNTIF('LME Overpayment'!$I$14:$I$2000,"Not Executed") | H26: =COUNTIF('LME Overpayment'!$I$14:$I$2000,"Blocked")
A27: Loan Invoice UI | B27: Lending Management | C27: =COUNTA('LME Invoice UI'!$B$14:$B$2000) | D27: =COUNTIF('LME Invoice UI'!$H$14:$H$2000,"Yes") | E27: =COUNTIF('LME Invoice UI'!$I$14:$I$2000,"Passed") | F27: =COUNTIF('LME Invoice UI'!$I$14:$I$2000,"Failed") | G27: =COUNTIF('LME Invoice UI'!$I$14:$I$2000,"Not Executed") | H27: =COUNTIF('LME Invoice UI'!$I$14:$I$2000,"Blocked")
A28: AR Payment | B28: Lending Management | C28: =COUNTA('LME AR Payment'!$B$14:$B$2000) | D28: =COUNTIF('LME AR Payment'!$H$14:$H$2000,"Yes") | E28: =COUNTIF('LME AR Payment'!$I$14:$I$2000,"Passed") | F28: =COUNTIF('LME AR Payment'!$I$14:$I$2000,"Failed") | G28: =COUNTIF('LME AR Payment'!$I$14:$I$2000,"Not Executed") | H28: =COUNTIF('LME AR Payment'!$I$14:$I$2000,"Blocked")
A29: Payment & Payoff | B29: Lending Management | C29: =COUNTA('LME Payment & Payoff'!$B$14:$B$2000) | D29: =COUNTIF('LME Payment & Payoff'!$H$14:$H$2000,"Yes") | E29: =COUNTIF('LME Payment & Payoff'!$I$14:$I$2000,"Passed") | F29: =COUNTIF('LME Payment & Payoff'!$I$14:$I$2000,"Failed") | G29: =COUNTIF('LME Payment & Payoff'!$I$14:$I$2000,"Not Executed") | H29: =COUNTIF('LME Payment & Payoff'!$I$14:$I$2000,"Blocked")
A30: View Audit Trail | B30: Lending Management | C30: =COUNTA('LME Audit Trail'!$B$14:$B$2000) | D30: =COUNTIF('LME Audit Trail'!$H$14:$H$2000,"Yes") | E30: =COUNTIF('LME Audit Trail'!$I$14:$I$2000,"Passed") | F30: =COUNTIF('LME Audit Trail'!$I$14:$I$2000,"Failed") | G30: =COUNTIF('LME Audit Trail'!$I$14:$I$2000,"Not Executed") | H30: =COUNTIF('LME Audit Trail'!$I$14:$I$2000,"Blocked")
A31: Permissions | B31: Lending Management | C31: =COUNTA('LME Permissions'!$B$14:$B$2000) | D31: =COUNTIF('LME Permissions'!$H$14:$H$2000,"Yes") | E31: =COUNTIF('LME Permissions'!$I$14:$I$2000,"Passed") | F31: =COUNTIF('LME Permissions'!$I$14:$I$2000,"Failed") | G31: =COUNTIF('LME Permissions'!$I$14:$I$2000,"Not Executed") | H31: =COUNTIF('LME Permissions'!$I$14:$I$2000,"Blocked")
A32: UI Copy / Label Changes | B32: Lending Management | C32: =COUNTA('LME UI Copy Changes'!$B$14:$B$2000)
A33: Account | B33: Depository Management | C33: =COUNTA('DMS Account'!$B$14:$B$2000) | D33: =COUNTIF('DMS Account'!$H$14:$H$2000,"Yes") | E33: =COUNTIF('DMS Account'!$I$14:$I$2000,"Passed") | F33: =COUNTIF('DMS Account'!$I$14:$I$2000,"Failed") | G33: =COUNTIF('DMS Account'!$I$14:$I$2000,"Not Executed") | H33: =COUNTIF('DMS Account'!$I$14:$I$2000,"Blocked")
A34: Details & Daily Interest | B34: Depository Management | C34: =COUNTA('DMS Details & Interest'!$B$14:$B$2000) | D34: =COUNTIF('DMS Details & Interest'!$H$14:$H$2000,"Yes") | E34: =COUNTIF('DMS Details & Interest'!$I$14:$I$2000,"Passed") | F34: =COUNTIF('DMS Details & Interest'!$I$14:$I$2000,"Failed") | G34: =COUNTIF('DMS Details & Interest'!$I$14:$I$2000,"Not Executed") | H34: =COUNTIF('DMS Details & Interest'!$I$14:$I$2000,"Blocked")
A35: Configuration | B35: Depository Management | C35: =COUNTA('DMS Configuration'!$B$14:$B$2000) | D35: =COUNTIF('DMS Configuration'!$H$14:$H$2000,"Yes") | E35: =COUNTIF('DMS Configuration'!$I$14:$I$2000,"Passed") | F35: =COUNTIF('DMS Configuration'!$I$14:$I$2000,"Failed") | G35: =COUNTIF('DMS Configuration'!$I$14:$I$2000,"Not Executed") | H35: =COUNTIF('DMS Configuration'!$I$14:$I$2000,"Blocked")
A36: Account Category | B36: Depository Management | C36: =COUNTA('DMS Account Category'!$B$14:$B$2000) | D36: =COUNTIF('DMS Account Category'!$H$14:$H$2000,"Yes") | E36: =COUNTIF('DMS Account Category'!$I$14:$I$2000,"Passed") | F36: =COUNTIF('DMS Account Category'!$I$14:$I$2000,"Failed") | G36: =COUNTIF('DMS Account Category'!$I$14:$I$2000,"Not Executed") | H36: =COUNTIF('DMS Account Category'!$I$14:$I$2000,"Blocked")
A37: Interest Rate | B37: Depository Management | C37: =COUNTA('DMS Interest Rate'!$B$14:$B$2000) | D37: =COUNTIF('DMS Interest Rate'!$H$14:$H$2000,"Yes") | E37: =COUNTIF('DMS Interest Rate'!$I$14:$I$2000,"Passed") | F37: =COUNTIF('DMS Interest Rate'!$I$14:$I$2000,"Failed") | G37: =COUNTIF('DMS Interest Rate'!$I$14:$I$2000,"Not Executed") | H37: =COUNTIF('DMS Interest Rate'!$I$14:$I$2000,"Blocked")
A38: Fee Type | B38: Depository Management | C38: =COUNTA('DMS Fee Type'!$B$14:$B$2000) | D38: =COUNTIF('DMS Fee Type'!$H$14:$H$2000,"Yes") | E38: =COUNTIF('DMS Fee Type'!$I$14:$I$2000,"Passed") | F38: =COUNTIF('DMS Fee Type'!$I$14:$I$2000,"Failed") | G38: =COUNTIF('DMS Fee Type'!$I$14:$I$2000,"Not Executed") | H38: =COUNTIF('DMS Fee Type'!$I$14:$I$2000,"Blocked")
A39: Other Adjustment | B39: Depository Management | C39: =COUNTA('DMS Other Adj Type'!$B$14:$B$2000) | D39: =COUNTIF('DMS Other Adj Type'!$H$14:$H$2000,"Yes") | E39: =COUNTIF('DMS Other Adj Type'!$I$14:$I$2000,"Passed") | F39: =COUNTIF('DMS Other Adj Type'!$I$14:$I$2000,"Failed") | G39: =COUNTIF('DMS Other Adj Type'!$I$14:$I$2000,"Not Executed") | H39: =COUNTIF('DMS Other Adj Type'!$I$14:$I$2000,"Blocked")
A40: Adjustment | B40: Depository Management | C40: =COUNTA('DMS Adjustment'!$B$14:$B$2000) | D40: =COUNTIF('DMS Adjustment'!$H$14:$H$2000,"Yes") | E40: =COUNTIF('DMS Adjustment'!$I$14:$I$2000,"Passed") | F40: =COUNTIF('DMS Adjustment'!$I$14:$I$2000,"Failed") | G40: =COUNTIF('DMS Adjustment'!$I$14:$I$2000,"Not Executed") | H40: =COUNTIF('DMS Adjustment'!$I$14:$I$2000,"Blocked")
A41: Deposits | B41: Depository Management | C41: =COUNTA('DMS Deposits'!$B$14:$B$2000) | D41: =COUNTIF('DMS Deposits'!$H$14:$H$2000,"Yes") | E41: =COUNTIF('DMS Deposits'!$I$14:$I$2000,"Passed") | F41: =COUNTIF('DMS Deposits'!$I$14:$I$2000,"Failed") | G41: =COUNTIF('DMS Deposits'!$I$14:$I$2000,"Not Executed") | H41: =COUNTIF('DMS Deposits'!$I$14:$I$2000,"Blocked")
A42: Withdrawal | B42: Depository Management | C42: =COUNTA('DMS Withdrawal'!$B$14:$B$2000) | D42: =COUNTIF('DMS Withdrawal'!$H$14:$H$2000,"Yes") | E42: =COUNTIF('DMS Withdrawal'!$I$14:$I$2000,"Passed") | F42: =COUNTIF('DMS Withdrawal'!$I$14:$I$2000,"Failed") | G42: =COUNTIF('DMS Withdrawal'!$I$14:$I$2000,"Not Executed") | H42: =COUNTIF('DMS Withdrawal'!$I$14:$I$2000,"Blocked")
A43: Transfer | B43: Depository Management | C43: =COUNTA('DMS Transfer'!$B$14:$B$2000) | D43: =COUNTIF('DMS Transfer'!$H$14:$H$2000,"Yes") | E43: =COUNTIF('DMS Transfer'!$I$14:$I$2000,"Passed") | F43: =COUNTIF('DMS Transfer'!$I$14:$I$2000,"Failed") | G43: =COUNTIF('DMS Transfer'!$I$14:$I$2000,"Not Executed") | H43: =COUNTIF('DMS Transfer'!$I$14:$I$2000,"Blocked")
A44: Close Account | B44: Depository Management | C44: =COUNTA('DMS Close Account'!$B$14:$B$2000) | D44: =COUNTIF('DMS Close Account'!$H$14:$H$2000,"Yes") | E44: =COUNTIF('DMS Close Account'!$I$14:$I$2000,"Passed") | F44: =COUNTIF('DMS Close Account'!$I$14:$I$2000,"Failed") | G44: =COUNTIF('DMS Close Account'!$I$14:$I$2000,"Not Executed") | H44: =COUNTIF('DMS Close Account'!$I$14:$I$2000,"Blocked")
A45: Interest and Statement Periods Workflow | B45: Depository Management | C45: =COUNTA('DMS Interest and Stmt Runs'!$B$14:$B$2000) | D45: =COUNTIF('DMS Interest and Stmt Runs'!$H$14:$H$2000,"Yes") | E45: =COUNTIF('DMS Interest and Stmt Runs'!$I$14:$I$2000,"Passed") | F45: =COUNTIF('DMS Interest and Stmt Runs'!$I$14:$I$2000,"Failed") | G45: =COUNTIF('DMS Interest and Stmt Runs'!$I$14:$I$2000,"Not Executed") | H45: =COUNTIF('DMS Interest and Stmt Runs'!$I$14:$I$2000,"Blocked")
A46: Statements | B46: Depository Management | C46: =COUNTA('DMS Statements'!$B$14:$B$2000) | D46: =COUNTIF('DMS Statements'!$H$14:$H$2000,"Yes") | E46: =COUNTIF('DMS Statements'!$I$14:$I$2000,"Passed") | F46: =COUNTIF('DMS Statements'!$I$14:$I$2000,"Failed") | G46: =COUNTIF('DMS Statements'!$I$14:$I$2000,"Not Executed") | H46: =COUNTIF('DMS Statements'!$I$14:$I$2000,"Blocked")
A47: Bulk Action Runs | B47: Depository Management | C47: =COUNTA('DMS Bulk Action Runs'!$B$14:$B$2000) | D47: =COUNTIF('DMS Bulk Action Runs'!$H$14:$H$2000,"Yes") | E47: =COUNTIF('DMS Bulk Action Runs'!$I$14:$I$2000,"Passed") | F47: =COUNTIF('DMS Bulk Action Runs'!$I$14:$I$2000,"Failed") | G47: =COUNTIF('DMS Bulk Action Runs'!$I$14:$I$2000,"Not Executed") | H47: =COUNTIF('DMS Bulk Action Runs'!$I$14:$I$2000,"Blocked")
A48: Ledger Report | B48: Depository Management | C48: =COUNTA('DMS Ledger Report'!$B$14:$B$2000) | D48: =COUNTIF('DMS Ledger Report'!$H$14:$H$2000,"Yes") | E48: =COUNTIF('DMS Ledger Report'!$I$14:$I$2000,"Passed") | F48: =COUNTIF('DMS Ledger Report'!$I$14:$I$2000,"Failed") | G48: =COUNTIF('DMS Ledger Report'!$I$14:$I$2000,"Not Executed") | H48: =COUNTIF('DMS Ledger Report'!$I$14:$I$2000,"Blocked")
A49: Roll Forward Report | B49: Depository Management | C49: =COUNTA('DMS Roll Forward'!$B$14:$B$2000) | D49: =COUNTIF('DMS Roll Forward'!$H$14:$H$2000,"Yes") | E49: =COUNTIF('DMS Roll Forward'!$I$14:$I$2000,"Passed") | F49: =COUNTIF('DMS Roll Forward'!$I$14:$I$2000,"Failed") | G49: =COUNTIF('DMS Roll Forward'!$I$14:$I$2000,"Not Executed") | H49: =COUNTIF('DMS Roll Forward'!$I$14:$I$2000,"Blocked")
A50: Permissions | B50: Depository Management | C50: =COUNTA('DMS Permissions'!$B$14:$B$2000) | D50: =COUNTIF('DMS Permissions'!$H$14:$H$2000,"Yes") | E50: =COUNTIF('DMS Permissions'!$I$14:$I$2000,"Passed") | F50: =COUNTIF('DMS Permissions'!$I$14:$I$2000,"Failed") | G50: =COUNTIF('DMS Permissions'!$I$14:$I$2000,"Not Executed") | H50: =COUNTIF('DMS Permissions'!$I$14:$I$2000,"Blocked")
A51: IADSSL-1792 | B51: Depository Management | C51: =COUNTA('IADSSL-1792'!$A$7:$A$25)-4 | D51: =COUNTIF('IADSSL-1792'!$H$7:$H$25,"Yes") | E51: =COUNTIF('IADSSL-1792'!$I$7:$I$25,"Passed") | F51: =COUNTIF('IADSSL-1792'!$I$7:$I$25,"Failed") | G51: =COUNTIF('IADSSL-1792'!$I$7:$I$25,"Not Executed") | H51: =COUNTIF('IADSSL-1792'!$I$7:$I$25,"Blocked")
A52: TOTAL | C52: =SUM(C5:C51) | D52: =SUM(D5:D51) | E52: =SUM(E5:E51) | F52: =SUM(F5:F51) | G52: =SUM(G5:G51) | H52: =SUM(H5:H51)
A54: Scope and usage notes
A55: 1. All test-case sheets use the exact 10 requested columns.
A56: 2. Status defaults to Not Executed; IS Automated defaults to TBD until the automation inventory is approved.
A57: 3. Existing scenarios were normalized from the supplied regression/test-case workbooks; prior execution results and defect commentary were intentionally not carried into the client baseline.
A58: 4. New Deposits, Withdrawal, Transfer, Close Depository Account, Statements, and Lending Overpayment cases are requirement-based design coverage. Jira references are marked TBD until approved requirement keys are supplied.
A59: 5. Items whose behavior depends on product policy (for example cross-currency transfers, account reopening, and overpayment disposition/allocation) are flagged in Comments for client confirmation.

Sheet LME Loan Category
A1: Prepared By | B1: Subah Tasnim Shiary | D1: Total Test Cases | E1: =COUNTA('LME Loan Category'!$B$14:$B$1995)
A2: Executed By | B2: Subah Tasnim Shiary | D2: Passed | E2: =COUNTIF('LME Loan Category'!$I$14:$I$1995,"Passed")
A3: Updated On | B3: 46262 | D3: Failed | E3: =COUNTIF('LME Loan Category'!$I$14:$I$1995,"Failed")
A4: Time est | B4: Initial testing: | D4: Untested | E4: =COUNTIF('LME Loan Category'!$I$14:$I$1995,"Not Executed")
B5: Bugfix testing: | D5: To be tested | E5: =COUNTIF('LME Loan Category'!$I$14:$I$1995,"In Progress")+COUNTIF('LME Loan Category'!$I$14:$I$1995,"Blocked")
A6: common preconditions
A7: navigation
A8: Lending - Loan Category
A9: Common Preconditions | C9: 1. User is signed in to Sage Intacct. 2. The correct Lending Management or Depository Management entity is selected. 3. The module is enabled for the company. 4. The user has the permission required for the scenario. 5. Required master/configuration records are active and available.
A11: Navigation: Applications > Lending Management > Loan account category | Client baseline | 103 test cases | Updated 2026-08-31
A13: Test Case ID | B13: Test Scenario | C13: Preconditions | D13: Test Data | E13: Test Steps | F13: Expected Result | G13: Requirement/Jira Reference | H13: IS Automated | I13: Status | J13: Comments
A14: LISTER (39 test cases)
A15: LC-001 | B15: Verify the lister page title/heading identifies the Loan account category list | C15: Refer to Common Preconditions above. Navigate to Applications > Lending Management > Loan account category to open the lister page. | D15: N/A (observation only) | E15: 1. Sign in to Sage Intacct application 2. Navigate to Applications > Lending Management > Loan account category 3. Observe the page title/heading at the top of the lister page. | F15: - The lister page displays a clear title - 'Loan account categories'. | G15: IADSSL-101 | H15: No | I15: Not Executed
A16: LC-002 | B16: Verify the lister grid displays the documented columns | C16: Refer to Common Preconditions above. | D16: Expected default columns: Name, Document sequence | E16: 1. Sign in to Sage Intacct application 2. Navigate to Applications > Lending Management > Loan account category 3. Observe the columns displayed in the lister grid by default. | F16: - The lister grid displays the following columns by default: Name, Document sequence. - Status is available via Configure columns but is not shown by default. | G16: IADSSL-101 | H16: No | I16: Not Executed
A17: LC-003 | B17: Verify no column is sorted by default | C17: Refer to Common Preconditions above. | D17: N/A (observation only) | E17: 1. Sign in to Sage Intacct application 2. Navigate to Applications > Lending Management > Loan account category 3. Observe the column headers on page load for a default sort indicator. | F17: - The 'Name' column is sorted ascending by default, shown by an upward arrow indicator. - No other column shows a sort indicator. | G17: IADSSL-101 | H17: No | I17: Not Executed
A18: LC-004 | B18: Verify Name is a drillable field that routes to the View loan account category screen | C18: Refer to Common Preconditions above. | D18: Name: QA Loan Category A (existing record) | E18: 1. Sign in to Sage Intacct application 2. Navigate to Applications > Lending Management > Loan account category 3. Click a row's value in the Name column. | F18: - Clicking the Name value navigates to the View loan account category screen for that record. | G18: IADSSL-101 | H18: No | I18: Not Executed
A19: LC-005 | B19: Verify Document sequence is a drillable field that routes to the View loan account category screen | C19: Refer to Common Preconditions above. | D19: Document sequence: existing record with a populated Document sequence value | E19: 1. Sign in to Sage Intacct application 2. Navigate to Applications > Lending Management > Loan account category 3. Click a row's value in the Document sequence column. | F19: - Clicking the Document sequence value navigates to the View loan account category screen for that record. | G19: IADSSL-101 | H19: No | I19: Not Executed
A20: LC-006 | B20: Verify the '+Create' button is present and functional | C20: Refer to Common Preconditions above. | D20: N/A (observation/action only) | E20: 1. Sign in to Sage Intacct application 2. Navigate to Applications > Lending Management > Loan account category 3. Locate the '+Create' button at the top right of the lister page. 4. Click the '+Create' button. | F20: - The '+Create' button is located at the top right of the lister page. - Clicking the '+Create' button redirects to the 'Create loan account category' page. | G20: IADSSL-101 | H20: No | I20: Not Executed
A21: LC-007 | B21: Verify the lister view-selection dropdown functionality | C21: Refer to Common Preconditions above. | D21: N/A (observation only) | E21: 1. Sign in to Sage Intacct application 2. Navigate to Applications > Lending Management > Loan account category 3. Click the view-selection dropdown at the top left of the lister. 4. Select a view from the list. | F21: - Clicking the view dropdown opens a list with a 'Search for view' field, a 'System views' section (including 'All'), and a 'User views' section. - Selecting any view updates the lister to reflect that view. | G21: IADSSL-101 | H21: No | I21: Not Executed
A22: LC-008 | B22: Verify the Split view / List view toggle | C22: Refer to Common Preconditions above. | D22: N/A (observation only) | E22: 1. Sign in to Sage Intacct application 2. Navigate to Applications > Lending Management > Loan account category 3. Click the Split view icon. 4. Click the List view icon. | F22: - Split view splits the screen into the lister on the left and the record detail on the right. - List view shows only the lister in full screen. | G22: IADSSL-101 | H22: No | I22: Not Executed
A23: LC-009 | B23: Verify the 'Filters' button opens the Advanced filter modal | C23: Refer to Common Preconditions above. | D23: N/A (observation only) | E23: 1. Sign in to Sage Intacct application 2. Navigate to Applications > Lending Management > Loan account category 3. Click the 'Filters' button at the top right of the lister. | F23: - A modal titled 'Advanced filter' opens containing Field/Operator/Value/Apply-criteria columns, Apply and Cancel buttons, and per-row '+' (add) and '-' (remove) controls. - No filters are selected by default. | G23: IADSSL-101 | H23: No | I23: Not Executed
A24: LC-010 | B24: Verify the Advanced filter 'Apply' button applies and persists filter changes | C24: Refer to Common Preconditions above. | D24: Filter row: Field = Name, Operator = Contains, Value = QA | E24: 1. Sign in to Sage Intacct application 2. Navigate to Applications > Lending Management > Loan account category 3. Click 'Filters' to open the Advanced filter modal. 4. Set Field = Name, Operator = Contains, Value = QA, then click 'Apply'. 5. Reopen Advanced filters. | F24: - The modal closes and the list updates to reflect the filter changes. - Reopening Advanced filters shows the previously applied filters persisted. - Rows left without any Field/Operator/Value are ignored. | G24: IADSSL-101 | H24: No | I24: Not Executed
A25: LC-011 | B25: Verify column filters and Advanced filters stay in sync | C25: Refer to Common Preconditions above. | D25: Column filter: Name column, value = QA | E25: 1. Sign in to Sage Intacct application 2. Navigate to Applications > Lending Management > Loan account category 3. Enter 'QA' in the Name column's filter input and press Enter. 4. Open the Advanced filter modal and check whether the filter appears there. 5. Add/edit a filter in the Advanced filter modal and check it is reflected back in the column filter input. | F25: - Filters applied from a column filter input appear in the Advanced filter modal. - Filters added/edited in Manage view/Advanced filter are reflected back in the column filter inputs. | G25: IADSSL-101 | H25: No | I25: Not Executed
A26: LC-012 | B26: Verify column sorting from the column header | C26: Refer to Common Preconditions above. | D26: Column: Name | E26: 1. Sign in to Sage Intacct application 2. Navigate to Applications > Lending Management > Loan account category 3. Click the Name column header once. 4. Click the Name column header a second time. | F26: - The first click sorts the column ascending with an upward arrow indicator. - The second click sorts descending with a downward arrow indicator. | G26: IADSSL-101 | H26: No | I26: Not Executed
... A53: LC-039 | B53: Verify overall lister UI consistency (spacing, alignment, controls) matches the design standard | C53: Refer to Common Preconditions above. | D53: N/A (visual inspection only) | E53: 1. Sign in to Sage Intacct application 2. Navigate to Applications > Lending Management > Loan account category 3. Visually inspect the lister page's headers, buttons, filters, and grid layout, spacing, and alignment. | F53: - The page header, buttons, column filters, and data grid use the same spacing, alignment, and control styling as every other module lister in the application, with no visibly misaligned, overlapping, or inconsistently styled element. | G53: IADSSL-101 | H53: No | I53: Not Executed
A54: CREATE (37 test cases)
A55: LC-040 | B55: Verify that create page title is 'Create loan account category' | C55: Refer to Common Preconditions above. | D55: Name: QA Loan Category Description: Client QA loan category Status: Active | E55: 1. Sign in to Sage Intacct application 2. Navigate to Applications > Lending Management > Loan account category 3. Click '+Create'. | F55: - The page title/heading reads exactly "Create loan account category". | G55: IADSSL-101 | H55: No | I55: Not Executed | J55: [UPDATED - title quoted exactly per client request]
A56: LC-041 | B56: verify that create page contains following sections Loan category information | C56: Refer to Common Preconditions above. | D56: N/A (observation only) | E56: 1. Sign in to Sage Intacct application 2. Navigate to Applications > Lending Management > Loan account category 3. Click '+Create'. | F56: - The Create page displays a 'Loan account category information' section (not 'Loan category information'). | G56: IADSSL-101 | H56: No | I56: Not Executed
A57: LC-042 | B57: Verify that Name is a mandatory field with red * mark | C57: Refer to Common Preconditions above. | D57: Name: (leave blank) Description: Client QA loan category Status: Active | E57: 1. Sign in to Sage Intacct application 2. Navigate to Applications > Lending Management > Loan account category 3. Click '+Create'. | F57: - The Name field label is marked with a red asterisk (*), indicating it is a mandatory field. | G57: IADSSL-101 | H57: No | I57: Not Executed
A58: LC-043 | B58: Verify record can be created successfully with a valid name | C58: Refer to Common Preconditions above. | D58: Name: QA Loan Category Description: Client QA loan category Status: Active | E58: 1. Sign in to Sage Intacct application 2. Navigate to Applications > Lending Management > Loan account category 3. Click '+Create'. 4. Enter 'QA Loan Category' in the Name field, 'Client QA loan category' in the Description field, and set Status to Active. 5. Click 'Save'. | F58: - The record saves successfully. - The View page displays 'QA Loan Category' in the Name field. | G58: IADSSL-101 | H58: No | I58: Not Executed
A59: LC-044 | B59: Verify max length of name is 200 characters | C59: Refer to Common Preconditions above. | D59: Name (200 chars, at limit): QA Name QA Name QA Name QA Name QA Name QA Name QA Name QA Name QA Name QA Name QA Name QA Name QA Name QA Name QA Name QA Name QA Name QA Name QA Name QA Name QA Name QA Name QA Name QA Name QA Name Description: Client QA loan category Status: Active | E59: 1. Sign in to Sage Intacct application 2. Navigate to Applications > Lending Management > Loan account category 3. Click '+Create'. 4. Enter the 200-character Name value (at the character limit) in the Name field, along with valid Description and Status. 5. Click 'Save'. | F59: - The record saves successfully with the full 200-character Name value accepted and displayed on the View page. - This confirms the maximum allowed length for the Name field is 200 characters. | G59: IADSSL-101 | H59: No | I59: Not Executed
A60: LC-045 | B60: Verify that an error is returned when the name field value is more than 200 character | C60: Refer to Common Preconditions above. | D60: Name (201 chars, over limit): QA Name QA Name QA Name QA Name QA Name QA Name QA Name QA Name QA Name QA Name QA Name QA Name QA Name QA Name QA Name QA Name QA Name QA Name QA Name QA Name QA Name QA Name QA Name QA Name QA Name Q Description: Client QA loan category Status: Active | E60: 1. Sign in to Sage Intacct application 2. Navigate to Applications > Lending Management > Loan account category 3. Click '+Create'. 4. Enter the 201-character Name value (one over the limit) in the Name field, along with valid Description and Status. 5. Click 'Save'. | F60: - A validation error appears stating the Name field cannot exceed 200 characters. - The record is not saved. | G60: IADSSL-101 | H60: No | I60: Not Executed
A61: LC-046 | B61: Verify that proper error is returned when the name field value is null/empty string | C61: Refer to Common Preconditions above. | D61: Name: (leave blank) Description: Client QA loan category Status: Active | E61: 1. Sign in to Sage Intacct application 2. Navigate to Applications > Lending Management > Loan account category 3. Click '+Create'. 4. Leave the Name field blank, enter valid Description and Status values. 5. Click 'Save'. | F61: - A validation error appears stating the Name field is required. - The record is not saved. | G61: IADSSL-101 | H61: No | I61: Not Executed
A62: LC-047 | B62: Verify that an error is returned when the name field value is white space only | C62: Refer to Common Preconditions above. | D62: Name: ' ' (three spaces, whitespace only) Description: Client QA loan category Status: Active | E62: 1. Sign in to Sage Intacct application 2. Navigate to Applications > Lending Management > Loan account category 3. Click '+Create'. 4. Enter three spaces (whitespace only) in the Name field, and valid Description and Status values. 5. Click 'Save'. | F62: - A validation error appears stating the Name field is required, since whitespace-only input is treated as blank. - The record is not saved. | G62: IADSSL-101 | H62: No | I62: Not Executed
A63: LC-048 | B63: Verify that an error is returned when the name field value is in invalid format | C63: Refer to Common Preconditions above. | D63: Name: <<>>###!!! (invalid/disallowed characters) Description: Client QA loan category Status: Active | E63: 1. Sign in to Sage Intacct application 2. Navigate to Applications > Lending Management > Loan account category 3. Click '+Create'. 4. Enter '<<>>###!!!' in the Name field, and valid Description and Status values. 5. Click 'Save'. | F63: - A validation error appears stating the Name field value is in an invalid format. - The record is not saved. | G63: IADSSL-101 | H63: No | I63: Not Executed
A64: LC-049 | B64: Reject creating a record with a duplicate Name | C64: Refer to Common Preconditions above. A record already exists with Name = 'QA Loan Category A'. | D64: Name: QA Loan Category A Existing record with the same Name: QA Loan Category A | E64: 1. Sign in to Sage Intacct application 2. Navigate to Applications > Lending Management > Loan account category 3. Confirm a record already exists with Name = 'QA Loan Category A'. 4. Click '+Create' and enter Name = 'QA Loan Category A' (the same value), with valid Description and Status. 5. Click 'Save'. | F64: - [DEFECT] A validation error appears reading exactly "Another loan-management/loan-category with name <Name> already exists. Use a unique value instead." This leaks the internal API object path ('loan-management/loan-category') to the end user instead of a friendly label like 'loan account category'. - Submission is blocked and the duplicate record is not created. | G64: IADSSL-101 | H64: No | I64: Not Executed
A65: LC-050 | B65: Verify Description is not a mandatory field | C65: Refer to Common Preconditions above. | D65: Name: QA Loan Category Description: (leave blank) Status: Active | E65: 1. Sign in to Sage Intacct application 2. Navigate to Applications > Lending Management > Loan account category 3. Click '+Create'. 4. Enter 'QA Loan Category' in the Name field, leave the Description field blank, and set Status to Active. 5. Click 'Save'. | F65: - The record saves successfully with no error raised for the blank Description field, confirming Description is not mandatory. | G65: IADSSL-101 | H65: No | I65: Not Executed
A66: LC-051 | B66: Verify that a valid description within 500 characters is accepted | C66: Refer to Common Preconditions above. | D66: Name: QA Loan Category Description (500 chars, at limit): QA Description QA Description QA Description QA Description QA Description QA Description QA Description QA Description QA Description QA Description QA Description QA Description QA Description QA Description QA Description QA Description QA Description QA Description QA Description QA Description QA Description QA Description QA Description QA Description QA Description QA Descrip Status: Active | E66: 1. Sign in to Sage Intacct application 2. Navigate to Applications > Lending Management > Loan account category 3. Click '+Create'. 4. Enter 'QA Loan Category' in the Name field and a 500-character Description value, and set Status to Active. 5. Click 'Save'. | F66: - The record saves successfully with the full 500-character Description value accepted and displayed on the View page. | G66: IADSSL-101 | H66: No | I66: Not Executed
A67: LC-052 | B67: Verify that an empty description is accepted | C67: Refer to Common Preconditions above. | D67: Name: QA Loan Category Description: (leave blank) Status: Active | E67: 1. Sign in to Sage Intacct application 2. Navigate to Applications > Lending Management > Loan account category 3. Click '+Create'. 4. Enter 'QA Loan Category' in the Name field, leave the Description field blank, and set Status to Active. 5. Click 'Save'. | F67: - The record saves successfully with the Description field accepted as empty. | G67: IADSSL-101 | H67: No | I67: Not Executed
A68: LC-053 | B68: Verify that a description exceeding 500 characters is not allowed | C68: Refer to Common Preconditions above. | D68: Name: QA Loan Category Description (501 chars, over limit): QA Description QA Description QA Description QA Description QA Description QA Description QA Description QA Description QA Description QA Description QA Description QA Description QA Description QA Description QA Description QA Description QA Description QA Description QA Description QA Description QA Description QA Description QA Description QA Description QA Description QA Descrip1 Status: Active | E68: 1. Sign in to Sage Intacct application 2. Navigate to Applications > Lending Management > Loan account category 3. Click '+Create'. 4. Enter 'QA Loan Category' in the Name field and a 501-character Description value (one over the 500-character limit), and set Status to Active. 5. Click 'Save'. | F68: - A validation error appears stating the Description field cannot exceed the configured character limit. - The record is not saved. | G68: IADSSL-101 | H68: No | I68: Not Executed
A69: LC-054 | B69: Verify that a description exceeding 500 characters is not allowed | C69: Refer to Common Preconditions above. | D69: Name: QA Loan Category Description: a 501-character string (exceeds the 500-character limit) | E69: 1. Sign in to Sage Intacct application 2. Navigate to Applications > Lending Management > Loan account category 3. Click '+Create'. 4. Enter 'QA Loan Category' in the Name field and a 1001-character Description value (one over the limit), and set Status to Active. 5. Click 'Save'. | F69: - A validation error appears reading exactly "Description cannot exceed 500 characters." - The record is not saved with the over-limit value. | G69: IADSSL-101 | H69: No | I69: Not Executed | J69: [UPDATED - verified live 2026-08-31, real limit is 500 characters, not 1000]
A70: LC-055 | B70: Verify the exact error message when Description exceeds 500 characters | C70: Refer to Common Preconditions above. | D70: Name: QA Loan Category Description: a 501-character string | E70: 1. Sign in to Sage Intacct application 2. Navigate to Applications > Lending Management > Loan account category 3. Click '+Create'. 4. Enter 'QA Loan Category' in the Name field and a 1001-character Description value (one over the limit), and set Status to Active. 5. Click 'Save'. | F70: - A validation error appears reading exactly "Description cannot exceed 500 characters." - The record is not saved. | G70: IADSSL-101 | H70: No | I70: Not Executed | J70: [UPDATED - verified live 2026-08-31, real limit is 500 characters, not 1000; this case duplicates LC-066's coverage]
A71: LC-056 | B71: Verify a valid Document sequence selection from the picker is accepted | C71: Refer to Common Preconditions above. | D71: Name: QA Loan Category Description: Client QA loan category Document sequence: 30--Invoice (selected from the picker) | E71: 1. Sign in to Sage Intacct application 2. Navigate to Applications > Lending Management > Loan account category 3. Click 'Create' to open the Create loan account category page. 4. Fill Name and Description, then open the Document sequence picker and select '30--Invoice' (or any unused sequence definition). 5. Click 'Save'. 6. Observe the View page. | F71: - The record saves successfully with the selected Document sequence value ('30--Invoice') accepted and displayed on the View page. | G71: IADSSL-101 | H71: No | I71: Not Executed | J71: [UPDATED - verified live 2026-08-31, Document sequence is a picker/combobox restricted to existing configured document sequence definitions, not free text]
A72: LC-057 | B72: Verify Document sequence can be left unselected since it is not mandatory | C72: Refer to Common Preconditions above. | D72: Name: QA Loan Category Description: Client QA loan category Document sequence: (leave unselected in the picker) Status: Active | E72: 1. Sign in to Sage Intacct application 2. Navigate to Applications > Lending Management > Loan account category 3. Click '+Create'. 4. Enter 'QA Loan Category' in the Name field and 'Client QA loan category' in Description, leave Document sequence blank, and set Status to Active. 5. Click 'Save'. | F72: - The record saves successfully with no error raised for the unselected Document sequence picker, confirming Document sequence is not mandatory. | G72: IADSSL-101 | H72: No | I72: Not Executed | J72: [UPDATED - verified live 2026-08-31, Document sequence is a picker, not a free-text field that could contain a 'null string']
A73: LC-058 | B73: Verify leaving the Document sequence picker unselected is accepted | C73: Refer to Common Preconditions above. | D73: Name: QA Loan Category Description: Client QA loan category Document sequence: (leave unselected) Status: Active | E73: 1. Sign in to Sage Intacct application 2. Navigate to Applications > Lending Management > Loan account category 3. Click '+Create'. 4. Enter 'QA Loan Category' in the Name field and valid Description and Status, leave the Document sequence field empty. 5. Click 'Save'. | F73: - The record saves successfully with the Document sequence field accepted as unselected/blank. | G73: IADSSL-101 | H73: No | I73: Not Executed | J73: [UPDATED - verified live 2026-08-31, duplicates LC-055's intent since Document sequence has no distinct 'empty string' state as a picker]
A74: LC-059 | B74: Verify selecting a Document sequence already assigned to another record on Create | C74: Refer to Common Preconditions above. | D74: Name: QA Loan Category B Description: Client QA loan category Document sequence: 30--Invoice (already assigned to an existing loan account category) Status: Active | E74: 1. Sign in to Sage Intacct application 2. Navigate to Applications > Lending Management > Loan account category 3. Confirm an existing record already uses Document sequence '30--Invoice'. 4. Click 'Create' to open the Create loan account category page. 5. Fill Name and Description, then select the same '30--Invoice' Document sequence already used by the existing record. 6. Click 'Save'. 7. Observe the validation message and whether the record saves. | F74: - Submission is blocked with the validation error: "Another loan category exists with this document sequence. Please use such a document sequence which has not been used for any loan category yet." - The duplicate record is not created. | G74: IADSSL-101 | H74: No | I74: Not Executed | J74: [UPDATED - verified live 2026-08-31, Document sequence is a picker so 'already used' must be tested by re-selecting an existing option, not typing a duplicate string]
A75: LC-060 | B75: Verify the Document sequence picker only offers valid, pre-configured sequence definitions | C75: Refer to Common Preconditions above. | D75: N/A - picker behavior observation | E75: 1. Sign in to Sage Intacct application 2. Navigate to Applications > Lending Management > Loan account category 3. Click 'Create' to open the Create loan account category page. 4. Open the Document sequence picker and attempt to type an arbitrary invalid string (e.g. '!!!###@@@'). 5. Observe whether any option matches or whether free text can be committed. | F75: - The Document sequence picker restricts selection to existing configured sequence definitions (e.g. '30--Invoice'). - Arbitrary typed text (e.g. special characters) cannot be committed as the field's value, since it is not a free-text field. | G75: IADSSL-101 | H75: No | I75: Not Executed | J75: [UPDATED - verified live 2026-08-31, this case as originally written assumed free-text entry which does not apply]
A76: LC-061 | B76: Verify the Document sequence picker's search/filter narrows the option list correctly | C76: Refer to Common Preconditions above. | D76: Search term: a partial match against an existing document sequence definition's name | E76: 1. Sign in to Sage Intacct application 2. Navigate to Applications > Lending Management > Loan account category 3. Click 'Create' to open the Create loan account category page. 4. Open the Document sequence picker and type a partial search term matching part of an existing sequence definition's name. 5. Observe the filtered option list. | F76: - Typing a partial search term in the Document sequence picker narrows the option list to matching sequence definitions only. | G76: IADSSL-101 | H76: No | I76: Not Executed | J76: [UPDATED - verified live 2026-08-31, replaces the original 'invalid request format' case which assumed free-text entry]
A77: LC-062 | B77: Verify category can be created from any location | C77: Refer to Common Preconditions above. | D77: Entity level: a child entity (e.g. Entity 1) Name: QA Loan Category Location Description: Client QA loan category Status: Active | E77: 1. Sign in to Sage Intacct application 2. Switch to a child entity location. 3. Navigate to Applications > Lending Management > Loan account category and click '+Create'. 4. Enter Name = 'QA Loan Category Location', Description = 'Client QA loan category', Status = Active. 5. Click 'Save'. | F77: - The record saves successfully regardless of the entity/location from which it was created. | G77: IADSSL-101 | H77: No | I77: Not Executed
A78: LC-063 | B78: Verify 'Save' dropdown is visible in create page | C78: Refer to Common Preconditions above. | D78: N/A (observation only) | E78: 1. Sign in to Sage Intacct application 2. Navigate to Applications > Lending Management > Loan account category 3. Click '+Create'. | F78: - A 'Save' dropdown is visible on the Create page. | G78: IADSSL-101 | H78: No | I78: Not Executed
A79: LC-064 | B79: Verify 'Save' dropdown contains 'Save', 'Save and New', 'Save and Close' options | C79: Refer to Common Preconditions above. | D79: Name: QA Loan Category Description: Client QA loan category Status: Active | E79: 1. Sign in to Sage Intacct application 2. Navigate to Applications > Lending Management > Loan account category 3. Click '+Create'. 4. Populate the Name, Description, and Status fields with the stated test data. 5. Click the dropdown arrow next to the 'Save' button. | F79: - The 'Save' dropdown displays three options: 'Save', 'Save and New', and 'Save and Close'. | G79: IADSSL-101 | H79: No | I79: Not Executed
A80: LC-065 | B80: Verify clicking 'Save and New' saves the form and opens a new blank form | C80: Refer to Common Preconditions above. | D80: Name: QA Loan Category Description: Client QA loan category Status: Active | E80: 1. Sign in to Sage Intacct application 2. Navigate to Applications > Lending Management > Loan account category 3. Click '+Create' and enter Name = 'QA Loan Category', Description = 'Client QA loan category', Status = Active. 4. Click the 'Save' dropdown and select 'Save and New'. | F80: - Clicking 'Save and New' saves the record successfully and opens a new blank Create form. | G80: IADSSL-101 | H80: No | I80: Not Executed
A81: LC-066 | B81: Verify clicking 'Save' saves the form and redirects to detail/view page | C81: Refer to Common Preconditions above. | D81: Name: QA Loan Category Description: Client QA loan category Status: Active | E81: 1. Sign in to Sage Intacct application 2. Navigate to Applications > Lending Management > Loan account category 3. Click '+Create'. 4. Populate the Name, Description, and Status fields with the stated test data. 5. Click the 'Save' button. | F81: - The record saves successfully and the page redirects to the loan account category's detail/view page, displaying the entered values. | G81: IADSSL-101 | H81: No | I81: Not Executed
A82: LC-067 | B82: Verify clicking 'Save and Close' saves the form and redirects to the list page | C82: Refer to Common Preconditions above. | D82: Name: QA Loan Category Description: Client QA loan category Status: Active | E82: 1. Sign in to Sage Intacct application 2. Navigate to Applications > Lending Management > Loan account category 3. Click '+Create'. 4. Populate the Name, Description, and Status fields with the stated test data. 5. Click the dropdown arrow next to 'Save' and select 'Save and Close'. | F82: - The record saves successfully and the page redirects to the loan account category list page, where the new record appears in the list. | G82: IADSSL-101 | H82: No | I82: Not Executed
A83: LC-068 | B83: Verify proper error messages appear when form has validation errors and any save option is clicked | C83: Refer to Common Preconditions above. | D83: Name: (leave blank) Description: Client QA loan category Status: Active | E83: 1. Sign in to Sage Intacct application 2. Navigate to Applications > Lending Management > Loan account category 3. Click '+Create', leave the Name field blank, and enter valid Description and Status values. 4. Click the 'Save' dropdown and select 'Save', then repeat with 'Save and New'. | F83: - A clear validation error message is displayed for the missing Name field regardless of which save option (Save, Save and New, etc.) is clicked. - The record is not saved. | G83: IADSSL-101 | H83: No | I83: Not Executed
A84: LC-069 | B84: Verify proper error messages appear when form has validation errors and 'Save' is clicked | C84: Refer to Common Preconditions above. | D84: Name: (leave blank) Description: Client QA loan category Status: Active | E84: 1. Sign in to Sage Intacct application 2. Navigate to Applications > Lending Management > Loan account category 3. Click '+Create', leave the Name field blank, and enter valid Description and Status values. 4. Click 'Save'. | F84: - A clear validation error message is displayed for the missing Name field. - The record is not saved. | G84: IADSSL-101 | H84: No | I84: Not Executed
A85: LC-070 | B85: Verify proper message appears when category is created successfully | C85: Refer to Common Preconditions above. | D85: Name: QA Loan Category Description: Client QA loan category Status: Active | E85: 1. Sign in to Sage Intacct application 2. Navigate to Applications > Lending Management > Loan account category 3. Click '+Create' and enter Name = 'QA Loan Category', Description = 'Client QA loan category', Status = Active. 4. Click 'Save'. | F85: - [DEFECT] The success toast reads exactly 'Loan category created' instead of the expected 'Loan account category created', dropping the word 'account' compared to the section/page naming elsewhere. | G85: IADSSL-101 | H85: No | I85: Not Executed
A86: LC-071 | B86: Verify proper entry is created in SNLLOANCATEGORY table | C86: Refer to Common Preconditions above. | D86: Name: QA Loan Category Description: Client QA loan category Status: Active | E86: 1. Sign in to Sage Intacct application 2. Navigate to Applications > Lending Management > Loan account category 3. Click '+Create' and enter Name = 'QA Loan Category', Description = 'Client QA loan category', Status = Active. 4. Click 'Save'. 5. Verify (via the platform/database or Custom Reports on the SNLLOANCATEGORY object) that a corresponding entry exists. | F86: - A proper entry is created in the SNLLOANCATEGORY table with values matching the submitted Name, Description, and Status. | G86: IADSSL-101 | H86: No | I86: Not Executed
A87: LC-072 | B87: Verify 'Categories' option is present | C87: Refer to Common Preconditions above. | D87: N/A (observation only) | E87: 1. Sign in to Sage Intacct application 2. Navigate to Applications > Lending Management 3. Locate the 'Categories' menu option under Lending Management. | F87: - A 'Categories' option is present in the Lending Management navigation. | G87: IADSSL-101 | H87: No | I87: Not Executed
A88: LC-073 | B88: verify all field values are read only | C88: Refer to Common Preconditions above. | D88: Name: QA Loan Category Description: Client QA loan category Status: Active | E88: 1. Sign in to Sage Intacct application 2. Navigate to Applications > Lending Management > Loan account category 3. Open an existing record's View page. 4. Attempt to click/edit each field value (Name, Description, Status) directly on the View page. | F88: - All field values on the View page are read-only and cannot be edited directly. | G88: IADSSL-101 | H88: No | I88: Not Executed
A89: LC-074 | B89: Confirm Status is not present on the Create form | C89: Refer to Common Preconditions above. | D89: N/A - field-presence observation | E89: 1. Sign in to Sage Intacct application 2. Navigate to Applications > Lending Management > Loan account category 3. Click 'Create' to open the Create loan account category page. 4. Observe the full list of fields on the form. | F89: - The Create form does not have a Status field. - The Status field only appears on the Edit form (as an editable dropdown, default 'Active') and the View page (read-only display). | G89: IADSSL-101 | H89: TBD | I89: Not Executed | J89: [ADDED - verified live 2026-08-31]
A90: LC-075 | B90: [DEFECT] Success and error toasts show a raw untranslated accessibility label | C90: Refer to Common Preconditions above. | D90: Any successful Create, Edit, or Delete action | E90: 1. Sign in to Sage Intacct application 2. Navigate to Applications > Lending Management > Loan account category 3. Perform a successful Create, Edit, or Delete action. 4. Inspect the toast notification's accessible/status region label. | F90: - [DEFECT] The toast notification's accessible/status region label displays the raw untranslated key 'IA.MESSAGE_ERROR_LABEL' on every toast (success and error alike), instead of a proper translated label. | G90: IADSSL-101 | H90: TBD | I90: Not Executed | J90: [ADDED - verified live 2026-08-31]
A91: LC-076 | B91: [DEFECT] Section header collapse control shows a raw untranslated key | C91: Refer to Common Preconditions above. | D91: N/A - UI element observation | E91: 1. Sign in to Sage Intacct application 2. Navigate to Applications > Lending Management > Loan account category 3. Open the Create or Edit page. 4. Inspect the 'Loan account category information' section header's collapse/expand control. | F91: - [DEFECT] The section header's collapse/expand control renders the raw key 'IA.COLLAPSE' as text, on both Create and Edit pages. | G91: IADSSL-101 | H91: TBD | I91: Not Executed | J91: [ADDED - verified live 2026-08-31]
A92: EDIT (12 test cases)
A93: LC-077 | B93: Verify page title displays 'Edit loan account category: <record ID>' | C93: Refer to Common Preconditions above. | D93: Name: QA Loan Category Description: Client QA loan category Status: Active | E93: 1. Sign in to Sage Intacct application 2. Navigate to Applications > Lending Management > Loan account category 3. Open an existing loan account category record from the list. 4. Click the 'Edit' button. | F93: - The page title/heading reads exactly "Edit loan account category: <record ID>". - [DEFECT] The title displays the numeric record ID, not the record's Name (e.g. "Edit loan account category: 1227"); this is a likely UX defect. | G93: IADSSL-101 | H93: No | I93: Not Executed | J93: [UPDATED - title quoted exactly per client request]
A94: LC-078 | B94: Verify 'Save' button is visible in edit page | C94: Refer to Common Preconditions above. | D94: Name: QA Loan Category Description: Client QA loan category Status: Active | E94: 1. Sign in to Sage Intacct application 2. Navigate to Applications > Lending Management > Loan account category 3. Open an existing loan account category record and click 'Edit'. | F94: - The 'Save' button is visible on the loan account category Edit page. | G94: IADSSL-101 | H94: No | I94: Not Executed
A95: LC-079 | B95: Verify clicking 'Save' updates the record and redirects to detail/view page | C95: Refer to Common Preconditions above. | D95: Name: QA Loan Category Description (updated): Updated client QA loan category Status: Active | E95: 1. Sign in to Sage Intacct application 2. Navigate to Applications > Lending Management > Loan account category 3. Open an existing loan account category record and click 'Edit'. 4. Update the Description field to 'Updated client QA loan category'. 5. Click the 'Save' button. | F95: - The record updates successfully and the page redirects to the loan account category's detail/view page, displaying the updated field values. | G95: IADSSL-101 | H95: No | I95: Not Executed
A96: LC-080 | B96: Verify record can be edited successfully with a valid name | C96: Refer to Common Preconditions above. | D96: Name (updated): QA Loan Category Updated Description: Client QA loan category Status: Active | E96: 1. Sign in to Sage Intacct application 2. Navigate to Applications > Lending Management > Loan account category 3. Open an existing loan account category record and click 'Edit'. 4. Update the Name field to 'QA Loan Category Updated'. 5. Click the 'Save' button. | F96: - The record saves successfully. - The View page displays the updated Name value ('QA Loan Category Updated'). | G96: IADSSL-101 | H96: No | I96: Not Executed
A97: LC-081 | B97: Verify that an error is returned when the Name field is cleared/left blank on the Edit form | C97: Refer to Common Preconditions above. An existing record is available to edit. | D97: Name: (leave blank) Description: Client QA loan category Status: Active | E97: 1. Sign in to Sage Intacct application 2. Navigate to Applications > Lending Management > Loan account category 3. Open an existing loan account category record and click 'Edit'. 4. Clear the Name field so it is blank. 5. Click the 'Save' button. | F97: - A validation error appears stating that the Name field is required and cannot be blank. - The record is not saved. | G97: IADSSL-101 | H97: No | I97: Not Executed
A98: LC-082 | B98: Verify that an error is returned when the Name field is updated to a value exceeding 200 characters on the Edit form | C98: Refer to Common Preconditions above. An existing record is available to edit. | D98: Name (201 chars, over limit): AAAAAAAAAAAAAAAAAAAAAAAAAAAAAAAAAAAAAAAAAAAAAAAAAAAAAAAAAAAAAAAAAAAAAAAAAAAAAAAAAAAAAAAAAAAAAAAAAAAAAAAAAAAAAAAAAAAAAAAAAAAAAAAAAAAAAAAAAAAAAAAAAAAAAAAAAAAAAAAAAAAAAAAAAAAAAAAAAAAAAAAAAAAAAAAAAAAAA Description: Client QA loan category Status: Active | E98: 1. Sign in to Sage Intacct application 2. Navigate to Applications > Lending Management > Loan account category 3. Open an existing loan account category record and click 'Edit'. 4. Update the Name field to a 201-character value (exceeding the 200-character limit). 5. Click the 'Save' button. | F98: - A validation error appears stating that the Name field cannot exceed 200 characters. - The record is not saved. | G98: IADSSL-101 | H98: No | I98: Not Executed
A99: LC-083 | B99: Reject renaming a record to a duplicate Name on Edit | C99: Refer to Common Preconditions above. Two existing records are available: one with Name = 'QA Loan Category A' and another with Name = 'QA Loan Category B'. | D99: Record being edited: QA Loan Category B Existing other record with Name: QA Loan Category A Name (attempted update): QA Loan Category A | E99: 1. Sign in to Sage Intacct application 2. Navigate to Applications > Lending Management > Loan account category 3. Open the record named 'QA Loan Category B' and click 'Edit'. 4. Change the Name field to 'QA Loan Category A' (already used by another existing record). 5. Click the 'Save' button. | F99: - A validation error appears stating that the Name 'QA Loan Category A' is already in use. - The save is blocked and the record's Name remains 'QA Loan Category B'. | G99: IADSSL-101 | H99: No | I99: Not Executed
A100: LC-084 | B100: Verify Description can be updated at any time, including after the category is assigned to a loan account, subject to the existing length validation | C100: Refer to Common Preconditions above. The category is already assigned to a loan account. | D100: Description update (at limit): a 500-character string Description update (over limit): a 501-character string | E100: 1. Sign in to Sage Intacct application 2. Navigate to Applications > Lending Management > Loan account category 3. Open a loan account category that is already assigned to loan account 'TS-013--ts amort' and click 'Edit'. 4. Update the Description field to the 500-character valid value and click 'Save'; confirm it saves successfully. 5. Re-open the record in Edit mode, update the Description field to the 501-character value (over the 500-character limit), and click 'Save'. | F100: - The 500-character Description update saves successfully even though the category is assigned to a loan account. - The 501-character Description update is rejected with a validation error reading exactly "Description cannot exceed 500 characters." and the edit is not saved. | G100: IADSSL-101 | H100: No | I100: Not Executed | J100: [UPDATED - verified live 2026-08-31, real limit is 500 characters, not 1000]
A101: LC-085 | B101: Verify the document sequence key cannot be edited once the category is assigned to a loan account | C101: Refer to Common Preconditions above. The category is already assigned to a loan account. | D101: Name: QA Loan Category Description: Client QA loan category Document sequence: QA-LOANCAT-SEQ Status: Active Assigned to loan account: TS-013--ts amort | E101: 1. Sign in to Sage Intacct application 2. Navigate to Applications > Lending Management > Loan account category 3. Open a loan account category that is already assigned to loan account 'TS-013--ts amort' and click 'Edit'. 4. Attempt to change the Document sequence field from 'QA-LOANCAT-SEQ' to a different value. | F101: - The Document sequence field is locked (read-only or disabled) once the loan account category has been assigned to a loan account, or any attempted change to it is rejected with a clear validation error. | G101: IADSSL-101 | H101: No | I101: Not Executed
A102: LC-086 | B102: Verify selecting a Document sequence already assigned to another record on Edit | C102: Refer to Common Preconditions above. Two existing records are available: one with Document sequence = 'QA-DOCSEQ-001' and another (not yet assigned to any loan account) with a different Document sequence value. | D102: Record being edited: QA Loan Category B (not assigned to a loan account) Document sequence (attempted change): 30--Invoice (already assigned to an existing loan account category) | E102: 1. Sign in to Sage Intacct application 2. Navigate to Applications > Lending Management > Loan account category 3. Confirm an existing record already uses Document sequence '30--Invoice'. 4. Open the record named 'QA Loan Category B' (not assigned to a loan account) and click 'Edit'. 5. Change the Document sequence picker selection to '30--Invoice' (already used by another record). 6. Click 'Save'. 7. Observe the validation message and whether the change saves. | F102: - Submission is blocked with the validation error: "Another loan category exists with this document sequence. Please use such a document sequence which has not been used for any loan category yet." - The record's Document sequence value is not changed. | G102: IADSSL-101 | H102: TBD | I102: Not Executed | J102: [ADDED - confirm exact wording] [UPDATED - verified live 2026-08-31, Document sequence is a picker, not free text]
A103: LC-087 | B103: Verify the Document sequence picker's options remain restricted to valid definitions on Edit | C103: Refer to Common Preconditions above. An existing record (not yet assigned to any loan account) is available to edit. | D103: Record being edited: QA Loan Category (not assigned to a loan account) | E103: 1. Sign in to Sage Intacct application 2. Navigate to Applications > Lending Management > Loan account category 3. Open an existing loan account category record (not assigned to a loan account) and click 'Edit'. 4. Open the Document sequence picker and attempt to type an arbitrary invalid string (e.g. '!!!###@@@'). 5. Observe whether any option matches or whether free text can be committed. | F103: - The Document sequence picker on Edit restricts selection to existing configured sequence definitions, same as Create. - Arbitrary typed text cannot be committed as the field's value. | G103: IADSSL-101 | H103: TBD | I103: Not Executed | J103: [ADDED - confirm exact wording] [UPDATED - verified live 2026-08-31, this case as originally written assumed free-text entry which does not apply]
A104: LC-088 | B104: Verify category can be edited from any location | C104: Refer to Common Preconditions above. | D104: Name: QA Loan Category Description: Client QA loan category Status: Active | E104: 1. Sign in to Sage Intacct application 2. Navigate to Applications > Lending Management > Loan account category 3. Open an existing loan account category record from the list page, and separately from the View page and from a related loan account record, clicking 'Edit' in each location. 4. Update the Description field in each case and click 'Save'. | F104: - The loan account category can be edited successfully from any valid entry point (list page, view page, or related record). - Changes are saved each time. | G104: IADSSL-101 | H104: No | I104: Not Executed
A105: VIEW (9 test cases)
A106: LC-089 | B106: Verify page title displays 'Loan account categories: <record ID>' | C106: Refer to Common Preconditions above. | D106: Name: QA Loan Category Description: Client QA loan category User role: Full Access | E106: 1. Sign in to Sage Intacct application 2. Navigate to Applications > Lending Management > Loan account category 3. Open an existing loan account category record from the list. | F106: - The page title/heading reads exactly "Loan account categories: <record ID>". - [DEFECT] The title does NOT display the record's Name (it shows the plural noun and a numeric record ID only), unlike the sheet's prior assumption that it should read "Loan account category: <Name>"; flagged as a likely UX defect. | G106: IADSSL-101 | H106: No | I106: Not Executed | J106: [UPDATED - title quoted exactly per client request]
A107: LC-090 | B107: Verify clicking categories option redirects to lister page | C107: Refer to Common Preconditions above. | D107: Name: QA Loan Category Description: Client QA loan category Status: Active | E107: 1. Sign in to Sage Intacct application 2. Navigate to Applications > Lending Management > Loan account category 3. Open an existing loan account category record's View page. 4. Click the breadcrumb/link labeled 'Categories'. | F107: - Clicking the 'Categories' link redirects to the loan account category lister page, showing the full list of categories. | G107: IADSSL-101 | H107: No | I107: Not Executed
A108: LC-091 | B108: Verify status field value is displayed as active by default | C108: Refer to Common Preconditions above. | D108: Name: QA Loan Category Description: Client QA loan category Status: (not explicitly set at creation) | E108: 1. Sign in to Sage Intacct application 2. Navigate to Applications > Lending Management > Loan account category 3. Open a loan account category record created without explicitly setting Status. | F108: - The Status field displays 'Active' by default when no other status was explicitly selected. | G108: IADSSL-101 | H108: No | I108: Not Executed
A109: LC-092 | B109: Verify Document sequence value displays correctly on the View page | C109: Refer to Common Preconditions above. A record has already been created with a valid, unique Document sequence value. | D109: Name: QA Loan Category Description: Client QA loan category Document sequence: QA-DOCSEQ-001 Status: Active | E109: 1. Sign in to Sage Intacct application 2. Navigate to Applications > Lending Management > Loan account category 3. Confirm a record exists with Name = 'QA Loan Category' and Document sequence = 'QA-DOCSEQ-001' (create one if it does not already exist). 4. Open that record's View page. 5. Observe the value displayed in the Document sequence field. | F109: - The Document sequence field on the View page displays 'QA-DOCSEQ-001' exactly as saved. | G109: IADSSL-101 | H109: TBD | I109: Not Executed | J109: [ADDED]
A110: LC-093 | B110: Verify the modal displays the confirmation message | C110: Refer to Common Preconditions above. | D110: Name: QA Loan Category Description: Client QA loan category Status: Active | E110: 1. Sign in to Sage Intacct application 2. Navigate to Applications > Lending Management > Loan account category 3. Open an existing loan account category record's View page. 4. Click the ellipsis (3-dot) menu and select 'Delete'. | F110: - The delete confirmation modal displays a clear confirmation message asking the user to confirm the delete action. | G110: IADSSL-101 | H110: No | I110: Not Executed
A111: LC-094 | B111: Verify functional 3 dot menu contains View audit trail Object definition | C111: Refer to Common Preconditions above. | D111: Name: QA Loan Category Description: Client QA loan category Status: Active | E111: 1. Sign in to Sage Intacct application 2. Navigate to Applications > Lending Management > Loan account category 3. Open an existing loan account category record's View page. 4. Click the ellipsis (3-dot) menu. | F111: - The ellipsis (3-dot) menu displays 'View audit trail' as an option. - The ellipsis (3-dot) menu displays 'Object definition' as an option. | G111: IADSSL-101 | H111: No | I111: Not Executed | J111: [UPDATED - Expected Result split into one point per component (presence only), per client request]
A112: LC-095 | B112: Verify 'Edit' button is visible and functional in view page | C112: Refer to Common Preconditions above. | D112: Name: QA Loan Category Description: Client QA loan category Status: Active | E112: 1. Sign in to Sage Intacct application 2. Navigate to Applications > Lending Management > Loan account category 3. Open an existing loan account category record's View page. 4. Click the 'Edit' button. | F112: - The 'Edit' button is visible on the View page. - Clicking the 'Edit' button successfully navigates to the record's Edit page. | G112: IADSSL-101 | H112: No | I112: Not Executed
A113: LC-096 | B113: Audit trail correctly records creation and a Name change with the exact field, before, and after values | C113: Refer to Common Preconditions above. | D113: loan account category: newly created, then Name changed from 'QA Category Old' to 'QA Category New' | E113: 1. Sign in to Sage Intacct application 2. Navigate to Applications > Lending Management > Loan account category 3. Create a new loan account category record, then open it and update the Name field from 'QA Category Old' to 'QA Category New' and save. 4. Open the record's View page, click the 3-dot (More actions) menu, and select 'View audit trail'. 5. Inspect the audit trail table's Date, Action, Completed by, Source, Field, Before, and After columns. | F113: - The audit trail shows a 'Create' row (Source = User interface, After = Created) as the oldest entry. - The audit trail shows a separate 'Modify' row for the Name change with Field = 'Name', Before = 'QA Category Old', After = 'QA Category New', the correct Completed by user, and a valid Date/time. - Unrelated fields do not appear as changed rows. | G113: IADSSL-101 | H113: TBD | I113: Not Executed | J113: [ADDED - audit trail content verification]
A114: LC-097 | B114: Confirm the 'Object definition' menu option opens the object definition page | C114: Refer to Common Preconditions above. | D114: N/A - navigation/observation only. | E114: 1. Sign in to Sage Intacct application 2. Navigate to Applications > Lending Management > Loan account category 3. Open an existing loan account category's View page. 4. Click the 3-dot/More actions menu and select 'Object definition'. | F114: - Clicking 'Object definition' opens the object definition page for this record type, showing its underlying object schema/metadata. | G114: IADSSL-101 | H114: TBD | I114: Not Executed | J114: [ADDED - functionality test for a component previously only asserted as present]
A115: DELETE (6 test cases)
A116: LC-098 | B116: Verify the modal displays the title correctly | C116: Refer to Common Preconditions above. | D116: Name: QA Loan Category Description: Client QA loan category Status: Active | E116: 1. Sign in to Sage Intacct application 2. Navigate to Applications > Lending Management > Loan account category 3. Open an existing loan account category record's View page. 4. Click the ellipsis (3-dot) menu and select 'Delete'. | F116: - From the View page's Delete button, the modal title reads exactly 'Delete loan category' (drops 'account'). - The modal message reads 'The following loan account category will be permanently deleted:' followed by the record's Name. | G116: IADSSL-101 | H116: No | I116: Not Executed
A117: LC-099 | B117: Verify 'Delete' button is visible and functional in view page | C117: Refer to Common Preconditions above. | D117: Name: QA Loan Category (disposable) Description: Client QA loan category Status: Active | E117: 1. Sign in to Sage Intacct application 2. Navigate to Applications > Lending Management > Loan account category 3. Open a disposable loan account category record's View page. 4. Click the 'Delete' button. | F117: - The 'Delete' button is visible on the View page. - The 'Delete' button is functional, opening the delete confirmation modal when clicked. | G117: IADSSL-101 | H117: No | I117: Not Executed
A118: LC-100 | B118: Verify clicking 'Delete' button opens the delete confirmation modal | C118: Refer to Common Preconditions above. | D118: Name: QA Loan Category (disposable) Description: Client QA loan category Status: Active | E118: 1. Sign in to Sage Intacct application 2. Navigate to Applications > Lending Management > Loan account category 3. Open a disposable loan account category record's View page. 4. Click the 'Delete' button. | F118: - Clicking the 'Delete' button opens the delete confirmation modal for the record. | G118: IADSSL-101 | H118: No | I118: Not Executed
A119: LC-101 | B119: Verify delete confirmation modal contains 'Title', 'Delete' and 'Cancel' buttons | C119: Refer to Common Preconditions above. | D119: Name: QA Loan Category (disposable) Description: Client QA loan category Status: Active | E119: 1. Sign in to Sage Intacct application 2. Navigate to Applications > Lending Management > Loan account category 3. Open a disposable loan account category record's View page. 4. Click the 'Delete' button to open the confirmation modal. | F119: - The delete confirmation modal displays a clear title. - The modal has functional 'Delete' and 'Cancel' buttons. | G119: IADSSL-101 | H119: No | I119: Not Executed
A120: LC-102 | B120: Verify clicking 'Cancel' closes the modal without deleting the record | C120: Refer to Common Preconditions above. | D120: Name: QA Loan Category Description: Client QA loan category Status: Active | E120: 1. Sign in to Sage Intacct application 2. Navigate to Applications > Lending Management > Loan account category 3. Open an existing loan account category record's View page. 4. Click the 'Delete' button to open the confirmation modal, then click 'Cancel'. | F120: - Clicking 'Cancel' in the delete confirmation modal closes the modal without deleting the record. - The record remains unchanged in the list. | G120: IADSSL-101 | H120: No | I120: Not Executed
A121: LC-103 | B121: Verify clicking 'Delete' in modal removes the record and redirects to the list page | C121: Refer to Common Preconditions above. | D121: Name: QA Loan Category (disposable) Description: Client QA loan category Status: Active | E121: 1. Sign in to Sage Intacct application 2. Navigate to Applications > Lending Management > Loan account category 3. Open a disposable loan account category record's View page. 4. Click the 'Delete' button to open the confirmation modal, then click 'Delete' to confirm. | F121: - The record is permanently removed. - The page redirects to the loan account category list page where the deleted record no longer appears. - A success toast appears reading exactly 'Loan category deleted'. | G121: IADSSL-101 | H121: No | I121: Not Executed

Sheet LME Loan Account
A1: Prepared By | B1: Subah Tasnim Shiary | D1: Total Test Cases | E1: =COUNTA('LME Loan Account'!$B$14:$B$2000)
A2: Executed By | B2: Subah Tasnim Shiary | D2: Passed | E2: =COUNTIF('LME Loan Account'!$I$14:$I$2000,"Passed")
A3: Updated On | B3: 46262 | D3: Failed | E3: =COUNTIF('LME Loan Account'!$I$14:$I$2000,"Failed")
A4: Time est | B4: Initial testing: | D4: Untested | E4: =COUNTIF('LME Loan Account'!$I$14:$I$2000,"Not Executed")
B5: Bugfix testing: | D5: To be tested | E5: =COUNTIF('LME Loan Account'!$I$14:$I$2000,"In Progress")+COUNTIF('LME Loan Account'!$I$14:$I$2000,"Blocked")
A6: common preconditions
A7: navigation
A8: Lending - Loan Account
A9: Common Preconditions | C9: 1. User is signed in to Sage Intacct. 2. The correct Lending Management or Depository Management entity is selected. 3. The module is enabled for the company. 4. The user has the permission required for the scenario. 5. Required master/configuration records are active and available.
A11: Navigation: Applications > Lending Management > Loan account | Client baseline | 220 test cases | Updated 2026-08-31
A13: Test Case ID | B13: Test Scenario | C13: Preconditions | D13: Test Data | E13: Test Steps | F13: Expected Result | G13: Requirement/Jira Reference | H13: IS Automated | I13: Status | J13: Comments
A14: LISTER (40 test cases)
A15: LA-001 | B15: Page title is 'Loans' | C15: Refer to Common Preconditions above. | D15: Account category: QA Loan Category Account number: LA-QA-001 User role: Full Access | E15: 1. Sign in to Sage Intacct application 2. Navigate to Applications > Lending Management > Loan account 3. Open the Loan account lister page 4. Observe the page header at the top of the page. | F15: - The page header (H1) displays "Loans". | G15: IADSSL-101 | H15: No | I15: Not Executed | J15: Source section: A. List page (IDs: TC-LA-131–145)
A16: LA-002 | B16: Verify the lister grid displays the documented columns | C16: Refer to Common Preconditions above. | D16: Expected columns (default lister grid, verified live 2026-08-31): Account number, Account name, Loan type name, Loan type, First loan invoice date, First payment date, First statement date, Record number, Amount, Loan origination date | E16: 1. Sign in to Sage Intacct application 2. Navigate to Applications > Lending Management > Loan account 3. Open the Loan account lister page 4. Observe the columns displayed in the lister grid. | F16: - The lister grid displays the following columns by default: Account number, Account name, Loan type name, Loan type, First loan invoice date, First payment date, First statement date, Record number, Amount, Loan origination date. - Account category, Customer, Vendor, State, and Status are real fields on the loan record but are not default lister columns - they are covered separately by the View-band field-display test cases. | G16: IADSSL-101 | H16: No | I16: Not Executed | J16: [UPDATED]
A17: LA-003 | B17: Verify no column is sorted by default | C17: Refer to Common Preconditions above. | D17: N/A | E17: 1. Sign in to Sage Intacct application 2. Navigate to Applications > Lending Management > Loan account 3. Open the Loan account lister page and inspect the column headers. | F17: - No column header shows a sort arrow/indicator by default. - The grid loads in its natural, unsorted order. | G17: IADSSL-101 | H17: No | I17: Not Executed
A18: LA-004 | B18: Verify Account number is a drillable field that routes to the View loan account screen | C18: Refer to Common Preconditions above. | D18: A record with a valid Account number value exists. | E18: 1. Sign in to Sage Intacct application 2. Navigate to Applications > Lending Management > Loan account 3. Open the Loan account lister page 4. Click the Account number value on any row. | F18: - Clicking the Account number value navigates to the View loan account screen for that record. | G18: IADSSL-101 | H18: No | I18: Not Executed
A19: LA-005 | B19: Verify Account name is a drillable field that routes to the View loan account screen | C19: Refer to Common Preconditions above. | D19: A record with a valid Account name value exists. | E19: 1. Sign in to Sage Intacct application 2. Navigate to Applications > Lending Management > Loan account 3. Open the Loan account lister page 4. Click the Account name value on any row. | F19: - Clicking the Account name value navigates to the View loan account screen for that record. | G19: IADSSL-101 | H19: No | I19: Not Executed
A20: LA-006 | B20: Verify the '+Create' button is present and functional | C20: Refer to Common Preconditions above. | D20: N/A | E20: 1. Sign in to Sage Intacct application 2. Navigate to Applications > Lending Management > Loan account 3. Open the Loan account lister page 4. Locate the '+Create' button at the top right of the lister page and click it. | F20: - The '+Create' button is located at the top right of the lister page. - Clicking '+Create' redirects to the 'Create loan account' page. | G20: IADSSL-101 | H20: No | I20: Not Executed
A21: LA-007 | B21: Verify the lister view-selection dropdown functionality | C21: Refer to Common Preconditions above. | D21: N/A | E21: 1. Sign in to Sage Intacct application 2. Navigate to Applications > Lending Management > Loan account 3. Open the Loan account lister page 4. Click the view-selection dropdown at the top left and inspect its contents, then select a view. | F21: - Clicking the view dropdown opens a list with a 'Search for view' field, a 'System views' section (including 'All'), and a 'User views' section. - Selecting any view updates the lister to reflect that view. | G21: IADSSL-101 | H21: No | I21: Not Executed
A22: LA-008 | B22: Verify the Split view / List view toggle | C22: Refer to Common Preconditions above. | D22: N/A | E22: 1. Sign in to Sage Intacct application 2. Navigate to Applications > Lending Management > Loan account 3. Open the Loan account lister page 4. Click the Split view icon 5. Click the List view icon. | F22: - Split view splits the screen into the lister on the left and the record detail on the right. - List view shows only the lister in full screen. | G22: IADSSL-101 | H22: No | I22: Not Executed
A23: LA-009 | B23: Verify the 'Filters' button opens the Advanced filter modal | C23: Refer to Common Preconditions above. | D23: N/A | E23: 1. Sign in to Sage Intacct application 2. Navigate to Applications > Lending Management > Loan account 3. Open the Loan account lister page 4. Click the 'Filters' button at the top right of the lister. | F23: - A modal titled 'Advanced filter' opens containing Field/Operator/Value/Apply-criteria columns, Apply and Cancel buttons, and per-row '+' (add) and '-' (remove) controls. - No filters are selected by default. | G23: IADSSL-101 | H23: No | I23: Not Executed
A24: LA-010 | B24: Verify the Advanced filter 'Apply' button applies and persists filter changes | C24: Refer to Common Preconditions above. | D24: Filter row: Field = Account category, Operator = Equals, Value = QA Loan Category | E24: 1. Sign in to Sage Intacct application 2. Navigate to Applications > Lending Management > Loan account 3. Open the Loan account lister page and click 'Filters' to open the Advanced filter modal 4. Add/edit/delete one or more filter rows (e.g. Field: Account category, Operator: Equals, Value: QA Loan Category), leaving any incomplete rows blank 5. Click 'Apply' 6. Reopen the Advanced filter modal. | F24: - Clicking 'Apply' closes the modal and the list updates to reflect the filter changes. - Reopening Advanced filters shows the previously applied filters persisted. - Rows left without any Field/Operator/Value are ignored. | G24: IADSSL-101 | H24: No | I24: Not Executed
A25: LA-011 | B25: Verify column filters and Advanced filters stay in sync | C25: Refer to Common Preconditions above. | D25: Column filter: Account category contains 'QA' | E25: 1. Sign in to Sage Intacct application 2. Navigate to Applications > Lending Management > Loan account 3. Open the Loan account lister page 4. Apply a filter via a column header's filter input (e.g. Account category contains 'QA'), then open the Advanced filter modal and check that it appears there 5. In the Advanced filter modal, add or edit a filter and click Apply, then check the corresponding column filter input. | F25: - Filters applied from a column filter input appear in the Advanced filter modal. - Filters added or edited in Manage view/Advanced filter are reflected back in the column filter inputs. | G25: IADSSL-101 | H25: No | I25: Not Executed
A26: LA-012 | B26: Verify column sorting from the column header | C26: Refer to Common Preconditions above. | D26: Column: Account number | E26: 1. Sign in to Sage Intacct application 2. Navigate to Applications > Lending Management > Loan account 3. Open the Loan account lister page 4. Click the Account number column header once 5. Click the Account number column header again. | F26: - The first click sorts the column ascending with an upward arrow indicator. - The second click sorts descending with a downward arrow indicator. | G26: IADSSL-101 | H26: No | I26: Not Executed
A27: LA-013 | B27: Verify column sorting from 'Configure column' / 'Column setting' options, including multi-column sort | C27: Refer to Common Preconditions above. | D27: Sort row 1: Account category, Ascending Sort row 2: Account number, Descending | E27: 1. Sign in to Sage Intacct application 2. Navigate to Applications > Lending Management > Loan account 3. Open the Loan account lister page and open the column header's Column setting (cog wheel) menu, or Settings > Sort 4. Choose Account category and Ascending order, click Apply 5. Add a second sort row for Account number set to Descending order, click Apply. | F27: - The grid sorts ascending/descending per the chosen order with the matching arrow indicator. - When multiple sort rows are configured, the dataset sorts by the first row's order first, then the second row's order for ties, continuing for any additional rows added. | G27: IADSSL-101 | H27: No | I27: Not Executed
A28: LA-014 | B28: Verify the 'Column setting' (cog wheel) menu functionality | C28: Refer to Common Preconditions above. | D28: N/A | E28: 1. Sign in to Sage Intacct application 2. Navigate to Applications > Lending Management > Loan account 3. Open the Loan account lister page 4. Click the Column setting/cog wheel icon on a column header. | F28: - A menu appears with Sort ascending, Sort descending, Freeze, Unfreeze all, and Text Wrapping (Clip / Wrap) options. | G28: IADSSL-101 | H28: No | I28: Not Executed
... A53: LA-039 | B53: Verify overall lister UI consistency (spacing, alignment, controls) matches the design standard | C53: Refer to Common Preconditions above. | D53: N/A | E53: 1. Sign in to Sage Intacct application 2. Navigate to Applications > Lending Management > Loan account 3. Open the Loan account lister page and visually inspect its layout, spacing, headers, buttons, filters, and grid. | F53: - The page header, buttons, column filters, and data grid use the same spacing, alignment, and control styling as every other module lister in the application, with no visibly misaligned, overlapping, or inconsistently styled element. | G53: IADSSL-101 | H53: No | I53: Not Executed
A54: LA-040 | B54: [KNOWN DEFECT] 'Loan account' tile on module landing page does not respond to clicks | C54: Refer to Common Preconditions above. | D54: N/A - module landing page navigation only | E54: 1. Sign in to Sage Intacct application 2. Navigate to Applications > Lending Management (module landing page, not the top-nav dropdown) 3. Click the 'Loan account' tile 4. Observe whether the page navigates. | F54: - [DEFECT] Clicking the 'Loan account' tile on the Lending Management module landing page does nothing - no navigation occurs and no network request fires. - The sibling 'Loan account categories' and 'Loan interest rates' tiles on the same page navigate correctly when clicked. - The Loan account lister page is still reachable via the top navigation bar's Lending Management dropdown > Transactions > Loan account link, which works correctly. | G54: IADSSL-101 | H54: TBD | I54: Not Executed | J54: [ADDED - verified live 2026-08-31]
A55: CREATE (78 test cases)
A56: LA-041 | B56: Page title is 'Create loan' | C56: Refer to Common Preconditions above. | D56: Account category: QA Loan Category Account number: LA-QA-001 | E56: 1. Sign in to Sage Intacct application 2. Navigate to Applications > Lending Management > Loan account 3. Click the '+Create' button 4. Observe the page header at the top of the page. | F56: - The page header (H1) displays "Create loan". | G56: IADSSL-101 | H56: No | I56: Not Executed | J56: Source section: B. Create page (IDs: TC-LA-001–058)
A57: LA-042 | B57: Loan information section present | C57: Refer to Common Preconditions above. | D57: Account category: QA Loan Category Account number: LA-QA-001 | E57: 1. Sign in to Sage Intacct application 2. Navigate to Applications > Lending Management > Loan account 3. Click the '+Create' button to open the Create loan account page. | F57: - The 'Loan information' section heading is visible on the Create loan account page. | G57: IADSSL-101 | H57: No | I57: Not Executed | J57: Source section: B. Create page (IDs: TC-LA-001–058)
A58: LA-043 | B58: Loan information fields present | C58: Refer to Common Preconditions above. | D58: Account category: QA Loan Category Account number: LA-QA-001 Account name: Client QA Loan 001 Customer: 1--Power Aerospace Materials Loan type: QA Non-Revolving Interest rate: 5.0000% Origination amount: 10000.00 Origination date: 2026-08-01 | E58: 1. Sign in to Sage Intacct application 2. Navigate to Applications > Lending Management > Loan account 3. Click the '+Create' button to open the Create loan account page 4. Inspect the 'Loan information' section. | F58: - The Account category, Account number, Account name, Customer, Vendor, Attachment, Description, Email statements, and Amount fields are all present on the Create loan account page. | G58: IADSSL-101 | H58: No | I58: Not Executed | J58: Source section: B. Create page (IDs: TC-LA-001–058)
A59: LA-044 | B59: Account category mandatory | C59: Refer to Common Preconditions above. | D59: Account category: (leave blank) Account number: LA-QA-001 Account name: Client QA Loan 001 Customer: 1--Power Aerospace Materials | E59: 1. Sign in to Sage Intacct application 2. Navigate to Applications > Lending Management > Loan account 3. Click the '+Create' button to open the Create loan account page 4. Inspect the Account category field label. | F59: - The Account category field label displays a red asterisk indicating it is a mandatory field. | G59: IADSSL-101 | H59: No | I59: Not Executed | J59: Source section: B. Create page (IDs: TC-LA-001–058)
A60: LA-045 | B60: Empty Account category error | C60: Refer to Common Preconditions above. | D60: Account category: (leave blank) Account number: LA-QA-001 Account name: Client QA Loan 001 Customer: 1--Power Aerospace Materials | E60: 1. Sign in to Sage Intacct application 2. Navigate to Applications > Lending Management > Loan account 3. Click the '+Create' button to open the Create loan account page 4. Leave the Account category field blank, complete the other required fields (Account number: LA-QA-001, Account name: Client QA Loan 001, Customer: 1--Power Aerospace Materials), and click 'Save'. | F60: - A validation error banner appears reading "Correct the fields below and try again." - A per-field line reads "Account category: Field is required." - The record is not saved. | G60: IADSSL-101 | H60: No | I60: Not Executed | J60: Source section: B. Create page (IDs: TC-LA-001–058)
A61: LA-046 | B61: Account category dropdown active-only | C61: Refer to Common Preconditions above. | D61: Account category: QA Loan Category Account number: LA-QA-001 Account name: Client QA Loan 001 Customer: 1--Power Aerospace Materials Loan type: QA Non-Revolving Interest rate: 5.0000% Origination amount: 10000.00 Origination date: 2026-08-01 | E61: 1. Sign in to Sage Intacct application 2. Navigate to Applications > Lending Management > Loan account 3. Click '+Create'. 4. Click the Account category dropdown. | F61: - Only active account categories (e.g. QA Loan Category) are listed. - Inactive categories do not appear. | G61: IADSSL-101 | H61: No | I61: Not Executed | J61: Source section: B. Create page (IDs: TC-LA-001–058)
A62: LA-047 | B62: Account number mandatory | C62: Refer to Common Preconditions above. | D62: Account category: QA Loan Category Account number: (leave blank) Account name: Client QA Loan 001 Customer: 1--Power Aerospace Materials | E62: 1. Sign in to Sage Intacct application 2. Navigate to Applications > Lending Management > Loan account 3. Click the '+Create' button to open the Create loan account page 4. Inspect the Account number field label. | F62: - The Account number field label displays a red asterisk indicating it is a mandatory field. | G62: IADSSL-101 | H62: No | I62: Not Executed | J62: Source section: B. Create page (IDs: TC-LA-001–058)
A63: LA-048 | B63: Empty Account number (no-sequence category) | C63: Refer to Common Preconditions above. | D63: Account category: QA Loan Category (no auto-sequence configured) Account number: (leave blank) Account name: Client QA Loan 001 Customer: 1--Power Aerospace Materials | E63: 1. Sign in to Sage Intacct application 2. Navigate to Applications > Lending Management > Loan account 3. Click the '+Create' button to open the Create loan account page 4. Select Account category 'QA Loan Category' (a category with no auto-numbering sequence configured), leave Account number blank, complete the other required fields, and click 'Save'. | F63: - A friendly validation error appears stating that Account number is required. - No internal object path or technical identifier is exposed in the message. - The record is not saved. | G63: IADSSL-101 | H63: No | I63: Not Executed | J63: Source section: B. Create page (IDs: TC-LA-001–058)
A64: LA-049 | B64: Account number accepts string value | C64: Refer to Common Preconditions above. | D64: Account category: QA Loan Category Account number: LA-QA-001 Account name: Client QA Loan 001 Customer: 1--Power Aerospace Materials Loan type: QA Non-Revolving Interest rate: 5.0000% Origination amount: 10000.00 Origination date: 2026-08-01 | E64: 1. Sign in to Sage Intacct application 2. Navigate to Applications > Lending Management > Loan account 3. Click '+Create'. 4. Enter 'LA-QA-001' (a hyphenated alphanumeric string) in the Account number field, and enter valid values in all other required fields. 5. Click 'Save'. | F64: - The record saves successfully with the hyphenated Account number string saved as entered. | G64: IADSSL-101 | H64: No | I64: Not Executed | J64: Source section: B. Create page (IDs: TC-LA-001–058)
A65: LA-050 | B65: Whitespace Account number rejected | C65: Refer to Common Preconditions above. | D65: Account category: QA Loan Category Account number: " " (whitespace only) Account name: Client QA Loan 001 Customer: 1--Power Aerospace Materials Loan type: QA Non-Revolving Interest rate: 5.0000% Origination amount: 10000.00 Origination date: 2026-08-01 | E65: 1. Sign in to Sage Intacct application 2. Navigate to Applications > Lending Management > Loan account 3. Click '+Create'. 4. Enter a whitespace-only value (e.g. spaces) in the Account number field, and enter valid values in all other required fields. 5. Click 'Save'. | F65: - A friendly validation error appears stating the Account number is required/invalid. - The record is not saved. | G65: IADSSL-101 | H65: No | I65: Not Executed | J65: Source section: B. Create page (IDs: TC-LA-001–058)
A66: LA-051 | B66: Reject a supplied account ID when the category has a document sequence | C66: Refer to Common Preconditions above. | D66: Account category: QA-LC-SEQUENCED (has a document sequence) Account number (ID supplied): MANUAL-001 | E66: 1. Sign in to Sage Intacct application 2. Navigate to Applications > Lending Management > Loan account 3. Select the QA-LC-SEQUENCED account category (configured with a document sequence). 4. Manually enter 'MANUAL-001' in the Account number field instead of leaving it for auto-generation, and complete the remaining required fields. 5. Click 'Save'. | F66: - Creation is blocked with a validation error stating the Account number cannot be manually supplied for a category with a document sequence, since sequenced categories must generate the ID server-side. | G66: IADSSL-101 | H66: No | I66: Not Executed
A67: LA-052 | B67: Account name mandatory | C67: Refer to Common Preconditions above. | D67: Account category: QA Loan Category Account number: LA-QA-001 Account name: (leave blank) Customer: 1--Power Aerospace Materials | E67: 1. Sign in to Sage Intacct application 2. Navigate to Applications > Lending Management > Loan account 3. Click the '+Create' button to open the Create loan account page 4. Inspect the Account name field label. | F67: - The Account name field label displays a red asterisk indicating it is a mandatory field. | G67: IADSSL-101 | H67: No | I67: Not Executed | J67: Source section: B. Create page (IDs: TC-LA-001–058)
A68: LA-053 | B68: Empty Account name error | C68: Refer to Common Preconditions above. | D68: Account category: QA Loan Category Account number: LA-QA-001 Account name: (leave blank) Customer: 1--Power Aerospace Materials | E68: 1. Sign in to Sage Intacct application 2. Navigate to Applications > Lending Management > Loan account 3. Click the '+Create' button to open the Create loan account page 4. Leave the Account name field blank, complete the other required fields (Account category: QA Loan Category, Account number: LA-QA-001, Customer: 1--Power Aerospace Materials), and click 'Save'. | F68: - A validation error banner appears reading "Correct the fields below and try again." - A per-field line reads "Account name: Field is required." - The record is not saved. | G68: IADSSL-101 | H68: No | I68: Not Executed | J68: Source section: B. Create page (IDs: TC-LA-001–058)
A69: LA-054 | B69: Account name >200 chars rejected | C69: Refer to Common Preconditions above. | D69: Account category: QA Loan Category Account number: LA-QA-001 Account name (201 chars, over limit): "Client QA Loan 001 AAAAAAAAAAAAAAAAAAAAAAAAAAAAAAAAAAAAAAAAAAAAAAAAAAAAAAAAAAAAAAAAAAAAAAAAAAAAAAAAAAAAAAAAAAAAAAAAAAAAAAAAAAAAAAAAAAAAAAAAAAAAAAAAAAAAAAAAAAAAAAAAAAAAAAAAAAAAAAAAAAAAAAAAAAAAAAAA" Customer: 1--Power Aerospace Materials Loan type: QA Non-Revolving Interest rate: 5.0000% Origination amount: 10000.00 Origination date: 2026-08-01 | E69: 1. Sign in to Sage Intacct application 2. Navigate to Applications > Lending Management > Loan account 3. Click the '+Create' button to open the Create loan account page 4. Enter an Account name value of 201 characters, complete the other required fields, and click 'Save'. | F69: - A friendly validation error appears stating the Account name field cannot exceed 200 characters. - No raw i18n translation key is exposed. - The record is not saved. | G69: IADSSL-101 | H69: No | I69: Not Executed | J69: Source section: B. Create page (IDs: TC-LA-001–058)
A70: LA-055 | B70: Whitespace Account name rejected | C70: Refer to Common Preconditions above. | D70: Account category: QA Loan Category Account number: LA-QA-001 Account name: " " (whitespace only) Customer: 1--Power Aerospace Materials Loan type: QA Non-Revolving Interest rate: 5.0000% Origination amount: 10000.00 Origination date: 2026-08-01 | E70: 1. Sign in to Sage Intacct application 2. Navigate to Applications > Lending Management > Loan account 3. Click '+Create'. 4. Enter a whitespace-only value (e.g. spaces) in the Account name field, and enter valid values in all other required fields. 5. Click 'Save'. | F70: - A friendly validation error appears stating the Account name is required/invalid. - The record is not saved. | G70: IADSSL-101 | H70: No | I70: Not Executed | J70: Source section: B. Create page (IDs: TC-LA-001–058)
A71: LA-056 | B71: Customer mandatory | C71: Refer to Common Preconditions above. | D71: Account category: QA Loan Category Account number: LA-QA-001 Account name: Client QA Loan 001 Customer: (leave blank) | E71: 1. Sign in to Sage Intacct application 2. Navigate to Applications > Lending Management > Loan account 3. Click the '+Create' button to open the Create loan account page 4. Inspect the Customer field label. | F71: - The Customer field label displays a red asterisk indicating it is a mandatory field. | G71: IADSSL-101 | H71: No | I71: Not Executed | J71: Source section: B. Create page (IDs: TC-LA-001–058)
A72: LA-057 | B72: Empty Customer error | C72: Refer to Common Preconditions above. | D72: Account category: QA Loan Category Account number: LA-QA-001 Account name: Client QA Loan 001 Customer: (leave blank) | E72: 1. Sign in to Sage Intacct application 2. Navigate to Applications > Lending Management > Loan account 3. Click the '+Create' button to open the Create loan account page 4. Leave the Customer field blank, complete the other required fields (Account category: QA Loan Category, Account number: LA-QA-001, Account name: Client QA Loan 001), and click 'Save'. | F72: - A validation error banner appears reading "Correct the fields below and try again." - A per-field line reads "Customer: Field is required." - The record is not saved. | G72: IADSSL-101 | H72: No | I72: Not Executed | J72: Source section: B. Create page (IDs: TC-LA-001–058)
A73: LA-058 | B73: Customer dropdown active-only | C73: Refer to Common Preconditions above. | D73: Account category: QA Loan Category Account number: LA-QA-001 Account name: Client QA Loan 001 Customer: 1--Power Aerospace Materials Loan type: QA Non-Revolving Interest rate: 5.0000% Origination amount: 10000.00 Origination date: 2026-08-01 | E73: 1. Sign in to Sage Intacct application 2. Navigate to Applications > Lending Management > Loan account 3. Click '+Create'. 4. Click the Customer dropdown. | F73: - Only active customers (e.g. 1--Power Aerospace Materials) are listed. - Inactive customers do not appear. | G73: IADSSL-101 | H73: No | I73: Not Executed | J73: Source section: B. Create page (IDs: TC-LA-001–058)
A74: LA-059 | B74: Vendor mandatory | C74: Refer to Common Preconditions above. | D74: Account category: QA Loan Category Account number: LA-QA-001 Account name: Client QA Loan 001 Customer: 1--Power Aerospace Materials Vendor: (leave blank) | E74: 1. Sign in to Sage Intacct application 2. Navigate to Applications > Lending Management > Loan account 3. Click the '+Create' button to open the Create loan account page 4. Inspect the Vendor field label. | F74: - The Vendor field label displays a red asterisk indicating it is a mandatory field. | G74: IADSSL-101 | H74: No | I74: Not Executed | J74: Source section: B. Create page (IDs: TC-LA-001–058)
A75: LA-060 | B75: Empty Vendor error | C75: Refer to Common Preconditions above. | D75: Account category: QA Loan Category Account number: LA-QA-001 Account name: Client QA Loan 001 Customer: 1--Power Aerospace Materials Vendor: (leave blank) | E75: 1. Sign in to Sage Intacct application 2. Navigate to Applications > Lending Management > Loan account 3. Click the '+Create' button to open the Create loan account page 4. Leave the Vendor field blank, complete the other required fields (Account category: QA Loan Category, Account number: LA-QA-001, Account name: Client QA Loan 001, Customer: 1--Power Aerospace Materials), and click 'Save'. | F75: - A validation error banner appears reading "Correct the fields below and try again." - A per-field line reads "Vendor: Field is required." - The record is not saved. | G75: IADSSL-101 | H75: No | I75: Not Executed | J75: Source section: B. Create page (IDs: TC-LA-001–058)
A76: LA-061 | B76: Vendor dropdown active-only | C76: Refer to Common Preconditions above. | D76: Account category: QA Loan Category Account number: LA-QA-001 Account name: Client QA Loan 001 Customer: 1--Power Aerospace Materials Loan type: QA Non-Revolving Interest rate: 5.0000% Origination amount: 10000.00 Origination date: 2026-08-01 | E76: 1. Sign in to Sage Intacct application 2. Navigate to Applications > Lending Management > Loan account 3. Click '+Create'. 4. Click the Vendor dropdown. | F76: - Only active vendors are listed. - Inactive vendors do not appear. | G76: IADSSL-101 | H76: No | I76: Not Executed | J76: Source section: B. Create page (IDs: TC-LA-001–058)
A77: LA-062 | B77: Attachment not mandatory | C77: Refer to Common Preconditions above. | D77: Attachment: qa-evidence.pdf (250 KB) — left unattached Account category: QA Loan Category Account number: LA-QA-001 Account name: Client QA Loan 001 Customer: 1--Power Aerospace Materials | E77: 1. Sign in to Sage Intacct application 2. Navigate to Applications > Lending Management > Loan account 3. Click the '+Create' button to open the Create loan account page 4. Inspect the Attachment field label 5. Complete the other required fields without adding an attachment and click 'Save'. | F77: - The Attachment field label shows no red asterisk, confirming it is optional. - The record saves successfully with no attachment provided. | G77: IADSSL-101 | H77: No | I77: Not Executed | J77: Source section: B. Create page (IDs: TC-LA-001–058)
A78: LA-063 | B78: Attachment shows clip icon | C78: Refer to Common Preconditions above. | D78: Attachment: qa-evidence.pdf (250 KB) Account category: QA Loan Category Account number: LA-QA-001 Account name: Client QA Loan 001 Customer: 1--Power Aerospace Materials Loan type: QA Non-Revolving Interest rate: 5.0000% Origination amount: 10000.00 | E78: 1. Sign in to Sage Intacct application 2. Navigate to Applications > Lending Management > Loan account 3. Click the '+Create' button to open the Create loan account page 4. Attach the file 'qa-evidence.pdf' (250 KB) in the Attachment field, complete the other required fields, and click 'Save'. | F78: - The record saves successfully. - A clip/paperclip icon indicating the attached file is visible. | G78: IADSSL-101 | H78: No | I78: Not Executed | J78: Source section: B. Create page (IDs: TC-LA-001–058)
... A93: LA-078 | B93: Renewal date optional for Revolving | C93: Refer to Common Preconditions above. | D93: Account category: QA Loan Category Account number: LA-QA-001 Account name: Client QA Loan 001 Customer: 1--Power Aerospace Materials Loan type: QA Non-Revolving Interest rate: 5.0000% Origination amount: 10000.00 Origination date: 2026-08-01 | E93: 1. Sign in to Sage Intacct application 2. Navigate to Applications > Lending Management > Loan account 3. Click '+Create'. 4. Select a Revolving Loan type. 5. Locate the Renewal date field. | F93: - No red asterisk appears next to the Renewal date field, indicating it is optional for Revolving loans. | G93: IADSSL-101 | H93: No | I93: Not Executed | J93: Source section: B. Create page (IDs: TC-LA-001–058)
A94: LA-079 | B94: Renewal date is allowed only for revolving loans | C94: Refer to Common Preconditions above. | D94: Loan type: Non-revolving Renewal date: 2027-08-01 | E94: 1. Sign in to Sage Intacct application 2. Navigate to Applications > Lending Management > Loan account 3. Click '+Create'. 4. Select 'Non-revolving' as the Loan type and attempt to enter 2027-08-01 in the Renewal date field. 5. Click 'Save'. | F94: - The Renewal date field does not appear anywhere on the Create form when Loan type is a Non-revolving loan type; the Loan terms section shows only Loan type, Loan origination date, Interest rate, Term in months, and First payment date. | G94: IADSSL-101 | H94: No | I94: Not Executed
A95: LA-080 | B95: Reject mismatched loan-type and interest-rate amortization types | C95: Refer to Common Preconditions above. | D95: Loan type: Revolving Interest rate type (on Interest Rate record): Non-revolving amortization | E95: 1. Sign in to Sage Intacct application 2. Navigate to Applications > Lending Management > Loan account 3. Click '+Create'. 4. Select 'Revolving' as the Loan type and select an interest rate configured with a Non-revolving amortization type. 5. Click 'Save'. | F95: - A validation error appears stating the loan type and interest rate amortization types do not match. - The record is not saved. | G95: IADSSL-101 | H95: No | I95: Not Executed
A96: LA-081 | B96: Preview amortization schedule modal | C96: Refer to Common Preconditions above. | D96: Account category: QA Loan Category Account number: LA-QA-001 Account name: Client QA Loan 001 Customer: 1--Power Aerospace Materials Loan type: QA Non-Revolving Interest rate: 5.0000% Origination amount: 10000.00 Origination date: 2026-08-01 | E96: 1. Sign in to Sage Intacct application 2. Navigate to Applications > Lending Management > Loan account 3. Click the '+Create' button to open the Create loan account page 4. Select Loan type 'QA Non-Revolving', complete the required fields (Account category: QA Loan Category, Account number: LA-QA-001, Account name: Client QA Loan 001, Customer: 1--Power Aerospace Materials, Interest rate: 5.0000%, Origination amount: 10000.00, Origination date: 2026-08-01), and click the amortization schedule 'Preview' link. | F96: - A modal opens displaying a populated amortization schedule table with the expected columns (e.g. payment number, date, principal, interest, balance). | G96: IADSSL-101 | H96: No | I96: Not Executed | J96: Source section: B. Create page (IDs: TC-LA-001–058)
A97: LA-082 | B97: Valid Non-revolving save succeeds | C97: Refer to Common Preconditions above. | D97: Account category: QA Loan Category Account number: LA-QA-001 Account name: Client QA Loan 001 Customer: 1--Power Aerospace Materials Loan type: QA Non-Revolving Interest rate: 5.0000% Origination amount: 10000.00 Origination date: 2026-08-01 | E97: 1. Sign in to Sage Intacct application 2. Navigate to Applications > Lending Management > Loan account 3. Click the '+Create' button to open the Create loan account page 4. Complete all fields with valid values (Account category: QA Loan Category, Account number: LA-QA-001, Account name: Client QA Loan 001, Customer: 1--Power Aerospace Materials, Loan type: QA Non-Revolving, Interest rate: 5.0000%, Origination amount: 10000.00, Origination date: 2026-08-01) and click 'Save'. | F97: - The record saves successfully. - The page redirects to the View loan account screen for the new record. | G97: IADSSL-101 | H97: No | I97: Not Executed | J97: Source section: B. Create page (IDs: TC-LA-001–058)
A98: LA-083 | B98: [KNOWN DEFECT] Revolving+amortization save crashes | C98: Refer to Common Preconditions above. | D98: Account category: QA Loan Category Account number: LA-QA-001 Account name: Client QA Loan 001 Customer: 1--Power Aerospace Materials Loan type: QA Revolving Amortization: checked Interest rate: 5.0000% Origination amount: 10000.00 Origination date: 2026-08-01 | E98: 1. Sign in to Sage Intacct application 2. Navigate to Applications > Lending Management > Loan account 3. Click the '+Create' button to open the Create loan account page 4. Select Loan type 'QA Revolving', check the amortization checkbox, complete the remaining required fields (Account category: QA Loan Category, Account number: LA-QA-001, Account name: Client QA Loan 001, Customer: 1--Power Aerospace Materials, Interest rate: 5.0000%, Origination amount: 10000.00, Origination date: 2026-08-01), and click 'Save'. | F98: - [DEFECT] Instead of saving or showing a friendly validation message, a raw/unhandled exception is displayed as a toast. - The user remains on the Create loan account page with the record not saved. | G98: IADSSL-101 | H98: No | I98: Not Executed | J98: Source section: B. Create page (IDs: TC-LA-001–058)
A99: LA-084 | B99: Amount mandatory numeric | C99: Refer to Common Preconditions above. | D99: Account category: QA Loan Category Account number: LA-QA-001 Account name: Client QA Loan 001 Customer: 1--Power Aerospace Materials Origination amount: (leave blank) | E99: 1. Sign in to Sage Intacct application 2. Navigate to Applications > Lending Management > Loan account 3. Click the '+Create' button to open the Create loan account page 4. Inspect the Origination amount field label. | F99: - The Origination amount field label displays a red asterisk indicating it is a mandatory numeric field. | G99: IADSSL-101 | H99: No | I99: Not Executed | J99: Source section: B. Create page (IDs: TC-LA-001–058)
A100: LA-085 | B100: Empty Amount error | C100: Refer to Common Preconditions above. | D100: Account category: QA Loan Category Account number: LA-QA-001 Account name: Client QA Loan 001 Customer: 1--Power Aerospace Materials Loan type: QA Non-Revolving Interest rate: 5.0000% Origination date: 2026-08-01 Amount (target field): (leave blank) | E100: 1. Sign in to Sage Intacct application 2. Navigate to Applications > Lending Management > Loan account 3. Click '+Create'. 4. Enter valid values in all required fields except leave the Amount field blank. 5. Click 'Save'. | F100: - A validation error banner appears reading "Correct the fields below and try again." - A per-field line reads "Amount: Field is required." - The record is not saved. | G100: IADSSL-101 | H100: No | I100: Not Executed | J100: Source section: B. Create page (IDs: TC-LA-001–058)
A101: LA-086 | B101: Negative Amount rejected | C101: Refer to Common Preconditions above. | D101: Account category: QA Loan Category Account number: LA-QA-001 Account name: Client QA Loan 001 Customer: 1--Power Aerospace Materials Loan type: QA Non-Revolving Interest rate: 5.0000% Origination date: 2026-08-01 Amount: -1.00 | E101: 1. Sign in to Sage Intacct application 2. Navigate to Applications > Lending Management > Loan account 3. Click '+Create'. 4. Enter valid values in all required fields and enter -1.00 in the Amount field. 5. Click 'Save'. | F101: - A friendly validation error appears stating the Amount must be a positive value. - No internal field name (e.g. "/originationAmount") is exposed in the message. - The record is not saved. | G101: IADSSL-101 | H101: No | I101: Not Executed | J101: Source section: B. Create page (IDs: TC-LA-001–058)
A102: LA-087 | B102: Amount = 0 accepted | C102: Refer to Common Preconditions above. | D102: Account category: QA Loan Category Account number: LA-QA-001 Account name: Client QA Loan 001 Customer: 1--Power Aerospace Materials Loan type: QA Non-Revolving Interest rate: 5.0000% Origination date: 2026-08-01 Amount: 0.00 | E102: 1. Sign in to Sage Intacct application 2. Navigate to Applications > Lending Management > Loan account 3. Click '+Create'. 4. Enter valid values in all required fields and enter 0.00 in the Amount field. 5. Click 'Save'. | F102: - The record saves successfully with an Amount of 0.00. | G102: IADSSL-101 | H102: No | I102: Not Executed | J102: Source section: B. Create page (IDs: TC-LA-001–058)
A103: LA-088 | B103: Origination date mandatory | C103: Refer to Common Preconditions above. | D103: Account category: QA Loan Category Account number: LA-QA-001 Account name: Client QA Loan 001 Customer: 1--Power Aerospace Materials Origination date (target field): (leave blank) | E103: 1. Sign in to Sage Intacct application 2. Navigate to Applications > Lending Management > Loan account 3. Click '+Create'. 4. Locate the Origination date field. | F103: - A red asterisk is displayed next to the Origination date field, indicating it is mandatory. | G103: IADSSL-101 | H103: No | I103: Not Executed | J103: Source section: B. Create page (IDs: TC-LA-001–058)
A104: LA-089 | B104: Origination date accepts future date | C104: Refer to Common Preconditions above. | D104: Account category: QA Loan Category Account number: LA-QA-001 Account name: Client QA Loan 001 Customer: 1--Power Aerospace Materials Loan type: QA Non-Revolving Interest rate: 5.0000% Origination amount: 10000.00 Origination date: 2026-09-30 (future date) | E104: 1. Sign in to Sage Intacct application 2. Navigate to Applications > Lending Management > Loan account 3. Click '+Create'. 4. Enter valid values in all required fields and enter 2026-09-30 (a future date) in the Origination date field. 5. Click 'Save'. | F104: - The record saves successfully with the future Origination date accepted. | G104: IADSSL-101 | H104: No | I104: Not Executed | J104: Source section: B. Create page (IDs: TC-LA-001–058)
A105: LA-090 | B105: Enforce the exact first-payment-date rule | C105: Refer to Common Preconditions above. | D105: Origination date: 2026-08-17 First payment date (invalid): 2026-09-17 First payment date (valid): 2026-09-01 | E105: 1. Sign in to Sage Intacct application 2. Navigate to Applications > Lending Management > Loan account 3. Click '+Create'. 4. Enter Origination date 2026-08-17 and First payment date 2026-09-17 (not the first day of the following month), then click 'Save'. 5. Repeat, entering First payment date 2026-09-01 (the first day of the following month) instead, then click 'Save'. | F105: - The 2026-09-17 First payment date is rejected with a validation error. - The 2026-09-01 First payment date is accepted and the record saves successfully. | G105: IADSSL-101 | H105: No | I105: Not Executed
A106: LA-091 | B106: Block origination in a statement period that is not open | C106: Refer to Common Preconditions above. | D106: Origination date: 2026-06-15 June statement run state: Completed | E106: 1. Sign in to Sage Intacct application 2. Navigate to Applications > Lending Management > Loan account 3. Click '+Create'. 4. Enter 2026-06-15 as the Origination date, where the June statement period run state is Completed, and enter valid values in all other required fields. 5. Click 'Save'. | F106: - A validation error appears stating the origination date falls within a processed/closed statement period. - The record is not saved. | G106: IADSSL-101 | H106: No | I106: Not Executed
A107: LA-092 | B107: Standard first invoice/statement dates are applicable, future-safe, and after origination | C107: Refer to Common Preconditions above. | D107: Automation: Standard Origination date: 2026-08-15 First invoice date: 2026-08-14 (before origination) | E107: 1. Sign in to Sage Intacct application 2. Navigate to Applications > Lending Management > Loan account 3. Click '+Create'. 4. Set Automation to 'Standard', Origination date to 2026-08-15, and First invoice date to 2026-08-14 (a date before origination), then complete remaining required fields. 5. Click 'Save'. | F107: - A validation error appears stating the applicable Standard first dates must follow the origination date and not be in the past. - The record is not saved. | G107: IADSSL-101 | H107: No | I107: Not Executed
A108: LA-093 | B108: Month-end loans reject Standard first invoice and statement dates | C108: Refer to Common Preconditions above. | D108: Automation: Month end First invoice date: 2026-09-01 | E108: 1. Sign in to Sage Intacct application 2. Navigate to Applications > Lending Management > Loan account 3. Click '+Create'. 4. Set Automation to 'Month end' and enter a First invoice date of 2026-09-01 (a Standard-style specific date), then complete remaining required fields. 5. Click 'Save'. | F108: - A validation error appears stating Standard first dates are not permitted under Month End automation. - The record is not saved. | G108: IADSSL-101 | H108: No | I108: Not Executed
A109: LA-094 | B109: Dimensions section fields present | C109: Refer to Common Preconditions above. | D109: Account category: QA Loan Category Account number: LA-QA-001 Account name: Client QA Loan 001 User role: Full Access | E109: 1. Sign in to Sage Intacct application 2. Navigate to Applications > Lending Management > Loan account 3. Click '+Create'. 4. Locate the Dimensions section on the Create page. | F109: - The Dimensions section displays fields for Department, Location, Project, Employee, Item, Class, Contract, Product Lines, Region, and Vertical (10 dimensions total). | G109: IADSSL-101 | H109: No | I109: Not Executed | J109: Source section: B. Create page (IDs: TC-LA-001–058)
A110: LA-095 | B110: Non-Location dimensions not mandatory | C110: Refer to Common Preconditions above. | D110: Account category: QA Loan Category Account number: LA-QA-001 Account name: Client QA Loan 001 Customer: 1--Power Aerospace Materials Department, Project, Class, Item (target fields): (leave blank) | E110: 1. Sign in to Sage Intacct application 2. Navigate to Applications > Lending Management > Loan account 3. Click '+Create'. 4. Enter valid values in all other required fields and leave Department, Project, Class, and Item blank. | F110: - No red asterisk appears next to the Department, Project, Class, or Item fields, indicating they are not mandatory. | G110: IADSSL-101 | H110: No | I110: Not Executed | J110: Source section: B. Create page (IDs: TC-LA-001–058)
A111: LA-096 | B111: [KNOWN DEFECT] Location has no asterisk | C111: Refer to Common Preconditions above. | D111: Account category: QA Loan Category Account number: LA-QA-001 Account name: Client QA Loan 001 Customer: 1--Power Aerospace Materials Loan type: QA Non-Revolving Interest rate: 5.0000% Origination amount: 10000.00 Origination date: 2026-08-01 | E111: 1. Sign in to Sage Intacct application 2. Navigate to Applications > Lending Management > Loan account 3. Click '+Create'. 4. Locate the Location field in the Dimensions section. | F111: - [DEFECT] No red asterisk appears on the Location field even though Location is enforced as mandatory when saving. | G111: IADSSL-101 | H111: No | I111: Not Executed | J111: Source section: B. Create page (IDs: TC-LA-001–058)
A112: LA-097 | B112: Empty Location error | C112: Refer to Common Preconditions above. | D112: Account category: QA Loan Category Account number: LA-QA-001 Account name: Client QA Loan 001 Customer: 1--Power Aerospace Materials Location (target field): (leave blank) | E112: 1. Sign in to Sage Intacct application 2. Navigate to Applications > Lending Management > Loan account 3. Click '+Create'. 4. Enter valid values in all other required fields and leave the Location field blank. 5. Click 'Save'. | F112: - A validation error banner appears reading "Correct the fields below and try again." - A per-field line reads "Location: Field is required." - The record is not saved. | G112: IADSSL-101 | H112: No | I112: Not Executed | J112: Source section: B. Create page (IDs: TC-LA-001–058)
A113: LA-098 | B113: Valid Location succeeds | C113: Refer to Common Preconditions above. | D113: Account category: QA Loan Category Account number: LA-QA-001 Account name: Client QA Loan 001 Customer: 1--Power Aerospace Materials Loan type: QA Non-Revolving Interest rate: 5.0000% Origination amount: 10000.00 Origination date: 2026-08-01 Location: A valid active location | E113: 1. Sign in to Sage Intacct application 2. Navigate to Applications > Lending Management > Loan account 3. Click '+Create'. 4. Enter valid values in all required fields, including a valid Location. 5. Click 'Save'. | F113: - The record saves successfully with the selected Location retained on the record. | G113: IADSSL-101 | H113: No | I113: Not Executed | J113: Source section: B. Create page (IDs: TC-LA-001–058)
A114: LA-099 | B114: Require all historical balances when importing an existing loan | C114: Refer to Common Preconditions above. | D114: Existing loan: Yes Historical principal balance: 8000.00 Historical interest: 200.00 Historical fees: (omitted, no writtenOffFeeAmount value) | E114: 1. Sign in to Sage Intacct application 2. Navigate to Applications > Lending Management > Loan account 3. Click '+Create'. 4. Check the 'Existing loan' checkbox and enter historical balance values, intentionally omitting the Written-off fee amount field. 5. Click 'Save'. | F114: - A validation error appears identifying the missing historical field (Written-off fee amount). - The record is not saved. | G114: IADSSL-101 | H114: No | I114: Not Executed
A115: LA-100 | B115: Require historical loan amount to equal origination amount | C115: Refer to Common Preconditions above. | D115: Existing loan: Yes Origination amount: 10000.00 Historical loan amount: 9999.00 | E115: 1. Sign in to Sage Intacct application 2. Navigate to Applications > Lending Management > Loan account 3. Click '+Create'. 4. Check the 'Existing loan' checkbox, enter Origination amount 10000.00 and Historical loan amount 9999.00 (mismatched values). 5. Click 'Save'. | F115: - A validation error appears stating the historical loan amount must equal the origination amount. - The record is not saved. | G115: IADSSL-101 | H115: No | I115: Not Executed
A116: LA-101 | B116: Reject historical fields when the existing-loan flag is false | C116: Refer to Common Preconditions above. | D116: Existing loan: No Historical principal balance: 8000.00 | E116: 1. Sign in to Sage Intacct application 2. Navigate to Applications > Lending Management > Loan account 3. Click '+Create'. 4. Leave the 'Existing loan' checkbox unchecked (False) but enter a value of 8000.00 in the Historical principal balance field. 5. Click 'Save'. | F116: - A validation error appears stating historical balances are not allowed unless the loan is marked as existing. - The record is not saved. | G116: IADSSL-101 | H116: No | I116: Not Executed
A117: LA-102 | B117: Existing-loan import creates history/adjustment/interest records and no AP bill | C117: Refer to Common Preconditions above. | D117: Existing loan: Yes Historical principal: 8000.00 Historical interest: 200.00 Historical fees: 50.00 | E117: 1. Sign in to Sage Intacct application 2. Navigate to Applications > Lending Management > Loan account 3. Click '+Create'. 4. Check 'Existing loan' and enter Historical principal 8000.00, Interest 200.00, and Fees 50.00, then complete remaining required fields. 5. Click 'Save', then open the loan's transaction history and check for an AP bill. | F117: - LoanHistory records are created. - A historical fee adjustment transaction is created. - A historical interest transaction is created. - No origination AP bill is created. | G117: IADSSL-101 | H117: No | I117: Not Executed
A118: LA-103 | B118: Save split-button options | C118: Refer to Common Preconditions above. | D118: Account category: QA Loan Category Account number: LA-QA-001 Account name: Client QA Loan 001 Customer: 1--Power Aerospace Materials Loan type: QA Non-Revolving Interest rate: 5.0000% Origination amount: 10000.00 Origination date: 2026-08-01 | E118: 1. Sign in to Sage Intacct application 2. Navigate to Applications > Lending Management > Loan account 3. Click '+Create'. 4. Enter valid values in all required fields. 5. Click the dropdown arrow next to the Save split button. | F118: - The dropdown lists 'Save', 'Save and close', and 'Save and new' options. | G118: IADSSL-101 | H118: No | I118: Not Executed | J118: Source section: B. Create page (IDs: TC-LA-001–058)
A119: LA-104 | B119: Success message on valid save | C119: Refer to Common Preconditions above. | D119: Account category: QA Loan Category Account number: LA-QA-001 Account name: Client QA Loan 001 Customer: 1--Power Aerospace Materials Loan type: QA Non-Revolving Interest rate: 5.0000% Origination amount: 10000.00 Origination date: 2026-08-01 | E119: 1. Sign in to Sage Intacct application 2. Navigate to Applications > Lending Management > Loan account 3. Click '+Create'. 4. Enter valid values in all required fields. 5. Click 'Save'. | F119: - A success toast/confirmation message appears. - The page redirects to confirm the loan account was saved. | G119: IADSSL-101 | H119: No | I119: Not Executed | J119: Source section: B. Create page (IDs: TC-LA-001–058)
A120: LA-105 | B120: Validation errors show banner + inline | C120: Refer to Common Preconditions above. | D120: Account category: QA Loan Category Account number: LA-QA-001 Account name: Client QA Loan 001 Customer: 1--Power Aerospace Materials Required fields (target): (leave blank) | E120: 1. Sign in to Sage Intacct application 2. Navigate to Applications > Lending Management > Loan account 3. Click '+Create'. 4. Leave one or more required fields blank. 5. Click 'Save'. | F120: - A validation error banner appears at the top of the page. - Inline error messages appear next to each invalid field. | G120: IADSSL-101 | H120: No | I120: Not Executed | J120: Source section: B. Create page (IDs: TC-LA-001–058)
A121: LA-106 | B121: Create a new loan with an amount above zero and check the AP bill | C121: Refer to Common Preconditions above. The loan is not marked as an existing loan. | D121: Loan account: LA-QA-ART-001 Origination amount: 10000.00 Existing loan: No | E121: 1. Sign in to Sage Intacct application 2. Navigate to Applications > Lending Management > Loan account 3. Click '+Create'. 4. Enter Account number LA-QA-ART-001 and Origination amount 10000.00, leaving 'Existing loan' unchecked, then complete remaining required fields. 5. Click 'Save', then open the loan's transaction history and related AP bill. | F121: - An origination transaction and its entries are created. - One AP bill for 10000.00 is created and linked to the loan. | G121: IADSSL-101 | H121: No | I121: Not Executed
A122: LA-107 | B122: Confirm a new loan origination does not create a separate loan journal entry | C122: Refer to Common Preconditions above. The loan is not marked as an existing loan. | D122: Loan account: LA-QA-ART-002 Origination amount: 8000.00 Existing loan: No | E122: 1. Sign in to Sage Intacct application 2. Navigate to Applications > Lending Management > Loan account 3. Click '+Create'. 4. Enter Account number LA-QA-ART-002 and Origination amount 8000.00, leaving 'Existing loan' unchecked, then complete remaining required fields. 5. Click 'Save', then review the AP bill and check for any separate loan-side journal entry. | F122: - The AP bill carries the full accounting impact. - No separate loan-side journal entry is created for the origination. | G122: IADSSL-101 | H122: No | I122: Not Executed
A123: LA-108 | B123: Create a new loan with zero amount and check related records | C123: Refer to Common Preconditions above. The loan is not marked as an existing loan. | D123: Loan account: LA-QA-ART-003 Origination amount: 0.00 Existing loan: No | E123: 1. Sign in to Sage Intacct application 2. Navigate to Applications > Lending Management > Loan account 3. Click '+Create'. 4. Enter Account number LA-QA-ART-003 and Origination amount 0.00, leaving 'Existing loan' unchecked, then complete remaining required fields. 5. Click 'Save', then review the loan's transaction history and AP bills. | F123: - The loan account is created. - No origination transaction, origination entry, or AP bill is created. | G123: IADSSL-101 | H123: No | I123: Not Executed
A124: LA-109 | B124: Create a new non-revolving loan with an amount above zero and check the invoice | C124: Refer to Common Preconditions above. A valid non-revolving loan type is available and the loan is not marked as existing. | D124: Loan account: LA-QA-ART-004 Loan type: Non-revolving Origination amount: 12000.00 | E124: 1. Sign in to Sage Intacct application 2. Navigate to Applications > Lending Management > Loan account 3. Click '+Create'. 4. Enter Account number LA-QA-ART-004, select Loan type 'Non-revolving', and enter Origination amount 12000.00, then complete remaining required fields. 5. Click 'Save', then review the AP bill and the loan invoice. | F124: - The origination transaction and AP bill are created. - The loan invoicing service creates the related loan invoice. | G124: IADSSL-101 | H124: No | I124: Not Executed
A125: LA-110 | B125: Non-revolving account shows Overview/Transaction history tabs | C125: Refer to Common Preconditions above. | D125: Account category: QA Loan Category Account number: LA-QA-001 Account name: Client QA Loan 001 Customer: 1--Power Aerospace Materials Loan type: QA Non-Revolving Interest rate: 5.0000% Origination amount: 10000.00 Origination date: 2026-08-01 | E125: 1. Sign in to Sage Intacct application 2. Navigate to Applications > Lending Management > Loan account 3. Open an existing non-revolving loan account's View page. | F125: - The Overview, Amortization schedule, and Transaction history tabs are all present on a Non-revolving loan account's View page. - The Amortization schedule tab loads and displays the full payment schedule grid. | G125: IADSSL-101 | H125: No | I125: Not Executed | J125: Source section: B. Create page (IDs: TC-LA-001–058)
A126: LA-111 | B126: Reject blank Loan type on Create | C126: Refer to Common Preconditions above. | D126: Account category: QA Loan Category Account number: LA-QA-002 Account name: Client QA Loan 002 Customer: 1--Power Aerospace Materials Vendor: VND-RT-0765--Vendor-Root-0765 Amount: 10000.00 Loan type: (leave blank) | E126: 1. Sign in to Sage Intacct application 2. Navigate to Applications > Lending Management > Loan account 3. Click the '+Create' button to open the Create loan account page 4. Fill all other required fields but leave Loan type blank 5. Click 'Save' 6. Observe the validation banner and per-field error line. | F126: - A validation error banner appears reading "Correct the fields below and try again." - A per-field line reads "Loan type: Field is required." - The record is not saved. | G126: IADSSL-101 | H126: TBD | I126: Not Executed
A127: LA-112 | B127: Reject blank Loan origination date on Create | C127: Refer to Common Preconditions above. | D127: Account category: QA Loan Category Account number: LA-QA-003 Account name: Client QA Loan 003 Customer: 1--Power Aerospace Materials Vendor: VND-RT-0765--Vendor-Root-0765 Amount: 10000.00 Loan origination date: (leave blank) | E127: 1. Sign in to Sage Intacct application 2. Navigate to Applications > Lending Management > Loan account 3. Click the '+Create' button to open the Create loan account page 4. Clear the Loan origination date field (it defaults to today's date) 5. Fill all other required fields 6. Click 'Save' 7. Observe the validation banner and per-field error line. | F127: - A validation error banner appears reading "Correct the fields below and try again." - A per-field line reads "Loan origination date: Field is required." - The record is not saved. | G127: IADSSL-101 | H127: TBD | I127: Not Executed
A128: LA-113 | B128: Reject duplicate Account number on Create | C128: Refer to Common Preconditions above. | D128: Account category: a category without a document sequence assigned Account number: an Account number that already exists on another loan account | E128: 1. Sign in to Sage Intacct application 2. Navigate to Applications > Lending Management > Loan account 3. Click the '+Create' button to open the Create loan account page 4. Select an Account category that does not have a document sequence assigned 5. Type an Account number that already exists on another loan account 6. Fill all other required fields 7. Click 'Save' 8. Observe the validation message and whether the record saves. | F128: - A duplicate-key validation error appears. - The record is not saved. | G128: IADSSL-101 | H128: TBD | I128: Not Executed | J128: [ADDED - confirm exact wording]
A129: LA-114 | B129: Field labels IA.LOAN_ACCOUNT_AMORTIZED_AMOUNT and IA.LOAN_ACCOUNT_DISBURSEMENT_AMOUNT show untranslated i18n keys | C129: Refer to Common Preconditions above. | D129: Loan type: any Non-revolving loan type Amount: 10000.00 | E129: 1. Sign in to Sage Intacct application 2. Navigate to Applications > Lending Management > Loan account 3. Click the '+Create' button to open the Create loan account page 4. Select any Non-revolving Loan type 5. Observe the field labels shown immediately after the Amount field. | F129: - [DEFECT] Both field labels display the raw, untranslated i18n key literals "IA.LOAN_ACCOUNT_AMORTIZED_AMOUNT" and "IA.LOAN_ACCOUNT_DISBURSEMENT_AMOUNT" instead of clean localized labels such as 'Amortized amount' and 'Disbursement amount'. | G129: IADSSL-101 | H129: TBD | I129: Not Executed | J129: [ADDED - verified live 2026-08-31]
A130: LA-115 | B130: Dimensions configured on the Loan Account auto-populate on the AP Bill generated for a fee/expense transaction | C130: Refer to Common Preconditions above. | D130: Department: Sales Location: HQ Class: Consulting Project: QA Project 001 (all configured in the Dimensions section on the Loan Account) Loan account: LA-QA-001 (non-revolving, amortized, with a fee) | E130: 1. Sign in to Sage Intacct application 2. Navigate to Applications > Lending Management > Loan account 3. Click '+Create', fill Account category, Account number, Account name, and set Department, Location, Class, and Project in the Dimensions section, complete a fee configuration in the Fees section 4. Click Save 5. Navigate to the resulting AP Bill in Accounts Payable and inspect its dimension fields. | F130: - The generated AP Bill's line item(s) carry the same Department, Location, Class, and Project dimension values configured on the Loan Account, with no manual entry required. | G130: IADSSL-101 | H130: TBD | I130: Not Executed | J130: [ADDED - dimension propagation verification]
A131: LA-116 | B131: Dimensions configured on the Loan Account auto-populate on the Order Entry invoice/transaction generated for loan invoicing | C131: Refer to Common Preconditions above. | D131: Department: Sales Location: HQ Class: Consulting Project: QA Project 001 (all configured in the Dimensions section on the Loan Account) Loan account: LA-QA-001 | E131: 1. Sign in to Sage Intacct application 2. Navigate to Applications > Lending Management > Loan account 3. Click '+Create', fill Account category, Account number, Account name, and set Department, Location, Class, and Project in the Dimensions section, complete all other required fields 4. Click Save 5. Navigate to the resulting Order Entry transaction (the transaction definition configured for loan invoicing) and inspect its dimension fields. | F131: - The generated Order Entry transaction's line item carries the same Department, Location, Class, and Project dimension values configured on the Loan Account, with no manual entry required. | G131: IADSSL-101 | H131: TBD | I131: Not Executed | J131: [ADDED - dimension propagation verification]
A132: LA-117 | B132: Dimensions configured on the Loan Account auto-populate on the AR invoice generated from loan invoicing | C132: Refer to Common Preconditions above. | D132: Department: Sales Location: HQ Class: Consulting Project: QA Project 001 (all configured in the Dimensions section on the Loan Account) Loan account: LA-QA-001 | E132: 1. Sign in to Sage Intacct application 2. Navigate to Applications > Lending Management > Loan account 3. Click '+Create', fill Account category, Account number, Account name, and set Department, Location, Class, and Project in the Dimensions section, complete all other required fields 4. Click Save, then generate an invoice for this loan account 5. Navigate to the resulting AR invoice in Accounts Receivable and inspect its dimension fields. | F132: - The generated AR invoice's line item carries the same Department, Location, Class, and Project dimension values configured on the Loan Account, with no manual entry required. | G132: IADSSL-101 | H132: TBD | I132: Not Executed | J132: [ADDED - dimension propagation verification]
A133: LA-118 | B133: Dimensions configured on the Loan Account auto-populate on the GL journal entry generated for a Loan Adjustment | C133: Refer to Common Preconditions above. | D133: Department: Sales Location: HQ Class: Consulting Project: QA Project 001 (all configured in the Dimensions section on the Loan Account) Loan account: LA-QA-001 Adjustment amount: 50.00 | E133: 1. Sign in to Sage Intacct application 2. Navigate to Applications > Lending Management > Loan account 3. Create (or use an existing) loan account with Department, Location, Class, and Project set in the Dimensions section 4. Navigate to Applications > Lending Management > Loan adjustment and create an adjustment against this loan account 5. Navigate to the General Ledger and inspect the journal entry generated for this loan adjustment. | F133: - The generated GL journal entry's line carries the same Department, Location, Class, and Project dimension values configured on the source Loan Account, with no manual entry required. | G133: IADSSL-101 | H133: TBD | I133: Not Executed | J133: [ADDED - dimension propagation verification]
A134: EDIT (40 test cases)
A135: LA-119 | B135: Edit navigates to Edit page | C135: Refer to Common Preconditions above. | D135: Account category: QA Loan Category Account number: LA-QA-001 Account name: Client QA Loan 001 Customer: 1--Power Aerospace Materials Loan type: QA Non-Revolving Interest rate: 5.0000% Origination amount: 10000.00 Origination date: 2026-08-01 | E135: 1. Sign in to Sage Intacct application 2. Navigate to Applications > Lending Management > Loan account 3. Open an existing loan account's View page and click 'Edit'. | F135: - The page navigates to the Edit page with the Edit heading clearly visible. | G135: IADSSL-101 | H135: No | I135: Not Executed | J135: Source section: C. View page (IDs: TC-LA-071–088)
A136: LA-120 | B136: [KNOWN DEFECT] Edit heading exposes object path | C136: Refer to Common Preconditions above. | D136: Account category: QA Loan Category Account number: LA-QA-001 Account name: Client QA Loan 001 Customer: 1--Power Aerospace Materials Loan type: QA Non-Revolving Interest rate: 5.0000% Origination amount: 10000.00 Origination date: 2026-08-01 | E136: 1. Sign in to Sage Intacct application 2. Navigate to Applications > Lending Management > Loan account 3. Open an existing loan account's View page and click 'Edit'. 4. Inspect the page heading (H1) text. | F136: - [DEFECT] The H1 heading shows a raw, untranslated i18n key literal in the format "IA.SNL_EDIT_LOAN_ACCOUNT: <account number>" (e.g. "IA.SNL_EDIT_LOAN_ACCOUNT: Rec#093#inv") instead of a clean localized title such as 'Edit loan'. | G136: IADSSL-101 | H136: No | I136: Not Executed | J136: Source section: E. Edit page (IDs: TC-LA-098–130)
A137: LA-121 | B137: Edit page heading reads 'Edit loan' | C137: Refer to Common Preconditions above. A loan account record exists and its Edit page is reached via the Edit action. | D137: Account category: Term Loan Account name: Test Loan Edit Title Customer: Existing active customer Vendor: Existing active vendor | E137: 1. Sign in to Sage Intacct application 2. Navigate to Applications > Lending Management > Loan account 3. Open an existing loan account and click 'Edit'. 4. Inspect the page heading (H1) text. | F137: - The Edit page heading (H1) reads a clean, correctly localized title such as 'Edit loan' - not a raw object/path string (e.g. not 'loan-management/loan-account') as seen in the related known defect (LA-120). - The Edit page heading is consistent with the naming convention used by the List ('Loans'), Create ('Create loan'), and View ('Loan: <id>') page titles on this sheet. | G137: IADSSL-101 | H137: No | I137: Not Executed
A138: LA-122 | B138: Loan information section present on Edit | C138: Refer to Common Preconditions above. | D138: Account category: QA Loan Category Account number: LA-QA-001 Account name: Client QA Loan 001 Customer: 1--Power Aerospace Materials Loan type: QA Non-Revolving Interest rate: 5.0000% Origination amount: 10000.00 Origination date: 2026-08-01 | E138: 1. Sign in to Sage Intacct application 2. Navigate to Applications > Lending Management > Loan account 3. Open an existing loan account's View page and click 'Edit'. | F138: - The Loan information section is visible on the Edit page. | G138: IADSSL-101 | H138: No | I138: Not Executed | J138: Source section: E. Edit page (IDs: TC-LA-098–130)
A139: LA-123 | B139: Account category read-only, drillable | C139: Refer to Common Preconditions above. | D139: Account category: QA Loan Category Account number: LA-QA-001 Account name: Client QA Loan 001 Customer: 1--Power Aerospace Materials Loan type: QA Non-Revolving Interest rate: 5.0000% Origination amount: 10000.00 Origination date: 2026-08-01 | E139: 1. Sign in to Sage Intacct application 2. Navigate to Applications > Lending Management > Loan account 3. Open an existing loan account's Edit page. 4. Locate the Account category field. | F139: - The Account category field displays as a drillable link rather than an editable combobox/input. | G139: IADSSL-101 | H139: No | I139: Not Executed | J139: Source section: E. Edit page (IDs: TC-LA-098–130)
A140: LA-124 | B140: Account number read-only | C140: Refer to Common Preconditions above. | D140: Account category: QA Loan Category Account number: LA-QA-001 Account name: Client QA Loan 001 Customer: 1--Power Aerospace Materials Loan type: QA Non-Revolving Interest rate: 5.0000% Origination amount: 10000.00 Origination date: 2026-08-01 | E140: 1. Sign in to Sage Intacct application 2. Navigate to Applications > Lending Management > Loan account 3. Open an existing loan account's Edit page. 4. Locate the Account number field. | F140: - The Account number field is not editable and has no <input> element present. | G140: IADSSL-101 | H140: No | I140: Not Executed | J140: Source section: E. Edit page (IDs: TC-LA-098–130)
...

Sheet LME Configuration
A1: Prepared By | B1: Subah Tasnim Shiary | D1: Total Test Cases | E1: =COUNTA('LME Configuration'!$B$14:$B$2000)
A2: Executed By | B2: Subah Tasnim Shiary | D2: Passed | E2: =COUNTIF('LME Configuration'!$I$14:$I$2000,"Passed")
A3: Updated On | B3: 46262 | D3: Failed | E3: =COUNTIF('LME Configuration'!$I$14:$I$2000,"Failed")
A4: Time est | B4: Initial testing: | D4: Untested | E4: =COUNTIF('LME Configuration'!$I$14:$I$2000,"Not Executed")
B5: Bugfix testing: | D5: To be tested | E5: =COUNTIF('LME Configuration'!$I$14:$I$2000,"In Progress")+COUNTIF('LME Configuration'!$I$14:$I$2000,"Blocked")
A6: common preconditions
A7: navigation
A8: Lending - Configuration
A9: Common Preconditions | C9: 1. User is signed in to Sage Intacct. 2. The correct Lending Management or Depository Management entity is selected. 3. The module is enabled for the company. 4. The user has the permission required for the scenario. 5. Required master/configuration records are active and available.
A11: Navigation: Applications > Lending Management > Configuration | Client baseline | 32 test cases | Updated 2026-08-31
A13: Test Case ID | B13: Test Scenario | C13: Preconditions | D13: Test Data | E13: Test Steps | F13: Expected Result | G13: Requirement/Jira Reference | H13: IS Automated | I13: Status | J13: Comments
A14: Initial setup (Create configuration) (10 test cases)
A15: CFG-001 | B15: Confirm the page title/heading on the initial Lending Management Configuration setup page | C15: Refer to Common Preconditions above. The Lending Management module has not yet been configured (no configuration record exists). | D15: Navigation: Applications > Lending Management > Configuration (no configuration saved yet) | E15: 1. Sign in to Sage Intacct application. 2. Navigate to Applications > Lending Management > Configuration before any configuration has been saved. 3. Observe the page title/heading. | F15: - The page title/heading clearly identifies the page as the Lending Management configuration setup page, consistent with the module/feature naming used elsewhere in Lending Management (e.g. 'Lending Management Configuration'). - The page title/heading is not blank, generic, or mismatched. | G15: IADSSL-101 | H15: No | I15: Not Executed
A16: CFG-002 | B16: Confirm the Lending Management configuration setup is required when the module is first subscribed | C16: Refer to Common Preconditions above. | D16: Company: newly subscribed to Lending Management Configuration record: none exists yet | E16: 1. Sign in to Sage Intacct application. 2. Navigate to Applications > Lending Management > Configuration for a company where the module was just subscribed. 3. Observe the page presented before any configuration has been saved. | F16: - The Lending Management configuration page requires the user to complete initial setup (Journals, GL accounts, Banking, Enable functionality, and Interest/invoice/statement generation settings) before Lending Management features can be used. | G16: IADSSL-101 | H16: No | I16: Not Executed | J16: Setup is a one-time step performed when a new company is created and Lending Management is subscribed.
A17: CFG-003 | B17: Confirm the Journals section accepts only active journal values on initial Create | C17: Refer to Common Preconditions above. | D17: Write-offs journal: LOAN--Loan Journal Adjustments journal: LOAN--Loan Journal Loan fees journal: LOAN--Loan Journal Inactive journal candidate: INACTIVE-JRNL | E17: 1. Sign in to Sage Intacct application. 2. Navigate to Applications > Lending Management > Configuration. 3. Open the initial Create configuration form. 4. Click the Write-offs journal dropdown and review the listed options; repeat for the Adjustments journal and Loan fees journal dropdowns. | F17: - The Write-offs journal dropdown lists only active journals. - The Adjustments journal dropdown lists only active journals. - The Loan fees journal dropdown lists only active journals. - No inactive journal (e.g. INACTIVE-JRNL) appears in any of the three dropdowns. | G17: IADSSL-101 | H17: No | I17: Not Executed
A18: CFG-004 | B18: Confirm each GL accounts field accepts only active GL accounts on initial Create | C18: Refer to Common Preconditions above. | D18: GL account fields checked: Loans receivable, Interest on loans receivable, Allowance for loan loss: Principal, Allowance for loan loss: Interest, Loan fees receivable, Miscellaneous interest income Inactive GL account candidate: 9999--Inactive Account | E18: 1. Sign in to Sage Intacct application. 2. Navigate to Applications > Lending Management > Configuration. 3. Open the initial Create configuration form. 4. Click each GL accounts dropdown in turn (Loans receivable, Interest on loans receivable, Allowance for loan loss: Principal, Allowance for loan loss: Interest, Loan fees receivable, Miscellaneous interest income) and review the listed options. | F18: - Every GL accounts dropdown (Loans receivable, Interest on loans receivable, Allowance for loan loss: Principal, Allowance for loan loss: Interest, Loan fees receivable, Miscellaneous interest income) lists only active GL accounts. - No inactive GL account (e.g. 9999--Inactive Account) appears in any of the six dropdowns. | G18: IADSSL-101 | H18: No | I18: Not Executed
A19: CFG-005 | B19: Confirm Default bank account dropdown accepts only active bank accounts on initial Create | C19: Refer to Common Preconditions above. | D19: Default bank account dropdown candidates: an active bank account, an inactive bank account | E19: 1. Sign in to Sage Intacct application. 2. Navigate to Applications > Lending Management > Configuration. 3. Open the initial Create configuration form and go to the Banking section. 4. Click the Default bank account dropdown and review the listed options. | F19: - The Default bank account dropdown lists only active bank accounts. - No inactive bank account appears in the dropdown. | G19: IADSSL-101 | H19: No | I19: Not Executed
A20: CFG-006 | B20: Confirm mandatory fields are enforced when saving the initial configuration | C20: Refer to Common Preconditions above. | D20: Loans receivable GL account: (leave blank) All other required Journals/GL accounts fields: (leave blank) | E20: 1. Sign in to Sage Intacct application. 2. Navigate to Applications > Lending Management > Configuration. 3. Open the initial Create configuration form. 4. Leave the required Journals and GL accounts fields (e.g. Loans receivable) blank. 5. Click the 'Save' button and observe the result. | F20: - A validation error appears identifying the missing required field(s) (e.g. Loans receivable is required). - The configuration is not saved until all required fields are provided. | G20: IADSSL-101 | H20: No | I20: Not Executed
A21: CFG-007 | B21: Confirm 'Enable negative interest balances' is unchecked by default and can be enabled on initial Create | C21: Refer to Common Preconditions above. | D21: Enable negative interest balances: unchecked (default), then checked | E21: 1. Sign in to Sage Intacct application. 2. Navigate to Applications > Lending Management > Configuration. 3. Open the initial Create configuration form and go to the Enable functionality section. 4. Observe the default state of the 'Enable negative interest balances' checkbox. 5. Check the 'Enable negative interest balances' checkbox and click the 'Save' button. 6. Open the View page and observe the state of the checkbox. | F21: - The 'Enable negative interest balances' checkbox is unchecked by default. - Checking the checkbox and saving persists the setting as enabled on the View page. | G21: IADSSL-101 | H21: No | I21: Not Executed
A22: CFG-008 | B22: Select Method = Standard on initial Create and confirm Presentment method and Recurring schedule fields appear | C22: Refer to Common Preconditions above. | D22: Method: Standard | E22: 1. Sign in to Sage Intacct application. 2. Navigate to Applications > Lending Management > Configuration. 3. Open the initial Create configuration form and go to the Interest, invoice, and statement generation settings section. 4. Select Method = Standard and observe the form. | F22: - Selecting Method = Standard reveals the Presentment method field. - Selecting Method = Standard reveals the Recurring schedule fields (Loan invoice repeats / Loan statement repeats). - These revealed fields are consistent with Standard automation configuration. | G22: IADSSL-101 | H22: No | I22: Not Executed
A23: CFG-009 | B23: Select Method = Month-end on initial Create and confirm First statement date field appears and is required | C23: Refer to Common Preconditions above. | D23: Method: Month-end First statement date: (leave blank) | E23: 1. Sign in to Sage Intacct application. 2. Navigate to Applications > Lending Management > Configuration. 3. Open the initial Create configuration form and go to the Interest, invoice, and statement generation settings section. 4. Select Method = Month-end and observe the form for the First statement date field. 5. Leave First statement date blank and click the 'Save' button. 6. Observe the result. | F23: - Selecting Method = Month-end reveals the First statement date field. - The First statement date field is marked as required. - Saving without a First statement date is blocked with a validation error stating First statement date is required. | G23: IADSSL-101 | H23: No | I23: Not Executed
A24: CFG-010 | B24: Save the initial Lending Management configuration with valid values for every field | C24: Refer to Common Preconditions above. | D24: Write-offs journal: LOAN--Loan Journal Adjustments journal: LOAN--Loan Journal Loan fees journal: LOAN--Loan Journal Loans receivable: 4000--Sales Interest on loans receivable: 7503--Loan Interest Allowance for loan loss: Principal: 1905--Employee Loans Allowance for loan loss: Interest: 7513--Loan Interest Expense Loan fees receivable: 6104--Directors Sitting Fees Miscellaneous interest income: 7002--Miscellaneous Interest Income Default bank account: (blank) Method: Month-end First statement date: 11/01/2024 | E24: 1. Sign in to Sage Intacct application. 2. Navigate to Applications > Lending Management > Configuration. 3. Open the initial Create configuration form. 4. Enter the Write-offs, Adjustments, and Loan fees journals, all six GL accounts, Method = Month-end and First statement date = 11/01/2024 as listed in Test Data. 5. Click the 'Save' button and observe the result. | F24: - The configuration saves successfully. - The page redirects to the View page. - The View page displays all saved values under Journals, GL accounts, Banking, Enable functionality, and Interest/invoice/statement generation settings. | G24: IADSSL-101 | H24: No | I24: Not Executed
A25: View and Edit configuration (11 test cases)
A26: CFG-011 | B26: Confirm the page title/heading on the Lending Management Configuration View and Edit pages | C26: Refer to Common Preconditions above. A Lending Management configuration record has already been saved. | D26: Navigation: Applications > Lending Management > Configuration (saved configuration record exists) | E26: 1. Sign in to Sage Intacct application. 2. Navigate to Applications > Lending Management > Configuration. 3. Open the saved configuration in View mode and observe the page title/heading. 4. Click 'Edit' and observe the page title/heading in Edit mode. | F26: - The View page displays a title/heading that clearly identifies the page as the Lending Management configuration, consistent with the naming used on the initial setup/Create page. - The Edit page displays a title/heading that clearly identifies the page as the Lending Management configuration, consistent with the naming used on the initial setup/Create page. - The heading is not blank, generic, or mismatched between View and Edit. | G26: IADSSL-101 | H26: No | I26: Not Executed
A27: CFG-012 | B27: Confirm the View page displays all sections with the saved configuration values | C27: Refer to Common Preconditions above. The Lending Management configuration has already been saved. | D27: Write-offs journal: LOAN--Loan Journal Loans receivable: 4000--Sales Method: Month-end First statement date: 11/01/2024 | E27: 1. Sign in to Sage Intacct application. 2. Navigate to Applications > Lending Management > Configuration. 3. Open the Lending Management configuration View page. 4. Expand and inspect the Journals, GL accounts, Banking, Enable functionality, and Interest/invoice/statement generation settings sections. | F27: - All sections (Journals, GL accounts, Banking, Enable functionality, and Interest/invoice/statement generation settings) are present and collapsible/expandable. - Each section displays the previously saved values: Write-offs/Adjustments/Loan fees journals, all six GL accounts, Default bank account, Enable negative interest balances, Method, and the recurrence/presentment or First statement date fields matching the saved Method. | G27: IADSSL-101 | H27: No | I27: Not Executed
A28: CFG-013 | B28: Confirm all reference fields on the View page are drillable links | C28: Refer to Common Preconditions above. | D28: Write-offs journal: LOAN--Loan Journal Loans receivable: 4000--Sales | E28: 1. Sign in to Sage Intacct application. 2. Navigate to Applications > Lending Management > Configuration. 3. Open the View page for the saved configuration. 4. Click the Write-offs journal link. 5. Return to the View page and click the Loans receivable GL account link. | F28: - Each reference field renders as a green drillable link. - Clicking the Write-offs journal link navigates to the corresponding journal record. - Clicking the Loans receivable GL account link navigates to the corresponding GL account record. | G28: IADSSL-101 | H28: No | I28: Not Executed
A29: CFG-014 | B29: Edit and save Journals and GL accounts fields, confirming only active values remain selectable | C29: Refer to Common Preconditions above. The configuration has already been saved. | D29: Loans receivable: change from 4000--Sales to a different active GL account Inactive GL account candidate: 9999--Inactive Account | E29: 1. Sign in to Sage Intacct application. 2. Navigate to Applications > Lending Management > Configuration. 3. Open the saved configuration's Edit page. 4. Change the Loans receivable GL account to a different active GL account. 5. Open another GL account dropdown and attempt to select the inactive GL account (9999--Inactive Account). 6. Click the 'Save' button for the valid change and observe the result. | F29: - The valid active GL account change saves successfully. - The inactive GL account (9999--Inactive Account) is not selectable/is excluded from the dropdown during edit. - This behavior is consistent with Create-time behavior. | G29: IADSSL-101 | H29: No | I29: Not Executed
A30: CFG-015 | B30: Confirm Default bank account dropdown excludes inactive bank accounts on Edit | C30: Refer to Common Preconditions above. The configuration has already been saved. | D30: Default bank account dropdown candidates: an active bank account, an inactive bank account | E30: 1. Sign in to Sage Intacct application. 2. Navigate to Applications > Lending Management > Configuration. 3. Open the saved configuration's Edit page and go to the Banking section. 4. Click the Default bank account dropdown and review the listed options. | F30: - The Default bank account dropdown lists only active bank accounts on Edit. - No inactive bank account appears in the dropdown. - This behavior is consistent with Create-time behavior. | G30: IADSSL-101 | H30: TBD | I30: Not Executed | J30: [ADDED]
A31: CFG-016 | B31: Edit and save the Default bank account and Enable negative interest balances settings | C31: Refer to Common Preconditions above. The configuration has already been saved. | D31: Default bank account: change to a different active bank account Enable negative interest balances: toggle from unchecked to checked | E31: 1. Sign in to Sage Intacct application. 2. Navigate to Applications > Lending Management > Configuration. 3. Open the saved configuration's Edit page. 4. Change the Default bank account to a different active bank account and check 'Enable negative interest balances'. 5. Click the 'Save' button and observe the View page. | F31: - The Default bank account change saves successfully and is reflected on the View page after saving. - The 'Enable negative interest balances' change saves successfully and is reflected on the View page after saving. | G31: IADSSL-101 | H31: No | I31: Not Executed
A32: CFG-017 | B32: Confirm the Method field is displayed as read-only (not editable) once the configuration has been saved | C32: Refer to Common Preconditions above. The Lending Management configuration has already been saved with a chosen Method. | D32: Method: Month-end (already saved) | E32: 1. Sign in to Sage Intacct application. 2. Navigate to Applications > Lending Management > Configuration. 3. Open the saved configuration's Edit page. 4. Inspect the Method radio group (Standard / Month-end). | F32: - The Method field is displayed as read-only / disabled on the Edit form. - Its previously saved value cannot be changed to the other option. | G32: IADSSL-101 | H32: No | I32: Not Executed | J32: Method is a one-time choice locked at initial setup, matching the Loan Type Automation Method lock.
A33: CFG-018 | B33: Confirm attempting to change Method via a direct/bypassed request is rejected | C33: Refer to Common Preconditions above. The configuration has already been saved with Method = Month-end. | D33: Saved Method: Month-end Attempted Method change: Standard (via direct/bypassed API request) | E33: 1. Sign in to Sage Intacct application. 2. Navigate to Applications > Lending Management > Configuration. 3. Confirm the configuration is saved with Method = Month-end. 4. Submit a configuration update via a direct request (bypassing the disabled UI control) that attempts to change Method from Month-end to Standard. 5. Observe the result. | F33: - The update is rejected with a validation error stating the Method field cannot be changed once set. - The saved Method value remains unchanged. | G33: IADSSL-101 | H33: No | I33: Not Executed
A34: CFG-019 | B34: Confirm editing First statement date (Month-end) or Presentment method / Recurring schedule (Standard) is possible without affecting the locked Method | C34: Refer to Common Preconditions above. The configuration has already been saved with a chosen Method. | D34: Method: Month-end (locked) First statement date: change from 11/01/2024 to 12/01/2024 | E34: 1. Sign in to Sage Intacct application. 2. Navigate to Applications > Lending Management > Configuration. 3. Open the saved configuration's Edit page. 4. Change First statement date from 11/01/2024 to 12/01/2024 (or, for Standard, change the Presentment method / Recurring schedule fields). 5. Click the 'Save' button and observe the result. | F34: - The date/recurrence-related field updates successfully. - The Method field remains locked to its original saved value. | G34: IADSSL-101 | H34: No | I34: Not Executed
A35: CFG-020 | B35: Confirm mandatory fields remain enforced when editing the saved configuration | C35: Refer to Common Preconditions above. The configuration has already been saved. | D35: Loans receivable: cleared/left blank | E35: 1. Sign in to Sage Intacct application. 2. Navigate to Applications > Lending Management > Configuration. 3. Open the saved configuration's Edit page. 4. Clear the Loans receivable field. 5. Click the 'Save' button and observe the result. | F35: - A validation error appears stating the required field cannot be left blank. - The change is not saved. - This is consistent with Create-time validation. | G35: IADSSL-101 | H35: No | I35: Not Executed
A36: CFG-021 | B36: Audit trail correctly records creation and a Default Journal change with the exact field, before, and after values | C36: Refer to Common Preconditions above. | D36: Lending Management configuration: newly created, then Default Journal changed from 'GJ-Old' to 'GJ-New' | E36: 1. Sign in to Sage Intacct application. 2. Navigate to Applications > Lending Management > Configuration. 3. Create a new Lending Management configuration record, then open it and update the Default Journal field from 'GJ-Old' to 'GJ-New' and save. 4. Open the record's View page, click the 3-dot (More actions) menu, and select 'View audit trail'. 5. Inspect the audit trail table's Date, Action, Completed by, Source, Field, Before, and After columns. | F36: - The audit trail shows a 'Create' row as the oldest entry, with Source = User interface and After = Created. - The audit trail shows a separate 'Modify' row for the Default Journal change, with Field = 'Default Journal', Before = 'GJ-Old', and After = 'GJ-New'. - The 'Modify' row shows the correct Completed by user and a valid Date/time. - Unrelated fields do not appear as changed rows. | G36: IADSSL-101 | H36: TBD | I36: Not Executed | J36: [ADDED - audit trail content verification]
A37: Automation method (Loan Type field) (11 test cases)
A38: CFG-022 | B38: Create a Loan Type with Standard automation | C38: Refer to Common Preconditions above. | D38: Name: QA Standard Automation Loan Type Automation method: Standard First statement date: N/A (not applicable to Standard) | E38: 1. Sign in to Sage Intacct application. 2. Navigate to Applications > Lending Management > Loan type. 3. Click '+Create'. 4. Enter 'QA Standard Automation Loan Type' in the Name field and select Automation method = Standard. 5. Complete the remaining required fields and click the 'Save' button. 6. Observe the result. | F38: - The loan type is created successfully. - The Automation method is saved as Standard. | G38: IADSSL-101 | H38: No | I38: Not Executed
A39: CFG-023 | B39: Create a Loan Type with Month end automation | C39: Refer to Common Preconditions above. | D39: Name: QA Month End Automation Loan Type Automation method: Month end First statement date: 2026-09-01 | E39: 1. Sign in to Sage Intacct application. 2. Navigate to Applications > Lending Management > Loan type. 3. Click '+Create'. 4. Enter 'QA Month End Automation Loan Type' in the Name field and select Automation method = Month end. 5. Enter First statement date = 2026-09-01, complete the remaining required fields, and click the 'Save' button. 6. Observe the result. | F39: - The loan type is created successfully. - The Automation method is saved as Month end. - The First statement date is saved as entered (2026-09-01). | G39: IADSSL-101 | H39: No | I39: Not Executed
A40: CFG-024 | B40: Hide First statement date when Standard automation is selected | C40: Refer to Common Preconditions above. | D40: Automation method: Standard | E40: 1. Sign in to Sage Intacct application. 2. Navigate to Applications > Lending Management > Loan type. 3. Click '+Create'. 4. Select Automation method = Standard and observe the form. | F40: - The First statement date field is not displayed on the form when Standard automation is selected. | G40: IADSSL-101 | H40: No | I40: Not Executed
A41: CFG-025 | B41: Show First statement date when Month end automation is selected | C41: Refer to Common Preconditions above. | D41: Automation method: Month end | E41: 1. Sign in to Sage Intacct application. 2. Navigate to Applications > Lending Management > Loan type. 3. Click '+Create'. 4. Select Automation method = Month end and observe the form. | F41: - The First statement date field is displayed on the form when Month end automation is selected. | G41: IADSSL-101 | H41: No | I41: Not Executed
A42: CFG-026 | B42: Require First statement date as mandatory when Month end automation is selected | C42: Refer to Common Preconditions above. | D42: Automation method: Month end First statement date field: displayed, expected to be marked required | E42: 1. Sign in to Sage Intacct application. 2. Navigate to Applications > Lending Management > Loan type. 3. Click '+Create'. 4. Select Automation method = Month end. 5. Inspect the First statement date field for a mandatory-field indicator (red asterisk). | F42: - The First statement date field is marked as mandatory (with a red asterisk indicator) when Month end automation is selected. | G42: IADSSL-101 | H42: No | I42: Not Executed
A43: CFG-027 | B43: Block saving a Loan Type when Month end automation is selected and First statement date is not provided | C43: Refer to Common Preconditions above. | D43: Automation method: Month end First statement date: (leave blank) | E43: 1. Sign in to Sage Intacct application. 2. Navigate to Applications > Lending Management > Loan type. 3. Click '+Create'. 4. Select Automation method = Month end and leave the First statement date field blank. 5. Click the 'Save' button and observe the result. | F43: - The save is blocked. - A validation error appears stating First statement date is required when Month end automation is selected. | G43: IADSSL-101 | H43: No | I43: Not Executed
A44: CFG-028 | B44: Block clearing First statement date when editing an existing Month end automation Loan Type | C44: Refer to Common Preconditions above. An existing record is available to edit. | D44: Existing loan type: QA Month End Automation Loan Type Saved automation method: Month end First statement date: cleared/left blank | E44: 1. Sign in to Sage Intacct application. 2. Navigate to Applications > Lending Management > Loan type. 3. Open the existing loan type 'QA Month End Automation Loan Type' Edit page. 4. Clear the First statement date field. 5. Click the 'Save' button and observe the result. | F44: - The First statement date field remains displayed and mandatory. - A validation error appears stating First statement date is required. - The save is blocked. | G44: IADSSL-101 | H44: No | I44: Not Executed
A45: CFG-029 | B45: Prevent updating the Automation method after the Loan Type has been saved | C45: Refer to Common Preconditions above. An existing Loan Type has already been saved with a chosen Automation method. | D45: Existing loan type: QA Month End Automation Loan Type Saved automation method: Month end | E45: 1. Sign in to Sage Intacct application. 2. Navigate to Applications > Lending Management > Loan type. 3. Open the existing loan type 'QA Month End Automation Loan Type' Edit page. 4. Inspect the Automation method field and attempt to change its value. | F45: - The Automation method field is not editable (read-only or disabled) once the loan type has been saved. - The value cannot be updated after initial creation. | G45: IADSSL-101 | H45: No | I45: Not Executed
A46: CFG-030 | B46: Reject setup references that do not resolve to active journals or GL accounts | C46: Refer to Common Preconditions above. | D46: Write-off journal: INVALID-KEY-999 Loan receivable account: inactive GL account (e.g. 9999--Inactive Account) | E46: 1. Sign in to Sage Intacct application. 2. Navigate to Applications > Lending Management > Configuration. 3. Submit a configuration setup via API using Write-off journal = 'INVALID-KEY-999' (a non-existent key) and Loan receivable account = an inactive GL account. 4. Observe the API response. | F46: - The API request is rejected with a not-found validation error for the invalid journal key ('INVALID-KEY-999'). - The API request is rejected with an inactive-record validation error for the inactive GL account. - No configuration is persisted. | G46: IADSSL-101 | H46: No | I46: Not Executed
A47: CFG-031 | B47: Standard automation uses recurring-job scheduling while legacy schedule/post endpoints return successful no-op | C47: Refer to Common Preconditions above. | D47: Automation method: Standard Schedule time: 02:00 | E47: 1. Sign in to Sage Intacct application. 2. Navigate to Applications > Lending Management > Configuration. 3. Confirm the configuration is saved with Automation method = Standard and Schedule time = 02:00. 4. Invoke the schedule-recurring-jobs endpoint/action, then invoke the legacy schedule-jobs and post-jobs endpoints/actions. 5. Observe the results of each invocation. | F47: - Recurring job groups are returned for Standard automation. - The legacy schedule-jobs endpoint completes successfully as a no-op without creating month-end runs. - The legacy post-jobs endpoint completes successfully as a no-op without creating month-end runs. | G47: IADSSL-101 | H47: No | I47: Not Executed
A48: CFG-032 | B48: Month-end and legacy-null automation retain statement-run processing | C48: Refer to Common Preconditions above. | D48: Automation method: Month end Scheduled date: 2026-09-01 | E48: 1. Sign in to Sage Intacct application. 2. Navigate to Applications > Lending Management > Configuration. 3. Confirm the configuration is saved with Automation method = Month end and Scheduled date = 2026-09-01. 4. Invoke the month-end schedule job, then the post job flow, for the prior period. 5. Observe the result. | F48: - A statement run for the prior period is created successfully through the month-end flow. - The statement run for the prior period is posted successfully through the month-end flow. | G48: IADSSL-101 | H48: No | I48: Not Executed

Sheet LME Loan Type
A1: Prepared By | B1: Subah Tasnim Shiary | D1: Total Test Cases | E1: =COUNTA('LME Loan Type'!$B$14:$B$2000)
A2: Executed By | B2: Subah Tasnim Shiary | D2: Passed | E2: =COUNTIF('LME Loan Type'!$I$14:$I$2000,"Passed")
A3: Updated On | B3: 46262 | D3: Failed | E3: =COUNTIF('LME Loan Type'!$I$14:$I$2000,"Failed")
A4: Time est | B4: Initial testing: | D4: Untested | E4: =COUNTIF('LME Loan Type'!$I$14:$I$2000,"Not Executed")
B5: Bugfix testing: | D5: To be tested | E5: =COUNTIF('LME Loan Type'!$I$14:$I$2000,"In Progress")+COUNTIF('LME Loan Type'!$I$14:$I$2000,"Blocked")
A6: common preconditions
A7: navigation
A8: Lending - Loan Type
A9: Common Preconditions | C9: 1. User is signed in to Sage Intacct. 2. The correct Lending Management or Depository Management entity is selected. 3. The module is enabled for the company. 4. The user has the permission required for the scenario. 5. Required master/configuration records are active and available.
A11: Navigation: Applications > Lending Management > Loan type | Client baseline | 149 test cases | Updated 2026-08-31
A13: Test Case ID | B13: Test Scenario | C13: Preconditions | D13: Test Data | E13: Test Steps | F13: Expected Result | G13: Requirement/Jira Reference | H13: IS Automated | I13: Status | J13: Comments
A14: LISTER (38 test cases)
A15: LT-001 | B15: Page title is 'Loan types' | C15: Refer to Common Preconditions above. | D15: Loan type record exists in the list (e.g. Name: QA Non-Revolving Loan Type). | E15: 1. Sign in to Sage Intacct application 2. Navigate to Applications > Lending Management > Loan type 3. Observe the page heading (H1). | F15: - The page heading (H1) reads "Loan types". | G15: IADSSL-101 | H15: No | I15: Not Executed | J15: Source section: A. List page (IDs: TC-LT-001–014)
A16: LT-002 | B16: Verify the lister grid displays the documented columns | C16: Refer to Common Preconditions above. | D16: N/A (default lister view, no configuration changes). | E16: 1. Sign in to Sage Intacct application 2. Navigate to Applications > Lending Management > Loan type 3. Observe the columns shown in the lister grid by default. | F16: - The lister grid displays the following columns by default: Loan type, Type, Interest calculation method, Interest type, Description. | G16: IADSSL-101 | H16: No | I16: Not Executed
A17: LT-003 | B17: Verify no column is sorted by default | C17: Refer to Common Preconditions above. | D17: N/A (default lister view, no sorting applied). | E17: 1. Sign in to Sage Intacct application 2. Navigate to Applications > Lending Management > Loan type 3. Observe the column headers for a sort indicator (arrow icon). | F17: - No column header shows a sort arrow/indicator by default. - The grid loads in its natural/unsorted order. | G17: IADSSL-101 | H17: No | I17: Not Executed
A18: LT-004 | B18: Verify Loan type is a drillable field that routes to the View loan type screen | C18: Refer to Common Preconditions above. | D18: An existing record with Loan type = QA Non-Revolving Loan Type. | E18: 1. Sign in to Sage Intacct application 2. Navigate to Applications > Lending Management > Loan type 3. Click the value in the Loan type column for an existing row. | F18: - Clicking the Loan type value navigates to the View loan type screen for that record. | G18: IADSSL-101 | H18: No | I18: Not Executed
A19: LT-005 | B19: Verify the '+Create' button is present and functional | C19: Refer to Common Preconditions above. | D19: N/A. | E19: 1. Sign in to Sage Intacct application 2. Navigate to Applications > Lending Management > Loan type 3. Locate the '+Create' button at the top right of the lister page and click it. | F19: - The '+Create' button is located at the top right of the lister page. - Clicking '+Create' redirects to the 'Create loan type' page. | G19: IADSSL-101 | H19: No | I19: Not Executed
A20: LT-006 | B20: Verify the lister view-selection dropdown functionality | C20: Refer to Common Preconditions above. | D20: N/A. | E20: 1. Sign in to Sage Intacct application 2. Navigate to Applications > Lending Management > Loan type 3. Click the view-selection dropdown at the top left of the lister and inspect its contents 4. Select a different view from the list. | F20: - The dropdown opens a list with a 'Search for view' field, a 'System views' section (including 'All'), and a 'User views' section. - Selecting any view updates the lister to reflect that view. | G20: IADSSL-101 | H20: No | I20: Not Executed
A21: LT-007 | B21: Verify the Split view / List view toggle | C21: Refer to Common Preconditions above. | D21: N/A. | E21: 1. Sign in to Sage Intacct application 2. Navigate to Applications > Lending Management > Loan type 3. Click the Split view icon 4. Click the List view icon. | F21: - Split view splits the screen into the lister on the left and the record detail on the right. - List view shows only the lister in full screen. | G21: IADSSL-101 | H21: No | I21: Not Executed
A22: LT-008 | B22: Verify the 'Filters' button opens the Advanced filter modal | C22: Refer to Common Preconditions above. | D22: N/A. | E22: 1. Sign in to Sage Intacct application 2. Navigate to Applications > Lending Management > Loan type 3. Click the 'Filters' button at the top right of the lister. | F22: - A modal titled 'Advanced filter' opens containing Field/Operator/Value/Apply-criteria columns, Apply and Cancel buttons, and per-row '+' (add) and '-' (remove) controls. - No filters are selected by default. | G22: IADSSL-101 | H22: No | I22: Not Executed
A23: LT-009 | B23: Verify the Advanced filter 'Apply' button applies and persists filter changes | C23: Refer to Common Preconditions above. | D23: Filter row: Field = Loan type, Operator = Contains, Value = QA. | E23: 1. Sign in to Sage Intacct application 2. Navigate to Applications > Lending Management > Loan type 3. Click 'Filters' to open the Advanced filter modal 4. Set Field to 'Loan type', Operator to 'Contains', Value to 'QA', then click Apply 5. Reopen the Advanced filter modal. | F23: - The modal closes and the list updates to reflect the filter changes. - Reopening Advanced filters shows the previously applied filters persisted. - Rows left without any Field/Operator/Value are ignored. | G23: IADSSL-101 | H23: No | I23: Not Executed
A24: LT-010 | B24: Verify column filters and Advanced filters stay in sync | C24: Refer to Common Preconditions above. | D24: Column filter value: 'QA' entered on the Loan type column header filter input. | E24: 1. Sign in to Sage Intacct application 2. Navigate to Applications > Lending Management > Loan type 3. Enter 'QA' in the Loan type column header's filter input and press Enter 4. Open the Advanced filter modal and check whether the same filter appears there 5. Add or edit a filter directly inside the Advanced filter modal and click Apply. | F24: - Filters applied from a column filter input appear in the Advanced filter modal. - Filters added/edited in Manage view/Advanced filter are reflected back in the column filter inputs. | G24: IADSSL-101 | H24: No | I24: Not Executed
A25: LT-011 | B25: Verify column sorting from the column header | C25: Refer to Common Preconditions above. | D25: N/A. | E25: 1. Sign in to Sage Intacct application 2. Navigate to Applications > Lending Management > Loan type 3. Click the 'Loan type' column header once 4. Click the 'Loan type' column header a second time. | F25: - The first click sorts the column ascending with an upward arrow indicator. - The second click sorts descending with a downward arrow indicator. | G25: IADSSL-101 | H25: No | I25: Not Executed
A26: LT-012 | B26: Verify column sorting from 'Configure column' / 'Column setting' options, including multi-column sort | C26: Refer to Common Preconditions above. | D26: Sort row 1: Loan type, Ascending. Sort row 2: Description, Descending. | E26: 1. Sign in to Sage Intacct application 2. Navigate to Applications > Lending Management > Loan type 3. Open the column header's Column setting menu and select Sort, choosing 'Loan type' with Ascending order 4. Click Apply 5. Add a second sort row for 'Description' with Descending order and click Apply. | F26: - The grid sorts ascending/descending per the chosen order with the matching arrow indicator. - When multiple sort rows are configured, the dataset sorts by the first row's order first, then the second row's order for ties, continuing for any additional rows added. | G26: IADSSL-101 | H26: No | I26: Not Executed
A27: LT-013 | B27: Verify the 'Column setting' (cog wheel) menu functionality | C27: Refer to Common Preconditions above. | D27: N/A. | E27: 1. Sign in to Sage Intacct application 2. Navigate to Applications > Lending Management > Loan type 3. Click the Column setting/cog wheel icon on a column header. | F27: - A menu appears with Sort ascending, Sort descending, Freeze, Unfreeze all, and Text Wrapping (Clip / Wrap) options. | G27: IADSSL-101 | H27: No | I27: Not Executed
... A52: LT-038 | B52: Verify overall lister UI consistency (spacing, alignment, controls) matches the design standard | C52: Refer to Common Preconditions above. | D52: N/A. | E52: 1. Sign in to Sage Intacct application 2. Navigate to Applications > Lending Management > Loan type 3. Visually inspect the lister page's headers, buttons, filters, and grid layout, spacing, and alignment. | F52: - The page header, buttons, column filters, and data grid use the same spacing, alignment, and control styling as every other module lister in the application, with no visibly misaligned, overlapping, or inconsistently styled element. | G52: IADSSL-101 | H52: No | I52: Not Executed
A53: CREATE (58 test cases)
A54: LT-039 | B54: Create page title is 'Create loan type' | C54: Refer to Common Preconditions above. Navigate to the Loan types list and click Create. | D54: N/A (page-chrome check only). | E54: 1. Sign in to Sage Intacct application 2. Navigate to Applications > Lending Management > Loan type 3. Click '+Create' to open the Create Loan Type page 4. Observe the page title/heading. | F54: - The Create page displays a page title/H1 that clearly identifies the action and entity (e.g. 'Create Loan Type'). - The Create page title is consistent with the naming convention used by the list page title ('Loan types') and the Delete modal title ('Delete loan type'). | G54: IADSSL-101 | H54: No | I54: Not Executed
A55: LT-040 | B55: Loan type name field present | C55: Refer to Common Preconditions above. | D55: Name field: Loan type name field (no value entered — presence check only). | E55: 1. Sign in to Sage Intacct application 2. Navigate to Applications > Lending Management > Loan type 3. Click '+Create' to open the Create Loan Type page 4. Observe the fields on the page. | F55: - A text input for the Loan type name is visible on the Create page. | G55: IADSSL-101 | H55: No | I55: Not Executed | J55: Source section: B. Create (IDs: TC-LT-028–046, TC-LT-057–066 new)
A56: LT-041 | B56: Empty name blocked | C56: Refer to Common Preconditions above. | D56: Name: (leave blank) Type: Non-revolving Interest calculation method: Simple Description: Client QA loan type | E56: 1. Sign in to Sage Intacct application 2. Navigate to Applications > Lending Management > Loan type 3. Click '+Create' to open the Create Loan Type page 4. Leave the Name field blank, fill Type 'Non-revolving', Interest calculation method 'Simple', Description 'Client QA loan type' 5. Click 'Save'. | F56: - A validation error appears stating 'Loan type: Field is required.' (the Name field is actually labeled 'Loan type', not 'Name'). - The record is not saved and the page stays on Create. | G56: IADSSL-101 | H56: No | I56: Not Executed | J56: Source section: B. Create (IDs: TC-LT-028–046, TC-LT-057–066 new)
A57: LT-042 | B57: Reject creating a record with a duplicate Name | C57: Refer to Common Preconditions above. A record already exists with Name = 'QA Loan Type A'. | D57: Existing record Name: QA Loan Type A New record Name (duplicate): QA Loan Type A | E57: 1. Sign in to Sage Intacct application 2. Navigate to Applications > Lending Management > Loan type and confirm a record named 'QA Loan Type A' already exists 3. Click '+Create' and enter Name 'QA Loan Type A' (matching the existing record exactly), completing the other required fields with valid values 4. Click 'Save'. | F57: - A validation error appears stating that the Name 'QA Loan Type A' is already in use. - The duplicate record is not created. | G57: IADSSL-101 | H57: No | I57: Not Executed
A58: LT-043 | B58: Description optional | C58: Refer to Common Preconditions above. | D58: Name: QA Non-Revolving Loan Type Type: Non-revolving Interest calculation method: Simple Description: (leave blank) | E58: 1. Sign in to Sage Intacct application 2. Navigate to Applications > Lending Management > Loan type 3. Click '+Create' to open the Create Loan Type page 4. Fill Name 'QA Non-Revolving Loan Type', Type 'Non-revolving', Interest calculation method 'Simple', and leave the Description field blank 5. Click 'Save'. | F58: - The Description label has no asterisk. - The record saves successfully with the Description field left empty. | G58: IADSSL-101 | H58: No | I58: Not Executed | J58: Source section: B. Create (IDs: TC-LT-028–046, TC-LT-057–066 new)
A59: LT-044 | B59: Type defaults visible | C59: Refer to Common Preconditions above. | D59: Name: QA Non-Revolving Loan Type Type: Non-revolving Interest calculation method: Simple Description: Client QA loan type | E59: 1. Sign in to Sage Intacct application 2. Navigate to Applications > Lending Management > Loan type 3. Click '+Create' to open the Create Loan Type page 4. Observe the Type field control. | F59: - Revolving and Non-revolving radio buttons are both visible on the Create page. | G59: IADSSL-101 | H59: No | I59: Not Executed | J59: Source section: B. Create (IDs: TC-LT-028–046, TC-LT-057–066 new)
A60: LT-045 | B60: Interest type options | C60: Refer to Common Preconditions above. | D60: Name: QA Non-Revolving Loan Type Type: Non-revolving Interest calculation method: Simple Description: Client QA loan type | E60: 1. Sign in to Sage Intacct application 2. Navigate to Applications > Lending Management > Loan type 3. Click '+Create' to open the Create Loan Type page 4. Select Type 'Non-revolving' and open the Interest type dropdown. | F60: - Both 'Simple' and 'Compound' are listed as Interest type options. | G60: IADSSL-101 | H60: No | I60: Not Executed | J60: Source section: B. Create (IDs: TC-LT-028–046, TC-LT-057–066 new)
A61: LT-046 | B61: Interest calculation method required | C61: Refer to Common Preconditions above. | D61: Name: QA Non-Revolving Loan Type Type: Non-revolving Interest calculation method: (leave blank) Description: Client QA loan type | E61: 1. Sign in to Sage Intacct application 2. Navigate to Applications > Lending Management > Loan type 3. Click '+Create' to open the Create Loan Type page 4. Select Type 'Non-revolving' and observe the Interest calculation method field label. | F61: - The Interest calculation method field appears (conditionally, after Type is selected) with an asterisk (*) indicating it is required. | G61: IADSSL-101 | H61: No | I61: Not Executed | J61: Source section: B. Create (IDs: TC-LT-028–046, TC-LT-057–066 new)
A62: LT-047 | B62: Interest calculation method options (Revolving) | C62: Refer to Common Preconditions above. | D62: Name: QA Revolving Loan Type Type: Revolving Description: Client QA loan type | E62: 1. Sign in to Sage Intacct application 2. Navigate to Applications > Lending Management > Loan type 3. Click '+Create' to open the Create Loan Type page 4. Select Type 'Revolving' and open the Interest calculation method dropdown. | F62: - 'Actual/365' and 'Actual/360' are listed as the Interest calculation method options for Revolving. | G62: IADSSL-101 | H62: No | I62: Not Executed | J62: Source section: B. Create (IDs: TC-LT-028–046, TC-LT-057–066 new)
A63: LT-048 | B63: Interest calculation method options (Non-revolving) | C63: Refer to Common Preconditions above. | D63: Name: QA Non-Revolving Loan Type Type: Non-revolving Description: Client QA loan type | E63: 1. Sign in to Sage Intacct application 2. Navigate to Applications > Lending Management > Loan type 3. Click '+Create' to open the Create Loan Type page 4. Select Type 'Non-revolving' and open the Interest calculation method dropdown. | F63: - 'Actual/365', 'Actual/360', and '30/360' are all listed as the Interest calculation method options for Non-revolving - a superset of Revolving's two options. | G63: IADSSL-101 | H63: No | I63: Not Executed | J63: Source section: B. Create (IDs: TC-LT-028–046, TC-LT-057–066 new)
A64: LT-049 | B64: Reject 30/360 for a revolving (non-amortized) loan type | C64: Refer to Common Preconditions above. | D64: Name: QA Revolving 30-360 Test Type: Revolving Interest calculation method: 30/360 | E64: 1. Sign in to Sage Intacct application 2. Navigate to Applications > Lending Management > Loan type 3. Click '+Create', fill Name 'QA Revolving 30-360 Test', select Type 'Revolving' 4. Attempt to select Interest calculation method '30/360' (not offered) or otherwise submit with it set 5. Click 'Save'. | F64: - Creation is blocked because revolving loan types only accept Actual/365 or Actual/360 as the Interest calculation method. - The record is not saved. | G64: IADSSL-101 | H64: No | I64: Not Executed
A65: LT-050 | B65: Accept Actual/365, Actual/360, and 30/360 for non-revolving loan types | C65: Refer to Common Preconditions above. | D65: Name: QA Non-Revolving Actual365; Type: Non-revolving; Interest calculation method: Actual/365 Name: QA Non-Revolving Actual360; Type: Non-revolving; Interest calculation method: Actual/360 Name: QA Non-Revolving 30-360; Type: Non-revolving; Interest calculation method: 30/360 | E65: 1. Sign in to Sage Intacct application 2. Navigate to Applications > Lending Management > Loan type 3. Click '+Create', fill Name 'QA Non-Revolving Actual365', Type 'Non-revolving', Interest calculation method 'Actual/365', complete other required fields, and click Save 4. Repeat step 3 for Name 'QA Non-Revolving Actual360' with Interest calculation method 'Actual/360' 5. Repeat step 3 for Name 'QA Non-Revolving 30-360' with Interest calculation method '30/360'. | F65: - All three non-revolving loan types save successfully with their respective Interest calculation methods. | G65: IADSSL-101 | H65: No | I65: Not Executed
A66: LT-051 | B66: Status defaults to Active | C66: Refer to Common Preconditions above. | D66: Name: QA Non-Revolving Loan Type Type: Non-revolving Interest calculation method: Simple Description: Client QA loan type | E66: 1. Sign in to Sage Intacct application 2. Navigate to Applications > Lending Management > Loan type 3. Click '+Create', fill Name 'QA Non-Revolving Loan Type', Type 'Non-revolving', Interest calculation method 'Simple', Description 'Client QA loan type', add a Principal and an Interest payment priority row, and click Save 4. Open the newly created record's View page. | F66: - The record's Status defaults to Active on the View page. - There is no Status field on the Create page itself. | G66: IADSSL-101 | H66: No | I66: Not Executed | J66: Source section: B. Create (IDs: TC-LT-028–046, TC-LT-057–066 new)
A67: LT-052 | B67: Order Entry transaction definition required | C67: Refer to Common Preconditions above. | D67: Name: QA Non-Revolving Loan Type Type: Non-revolving Interest calculation method: Simple Description: Client QA loan type Order Entry transaction definition: (leave blank) | E67: 1. Sign in to Sage Intacct application 2. Navigate to Applications > Lending Management > Loan type 3. Click '+Create' to open the Create Loan Type page 4. Observe the Order Entry transaction definition field label. | F67: - The Order Entry transaction definition label displays an asterisk (*) indicating it is required. | G67: IADSSL-101 | H67: No | I67: Not Executed | J67: Source section: B. Create (IDs: TC-LT-028–046, TC-LT-057–066 new)
A68: LT-053 | B68: Reject a transaction definition that is not an Invoice in the Loan workflow | C68: Refer to Common Preconditions above. | D68: Transaction definition document class: Sales Order Workflow category: Other Name: QA Invalid TxnDef Loan Type | E68: 1. Sign in to Sage Intacct application 2. Navigate to Applications > Lending Management > Loan type 3. Click '+Create' to open the New loan type form 4. In the Order Entry transaction definition field, select a transaction definition whose document class is Sales Order and whose workflow category is Other (not Invoice in the Loan workflow) 5. Click 'Save'. | F68: - A validation error appears stating the transaction definition must be an Invoice document in the Loan workflow. - The loan type is not saved. | G68: IADSSL-101 | H68: No | I68: Not Executed
A69: LT-054 | B69: Item for loan principal posting required | C69: Refer to Common Preconditions above. | D69: Name: QA Non-Revolving Loan Type Type: Non-revolving Interest calculation method: Simple Description: Client QA loan type Item for loan principal posting: (leave blank) | E69: 1. Sign in to Sage Intacct application 2. Navigate to Applications > Lending Management > Loan type 3. Click '+Create' to open the Create Loan Type page 4. Observe the Item for loan principal posting field label. | F69: - The Item for loan principal posting label displays an asterisk (*) indicating it is required. | G69: IADSSL-101 | H69: No | I69: Not Executed | J69: Source section: B. Create (IDs: TC-LT-028–046, TC-LT-057–066 new)
A70: LT-055 | B70: Reject principal, interest, or fee items whose GL groups are absent from the transaction definition | C70: Refer to Common Preconditions above. | D70: Principal item: QA-Principal-Item (GL group: GL-Group-X) Interest item: QA-Interest-Item (GL group: GL-Group-Y) Fee item: QA-Fee-Item (GL group: GL-Group-Z) Order Entry transaction definition: does not include GL-Group-X, GL-Group-Y, or GL-Group-Z | E70: 1. Sign in to Sage Intacct application 2. Navigate to Applications > Lending Management > Loan type 3. Click '+Create' to open the New loan type form 4. Select an Order Entry transaction definition, then select a Principal item whose GL group is not included in that transaction definition, and click 'Save' 5. Repeat separately for the Interest item and then the Fee item, each with a GL group absent from the transaction definition. | F70: - A validation error appears for the Principal item stating its GL group is not included in the selected transaction definition. - A validation error appears for the Interest item stating its GL group is not included in the selected transaction definition. - A validation error appears for the Fee item stating its GL group is not included in the selected transaction definition. - The record is not saved in any of the three cases. | G70: IADSSL-101 | H70: No | I70: Not Executed
