Workbook

Sheet Summary
A1: SNL Focused Test Cases - Audit, AR Payment, Invoice, and Standard Statements
A2: Simple test cases based on the current SNL baseline and local implementation evidence. All cases start as Not Executed.
A4: Module | B4: Area | C4: Test Cases | D4: Automated | E4: Passed | F4: Failed | G4: Not Executed | H4: Blocked
A5: View Audit Trail - UI and Features | B5: Lending Management | C5: =COUNTA('Audit Trail'!$A$7:$A$30)-4 -> 20 | D5: =COUNTIF('Audit Trail'!$H$7:$H$30,"Yes") -> 0 | E5: =COUNTIF('Audit Trail'!$I$7:$I$30,"Passed") -> 0 | F5: =COUNTIF('Audit Trail'!$I$7:$I$30,"Failed") -> 0 | G5: =COUNTIF('Audit Trail'!$I$7:$I$30,"Not Executed") -> 20 | H5: =COUNTIF('Audit Trail'!$I$7:$I$30,"Blocked") -> 0
A6: AR Payment and Reversal Using Loan Invoices | B6: Lending Management | C6: =COUNTA('AR Payment and Reversal'!$A$7:$A$30)-4 -> 20 | D6: =COUNTIF('AR Payment and Reversal'!$H$7:$H$30,"Yes") -> 0 | E6: =COUNTIF('AR Payment and Reversal'!$I$7:$I$30,"Passed") -> 0 | F6: =COUNTIF('AR Payment and Reversal'!$I$7:$I$30,"Failed") -> 0 | G6: =COUNTIF('AR Payment and Reversal'!$I$7:$I$30,"Not Executed") -> 20 | H6: =COUNTIF('AR Payment and Reversal'!$I$7:$I$30,"Blocked") -> 0
A7: Loan Invoice - Full UI Coverage | B7: Lending Management | C7: =COUNTA('Invoice UI'!$A$7:$A$33)-5 -> 22 | D7: =COUNTIF('Invoice UI'!$H$7:$H$33,"Yes") -> 0 | E7: =COUNTIF('Invoice UI'!$I$7:$I$33,"Passed") -> 0 | F7: =COUNTIF('Invoice UI'!$I$7:$I$33,"Failed") -> 0 | G7: =COUNTIF('Invoice UI'!$I$7:$I$33,"Not Executed") -> 22 | H7: =COUNTIF('Invoice UI'!$I$7:$I$33,"Blocked") -> 0
A8: Standard Automation - Statement Generation and Reversal | B8: Lending Management | C8: =COUNTA('Standard Statements'!$A$7:$A$32)-4 -> 22 | D8: =COUNTIF('Standard Statements'!$H$7:$H$32,"Yes") -> 0 | E8: =COUNTIF('Standard Statements'!$I$7:$I$32,"Passed") -> 0 | F8: =COUNTIF('Standard Statements'!$I$7:$I$32,"Failed") -> 0 | G8: =COUNTIF('Standard Statements'!$I$7:$I$32,"Not Executed") -> 22 | H8: =COUNTIF('Standard Statements'!$I$7:$I$32,"Blocked") -> 0
A9: TOTAL | C9: =SUM(C5:C8) -> 84 | D9: =SUM(D5:D8) -> 0 | E9: =SUM(E5:E8) -> 0 | F9: =SUM(F5:F8) -> 0 | G9: =SUM(G5:G8) -> 84 | H9: =SUM(H5:H8) -> 0
A11: Coverage basis
A12: 1. Requirement references come from the current SNL client workbook, including PR #1457 sections already captured there.
A13: 2. Audit trail entry points are implemented in the current loan account, loan type, and category page objects and tests.
A14: 3. Local Lending Workbench tests cover interest and invoice generation, statement generation, reversal, regeneration, and balance carry-forward.
A15: 4. Cases that are not proven by current automation stay marked Not Executed for manual verification.
A16: 5. Suggested local evidence: pages/loan_account/account_page.py, tests/lending_workbench/test_workbench_e2e.py, and tests/lending_workbench/test_workbench_behavior.py.

Sheet Audit Trail
A1: View Audit Trail - UI and Features
A2: Common Preconditions | C2: 1. User is signed in to Sage Intacct. 2. The correct Lending Management entity is selected. 3. Lending Management is enabled. 4. The user has the needed permission. 5. Required loan, customer, invoice, and setup records are active.
A4: Navigation: Applications > Lending Management > Record View > More actions > View audit trail | Client baseline | 20 test cases | Updated 2026-08-28
A6: Test Case ID | B6: Test Scenario | C6: Preconditions | D6: Test Data | E6: Test Steps | F6: Expected Result | G6: Requirement/Jira Reference | H6: IS Automated | I6: Status | J6: Comments
A7: ACCESS AND NAVIGATION (4 test cases)
A8: SNL-AUD-001 | B8: Show the More actions button on a record View page | C8: Refer to Common Preconditions above. | D8: Record: LOAN-QA-001 | E8: 1. Sign in to Sage Intacct. 2. Go to Applications > Lending Management > Record View > More actions > View audit trail. 3. Prepare the test data: Open an active loan record. 4. Look at the page header. 5. Save or confirm when needed. 6. Check the page and related records. | F8: The More actions button is visible and enabled. | G8: Audit trail UI and feature requirement; Jira reference TBD | H8: TBD | I8: Not Executed | J8: Implemented in the current loan account page object.
A9: SNL-AUD-002 | B9: Show View audit trail in the More actions menu | C9: Refer to Common Preconditions above. | D9: Record: LOAN-QA-001 | E9: 1. Sign in to Sage Intacct. 2. Go to Applications > Lending Management > Record View > More actions > View audit trail. 3. Prepare the test data: Open an active loan record. 4. Open the More actions menu. 5. Save or confirm when needed. 6. Check the page and related records. | F9: The menu shows View audit trail. | G9: Audit trail UI and feature requirement; Jira reference TBD | H9: TBD | I9: Not Executed | J9: Implemented in loan account, loan type, and category page objects.
A10: SNL-AUD-003 | B10: Open the audit trail for the selected record | C10: Refer to Common Preconditions above. | D10: Record: LOAN-QA-001 | E10: 1. Sign in to Sage Intacct. 2. Go to Applications > Lending Management > Record View > More actions > View audit trail. 3. Prepare the test data: Open an active loan record. 4. Click View audit trail. 5. Save or confirm when needed. 6. Check the page and related records. | F10: The audit page opens for LOAN-QA-001. | G10: Audit trail UI and feature requirement; Jira reference TBD | H10: TBD | I10: Not Executed | J10: A local UI test confirms the audit view opens.
A11: SNL-AUD-004 | B11: Return from audit trail to the same record | C11: Refer to Common Preconditions above. | D11: Record: LOAN-QA-001 | E11: 1. Sign in to Sage Intacct. 2. Go to Applications > Lending Management > Record View > More actions > View audit trail. 3. Prepare the test data: Open the audit trail. 4. Use Back or the breadcrumb. 5. Save or confirm when needed. 6. Check the page and related records. | F11: The same loan record opens without any data change. | G11: Audit trail UI and feature requirement; Jira reference TBD | H11: TBD | I11: Not Executed
A12: AUDIT TRAIL UI (6 test cases)
A13: SNL-AUD-005 | B13: Show a clear audit trail page title | C13: Refer to Common Preconditions above. | D13: Record: LOAN-QA-001 | E13: 1. Sign in to Sage Intacct. 2. Go to Applications > Lending Management > Record View > More actions > View audit trail. 3. Prepare the test data: Open the audit trail. 4. Read the page title. 5. Save or confirm when needed. 6. Check the page and related records. | F13: The title clearly says Audit trail and identifies the record. | G13: Audit trail UI and feature requirement; Jira reference TBD | H13: TBD | I13: Not Executed
A14: SNL-AUD-006 | B14: Show the main audit columns | C14: Refer to Common Preconditions above. | D14: Record: LOAN-QA-001 | E14: 1. Sign in to Sage Intacct. 2. Go to Applications > Lending Management > Record View > More actions > View audit trail. 3. Prepare the test data: Open an audit trail with history. 4. Review the column names. 5. Save or confirm when needed. 6. Check the page and related records. | F14: The page shows action, user, date and time, field, old value, and new value. | G14: Audit trail UI and feature requirement; Jira reference TBD | H14: TBD | I14: Not Executed
A15: SNL-AUD-007 | B15: Show the newest audit entry first | C15: Refer to Common Preconditions above. | D15: Record: LOAN-QA-001; Latest change: Account name | E15: 1. Sign in to Sage Intacct. 2. Go to Applications > Lending Management > Record View > More actions > View audit trail. 3. Prepare the test data: Make two changes at different times. 4. Open the audit trail. 5. Save or confirm when needed. 6. Check the page and related records. | F15: The latest change is shown before the older change. | G15: Audit trail UI and feature requirement; Jira reference TBD | H15: TBD | I15: Not Executed
A16: SNL-AUD-008 | B16: Show long old and new values clearly | C16: Refer to Common Preconditions above. | D16: Old description: 200 characters; New description: 300 characters | E16: 1. Sign in to Sage Intacct. 2. Go to Applications > Lending Management > Record View > More actions > View audit trail. 3. Prepare the test data: Update a long description. 4. Open the audit entry. 5. Save or confirm when needed. 6. Check the page and related records. | F16: Both values are readable and do not overlap other columns. | G16: Audit trail UI and feature requirement; Jira reference TBD | H16: TBD | I16: Not Executed
A17: SNL-AUD-009 | B17: Show a clear message when there is no history | C17: Refer to Common Preconditions above. | D17: New record: QA-AUDIT-EMPTY-001 | E17: 1. Sign in to Sage Intacct. 2. Go to Applications > Lending Management > Record View > More actions > View audit trail. 3. Prepare the test data: Use a record with no saved change after creation. 4. Open the audit trail. 5. Save or confirm when needed. 6. Check the page and related records. | F17: The page shows the available create entry or a clear no-history message. | G17: Audit trail UI and feature requirement; Jira reference TBD | H17: TBD | I17: Not Executed
A18: SNL-AUD-010 | B18: Refresh the audit trail after a new change | C18: Refer to Common Preconditions above. | D18: Record: LOAN-QA-001; Field: Description | E18: 1. Sign in to Sage Intacct. 2. Go to Applications > Lending Management > Record View > More actions > View audit trail. 3. Prepare the test data: Keep the audit page open and edit the record in another session. 4. Refresh the audit page. 5. Save or confirm when needed. 6. Check the page and related records. | F18: The new change appears after refresh. | G18: Audit trail UI and feature requirement; Jira reference TBD | H18: TBD | I18: Not Executed
A19: AUDIT DATA (8 test cases)
A20: SNL-AUD-011 | B20: Record the creation of a new record | C20: Refer to Common Preconditions above. | D20: New loan: LOAN-AUDIT-NEW-001 | E20: 1. Sign in to Sage Intacct. 2. Go to Applications > Lending Management > Record View > More actions > View audit trail. 3. Prepare the test data: Create and save a new loan. 4. Open its audit trail. 5. Save or confirm when needed. 6. Check the page and related records. | F20: A Create entry shows the user and creation time. | G20: Audit trail UI and feature requirement; Jira reference TBD | H20: TBD | I20: Not Executed
A21: SNL-AUD-012 | B21: Record one changed field with old and new values | C21: Refer to Common Preconditions above. | D21: Record: LOAN-QA-001; Account name: Old name to New name | E21: 1. Sign in to Sage Intacct. 2. Go to Applications > Lending Management > Record View > More actions > View audit trail. 3. Prepare the test data: Edit only the account name. 4. Save and open the audit trail. 5. Save or confirm when needed. 6. Check the page and related records. | F21: The entry shows Account name, Old name, and New name. | G21: Audit trail UI and feature requirement; Jira reference TBD | H21: TBD | I21: Not Executed
A22: SNL-AUD-013 | B22: Record all fields changed in one save | C22: Refer to Common Preconditions above. | D22: Record: LOAN-QA-001; Amount: 1000 to 1200; Description: A to B | E22: 1. Sign in to Sage Intacct. 2. Go to Applications > Lending Management > Record View > More actions > View audit trail. 3. Prepare the test data: Change two editable fields. 4. Save and open the audit trail. 5. Save or confirm when needed. 6. Check the page and related records. | F22: Both field changes appear under the same save action. | G22: Audit trail UI and feature requirement; Jira reference TBD | H22: TBD | I22: Not Executed
A23: SNL-AUD-014 | B23: Record a status change | C23: Refer to Common Preconditions above. | D23: Record: LOAN-QA-001; Status: Open to Closed | E23: 1. Sign in to Sage Intacct. 2. Go to Applications > Lending Management > Record View > More actions > View audit trail. 3. Prepare the test data: Change the record status. 4. Save and open the audit trail. 5. Save or confirm when needed. 6. Check the page and related records. | F23: The old and new status values are correct. | G23: Audit trail UI and feature requirement; Jira reference TBD | H23: TBD | I23: Not Executed
A24: SNL-AUD-015 | B24: Show the correct user for each change | C24: Refer to Common Preconditions above. | D24: Users: QA-AUDITOR-A and QA-AUDITOR-B | E24: 1. Sign in to Sage Intacct. 2. Go to Applications > Lending Management > Record View > More actions > View audit trail. 3. Prepare the test data: Save one change with each user. 4. Open the audit trail. 5. Save or confirm when needed. 6. Check the page and related records. | F24: Each entry shows the user who made that change. | G24: Audit trail UI and feature requirement; Jira reference TBD | H24: TBD | I24: Not Executed
A25: SNL-AUD-016 | B25: Show the correct date, time, and time zone | C25: Refer to Common Preconditions above. | D25: Change time: 08/28/2026 10:30 AM local time | E25: 1. Sign in to Sage Intacct. 2. Go to Applications > Lending Management > Record View > More actions > View audit trail. 3. Prepare the test data: Save a known change. 4. Compare the audit time with the save time. 5. Save or confirm when needed. 6. Check the page and related records. | F25: The audit time is correct for the company or user time zone. | G25: Audit trail UI and feature requirement; Jira reference TBD | H25: TBD | I25: Not Executed
A26: SNL-AUD-017 | B26: Do not create a false change when no value changed | C26: Refer to Common Preconditions above. | D26: Record: LOAN-QA-001 | E26: 1. Sign in to Sage Intacct. 2. Go to Applications > Lending Management > Record View > More actions > View audit trail. 3. Prepare the test data: Open Edit and leave all values unchanged. 4. Save the record and open the audit trail. 5. Save or confirm when needed. 6. Check the page and related records. | F26: No false field-change entry is added. | G26: Audit trail UI and feature requirement; Jira reference TBD | H26: TBD | I26: Not Executed
A27: SNL-AUD-018 | B27: Keep special characters in audited values | C27: Refer to Common Preconditions above. | D27: Description: Fee & tax - 10% (QA) | E27: 1. Sign in to Sage Intacct. 2. Go to Applications > Lending Management > Record View > More actions > View audit trail. 3. Prepare the test data: Save text with special characters. 4. Open the audit trail. 5. Save or confirm when needed. 6. Check the page and related records. | F27: The saved text appears correctly in the new value. | G27: Audit trail UI and feature requirement; Jira reference TBD | H27: TBD | I27: Not Executed
A28: SECURITY (2 test cases)
A29: SNL-AUD-019 | B29: Allow an authorized user to view the audit trail | C29: Refer to Common Preconditions above. | D29: User: QA-AUDIT-ALLOWED | E29: 1. Sign in to Sage Intacct. 2. Go to Applications > Lending Management > Record View > More actions > View audit trail. 3. Prepare the test data: Give the user audit access. 4. Open View audit trail. 5. Save or confirm when needed. 6. Check the page and related records. | F29: The audit page opens and shows data. | G29: Audit trail UI and feature requirement; Jira reference TBD | H29: TBD | I29: Not Executed
A30: SNL-AUD-020 | B30: Block an unauthorized user from audit data | C30: Refer to Common Preconditions above. | D30: User: QA-AUDIT-BLOCKED | E30: 1. Sign in to Sage Intacct. 2. Go to Applications > Lending Management > Record View > More actions > View audit trail. 3. Prepare the test data: Remove the user's audit permission. 4. Try to open the audit trail. 5. Save or confirm when needed. 6. Check the page and related records. | F30: The action is hidden or access is denied with a clear message. | G30: Audit trail UI and feature requirement; Jira reference TBD | H30: TBD | I30: Not Executed

Sheet AR Payment and Reversal
A1: AR Payment and Reversal Using Loan Invoices
A2: Common Preconditions | C2: 1. User is signed in to Sage Intacct. 2. The correct Lending Management entity is selected. 3. Lending Management is enabled. 4. The user has the needed permission. 5. Required loan, customer, invoice, and setup records are active.
A4: Navigation: Applications > Accounts Receivable > Receive payment | Client baseline | 20 test cases | Updated 2026-08-28
A6: Test Case ID | B6: Test Scenario | C6: Preconditions | D6: Test Data | E6: Test Steps | F6: Expected Result | G6: Requirement/Jira Reference | H6: IS Automated | I6: Status | J6: Comments
A7: PAYMENT UI (5 test cases)
A8: SNL-ARP-001 | B8: Open the AR payment page from Accounts Receivable | C8: Refer to Common Preconditions above. | D8: Customer: CUST-QA-AR-001 | E8: 1. Sign in to Sage Intacct. 2. Go to Applications > Accounts Receivable > Receive payment. 3. Prepare the test data: Use a customer with open loan invoices. 4. Open Receive payment. 5. Save or confirm when needed. 6. Check the page and related records. | F8: The payment page opens without an error. | G8: LME AR Payment client requirement; Jira reference TBD | H8: TBD | I8: Not Executed
A9: SNL-ARP-002 | B9: Show only open invoices for the selected customer | C9: Refer to Common Preconditions above. | D9: Customer: CUST-QA-AR-001; Open invoice: INV-QA-001; Paid invoice: INV-QA-PAID | E9: 1. Sign in to Sage Intacct. 2. Go to Applications > Accounts Receivable > Receive payment. 3. Prepare the test data: Select the customer. 4. Open the invoice selection list. 5. Save or confirm when needed. 6. Check the page and related records. | F9: INV-QA-001 is available and INV-QA-PAID is not available. | G9: LME AR Payment client requirement; Jira reference TBD | H9: TBD | I9: Not Executed
A10: SNL-ARP-003 | B10: Show invoice number, date, due date, and open amount | C10: Refer to Common Preconditions above. | D10: Invoice: INV-QA-001 | E10: 1. Sign in to Sage Intacct. 2. Go to Applications > Accounts Receivable > Receive payment. 3. Prepare the test data: Select the customer. 4. Review the invoice grid. 5. Save or confirm when needed. 6. Check the page and related records. | F10: The invoice details and open amount are correct. | G10: LME AR Payment client requirement; Jira reference TBD | H10: TBD | I10: Not Executed
A11: SNL-ARP-004 | B11: Require the main payment fields | C11: Refer to Common Preconditions above. | D11: Customer: blank; Payment date: blank; Amount: blank | E11: 1. Sign in to Sage Intacct. 2. Go to Applications > Accounts Receivable > Receive payment. 3. Prepare the test data: Open a new AR payment. 4. Try to save with required fields blank. 5. Save or confirm when needed. 6. Check the page and related records. | F11: Save is blocked and each missing field shows a clear message. | G11: LME AR Payment client requirement; Jira reference TBD | H11: TBD | I11: Not Executed
A12: SNL-ARP-005 | B12: Block an amount greater than the selected invoice balance | C12: Refer to Common Preconditions above. | D12: Invoice open amount: 100.00; Payment amount: 120.00 | E12: 1. Sign in to Sage Intacct. 2. Go to Applications > Accounts Receivable > Receive payment. 3. Prepare the test data: Select INV-QA-001. 4. Enter 120.00 and save. 5. Save or confirm when needed. 6. Check the page and related records. | F12: The payment is blocked or the extra amount needs an allowed handling option. | G12: LME AR Payment client requirement; Jira reference TBD | H12: TBD | I12: Not Executed
A13: APPLY PAYMENT (6 test cases)
A14: SNL-ARP-006 | B14: Pay one loan invoice in full | C14: Refer to Common Preconditions above. | D14: Invoice: INV-QA-001; Open amount: 100.00; Payment: 100.00 | E14: 1. Sign in to Sage Intacct. 2. Go to Applications > Accounts Receivable > Receive payment. 3. Prepare the test data: Select one open loan invoice. 4. Enter 100.00 and save. 5. Save or confirm when needed. 6. Check the page and related records. | F14: The payment posts and the invoice balance becomes 0.00. | G14: LME AR Payment client requirement; Jira reference TBD | H14: TBD | I14: Not Executed
A15: SNL-ARP-007 | B15: Pay one loan invoice partly | C15: Refer to Common Preconditions above. | D15: Invoice: INV-QA-002; Open amount: 200.00; Payment: 75.00 | E15: 1. Sign in to Sage Intacct. 2. Go to Applications > Accounts Receivable > Receive payment. 3. Prepare the test data: Select one open loan invoice. 4. Enter 75.00 and save. 5. Save or confirm when needed. 6. Check the page and related records. | F15: The invoice stays open with 125.00 remaining. | G15: LME AR Payment client requirement; Jira reference TBD | H15: TBD | I15: Not Executed
A16: SNL-ARP-008 | B16: Pay two loan invoices in one payment | C16: Refer to Common Preconditions above. | D16: Invoice 1: 100.00; Invoice 2: 150.00; Payment: 250.00 | E16: 1. Sign in to Sage Intacct. 2. Go to Applications > Accounts Receivable > Receive payment. 3. Prepare the test data: Select both open invoices. 4. Apply the full amount and save. 5. Save or confirm when needed. 6. Check the page and related records. | F16: One payment is applied to both invoices for the correct amounts. | G16: LME AR Payment client requirement; Jira reference TBD | H16: TBD | I16: Not Executed
A17: SNL-ARP-009 | B17: Block invoices from another customer | C17: Refer to Common Preconditions above. | D17: Customer A invoice: INV-A; Customer B invoice: INV-B | E17: 1. Sign in to Sage Intacct. 2. Go to Applications > Accounts Receivable > Receive payment. 3. Prepare the test data: Select Customer A. 4. Try to add INV-B. 5. Save or confirm when needed. 6. Check the page and related records. | F17: The invoice from Customer B cannot be selected. | G17: LME AR Payment client requirement; Jira reference TBD | H17: TBD | I17: Not Executed
A18: SNL-ARP-010 | B18: Create the loan payment entry for each paid invoice | C18: Refer to Common Preconditions above. | D18: Invoices: INV-QA-001 and INV-QA-002 | E18: 1. Sign in to Sage Intacct. 2. Go to Applications > Accounts Receivable > Receive payment. 3. Prepare the test data: Post one payment to both invoices. 4. Open each loan transaction history. 5. Save or confirm when needed. 6. Check the page and related records. | F18: Each loan shows the correct payment amount and reference. | G18: LME AR Payment client requirement; Jira reference TBD | H18: TBD | I18: Not Executed | J18: Local baseline expects a loan-side transaction for each invoice.
A19: SNL-ARP-011 | B19: Update invoice and loan balances after payment | C19: Refer to Common Preconditions above. | D19: Invoice: INV-QA-002; Payment: 75.00 | E19: 1. Sign in to Sage Intacct. 2. Go to Applications > Accounts Receivable > Receive payment. 3. Prepare the test data: Post a partial payment. 4. Open the invoice and loan account. 5. Save or confirm when needed. 6. Check the page and related records. | F19: The invoice balance and loan balance show the same applied amount. | G19: LME AR Payment client requirement; Jira reference TBD | H19: TBD | I19: Not Executed
A20: REVERSAL (8 test cases)
A21: SNL-ARP-012 | B21: Show Reverse for a posted AR payment | C21: Refer to Common Preconditions above. | D21: Payment: PMT-QA-001; Status: Posted | E21: 1. Sign in to Sage Intacct. 2. Go to Applications > Accounts Receivable > Receive payment. 3. Prepare the test data: Open the posted payment. 4. Review the available actions. 5. Save or confirm when needed. 6. Check the page and related records. | F21: Reverse is visible for an eligible payment. | G21: LME AR Payment client requirement; Jira reference TBD | H21: TBD | I21: Not Executed
A22: SNL-ARP-013 | B22: Show a confirmation before reversal | C22: Refer to Common Preconditions above. | D22: Payment: PMT-QA-001 | E22: 1. Sign in to Sage Intacct. 2. Go to Applications > Accounts Receivable > Receive payment. 3. Prepare the test data: Open the posted payment. 4. Click Reverse. 5. Save or confirm when needed. 6. Check the page and related records. | F22: A confirmation message identifies the payment and amount. | G22: LME AR Payment client requirement; Jira reference TBD | H22: TBD | I22: Not Executed
A23: SNL-ARP-014 | B23: Reverse a full payment on one invoice | C23: Refer to Common Preconditions above. | D23: Payment: PMT-QA-001; Invoice: INV-QA-001; Amount: 100.00 | E23: 1. Sign in to Sage Intacct. 2. Go to Applications > Accounts Receivable > Receive payment. 3. Prepare the test data: Use a fully paid invoice. 4. Confirm the reversal. 5. Save or confirm when needed. 6. Check the page and related records. | F23: The payment is reversed and the invoice reopens for 100.00. | G23: LME AR Payment client requirement; Jira reference TBD | H23: TBD | I23: Not Executed
A24: SNL-ARP-015 | B24: Reverse one payment applied to two invoices | C24: Refer to Common Preconditions above. | D24: Payment: PMT-QA-002; Invoice 1: 100.00; Invoice 2: 150.00 | E24: 1. Sign in to Sage Intacct. 2. Go to Applications > Accounts Receivable > Receive payment. 3. Prepare the test data: Use one payment applied to two invoices. 4. Confirm the reversal. 5. Save or confirm when needed. 6. Check the page and related records. | F24: Both invoice applications reverse in one action. | G24: LME AR Payment client requirement; Jira reference TBD | H24: TBD | I24: Not Executed
A25: SNL-ARP-016 | B25: Mark every loan-side payment entry as reversed | C25: Refer to Common Preconditions above. | D25: Payment: PMT-QA-002; Two loan accounts | E25: 1. Sign in to Sage Intacct. 2. Go to Applications > Accounts Receivable > Receive payment. 3. Prepare the test data: Reverse the multi-invoice payment. 4. Open both loan transaction histories. 5. Save or confirm when needed. 6. Check the page and related records. | F25: Both original loan payment entries show Reversed. | G25: LME AR Payment client requirement; Jira reference TBD | H25: TBD | I25: Not Executed
A26: SNL-ARP-017 | B26: Create an equal reversing transaction | C26: Refer to Common Preconditions above. | D26: Original payment: 250.00 | E26: 1. Sign in to Sage Intacct. 2. Go to Applications > Accounts Receivable > Receive payment. 3. Prepare the test data: Reverse PMT-QA-002. 4. Review the related transactions. 5. Save or confirm when needed. 6. Check the page and related records. | F26: The reversal offsets exactly 250.00 and links to the original payment. | G26: LME AR Payment client requirement; Jira reference TBD | H26: TBD | I26: Not Executed
A27: SNL-ARP-018 | B27: Allow a reopened invoice to be paid again | C27: Refer to Common Preconditions above. | D27: Reopened invoice: INV-QA-001; New payment: 100.00 | E27: 1. Sign in to Sage Intacct. 2. Go to Applications > Accounts Receivable > Receive payment. 3. Prepare the test data: Reverse the original payment. 4. Create and post a new payment. 5. Save or confirm when needed. 6. Check the page and related records. | F27: The new payment posts normally and closes the invoice again. | G27: LME AR Payment client requirement; Jira reference TBD | H27: TBD | I27: Not Executed
A28: SNL-ARP-019 | B28: Block reversal when one related loan is closed | C28: Refer to Common Preconditions above. | D28: Loan A: Open; Loan B: Closed; Payment: PMT-QA-002 | E28: 1. Sign in to Sage Intacct. 2. Go to Applications > Accounts Receivable > Receive payment. 3. Prepare the test data: Close one loan after the payment. 4. Try to reverse the payment. 5. Save or confirm when needed. 6. Check the page and related records. | F28: The whole reversal is blocked and no invoice is partly reopened. | G28: LME AR Payment client requirement; Jira reference TBD | H28: TBD | I28: Not Executed
A29: ACCOUNTING AND HISTORY (1 test case)
A30: SNL-ARP-020 | B30: Create balanced accounting entries for payment and reversal | C30: Refer to Common Preconditions above. | D30: Payment: 250.00; Reversal: 250.00 | E30: 1. Sign in to Sage Intacct. 2. Go to Applications > Accounts Receivable > Receive payment. 3. Prepare the test data: Post and then reverse a payment. 4. Review the accounting entries. 5. Save or confirm when needed. 6. Check the page and related records. | F30: Each transaction is balanced and the reversal offsets the payment. | G30: LME AR Payment client requirement; Jira reference TBD | H30: TBD | I30: Not Executed

Sheet Invoice UI
A1: Loan Invoice - Full UI Coverage
A2: Common Preconditions | C2: 1. User is signed in to Sage Intacct. 2. The correct Lending Management entity is selected. 3. Lending Management is enabled. 4. The user has the needed permission. 5. Required loan, customer, invoice, and setup records are active.
A4: Navigation: Applications > Accounts Receivable > Invoices / Lending Management > Related invoices | Client baseline | 22 test cases | Updated 2026-08-28
A6: Test Case ID | B6: Test Scenario | C6: Preconditions | D6: Test Data | E6: Test Steps | F6: Expected Result | G6: Requirement/Jira Reference | H6: IS Automated | I6: Status | J6: Comments
A7: INVOICE LIST (7 test cases)
A8: SNL-INV-001 | B8: Open the loan invoice list | C8: Refer to Common Preconditions above. | D8: Entity: LME QA | E8: 1. Sign in to Sage Intacct. 2. Go to Applications > Accounts Receivable > Invoices / Lending Management > Related invoices. 3. Prepare the test data: Use an entity with loan invoices. 4. Open the invoice list. 5. Save or confirm when needed. 6. Check the page and related records. | F8: The invoice list loads without an error. | G8: Loan invoice UI requirement; Jira reference TBD | H8: TBD | I8: Not Executed
A9: SNL-INV-002 | B9: Show the main invoice columns | C9: Refer to Common Preconditions above. | D9: Invoice: INV-UI-001 | E9: 1. Sign in to Sage Intacct. 2. Go to Applications > Accounts Receivable > Invoices / Lending Management > Related invoices. 3. Prepare the test data: Open the invoice list. 4. Review the column names. 5. Save or confirm when needed. 6. Check the page and related records. | F9: The list shows invoice number, customer, loan, dates, status, total, paid, and balance. | G9: Loan invoice UI requirement; Jira reference TBD | H9: TBD | I9: Not Executed
A10: SNL-INV-003 | B10: Search by invoice number | C10: Refer to Common Preconditions above. | D10: Search: INV-UI-001 | E10: 1. Sign in to Sage Intacct. 2. Go to Applications > Accounts Receivable > Invoices / Lending Management > Related invoices. 3. Prepare the test data: Open the invoice list. 4. Search for INV-UI-001. 5. Save or confirm when needed. 6. Check the page and related records. | F10: Only matching invoices are shown. | G10: Loan invoice UI requirement; Jira reference TBD | H10: TBD | I10: Not Executed
A11: SNL-INV-004 | B11: Filter invoices by status | C11: Refer to Common Preconditions above. | D11: Status: Open | E11: 1. Sign in to Sage Intacct. 2. Go to Applications > Accounts Receivable > Invoices / Lending Management > Related invoices. 3. Prepare the test data: Open the invoice list. 4. Apply the Open status filter. 5. Save or confirm when needed. 6. Check the page and related records. | F11: Only open invoices are shown. | G11: Loan invoice UI requirement; Jira reference TBD | H11: TBD | I11: Not Executed
A12: SNL-INV-005 | B12: Filter invoices by customer | C12: Refer to Common Preconditions above. | D12: Customer: CUST-QA-INV-001 | E12: 1. Sign in to Sage Intacct. 2. Go to Applications > Accounts Receivable > Invoices / Lending Management > Related invoices. 3. Prepare the test data: Open the invoice list. 4. Apply the customer filter. 5. Save or confirm when needed. 6. Check the page and related records. | F12: Only invoices for the selected customer are shown. | G12: Loan invoice UI requirement; Jira reference TBD | H12: TBD | I12: Not Executed
A13: SNL-INV-006 | B13: Sort invoice dates and amounts | C13: Refer to Common Preconditions above. | D13: Invoices with different dates and totals | E13: 1. Sign in to Sage Intacct. 2. Go to Applications > Accounts Receivable > Invoices / Lending Management > Related invoices. 3. Prepare the test data: Open the invoice list. 4. Sort Date and then Total in both directions. 5. Save or confirm when needed. 6. Check the page and related records. | F13: Rows follow the selected sort order. | G13: Loan invoice UI requirement; Jira reference TBD | H13: TBD | I13: Not Executed
A14: SNL-INV-007 | B14: Keep selected columns after leaving the page | C14: Refer to Common Preconditions above. | D14: Add column: Loan account | E14: 1. Sign in to Sage Intacct. 2. Go to Applications > Accounts Receivable > Invoices / Lending Management > Related invoices. 3. Prepare the test data: Open Configure columns. 4. Add the column, leave the page, and return. 5. Save or confirm when needed. 6. Check the page and related records. | F14: The selected column is still visible. | G14: Loan invoice UI requirement; Jira reference TBD | H14: TBD | I14: Not Executed
A15: INVOICE VIEW (8 test cases)
A16: SNL-INV-008 | B16: Open an invoice from the list | C16: Refer to Common Preconditions above. | D16: Invoice: INV-UI-001 | E16: 1. Sign in to Sage Intacct. 2. Go to Applications > Accounts Receivable > Invoices / Lending Management > Related invoices. 3. Prepare the test data: Find the invoice in the list. 4. Click the invoice number. 5. Save or confirm when needed. 6. Check the page and related records. | F16: The correct invoice View page opens. | G16: Loan invoice UI requirement; Jira reference TBD | H16: TBD | I16: Not Executed
A17: SNL-INV-009 | B17: Show a clear invoice page title and status | C17: Refer to Common Preconditions above. | D17: Invoice: INV-UI-001; Status: Open | E17: 1. Sign in to Sage Intacct. 2. Go to Applications > Accounts Receivable > Invoices / Lending Management > Related invoices. 3. Prepare the test data: Open the invoice. 4. Read the page header. 5. Save or confirm when needed. 6. Check the page and related records. | F17: The invoice number and current status are clear. | G17: Loan invoice UI requirement; Jira reference TBD | H17: TBD | I17: Not Executed
A18: SNL-INV-010 | B18: Show customer and loan links | C18: Refer to Common Preconditions above. | D18: Customer: CUST-QA-INV-001; Loan: LOAN-QA-INV-001 | E18: 1. Sign in to Sage Intacct. 2. Go to Applications > Accounts Receivable > Invoices / Lending Management > Related invoices. 3. Prepare the test data: Open the invoice. 4. Review the Customer and Loan fields. 5. Save or confirm when needed. 6. Check the page and related records. | F18: Both values are correct and open the related records. | G18: Loan invoice UI requirement; Jira reference TBD | H18: TBD | I18: Not Executed
A19: SNL-INV-011 | B19: Show invoice date, due date, and payment terms | C19: Refer to Common Preconditions above. | D19: Invoice date: 08/01/2026; Due date: 08/31/2026; Terms: Net 30 | E19: 1. Sign in to Sage Intacct. 2. Go to Applications > Accounts Receivable > Invoices / Lending Management > Related invoices. 3. Prepare the test data: Open the invoice. 4. Review the date and terms fields. 5. Save or confirm when needed. 6. Check the page and related records. | F19: All values match the saved invoice. | G19: Loan invoice UI requirement; Jira reference TBD | H19: TBD | I19: Not Executed
A20: SNL-INV-012 | B20: Show principal, interest, and fee lines | C20: Refer to Common Preconditions above. | D20: Principal: 800.00; Interest: 150.00; Fee: 50.00 | E20: 1. Sign in to Sage Intacct. 2. Go to Applications > Accounts Receivable > Invoices / Lending Management > Related invoices. 3. Prepare the test data: Open an invoice with all line types. 4. Review the line grid. 5. Save or confirm when needed. 6. Check the page and related records. | F20: Each line type and amount is correct. | G20: Loan invoice UI requirement; Jira reference TBD | H20: TBD | I20: Not Executed
A21: SNL-INV-013 | B21: Show correct invoice totals | C21: Refer to Common Preconditions above. | D21: Subtotal: 1000.00; Paid: 250.00; Balance: 750.00 | E21: 1. Sign in to Sage Intacct. 2. Go to Applications > Accounts Receivable > Invoices / Lending Management > Related invoices. 3. Prepare the test data: Open a partly paid invoice. 4. Review the totals. 5. Save or confirm when needed. 6. Check the page and related records. | F21: Subtotal minus paid equals the remaining balance. | G21: Loan invoice UI requirement; Jira reference TBD | H21: TBD | I21: Not Executed
A22: SNL-INV-014 | B22: Format dates and currency clearly | C22: Refer to Common Preconditions above. | D22: Date: 08/31/2026; Amount: 1234.50; Currency: USD | E22: 1. Sign in to Sage Intacct. 2. Go to Applications > Accounts Receivable > Invoices / Lending Management > Related invoices. 3. Prepare the test data: Open the invoice. 4. Review dates and money values. 5. Save or confirm when needed. 6. Check the page and related records. | F22: Dates and currency use the company format and show two decimals. | G22: Loan invoice UI requirement; Jira reference TBD | H22: TBD | I22: Not Executed
A23: SNL-INV-015 | B23: Show long descriptions without clipping | C23: Refer to Common Preconditions above. | D23: Line description: 250 characters | E23: 1. Sign in to Sage Intacct. 2. Go to Applications > Accounts Receivable > Invoices / Lending Management > Related invoices. 3. Prepare the test data: Use an invoice with a long line description. 4. Open the invoice. 5. Save or confirm when needed. 6. Check the page and related records. | F23: The full description can be read. | G23: Loan invoice UI requirement; Jira reference TBD | H23: TBD | I23: Not Executed
A24: PAYMENT STATUS (4 test cases)
A25: SNL-INV-016 | B25: Show Open before any payment | C25: Refer to Common Preconditions above. | D25: Invoice: INV-UI-OPEN; Balance: 100.00 | E25: 1. Sign in to Sage Intacct. 2. Go to Applications > Accounts Receivable > Invoices / Lending Management > Related invoices. 3. Prepare the test data: Open an unpaid invoice. 4. Review its status and balance. 5. Save or confirm when needed. 6. Check the page and related records. | F25: Status is Open and balance is 100.00. | G25: Loan invoice UI requirement; Jira reference TBD | H25: TBD | I25: Not Executed
A26: SNL-INV-017 | B26: Show Partially paid after a partial payment | C26: Refer to Common Preconditions above. | D26: Invoice: INV-UI-PART; Total: 200.00; Paid: 75.00 | E26: 1. Sign in to Sage Intacct. 2. Go to Applications > Accounts Receivable > Invoices / Lending Management > Related invoices. 3. Prepare the test data: Post a 75.00 payment. 4. Open the invoice. 5. Save or confirm when needed. 6. Check the page and related records. | F26: Status and remaining balance show the partial payment correctly. | G26: Loan invoice UI requirement; Jira reference TBD | H26: TBD | I26: Not Executed
A27: SNL-INV-018 | B27: Show Paid after a full payment | C27: Refer to Common Preconditions above. | D27: Invoice: INV-UI-PAID; Total: 100.00; Paid: 100.00 | E27: 1. Sign in to Sage Intacct. 2. Go to Applications > Accounts Receivable > Invoices / Lending Management > Related invoices. 3. Prepare the test data: Post the full payment. 4. Open the invoice. 5. Save or confirm when needed. 6. Check the page and related records. | F27: Status is Paid and balance is 0.00. | G27: Loan invoice UI requirement; Jira reference TBD | H27: TBD | I27: Not Executed
A28: SNL-INV-019 | B28: Reopen the invoice after payment reversal | C28: Refer to Common Preconditions above. | D28: Invoice: INV-UI-REV; Reversed payment: 100.00 | E28: 1. Sign in to Sage Intacct. 2. Go to Applications > Accounts Receivable > Invoices / Lending Management > Related invoices. 3. Prepare the test data: Pay the invoice and reverse the payment. 4. Open the invoice. 5. Save or confirm when needed. 6. Check the page and related records. | F28: Status is Open again and the balance is restored. | G28: Loan invoice UI requirement; Jira reference TBD | H28: TBD | I28: Not Executed
A29: RELATED FEATURES (2 test cases)
A30: SNL-INV-020 | B30: Show the invoice in the Lending workbench | C30: Refer to Common Preconditions above. | D30: Loan: LOAN-QA-INV-001; Invoice: INV-UI-001 | E30: 1. Sign in to Sage Intacct. 2. Go to Applications > Accounts Receivable > Invoices / Lending Management > Related invoices. 3. Prepare the test data: Generate an invoice for the loan. 4. Open and filter the Lending workbench. 5. Save or confirm when needed. 6. Check the page and related records. | F30: The row shows the latest invoice and invoice state. | G30: Loan invoice UI requirement; Jira reference TBD | H30: TBD | I30: Not Executed | J30: Local end-to-end tests check invoice data in the workbench.
A31: SNL-INV-021 | B31: Open the invoice audit trail | C31: Refer to Common Preconditions above. | D31: Invoice: INV-UI-001 | E31: 1. Sign in to Sage Intacct. 2. Go to Applications > Accounts Receivable > Invoices / Lending Management > Related invoices. 3. Prepare the test data: Open an invoice View page. 4. Open More actions and click View audit trail. 5. Save or confirm when needed. 6. Check the page and related records. | F31: The audit page opens for the invoice. | G31: Loan invoice UI requirement; Jira reference TBD | H31: TBD | I31: Not Executed
A32: SECURITY (1 test case)
A33: SNL-INV-022 | B33: Hide invoice data from a user without access | C33: Refer to Common Preconditions above. | D33: User: QA-INVOICE-BLOCKED | E33: 1. Sign in to Sage Intacct. 2. Go to Applications > Accounts Receivable > Invoices / Lending Management > Related invoices. 3. Prepare the test data: Remove invoice access from the user. 4. Try to open the invoice list and direct invoice link. 5. Save or confirm when needed. 6. Check the page and related records. | F33: Invoice data is hidden or access is denied clearly. | G33: Loan invoice UI requirement; Jira reference TBD | H33: TBD | I33: Not Executed

Sheet Standard Statements
A1: Standard Automation - Statement Generation and Reversal
A2: Common Preconditions | C2: 1. User is signed in to Sage Intacct. 2. The correct Lending Management entity is selected. 3. Lending Management is enabled. 4. The user has the needed permission. 5. Required loan, customer, invoice, and setup records are active.
A4: Navigation: Applications > Lending Management > Workbench / Statements | Client baseline | 22 test cases | Updated 2026-08-28
A6: Test Case ID | B6: Test Scenario | C6: Preconditions | D6: Test Data | E6: Test Steps | F6: Expected Result | G6: Requirement/Jira Reference | H6: IS Automated | I6: Status | J6: Comments
A7: STANDARD SETUP (5 test cases)
A8: SNL-STD-001 | B8: Allow Standard automation on a loan type | C8: Refer to Common Preconditions above. | D8: Loan type: LT-STD-001; Automation: Standard | E8: 1. Sign in to Sage Intacct. 2. Go to Applications > Lending Management > Workbench / Statements. 3. Prepare the test data: Create or edit a loan type. 4. Select Standard automation and save. 5. Save or confirm when needed. 6. Check the page and related records. | F8: The loan type saves with Standard automation. | G8: PR #1457 sections 9.1 and 9.5 Standard automation; Jira reference TBD | H8: TBD | I8: Not Executed
A9: SNL-STD-002 | B9: Allow Statement presentment for Standard automation | C9: Refer to Common Preconditions above. | D9: Presentment: Statement; Statement repeats: Monthly | E9: 1. Sign in to Sage Intacct. 2. Go to Applications > Lending Management > Workbench / Statements. 3. Prepare the test data: Use a Standard loan type. 4. Select Statement and save. 5. Save or confirm when needed. 6. Check the page and related records. | F9: The setup saves and no invoice recurrence is required. | G9: PR #1457 sections 9.1 and 9.5 Standard automation; Jira reference TBD | H9: TBD | I9: Not Executed
A10: SNL-STD-003 | B10: Allow Invoice and Statement presentment | C10: Refer to Common Preconditions above. | D10: Presentment: Invoice & Statements; Invoice repeats: Monthly; Statement repeats: Quarterly | E10: 1. Sign in to Sage Intacct. 2. Go to Applications > Lending Management > Workbench / Statements. 3. Prepare the test data: Use a Standard loan type. 4. Select both presentment options and save. 5. Save or confirm when needed. 6. Check the page and related records. | F10: The setup saves with both recurrence values. | G10: PR #1457 sections 9.1 and 9.5 Standard automation; Jira reference TBD | H10: TBD | I10: Not Executed
A11: SNL-STD-004 | B11: Block Statement presentment with annual statement cadence | C11: Refer to Common Preconditions above. | D11: Presentment: Statement; Statement repeats: Annually | E11: 1. Sign in to Sage Intacct. 2. Go to Applications > Lending Management > Workbench / Statements. 3. Prepare the test data: Use a Standard loan type. 4. Try to save the annual cadence. 5. Save or confirm when needed. 6. Check the page and related records. | F11: Save is blocked with a clear validation message. | G11: PR #1457 sections 9.1 and 9.5 Standard automation; Jira reference TBD | H11: TBD | I11: Not Executed
A12: SNL-STD-005 | B12: Require valid first statement and invoice dates | C12: Refer to Common Preconditions above. | D12: Origination: 08/01/2026; First invoice: 08/31/2026; First statement: 09/15/2026 | E12: 1. Sign in to Sage Intacct. 2. Go to Applications > Lending Management > Workbench / Statements. 3. Prepare the test data: Create a Standard loan account. 4. Enter the dates and save. 5. Save or confirm when needed. 6. Check the page and related records. | F12: The dates save because they are after origination. | G12: PR #1457 sections 9.1 and 9.5 Standard automation; Jira reference TBD | H12: TBD | I12: Not Executed
A13: GENERATION (9 test cases)
A14: SNL-STD-006 | B14: Generate a monthly Standard statement | C14: Refer to Common Preconditions above. | D14: Loan: LOAN-STD-001; First statement: 09/15/2026; Repeats: Monthly | E14: 1. Sign in to Sage Intacct. 2. Go to Applications > Lending Management > Workbench / Statements. 3. Prepare the test data: Use an eligible open Standard loan. 4. Run the due Standard statement process. 5. Save or confirm when needed. 6. Check the page and related records. | F14: One statement is created for the correct period. | G14: PR #1457 sections 9.1 and 9.5 Standard automation; Jira reference TBD | H14: TBD | I14: Not Executed | J14: Local automation confirms the loanStatement process creates a statement row.
A15: SNL-STD-007 | B15: Generate a quarterly Standard statement | C15: Refer to Common Preconditions above. | D15: Loan: LOAN-STD-002; First statement: 09/30/2026; Repeats: Quarterly | E15: 1. Sign in to Sage Intacct. 2. Go to Applications > Lending Management > Workbench / Statements. 3. Prepare the test data: Use an eligible open Standard loan. 4. Run the due Standard statement process. 5. Save or confirm when needed. 6. Check the page and related records. | F15: One statement is created and the next date moves three months. | G15: PR #1457 sections 9.1 and 9.5 Standard automation; Jira reference TBD | H15: TBD | I15: Not Executed
A16: SNL-STD-008 | B16: Generate statements for revolving and non-revolving loans | C16: Refer to Common Preconditions above. | D16: Loans: LOAN-STD-REV and LOAN-STD-NONREV | E16: 1. Sign in to Sage Intacct. 2. Go to Applications > Lending Management > Workbench / Statements. 3. Prepare the test data: Make both loans due for a statement. 4. Run the Standard statement process. 5. Save or confirm when needed. 6. Check the page and related records. | F16: Each eligible loan gets the correct statement. | G16: PR #1457 sections 9.1 and 9.5 Standard automation; Jira reference TBD | H16: TBD | I16: Not Executed
A17: SNL-STD-009 | B17: Process the statement before the invoice when both dates match | C17: Refer to Common Preconditions above. | D17: Next invoice: 09/30/2026; Next statement: 09/30/2026 | E17: 1. Sign in to Sage Intacct. 2. Go to Applications > Lending Management > Workbench / Statements. 3. Prepare the test data: Use Invoice & Statements presentment. 4. Run the Standard process on the tie date. 5. Save or confirm when needed. 6. Check the page and related records. | F17: The statement step runs first, then the invoice step runs. | G17: PR #1457 sections 9.1 and 9.5 Standard automation; Jira reference TBD | H17: TBD | I17: Not Executed
A18: SNL-STD-010 | B18: Do not create an AR invoice for Statement-only presentment | C18: Refer to Common Preconditions above. | D18: Presentment: Statement; Loan: LOAN-STD-003 | E18: 1. Sign in to Sage Intacct. 2. Go to Applications > Lending Management > Workbench / Statements. 3. Prepare the test data: Make the loan due for a statement. 4. Run the Standard process. 5. Save or confirm when needed. 6. Check the page and related records. | F18: A statement is created and no AR invoice is created. | G18: PR #1457 sections 9.1 and 9.5 Standard automation; Jira reference TBD | H18: TBD | I18: Not Executed
A19: SNL-STD-011 | B19: Create both artifacts for Invoice and Statements presentment | C19: Refer to Common Preconditions above. | D19: Presentment: Invoice & Statements; Loan: LOAN-STD-004 | E19: 1. Sign in to Sage Intacct. 2. Go to Applications > Lending Management > Workbench / Statements. 3. Prepare the test data: Make the loan due for both artifacts. 4. Run the Standard process. 5. Save or confirm when needed. 6. Check the page and related records. | F19: The statement and AR invoice are both created. | G19: PR #1457 sections 9.1 and 9.5 Standard automation; Jira reference TBD | H19: TBD | I19: Not Executed
A20: SNL-STD-012 | B20: Show the generated statement in the Statements list | C20: Refer to Common Preconditions above. | D20: Loan: LOAN-STD-001 | E20: 1. Sign in to Sage Intacct. 2. Go to Applications > Lending Management > Workbench / Statements. 3. Prepare the test data: Generate a Standard statement. 4. Open the Statements list and search for the loan. 5. Save or confirm when needed. 6. Check the page and related records. | F20: The new statement is shown with Active status. | G20: PR #1457 sections 9.1 and 9.5 Standard automation; Jira reference TBD | H20: TBD | I20: Not Executed
A21: SNL-STD-013 | B21: Open the generated statement PDF | C21: Refer to Common Preconditions above. | D21: Statement: STMT-STD-001; Status: Completed | E21: 1. Sign in to Sage Intacct. 2. Go to Applications > Lending Management > Workbench / Statements. 3. Prepare the test data: Generate a completed Standard statement. 4. Click the Statement PDF link. 5. Save or confirm when needed. 6. Check the page and related records. | F21: The PDF opens and belongs to the correct loan and period. | G21: PR #1457 sections 9.1 and 9.5 Standard automation; Jira reference TBD | H21: TBD | I21: Not Executed
A22: SNL-STD-014 | B22: Carry the closing balance to the next statement | C22: Refer to Common Preconditions above. | D22: Period 1 ending: 950.00; Period 2 beginning: 950.00 | E22: 1. Sign in to Sage Intacct. 2. Go to Applications > Lending Management > Workbench / Statements. 3. Prepare the test data: Generate two statement periods in order. 4. Open both statements. 5. Save or confirm when needed. 6. Check the page and related records. | F22: Period 2 begins with the Period 1 ending balance. | G22: PR #1457 sections 9.1 and 9.5 Standard automation; Jira reference TBD | H22: TBD | I22: Not Executed | J22: Local multi-period automation checks balance carry-forward.
A23: REVERSAL (6 test cases)
A24: SNL-STD-015 | B24: Show Reverse for an eligible Standard statement | C24: Refer to Common Preconditions above. | D24: Statement: STMT-STD-001; Status: Active | E24: 1. Sign in to Sage Intacct. 2. Go to Applications > Lending Management > Workbench / Statements. 3. Prepare the test data: Open the related workbench row. 4. Select the row and review actions. 5. Save or confirm when needed. 6. Check the page and related records. | F24: Reverse is enabled for the eligible statement. | G24: PR #1457 sections 9.1 and 9.5 Standard automation; Jira reference TBD | H24: TBD | I24: Not Executed
A25: SNL-STD-016 | B25: Reverse a Standard statement | C25: Refer to Common Preconditions above. | D25: Statement: STMT-STD-001 | E25: 1. Sign in to Sage Intacct. 2. Go to Applications > Lending Management > Workbench / Statements. 3. Prepare the test data: Use a statement with no later blocking record. 4. Click Reverse and confirm. 5. Save or confirm when needed. 6. Check the page and related records. | F25: The statement changes to Reversed. | G25: PR #1457 sections 9.1 and 9.5 Standard automation; Jira reference TBD | H25: TBD | I25: Not Executed
A26: SNL-STD-017 | B26: Show the reversed status in the Statements list | C26: Refer to Common Preconditions above. | D26: Statement: STMT-STD-001 | E26: 1. Sign in to Sage Intacct. 2. Go to Applications > Lending Management > Workbench / Statements. 3. Prepare the test data: Reverse the statement. 4. Open the Statements list. 5. Save or confirm when needed. 6. Check the page and related records. | F26: The same statement is shown with Reversed status. | G26: PR #1457 sections 9.1 and 9.5 Standard automation; Jira reference TBD | H26: TBD | I26: Not Executed
A27: SNL-STD-018 | B27: Block reversal when a later invoice exists | C27: Refer to Common Preconditions above. | D27: Statement date: 09/30/2026; Later invoice: 10/15/2026 | E27: 1. Sign in to Sage Intacct. 2. Go to Applications > Lending Management > Workbench / Statements. 3. Prepare the test data: Create a later invoice for the same loan. 4. Try to reverse the earlier statement. 5. Save or confirm when needed. 6. Check the page and related records. | F27: Reversal is blocked and the reason is clear. | G27: PR #1457 sections 9.1 and 9.5 Standard automation; Jira reference TBD | H27: TBD | I27: Not Executed | J27: PR reference includes SNL-2034 and SNL-2035.
A28: SNL-STD-019 | B28: Block reversal when a later completed statement exists | C28: Refer to Common Preconditions above. | D28: Earlier statement: 09/30/2026; Later statement: 10/31/2026 | E28: 1. Sign in to Sage Intacct. 2. Go to Applications > Lending Management > Workbench / Statements. 3. Prepare the test data: Complete the later statement. 4. Try to reverse the earlier statement. 5. Save or confirm when needed. 6. Check the page and related records. | F28: Reversal is blocked and no statement data changes. | G28: PR #1457 sections 9.1 and 9.5 Standard automation; Jira reference TBD | H28: TBD | I28: Not Executed | J28: PR reference includes SNL-2034 and SNL-2035.
A29: SNL-STD-020 | B29: Block a second reversal of the same statement | C29: Refer to Common Preconditions above. | D29: Statement: STMT-STD-001; Status: Reversed | E29: 1. Sign in to Sage Intacct. 2. Go to Applications > Lending Management > Workbench / Statements. 3. Prepare the test data: Reverse the statement once. 4. Try to reverse it again. 5. Save or confirm when needed. 6. Check the page and related records. | F29: The second reversal is blocked. | G29: PR #1457 sections 9.1 and 9.5 Standard automation; Jira reference TBD | H29: TBD | I29: Not Executed
A30: HISTORY AND SECURITY (2 test cases)
A31: SNL-STD-021 | B31: Record generation and reversal in history | C31: Refer to Common Preconditions above. | D31: Statement: STMT-STD-001 | E31: 1. Sign in to Sage Intacct. 2. Go to Applications > Lending Management > Workbench / Statements. 3. Prepare the test data: Generate and then reverse the statement. 4. Open the audit trail or run history. 5. Save or confirm when needed. 6. Check the page and related records. | F31: Both actions show the correct user, time, and status. | G31: PR #1457 sections 9.1 and 9.5 Standard automation; Jira reference TBD | H31: TBD | I31: Not Executed
A32: SNL-STD-022 | B32: Block statement actions for a user without permission | C32: Refer to Common Preconditions above. | D32: User: QA-STD-BLOCKED | E32: 1. Sign in to Sage Intacct. 2. Go to Applications > Lending Management > Workbench / Statements. 3. Prepare the test data: Remove statement process permission. 4. Try to generate or reverse a statement. 5. Save or confirm when needed. 6. Check the page and related records. | F32: The actions are hidden or access is denied clearly. | G32: PR #1457 sections 9.1 and 9.5 Standard automation; Jira reference TBD | H32: TBD | I32: Not Executed
